Workbook

Sheet Estado de Resultados
A1: =+Códigos!$A$1 -> LIBRO DIARIO OFICINA
A2: ESTADO DE RESULTADOS
A3: =+Códigos!$A$3 -> AÑO: | B3: =+Códigos!$B$3 -> 2025
C4: EDO de RDOS | D4: OFICINA 2020 | F4: Diferencias | G4: Revisión
B5: TOTAL INGRESOS | C5: =+C46 -> 791027153 | D5: =+'INGRESOS A CAJA'!G2 -> 634239583 | F5: =+C5-D5 -> 156787570 | G5: Dif OK/fras
B6: TOTALES EGRESOS | C6: =+C113 -> 629110853 | D6: =+'EGRESOS DE CAJA'!H2 -> 633732083 | F6: =+C6-D6 -> -4621230 | G6: Dif OK/IVA
G7: PROM MENSUAL
C8: Utilidad (+) o Pérdida (-) OPERACIONAL | D8: =+D46-D75 -> -161991104 | G8: =+D8/3 -> -53997035
C9: Utilidad (+) o Pérdida (-) GENERAL | D9: =+D46-D113 -> -412385813 | G9: =+D9/3 -> -1.3746194e+08
A11: CÓDIGO | B11: CONCEPTO | C11: OFICINA | D11: RESULTADOS
A14: INGRESOS A CAJA
A15: INGRESOS DE OPERACIÓN
B16: FACTURAS -GERMÁN TULIO FERNÁNDEZ FERNÁNDEZ- | C16: =+FACTURACIÓN!G98 -> 29603000 | D16: =+C16 -> 29603000
B17: OTROS COBROS -GERMÁN TULIO FERNÁNDEZ FERNÁNDEZ- | C17: =+FACTURACIÓN!G141 -> 0
B18: CUENTAS DE COBRO -DIEGO ALBERTO FERNÁNDEZ FERNÁNDEZ- | C18: =+FACTURACIÓN!G300 -> 121560000
B19: OTROS INGRESOS SIN FACTURACIÓN | C19: =+FACTURACIÓN!G322 -> 0 | D19: =+C19-FACTURACIÓN!J322 -> 0
B20: I V A | C20: =+FACTURACIÓN!H324 -> 5624570 | D20: =+C20 -> 5624570
B21: =_xlfn.XLOOKUP(A21,Códigos!$A$489:$A$522,Códigos!$B$489:$B$522,"Verificar",0) -> 0 | C21: =SUMIF('INGRESOS A CAJA'!$B$9:$B$4452,A21,'INGRESOS A CAJA'!$F$9:$F$4452) -> 0
A24: TOTAL INGRESOS DE OPERACIÓN | C24: =SUM(C16:C23) -> 156787570 | D24: =SUM(D16:D23) -> 35227570
A26: NO INGRESOS A CAJA
A28: A | B28: =_xlfn.XLOOKUP(A28,Códigos!$A$489:$A$522,Códigos!$B$489:$B$522,"Verificar",0) -> Recibido por: -FACTURAS -GTFF | C28: =SUMIF('INGRESOS A CAJA'!$B$9:$B$4452,A28,'INGRESOS A CAJA'!$F$9:$F$4452) -> 45615800
A29: B | B29: =_xlfn.XLOOKUP(A29,Códigos!$A$489:$A$522,Códigos!$B$489:$B$522,"Verificar",0) -> Recibido por: -Cuentas de cobro -GTFF | C29: =SUMIF('INGRESOS A CAJA'!$B$9:$B$4452,A29,'INGRESOS A CAJA'!$F$9:$F$4452) -> 0
A30: C | B30: =_xlfn.XLOOKUP(A30,Códigos!$A$489:$A$522,Códigos!$B$489:$B$522,"Verificar",0) -> Recibido por: -Cuentas de cobro -DAFF | C30: =SUMIF('INGRESOS A CAJA'!$B$9:$B$4452,A30,'INGRESOS A CAJA'!$F$9:$F$4452) -> 42540000
A31: D | B31: =_xlfn.XLOOKUP(A31,Códigos!$A$489:$A$522,Códigos!$B$489:$B$522,"Verificar",0) -> Recibido por: -Otros ingresos Sin Facturación | C31: =SUMIF('INGRESOS A CAJA'!$B$9:$B$4452,A31,'INGRESOS A CAJA'!$F$9:$F$4452) -> 0
A32: E | B32: =_xlfn.XLOOKUP(A32,Códigos!$A$489:$A$522,Códigos!$B$489:$B$522,"Verificar",0) -> Ingresos Recibidos de terceros para pagos | C32: =SUMIF('INGRESOS A CAJA'!$B$9:$B$4452,A32,'INGRESOS A CAJA'!$F$9:$F$4452) -> 1096000
A33: F | B33: =_xlfn.XLOOKUP(A33,Códigos!$A$489:$A$522,Códigos!$B$489:$B$522,"Verificar",0) -> Recibido por: -Cuentas por Cobrar | C33: =SUMIF('INGRESOS A CAJA'!$B$9:$B$4452,A33,'INGRESOS A CAJA'!$F$9:$F$4452) -> 10076800
A34: G | B34: =_xlfn.XLOOKUP(A34,Códigos!$A$489:$A$522,Códigos!$B$489:$B$522,"Verificar",0) -> Recibido por: -Abono a préstamos por Nómina de: | C34: =SUMIF('INGRESOS A CAJA'!$B$9:$B$4452,A34,'INGRESOS A CAJA'!$F$9:$F$4452) -> 1744200
A35: H | B35: =_xlfn.XLOOKUP(A35,Códigos!$A$489:$A$522,Códigos!$B$489:$B$522,"Verificar",0) -> Recibido por: -Abono a préstamos por Nómina de: | C35: =SUMIF('INGRESOS A CAJA'!$B$9:$B$4452,A35,'INGRESOS A CAJA'!$F$9:$F$4452) -> 0
A36: I | B36: =_xlfn.XLOOKUP(A36,Códigos!$A$489:$A$522,Códigos!$B$489:$B$522,"Verificar",0) -> -Retiros y Traslados de Bancos | C36: =SUMIF('INGRESOS A CAJA'!$B$9:$B$4452,A36,'INGRESOS A CAJA'!$F$9:$F$4452) -> 533166783
A37: J | B37: =_xlfn.XLOOKUP(A37,Códigos!$A$489:$A$522,Códigos!$B$489:$B$522,"Verificar",0) -> -Consignaciones pendientes de identificar | C37: =SUMIF('INGRESOS A CAJA'!$B$9:$B$4452,A37,'INGRESOS A CAJA'!$F$9:$F$4452) -> 0
A38: K | B38: =_xlfn.XLOOKUP(A38,Códigos!$A$489:$A$522,Códigos!$B$489:$B$522,"Verificar",0) -> Recibido por: -Préstamos a favor de la oficina | C38: =SUMIF('INGRESOS A CAJA'!$B$9:$B$4452,A38,'INGRESOS A CAJA'!$F$9:$F$4452) -> 0
A39: L | B39: =_xlfn.XLOOKUP(A39,Códigos!$A$489:$A$522,Códigos!$B$489:$B$522,"Verificar",0) -> Reembolsos y recuperaciones | C39: =SUMIF('INGRESOS A CAJA'!$B$9:$B$4452,A39,'INGRESOS A CAJA'!$F$9:$F$4452) -> 0
B40: RETENCIÓN EN LA FUENTE | C40: =SUMIF('INGRESOS A CAJA'!$B$9:$B$4452,A40,'INGRESOS A CAJA'!$F$9:$F$4452) -> 0 | D40: =-FACTURACIÓN!J324 -> -3256330
B41: =_xlfn.XLOOKUP(A41,Códigos!$A$489:$A$522,Códigos!$B$489:$B$522,"Verificar",0) -> 0 | C41: =SUMIF('INGRESOS A CAJA'!$B$9:$B$4452,A41,'INGRESOS A CAJA'!$F$9:$F$4452) -> 0
A44: TOTAL NO INGRESOS A CAJA | C44: =SUM(C28:C43) -> 634239583 | D44: =SUM(D28:D43) -> -3256330
A46: TOTAL INGRESOS A CAJA | C46: =+C24+C44 -> 791027153 | D46: =+D24+D44 -> 31971240 | F46: =+D46-D75 -> -161991104 | G46: Utilidad (+) o Pérdida (-) OPERACIONAL
A50: EGRESOS DE CAJA
A51: COSTOS Y GASTOS DE OPERACIÓN
A52: 2 | B52: =_xlfn.XLOOKUP(A52,Códigos!$A$421:$A$483,Códigos!$B$421:$B$483,"Verificar",0) -> Pago de Salarios a: | C52: =SUMIF('EGRESOS DE CAJA'!$B$9:$B$5958,A52,'EGRESOS DE CAJA'!$G$9:$G$5958) -> 57460000 | D52: =+C52 -> 57460000
A53: 3 | B53: =_xlfn.XLOOKUP(A53,Códigos!$A$421:$A$483,Códigos!$B$421:$B$483,"Verificar",0) -> Pago de Prestaciones sociales a: | C53: =SUMIF('EGRESOS DE CAJA'!$B$9:$B$5958,A53,'EGRESOS DE CAJA'!$G$9:$G$5958) -> 0
A54: 4 | B54: =_xlfn.XLOOKUP(A54,Códigos!$A$421:$A$483,Códigos!$B$421:$B$483,"Verificar",0) -> Pago de Bonificación a: | C54: =SUMIF('EGRESOS DE CAJA'!$B$9:$B$5958,A54,'EGRESOS DE CAJA'!$G$9:$G$5958) -> 0
A55: 5 | B55: =_xlfn.XLOOKUP(A55,Códigos!$A$421:$A$483,Códigos!$B$421:$B$483,"Verificar",0) -> Préstamos por Nómina a: | C55: =SUMIF('EGRESOS DE CAJA'!$B$9:$B$5958,A55,'EGRESOS DE CAJA'!$G$9:$G$5958) -> 12065900 | D55: =+C55 -> 12065900
A56: 6 | B56: =_xlfn.XLOOKUP(A56,Códigos!$A$421:$A$483,Códigos!$B$421:$B$483,"Verificar",0) -> Préstamos por Nómina a: | C56: =SUMIF('EGRESOS DE CAJA'!$B$9:$B$5958,A56,'EGRESOS DE CAJA'!$G$9:$G$5958) -> 67737400 | D56: =+C56 -> 67737400
A57: 7 | B57: =_xlfn.XLOOKUP(A57,Códigos!$A$421:$A$483,Códigos!$B$421:$B$483,"Verificar",0) -> Pagos de: -Seguridad Social | C57: =SUMIF('EGRESOS DE CAJA'!$B$9:$B$5958,A57,'EGRESOS DE CAJA'!$G$9:$G$5958) -> 27296800 | D57: =+C57 -> 27296800
A58: 9 | B58: =_xlfn.XLOOKUP(A58,Códigos!$A$421:$A$483,Códigos!$B$421:$B$483,"Verificar",0) -> Pagos de: -Servicios públicos -OFICINA- | C58: =SUMIF('EGRESOS DE CAJA'!$B$9:$B$5958,A58,'EGRESOS DE CAJA'!$G$9:$G$5958) -> 10779655 | D58: =+C58 -> 10779655
A59: 12 | B59: =_xlfn.XLOOKUP(A59,Códigos!$A$421:$A$483,Códigos!$B$421:$B$483,"Verificar",0) -> Pagos de: -Celulares | C59: =SUMIF('EGRESOS DE CAJA'!$B$9:$B$5958,A59,'EGRESOS DE CAJA'!$G$9:$G$5958) -> 3595890 | D59: =+C59 -> 3595890
A60: 13 | B60: =_xlfn.XLOOKUP(A60,Códigos!$A$421:$A$483,Códigos!$B$421:$B$483,"Verificar",0) -> Pagos de: -Suscripciones | C60: =SUMIF('EGRESOS DE CAJA'!$B$9:$B$5958,A60,'EGRESOS DE CAJA'!$G$9:$G$5958) -> 0 | D60: =+C60 -> 0
A61: 14 | B61: =_xlfn.XLOOKUP(A61,Códigos!$A$421:$A$483,Códigos!$B$421:$B$483,"Verificar",0) -> Pagos de: -Seminarios y capacitaciones | C61: =SUMIF('EGRESOS DE CAJA'!$B$9:$B$5958,A61,'EGRESOS DE CAJA'!$G$9:$G$5958) -> 0 | D61: =+C61 -> 0
A62: 15 | B62: =_xlfn.XLOOKUP(A62,Códigos!$A$421:$A$483,Códigos!$B$421:$B$483,"Verificar",0) -> Pagos de: -Mantenimiento de equipos y telefonía | C62: =SUMIF('EGRESOS DE CAJA'!$B$9:$B$5958,A62,'EGRESOS DE CAJA'!$G$9:$G$5958) -> 0 | D62: =+C62 -> 0
A63: 17 | B63: =_xlfn.XLOOKUP(A63,Códigos!$A$421:$A$483,Códigos!$B$421:$B$483,"Verificar",0) -> Pagos de: -Sanciones e intereses asumidos | C63: =SUMIF('EGRESOS DE CAJA'!$B$9:$B$5958,A63,'EGRESOS DE CAJA'!$G$9:$G$5958) -> 0 | D63: =+C63 -> 0
A64: 18 | B64: =_xlfn.XLOOKUP(A64,Códigos!$A$421:$A$483,Códigos!$B$421:$B$483,"Verificar",0) -> Pagos de: -Pasajes y transportes | C64: =SUMIF('EGRESOS DE CAJA'!$B$9:$B$5958,A64,'EGRESOS DE CAJA'!$G$9:$G$5958) -> 80000 | D64: =+C64 -> 80000
A65: 20 | B65: =_xlfn.XLOOKUP(A65,Códigos!$A$421:$A$483,Códigos!$B$421:$B$483,"Verificar",0) -> Pagos de: -Demás Gastos oficina | C65: =SUMIF('EGRESOS DE CAJA'!$B$9:$B$5958,A65,'EGRESOS DE CAJA'!$G$9:$G$5958) -> 80000 | D65: =+C65 -> 80000
A66: 22 | B66: =_xlfn.XLOOKUP(A66,Códigos!$A$421:$A$483,Códigos!$B$421:$B$483,"Verificar",0) -> Compra de: -Equipos, dotaciones y repuestos para oficina | C66: =SUMIF('EGRESOS DE CAJA'!$B$9:$B$5958,A66,'EGRESOS DE CAJA'!$G$9:$G$5958) -> 8425299 | D66: =+C66 -> 8425299
... A71: 27 | B71: =_xlfn.XLOOKUP(A71,Códigos!$A$421:$A$483,Códigos!$B$421:$B$483,"Verificar",0) -> Compra de: -Restaurante y cafetería | C71: =SUMIF('EGRESOS DE CAJA'!$B$9:$B$5958,A71,'EGRESOS DE CAJA'!$G$9:$G$5958) -> 5426000 | D71: =+C71 -> 5426000
B72: =_xlfn.XLOOKUP(A72,Códigos!$A$421:$A$483,Códigos!$B$421:$B$483,"Verificar",0) -> 0 | C72: =SUMIF('EGRESOS DE CAJA'!$B$9:$B$5958,A72,'EGRESOS DE CAJA'!$G$9:$G$5958) -> 0
A75: TOTAL EGRESOS | C75: =SUM(C52:C74) -> 193962344 | D75: =SUM(D52:D74) -> 193962344
A78: EGRESOS DE CAJA
A79: GASTOS ADMINISTRATIVOS
A80: 1 | B80: =_xlfn.XLOOKUP(A80,Códigos!$A$421:$A$483,Códigos!$B$421:$B$483,"Verificar",0) -> Gastos personales | C80: =SUMIF('EGRESOS DE CAJA'!$B$9:$B$5958,A80,'EGRESOS DE CAJA'!$G$9:$G$5958) -> 193927304 | D80: =+C80 -> 193927304
A81: 8 | B81: =_xlfn.XLOOKUP(A81,Códigos!$A$421:$A$483,Códigos!$B$421:$B$483,"Verificar",0) -> Pagos de: -Cuota para alimentos y Manuntención | C81: =SUMIF('EGRESOS DE CAJA'!$B$9:$B$5958,A81,'EGRESOS DE CAJA'!$G$9:$G$5958) -> 43358150 | D81: =+C81 -> 43358150
A82: 10 | B82: =_xlfn.XLOOKUP(A82,Códigos!$A$421:$A$483,Códigos!$B$421:$B$483,"Verificar",0) -> Pagos de: -Servicios públicos -NIÑAS- | C82: =SUMIF('EGRESOS DE CAJA'!$B$9:$B$5958,A82,'EGRESOS DE CAJA'!$G$9:$G$5958) -> 816300 | D82: =+C82 -> 816300
A83: 11 | B83: =_xlfn.XLOOKUP(A83,Códigos!$A$421:$A$483,Códigos!$B$421:$B$483,"Verificar",0) -> Pagos de: -Servicios Administracion y otros Oficina | C83: =SUMIF('EGRESOS DE CAJA'!$B$9:$B$5958,A83,'EGRESOS DE CAJA'!$G$9:$G$5958) -> 6596185 | D83: =+C83 -> 6596185
A84: 16 | B84: =_xlfn.XLOOKUP(A84,Códigos!$A$421:$A$483,Códigos!$B$421:$B$483,"Verificar",0) -> Pagos de: -Aguinaldos y Propinas | C84: =SUMIF('EGRESOS DE CAJA'!$B$9:$B$5958,A84,'EGRESOS DE CAJA'!$G$9:$G$5958) -> 0 | D84: =+C84 -> 0
A85: 19 | B85: =_xlfn.XLOOKUP(A85,Códigos!$A$421:$A$483,Códigos!$B$421:$B$483,"Verificar",0) -> Pagos de: -Gastos Barbosa | C85: =SUMIF('EGRESOS DE CAJA'!$B$9:$B$5958,A85,'EGRESOS DE CAJA'!$G$9:$G$5958) -> 0 | D85: =+C85 -> 0
A86: 35 | B86: =_xlfn.XLOOKUP(A86,Códigos!$A$421:$A$483,Códigos!$B$421:$B$483,"Verificar",0) -> Impuestos, tasas y contribuciones -GTFF- | C86: =SUMIF('EGRESOS DE CAJA'!$B$9:$B$5958,A86,'EGRESOS DE CAJA'!$G$9:$G$5958)-F106 -> 72200 | D86: =+C86 -> 72200
B87: =_xlfn.XLOOKUP(A87,Códigos!$A$421:$A$483,Códigos!$B$421:$B$483,"Verificar",0) -> 0 | C87: =SUMIF('EGRESOS DE CAJA'!$B$9:$B$5958,A87,'EGRESOS DE CAJA'!$G$9:$G$5958) -> 0
A90: TOTAL EGRESOS | C90: =SUM(C80:C89) -> 244770139 | D90: =SUM(D80:D89) -> 244770139
A95: EGRESOS DE CAJA
A96: NO COSTOS NI GASTOS
A97: 21 | B97: =_xlfn.XLOOKUP(A97,Códigos!$A$421:$A$483,Códigos!$B$421:$B$483,"Verificar",0) -> Pagos de: -Cuentas por Pagar a: | C97: =SUMIF('EGRESOS DE CAJA'!$B$9:$B$5958,A97,'EGRESOS DE CAJA'!$G$9:$G$5958) -> 5929000
A98: 28 | B98: =_xlfn.XLOOKUP(A98,Códigos!$A$421:$A$483,Códigos!$B$421:$B$483,"Verificar",0) -> Préstamos a: | C98: =SUMIF('EGRESOS DE CAJA'!$B$9:$B$5958,A98,'EGRESOS DE CAJA'!$G$9:$G$5958) -> 41111900
A99: 29 | B99: =_xlfn.XLOOKUP(A99,Códigos!$A$421:$A$483,Códigos!$B$421:$B$483,"Verificar",0) -> Egresos por Cuenta de Terceros -Pagos impuestos- | C99: =SUMIF('EGRESOS DE CAJA'!$B$9:$B$5958,A99,'EGRESOS DE CAJA'!$G$9:$G$5958) -> 11346300
A100: 30 | B100: =_xlfn.XLOOKUP(A100,Códigos!$A$421:$A$483,Códigos!$B$421:$B$483,"Verificar",0) -> Egresos por Cuenta de Terceros -Seguridad social- | C100: =SUMIF('EGRESOS DE CAJA'!$B$9:$B$5958,A100,'EGRESOS DE CAJA'!$G$9:$G$5958) -> 0
A101: 31 | B101: =_xlfn.XLOOKUP(A101,Códigos!$A$421:$A$483,Códigos!$B$421:$B$483,"Verificar",0) -> Egresos por Cuenta de Terceros -Certificados y otros | C101: =SUMIF('EGRESOS DE CAJA'!$B$9:$B$5958,A101,'EGRESOS DE CAJA'!$G$9:$G$5958) -> 0
A102: 32 | B102: =_xlfn.XLOOKUP(A102,Códigos!$A$421:$A$483,Códigos!$B$421:$B$483,"Verificar",0) -> Egresos por Cuenta de Terceros -Mantenimiento o compras de equipos y repuestos | C102: =SUMIF('EGRESOS DE CAJA'!$B$9:$B$5958,A102,'EGRESOS DE CAJA'!$G$9:$G$5958) -> 0
A103: 33 | B103: =_xlfn.XLOOKUP(A103,Códigos!$A$421:$A$483,Códigos!$B$421:$B$483,"Verificar",0) -> AJUSTE POR -Consignación - Traslado a Bancos | C103: =SUMIF('EGRESOS DE CAJA'!$B$9:$B$5958,A103,'EGRESOS DE CAJA'!$G$9:$G$5958) -> 125181600
A104: 34 | B104: =_xlfn.XLOOKUP(A104,Códigos!$A$421:$A$483,Códigos!$B$421:$B$483,"Verificar",0) -> AJUSTE POR -Consignaciones pendientes de identificar | C104: =SUMIF('EGRESOS DE CAJA'!$B$9:$B$5958,A104,'EGRESOS DE CAJA'!$G$9:$G$5958) -> 0
B105: I V A -Facturación del año
B106: Pago I V A -años anteriores | C106: =+F106 -> 1185000 | F106: =+'EGRESOS DE CAJA'!G52 -> 1185000
B107: I V A -Por pagar en el año | C107: =+C20 -> 5624570 | D107: =+C107 -> 5624570
B108: =_xlfn.XLOOKUP(A108,Códigos!$A$421:$A$483,Códigos!$B$421:$B$483,"Verificar",0) -> 0 | C108: =SUMIF('EGRESOS DE CAJA'!$B$9:$B$5958,A108,'EGRESOS DE CAJA'!$G$9:$G$5958) -> 0
A111: TOTAL EGRESOS | C111: =SUM(C97:C110) -> 190378370 | D111: =SUM(D97:D110) -> 5624570
A113: TOTAL EGRESOS DE CAJA | C113: =+C111+C90+C75 -> 629110853 | D113: =+D111+D90+D75 -> 444357053

Sheet Revisión-Pruebas-Ejercicios
A1: GERMÁN TULIO FERNÁNDEZ FERNÁNDEZ
A2: REVISIONES - PRUEBAS - EJERCICIOS
A4: MOVIMIENTOS | H4: ACUMULADOS DE CAJA: Así se resume el movimiento en la caja
A6: DUQUE ECHEVERRÍ GERMÁN
A7: MOVIMIENTO DE INGRESOS A CAJA DIARIO | G7: CONTRA | H7: INGRESOS
A8: 43846 | B8: C | C8: 295 | D8: =_xlfn.XLOOKUP(B8,Códigos!$A$489:$A$522,Códigos!$B$489:$B$522,"Verificar",0) -> Recibido por: -Cuentas de cobro -DAFF | E8: =_xlfn.XLOOKUP(C8,Códigos!$A$11:$A$415,Códigos!$B$11:$B$415,"Verificar",0) -> NOMBRE 77 | F8: 600000 | H8: C | I8: =_xlfn.XLOOKUP(H8,Códigos!$A$489:$A$522,Códigos!$B$489:$B$522,"Verificar",0) -> Recibido por: -Cuentas de cobro -DAFF | J8: =SUMIF(B8,H8,F8) -> 600000
A10: MOVIMIENTO DE EGRESOS DE CAJA DIARIO | H10: EGRESOS
A11: 43846 | B11: 33 | C11: 295 | D11: =_xlfn.XLOOKUP(B11,Códigos!$A$421:$A$483,Códigos!$B$421:$B$483,"Verificar",0) -> AJUSTE POR -Consignación - Traslado a Bancos | E11: =_xlfn.XLOOKUP(C11,Códigos!$A$11:$A$415,Códigos!$B$11:$B$415,"Verificar",0) -> NOMBRE 77 | F11: 600000 | H11: 33 | I11: =_xlfn.XLOOKUP(H11,Códigos!$A$421:$A$483,Códigos!$B$421:$B$483,"Verificar",0) -> AJUSTE POR -Consignación - Traslado a Bancos | J11: =SUMIF(B11,H11,F11) -> 600000
I12: OK/Efecto neutro | J12: =+J8-J11 -> 0
C13: CARTERA del año
C14: CÓD | D14: APELLIDOS Y NOMBRES o RAZÓN SOCIAL DEL CLIENTE o TERCERO | E14: SALDOS POR COBRAR AÑOS ANTERIORES | F14: ABONOS EN EL AÑO | G14: FACTURAS y CUENTAS DE COBRO DEL AÑO | H14: INGRESOS EN EL AÑO | I14: EGRESOS EN EL AÑO | J14: SALDO TOTAL PENDIENTE POR COBRAR
C15: 295 | D15: =_xlfn.XLOOKUP(C15,Códigos!$A$11:$A$415,Códigos!$B$11:$B$415,"Verificar",0) -> NOMBRE 77 | E15: =SUMIF('CARTERA años anteriores'!$C$9:$C$133,C15,'CARTERA años anteriores'!$J$9:$J$133) -> 0 | F15: =SUMIF(FACTURACIÓN!$C$8:$C$1082,C15,FACTURACIÓN!$K$8:$K$1082) -> 900000 | G15: =SUMIF('INGRESOS A CAJA'!$C$10:$C$954,C15,'INGRESOS A CAJA'!$F$10:$F$954) -> 900000 | H15: =SUMIF('EGRESOS DE CAJA'!$C$10:$C$2251,C15,'EGRESOS DE CAJA'!$G$10:$G$2251) -> 0 | I15: =+E15+F15-G15+H15 -> 0
A19: CÁRDENAS GUTIÉRREZ SERGIO
A20: MOVIMIENTO DE INGRESOS A CAJA DIARIO | G20: CONTRA | H20: INGRESOS | K20: Consigna 5.900.000
A21: 43846 | B21: E | C21: 65 | D21: =_xlfn.XLOOKUP(B21,Códigos!$A$489:$A$522,Códigos!$B$489:$B$522,"Verificar",0) -> Ingresos Recibidos de terceros para pagos | E21: =_xlfn.XLOOKUP(C21,Códigos!$A$11:$A$415,Códigos!$B$11:$B$415,"Verificar",0) -> NOMBRE 44 | F21: 5824000 | H21: E | I21: =_xlfn.XLOOKUP(H21,Códigos!$A$489:$A$522,Códigos!$B$489:$B$522,"Verificar",0) -> Ingresos Recibidos de terceros para pagos | J21: =SUMIF(B21,H21,F21) -> 5824000
A22: 43846 | B22: D | C22: 65 | D22: =_xlfn.XLOOKUP(B22,Códigos!$A$489:$A$522,Códigos!$B$489:$B$522,"Verificar",0) -> Recibido por: -Otros ingresos Sin Facturación | E22: =_xlfn.XLOOKUP(C22,Códigos!$A$11:$A$415,Códigos!$B$11:$B$415,"Verificar",0) -> NOMBRE 44 | F22: =5900000-F21 -> 76000 | H22: D | I22: =_xlfn.XLOOKUP(H22,Códigos!$A$489:$A$522,Códigos!$B$489:$B$522,"Verificar",0) -> Recibido por: -Otros ingresos Sin Facturación | J22: =SUMIF(B22,H22,F22) -> 76000 | K22: =+J22+J21 -> 5900000
K23: OK/Consignación
A24: MOVIMIENTO DE EGRESOS DE CAJA DIARIO | H24: EGRESOS
A25: 43846 | B25: 29 | C25: 65 | D25: =_xlfn.XLOOKUP(B25,Códigos!$A$421:$A$483,Códigos!$B$421:$B$483,"Verificar",0) -> Egresos por Cuenta de Terceros -Pagos impuestos- | E25: =_xlfn.XLOOKUP(C25,Códigos!$A$11:$A$415,Códigos!$B$11:$B$415,"Verificar",0) -> NOMBRE 44 | F25: 5824000 | H25: 29 | I25: =_xlfn.XLOOKUP(H25,Códigos!$A$421:$A$483,Códigos!$B$421:$B$483,"Verificar",0) -> Egresos por Cuenta de Terceros -Pagos impuestos- | J25: =SUMIF(B25,H25,F25) -> 5824000 | K25: Se le paga el impto
A26: 43846 | B26: 33 | C26: 65 | D26: =_xlfn.XLOOKUP(B26,Códigos!$A$421:$A$483,Códigos!$B$421:$B$483,"Verificar",0) -> AJUSTE POR -Consignación - Traslado a Bancos | E26: =_xlfn.XLOOKUP(C26,Códigos!$A$11:$A$415,Códigos!$B$11:$B$415,"Verificar",0) -> NOMBRE 44 | F26: 76000 | H26: 33 | I26: =_xlfn.XLOOKUP(H26,Códigos!$A$421:$A$483,Códigos!$B$421:$B$483,"Verificar",0) -> AJUSTE POR -Consignación - Traslado a Bancos | J26: =SUMIF(B26,H26,F26) -> 76000 | K26: Nos queda a favor en el banco
A27: 43873 | B27: 31 | C27: 65 | D27: =_xlfn.XLOOKUP(B27,Códigos!$A$421:$A$483,Códigos!$B$421:$B$483,"Verificar",0) -> Egresos por Cuenta de Terceros -Certificados y otros | E27: =_xlfn.XLOOKUP(C27,Códigos!$A$11:$A$415,Códigos!$B$11:$B$415,"Verificar",0) -> NOMBRE 44 | F27: 6100 | H27: 31 | I27: =_xlfn.XLOOKUP(H27,Códigos!$A$421:$A$483,Códigos!$B$421:$B$483,"Verificar",0) -> Egresos por Cuenta de Terceros -Certificados y otros | J27: =SUMIF(B27,H27,F27) -> 6100
I28: OK/Equivale a que sacamos y prestamos efectivo | J28: =+J21+J22-J25-J26-J27 -> -6100
C29: CARTERA del año
C30: CÓD | D30: APELLIDOS Y NOMBRES o RAZÓN SOCIAL DEL CLIENTE o TERCERO | E30: SALDOS POR COBRAR AÑOS ANTERIORES | F30: ABONOS EN EL AÑO | G30: FACTURAS y CUENTAS DE COBRO DEL AÑO | H30: INGRESOS EN EL AÑO | I30: EGRESOS EN EL AÑO | J30: SALDO TOTAL PENDIENTE POR COBRAR
C31: 65 | D31: =_xlfn.XLOOKUP(C31,Códigos!$A$11:$A$415,Códigos!$B$11:$B$415,"Verificar",0) -> NOMBRE 44 | E31: =SUMIF('CARTERA años anteriores'!$C$9:$C$133,C31,'CARTERA años anteriores'!$J$9:$J$133) -> 0 | F31: =SUMIF('CARTERA años anteriores'!$C$9:$C$133,C31,'CARTERA años anteriores'!$L$9:$L$133) -> 0 | G31: =SUMIF(FACTURACIÓN!$C$8:$C$1082,C31,FACTURACIÓN!$K$8:$K$1082) -> 4170000 | H31: =SUMIF('INGRESOS A CAJA'!$C$10:$C$954,C31,'INGRESOS A CAJA'!$F$10:$F$954) -> 0 | I31: =SUMIF('EGRESOS DE CAJA'!$C$10:$C$2251,C31,'EGRESOS DE CAJA'!$G$10:$G$2251) -> 0 | J31: =+E31-F31+G31-H31+I31 -> 4170000
A34: CONSIGNACIÓN POR IDENTIFICAR
A35: MOVIMIENTO DE INGRESOS A CAJA DIARIO | G35: CONTRA | H35: INGRESOS
A36: 43839 | B36: J | C36: 0 | D36: =_xlfn.XLOOKUP(B36,Códigos!$A$489:$A$522,Códigos!$B$489:$B$522,"Verificar",0) -> -Consignaciones pendientes de identificar | E36: =_xlfn.XLOOKUP(C36,Códigos!$A$11:$A$415,Códigos!$B$11:$B$415,"Verificar",0) -> CONSIGNACIÓN POR IDENTIFICAR | F36: 1000000 | H36: J | I36: =_xlfn.XLOOKUP(H36,Códigos!$A$489:$A$522,Códigos!$B$489:$B$522,"Verificar",0) -> -Consignaciones pendientes de identificar | J36: =SUMIF(B36,H36,F36) -> 1000000
A37: MOVIMIENTO DE EGRESOS DE CAJA DIARIO | H37: EGRESOS
A38: 43839 | B38: 34 | C38: 0 | D38: =_xlfn.XLOOKUP(B38,Códigos!$A$421:$A$483,Códigos!$B$421:$B$483,"Verificar",0) -> AJUSTE POR -Consignaciones pendientes de identificar | E38: =_xlfn.XLOOKUP(C38,Códigos!$A$11:$A$415,Códigos!$B$11:$B$415,"Verificar",0) -> CONSIGNACIÓN POR IDENTIFICAR | F38: 1000000 | H38: 34 | I38: =_xlfn.XLOOKUP(H38,Códigos!$A$421:$A$483,Códigos!$B$421:$B$483,"Verificar",0) -> AJUSTE POR -Consignaciones pendientes de identificar | J38: =SUMIF(B38,H38,F38) -> 1000000
A40: MOVIMIENTO DE INGRESOS A CAJA DIARIO
A41: 43847 | B41: J | C41: 0 | D41: =_xlfn.XLOOKUP(B41,Códigos!$A$489:$A$522,Códigos!$B$489:$B$522,"Verificar",0) -> -Consignaciones pendientes de identificar | E41: =_xlfn.XLOOKUP(C41,Códigos!$A$11:$A$415,Códigos!$B$11:$B$415,"Verificar",0) -> CONSIGNACIÓN POR IDENTIFICAR | F41: 1500000 | H41: J | I41: =_xlfn.XLOOKUP(H41,Códigos!$A$489:$A$522,Códigos!$B$489:$B$522,"Verificar",0) -> -Consignaciones pendientes de identificar | J41: =SUMIF(B41,H41,F41) -> 1500000
A42: MOVIMIENTO DE EGRESOS DE CAJA DIARIO | H42: EGRESOS
A43: 43847 | B43: 34 | C43: 0 | D43: =_xlfn.XLOOKUP(B43,Códigos!$A$421:$A$483,Códigos!$B$421:$B$483,"Verificar",0) -> AJUSTE POR -Consignaciones pendientes de identificar | E43: =_xlfn.XLOOKUP(C43,Códigos!$A$11:$A$415,Códigos!$B$11:$B$415,"Verificar",0) -> CONSIGNACIÓN POR IDENTIFICAR | F43: 1500000 | H43: 34 | I43: =_xlfn.XLOOKUP(H43,Códigos!$A$421:$A$483,Códigos!$B$421:$B$483,"Verificar",0) -> AJUSTE POR -Consignaciones pendientes de identificar | J43: =SUMIF(B43,H43,F43) -> 1500000 | K43: Para no distorsionar la caja
I44: OK/Efecto neutro | J44: =+J36+J41-J38-J43 -> 0
H45: ACUMULADOS DE CAJA
H46: J | I46: =_xlfn.XLOOKUP(H46,Códigos!$A$489:$A$522,Códigos!$B$489:$B$522,"Verificar",0) -> -Consignaciones pendientes de identificar | J46: =SUMIF('INGRESOS A CAJA'!$B$9:$B$4452,H46,'INGRESOS A CAJA'!$F$9:$F$4452) -> 0 | K46: OK/Saldo final
A49: LEMOS DE GONZÁLEZ AMPARO DE JESÚS
A50: MOVIMIENTO DE INGRESOS A CAJA DIARIO | H50: INGRESOS
A51: 43848 | B51: C | C51: 122 | D51: =_xlfn.XLOOKUP(B51,Códigos!$A$489:$A$522,Códigos!$B$489:$B$522,"Verificar",0) -> Recibido por: -Cuentas de cobro -DAFF | E51: =_xlfn.XLOOKUP(C51,Códigos!$A$11:$A$415,Códigos!$B$11:$B$415,"Verificar",0) -> NOMBRE 191 | F51: 470000 | H51: C | I51: =_xlfn.XLOOKUP(H51,Códigos!$A$489:$A$522,Códigos!$B$489:$B$522,"Verificar",0) -> Recibido por: -Cuentas de cobro -DAFF | J51: =SUMIF(B51,H51,F51) -> 470000
A52: MOVIMIENTO DE EGRESOS DE CAJA DIARIO | H52: EGRESOS
A53: 43848 | B53: 33 | C53: 122 | D53: =_xlfn.XLOOKUP(B53,Códigos!$A$421:$A$483,Códigos!$B$421:$B$483,"Verificar",0) -> AJUSTE POR -Consignación - Traslado a Bancos | E53: =_xlfn.XLOOKUP(C53,Códigos!$A$11:$A$415,Códigos!$B$11:$B$415,"Verificar",0) -> NOMBRE 191 | F53: 470000 | H53: 33 | I53: =_xlfn.XLOOKUP(H53,Códigos!$A$421:$A$483,Códigos!$B$421:$B$483,"Verificar",0) -> AJUSTE POR -Consignación - Traslado a Bancos | J53: =SUMIF(B53,H53,F53) -> 470000 | K53: Nos queda a favor en el banco
I54: OK/Efecto neutro | J54: =+J51-J53 -> 0
C55: CARTERA del año
C56: CÓD | D56: APELLIDOS Y NOMBRES o RAZÓN SOCIAL DEL CLIENTE o TERCERO | E56: SALDOS POR COBRAR AÑOS ANTERIORES | F56: ABONOS EN EL AÑO | G56: FACTURAS y CUENTAS DE COBRO DEL AÑO | H56: INGRESOS EN EL AÑO | I56: EGRESOS EN EL AÑO | J56: SALDO TOTAL PENDIENTE POR COBRAR
C57: 122 | D57: =_xlfn.XLOOKUP(C57,Códigos!$A$11:$A$415,Códigos!$B$11:$B$415,"Verificar",0) -> NOMBRE 191 | E57: =SUMIF('CARTERA años anteriores'!$C$9:$C$133,C57,'CARTERA años anteriores'!$J$9:$J$133) -> 0 | F57: =SUMIF('CARTERA años anteriores'!$C$9:$C$133,C57,'CARTERA años anteriores'!$L$9:$L$133) -> 0 | G57: =SUMIF(FACTURACIÓN!$C$8:$C$1082,C57,FACTURACIÓN!$K$8:$K$1082) -> 690000 | H57: =SUMIF('INGRESOS A CAJA'!$C$10:$C$954,C57,'INGRESOS A CAJA'!$F$10:$F$954) -> 0 | I57: =SUMIF('EGRESOS DE CAJA'!$C$10:$C$2251,C57,'EGRESOS DE CAJA'!$G$10:$G$2251) -> 0 | J57: =+E57-F57+G57-H57+I57 -> 690000
A61: CORRUFORMAS SAS
A62: MOVIMIENTO DE INGRESOS A CAJA DIARIO | H62: INGRESOS | K62: retiro pago impuestos
A63: 43850 | B63: I | C63: 262 | D63: =_xlfn.XLOOKUP(B63,Códigos!$A$489:$A$522,Códigos!$B$489:$B$522,"Verificar",0) -> -Retiros y Traslados de Bancos | E63: =_xlfn.XLOOKUP(C63,Códigos!$A$11:$A$415,Códigos!$B$11:$B$415,"Verificar",0) -> NOMBRE 95 | F63: =1797495-F64 -> 1042245 | H63: I | I63: =_xlfn.XLOOKUP(H63,Códigos!$A$489:$A$522,Códigos!$B$489:$B$522,"Verificar",0) -> -Retiros y Traslados de Bancos | J63: =SUMIF(B63,H63,F63) -> 1042245
A64: 43850 | B64: I | C64: 262 | D64: =_xlfn.XLOOKUP(B64,Códigos!$A$489:$A$522,Códigos!$B$489:$B$522,"Verificar",0) -> -Retiros y Traslados de Bancos | E64: =_xlfn.XLOOKUP(C64,Códigos!$A$11:$A$415,Códigos!$B$11:$B$415,"Verificar",0) -> NOMBRE 95 | F64: =795000-(79500/2) -> 755250 | H64: I | I64: =_xlfn.XLOOKUP(H64,Códigos!$A$489:$A$522,Códigos!$B$489:$B$522,"Verificar",0) -> -Retiros y Traslados de Bancos | J64: =SUMIF(B64,H64,F64) -> 755250
A65: 43850 | B65: E | C65: 8 | D65: =_xlfn.XLOOKUP(B65,Códigos!$A$489:$A$522,Códigos!$B$489:$B$522,"Verificar",0) -> Ingresos Recibidos de terceros para pagos | E65: =_xlfn.XLOOKUP(C65,Códigos!$A$11:$A$415,Códigos!$B$11:$B$415,"Verificar",0) -> NOMBRE 64 | F65: =2089000+35000 -> 2124000 | H65: E | I65: =_xlfn.XLOOKUP(H65,Códigos!$A$489:$A$522,Códigos!$B$489:$B$522,"Verificar",0) -> Ingresos Recibidos de terceros para pagos | J65: =SUMIF(B65,H65,F65) -> 2124000 | K65: Consignacion Corruformas 2.132.496
A66: 43850 | B66: D | C66: 8 | D66: =_xlfn.XLOOKUP(B66,Códigos!$A$489:$A$522,Códigos!$B$489:$B$522,"Verificar",0) -> Recibido por: -Otros ingresos Sin Facturación | E66: =_xlfn.XLOOKUP(C66,Códigos!$A$11:$A$415,Códigos!$B$11:$B$415,"Verificar",0) -> NOMBRE 64 | F66: =2132496-F65 -> 8496 | H66: D | I66: =_xlfn.XLOOKUP(H66,Códigos!$A$489:$A$522,Códigos!$B$489:$B$522,"Verificar",0) -> Recibido por: -Otros ingresos Sin Facturación | J66: =SUMIF(B66,H66,F66) -> 8496 | K66: =SUM(J65:J66) -> 2132496
K67: OK/Consignación
K68: Retiro para hacer pagos -En DAFF
A69: MOVIMIENTO DE EGRESOS DE CAJA DIARIO | E69: Se retiró para pagar: | H69: EGRESOS | K69: 3921495
A70: 43850 | B70: 29 | C70: 8 | D70: =_xlfn.XLOOKUP(B70,Códigos!$A$421:$A$483,Códigos!$B$421:$B$483,"Verificar",0) -> Egresos por Cuenta de Terceros -Pagos impuestos- | E70: =_xlfn.XLOOKUP(C70,Códigos!$A$11:$A$415,Códigos!$B$11:$B$415,"Verificar",0) -> NOMBRE 64 | F70: =2089000+35000 -> 2124000 | H70: 29 | I70: =_xlfn.XLOOKUP(H70,Códigos!$A$421:$A$483,Códigos!$B$421:$B$483,"Verificar",0) -> Egresos por Cuenta de Terceros -Pagos impuestos- | J70: =SUMIF(B70,H70,F70) -> 2124000 | K70: =SUM(J70+J72+J73) -> 3921495
A71: 43850 | B71: 33 | C71: 8 | D71: =_xlfn.XLOOKUP(B71,Códigos!$A$421:$A$483,Códigos!$B$421:$B$483,"Verificar",0) -> AJUSTE POR -Consignación - Traslado a Bancos | E71: =_xlfn.XLOOKUP(C71,Códigos!$A$11:$A$415,Códigos!$B$11:$B$415,"Verificar",0) -> NOMBRE 64 | F71: =2132496-F70 -> 8496 | H71: 33 | I71: =_xlfn.XLOOKUP(H71,Códigos!$A$421:$A$483,Códigos!$B$421:$B$483,"Verificar",0) -> AJUSTE POR -Consignación - Traslado a Bancos | J71: =SUMIF(B71,H71,F71) -> 8496 | K71: Nos queda a favor en el banco
A72: 43850 | B72: 14 | C72: 361 | D72: =_xlfn.XLOOKUP(B72,Códigos!$A$421:$A$483,Códigos!$B$421:$B$483,"Verificar",0) -> Pagos de: -Seminarios y capacitaciones | E72: =_xlfn.XLOOKUP(C72,Códigos!$A$11:$A$415,Códigos!$B$11:$B$415,"Verificar",0) -> NOMBRE 49 | F72: =1797495-F73 -> 1042245 | H72: 14 | I72: =_xlfn.XLOOKUP(H72,Códigos!$A$421:$A$483,Códigos!$B$421:$B$483,"Verificar",0) -> Pagos de: -Seminarios y capacitaciones | J72: =SUMIF(B72,H72,F72) -> 1042245
A73: 43850 | B73: 28 | C73: 250 | D73: =_xlfn.XLOOKUP(B73,Códigos!$A$421:$A$483,Códigos!$B$421:$B$483,"Verificar",0) -> Préstamos a: | E73: =_xlfn.XLOOKUP(C73,Códigos!$A$11:$A$415,Códigos!$B$11:$B$415,"Verificar",0) -> NOMBRE 75 | F73: =795000-(79500/2) -> 755250 | H73: 28 | I73: =_xlfn.XLOOKUP(H73,Códigos!$A$421:$A$483,Códigos!$B$421:$B$483,"Verificar",0) -> Préstamos a: | J73: =SUMIF(B73,H73,F73) -> 755250
I74: OK/Efecto neutro | J74: =SUM(J63:J66)-SUM(J70:J73) -> 0 | K74: OK/Saldo final
A75: CORRUFORMAS SAS
A76: MOVIMIENTO DE INGRESOS A CAJA DIARIO | H76: INGRESOS | I76: Cuando el cliente consigna
A77: 43884 | B77: F | C77: 8 | D77: =_xlfn.XLOOKUP(B77,Códigos!$A$489:$A$522,Códigos!$B$489:$B$522,"Verificar",0) -> Recibido por: -Cuentas por Cobrar | E77: =_xlfn.XLOOKUP(C77,Códigos!$A$11:$A$415,Códigos!$B$11:$B$415,"Verificar",0) -> NOMBRE 64 | F77: 30000 | H77: F | I77: =_xlfn.XLOOKUP(H77,Códigos!$A$489:$A$522,Códigos!$B$489:$B$522,"Verificar",0) -> Recibido por: -Cuentas por Cobrar | J77: =SUMIF(B77,H77,F77) -> 30000
A79: MOVIMIENTO DE EGRESOS DE CAJA DIARIO | H79: EGRESOS | I79: Cuando se le presta o se le pagó la cuenta
A80: 43884 | B80: 33 | C80: 8 | D80: =_xlfn.XLOOKUP(B80,Códigos!$A$421:$A$483,Códigos!$B$421:$B$483,"Verificar",0) -> AJUSTE POR -Consignación - Traslado a Bancos | E80: =_xlfn.XLOOKUP(C80,Códigos!$A$11:$A$415,Códigos!$B$11:$B$415,"Verificar",0) -> NOMBRE 64 | F80: 30000 | H80: 28 | I80: =_xlfn.XLOOKUP(H80,Códigos!$A$421:$A$483,Códigos!$B$421:$B$483,"Verificar",0) -> Préstamos a: | K80: OJO - Hay que verfificar si es una cuenta por cobrar del año anterior o quedó faltando el asiento de lo que se le prestó este año.
I81: OJO -Será que falta el EGRESO | J81: =+J77-J80 -> 30000 | K81: - OJO -
C83: CARTERA del año
C84: CÓD | D84: APELLIDOS Y NOMBRES o RAZÓN SOCIAL DEL CLIENTE o TERCERO | E84: SALDOS POR COBRAR AÑOS ANTERIORES | F84: ABONOS EN EL AÑO | G84: FACTURAS y CUENTAS DE COBRO DEL AÑO | H84: INGRESOS EN EL AÑO | I84: EGRESOS EN EL AÑO | J84: SALDO TOTAL PENDIENTE POR COBRAR
C85: 8 | D85: =_xlfn.XLOOKUP(C85,Códigos!$A$11:$A$415,Códigos!$B$11:$B$415,"Verificar",0) -> NOMBRE 64 | E85: =SUMIF('CARTERA años anteriores'!$C$9:$C$133,C85,'CARTERA años anteriores'!$J$9:$J$133) -> 252000 | F85: =SUMIF('CARTERA años anteriores'!$C$9:$C$133,C85,'CARTERA años anteriores'!$L$9:$L$133) -> 0 | G85: =SUMIF(FACTURACIÓN!$C$8:$C$1082,C85,FACTURACIÓN!$K$8:$K$1082) -> 0 | H85: =SUMIF('INGRESOS A CAJA'!$C$10:$C$954,C85,'INGRESOS A CAJA'!$F$10:$F$954) -> 0 | I85: =SUMIF('EGRESOS DE CAJA'!$C$10:$C$2251,C85,'EGRESOS DE CAJA'!$G$10:$G$2251) -> 900100 | J85: =+E85-F85+G85-H85+I85 -> 1152100 | K85: Revisar el porque queda saldo diferente a los 470.000
A90: FERNÁNDEZ RESTREPO ÁLVARO
A91: MOVIMIENTO DE INGRESOS A CAJA DIARIO | H91: INGRESOS | I91: Cuando el cliente consigna
A92: 43850 | B92: F | C92: 222 | D92: =_xlfn.XLOOKUP(B92,Códigos!$A$489:$A$522,Códigos!$B$489:$B$522,"Verificar",0) -> Recibido por: -Cuentas por Cobrar | E92: =_xlfn.XLOOKUP(C92,Códigos!$A$11:$A$415,Códigos!$B$11:$B$415,"Verificar",0) -> NOMBRE 101 | H92: F | I92: =_xlfn.XLOOKUP(H92,Códigos!$A$489:$A$522,Códigos!$B$489:$B$522,"Verificar",0) -> Recibido por: -Cuentas por Cobrar | J92: =SUMIF(B92,H92,F92) -> 0
A93: 43857 | B93: F | C93: 222 | D93: =_xlfn.XLOOKUP(B93,Códigos!$A$489:$A$522,Códigos!$B$489:$B$522,"Verificar",0) -> Recibido por: -Cuentas por Cobrar | E93: =_xlfn.XLOOKUP(C93,Códigos!$A$11:$A$415,Códigos!$B$11:$B$415,"Verificar",0) -> NOMBRE 101 | F93: 547200 | H93: F | I93: =_xlfn.XLOOKUP(H93,Códigos!$A$489:$A$522,Códigos!$B$489:$B$522,"Verificar",0) -> Recibido por: -Cuentas por Cobrar | J93: =SUMIF(B93,H93,F93) -> 547200
A94: 43878 | B94: F | C94: 222 | D94: =_xlfn.XLOOKUP(B94,Códigos!$A$489:$A$522,Códigos!$B$489:$B$522,"Verificar",0) -> Recibido por: -Cuentas por Cobrar | E94: =_xlfn.XLOOKUP(C94,Códigos!$A$11:$A$415,Códigos!$B$11:$B$415,"Verificar",0) -> NOMBRE 101 | F94: 254500 | H94: F | I94: =_xlfn.XLOOKUP(H94,Códigos!$A$489:$A$522,Códigos!$B$489:$B$522,"Verificar",0) -> Recibido por: -Cuentas por Cobrar | J94: =SUMIF(B94,H94,F94) -> 254500
A95: 43903 | B95: F | C95: 222 | D95: =_xlfn.XLOOKUP(B95,Códigos!$A$489:$A$522,Códigos!$B$489:$B$522,"Verificar",0) -> Recibido por: -Cuentas por Cobrar | E95: =_xlfn.XLOOKUP(C95,Códigos!$A$11:$A$415,Códigos!$B$11:$B$415,"Verificar",0) -> NOMBRE 101 | F95: 547200 | H95: F | I95: =_xlfn.XLOOKUP(H95,Códigos!$A$489:$A$522,Códigos!$B$489:$B$522,"Verificar",0) -> Recibido por: -Cuentas por Cobrar | J95: =SUMIF(B95,H95,F95) -> 547200
A98: MOVIMIENTO DE EGRESOS DE CAJA DIARIO | H98: EGRESOS | I98: Cuando se le pagan las cuentas: (se le presta)
A99: 43844 | B99: 28 | C99: 222 | D99: =_xlfn.XLOOKUP(B99,Códigos!$A$421:$A$483,Códigos!$B$421:$B$483,"Verificar",0) -> Préstamos a: | E99: =_xlfn.XLOOKUP(C99,Códigos!$A$11:$A$415,Códigos!$B$11:$B$415,"Verificar",0) -> NOMBRE 101 | F99: 547200 | H99: 28 | I99: =_xlfn.XLOOKUP(H99,Códigos!$A$421:$A$483,Códigos!$B$421:$B$483,"Verificar",0) -> Préstamos a: | J99: =SUMIF(B99,H99,F99) -> 547200
A100: 43857 | B100: 33 | C100: 355 | D100: =_xlfn.XLOOKUP(B100,Códigos!$A$421:$A$483,Códigos!$B$421:$B$483,"Verificar",0) -> AJUSTE POR -Consignación - Traslado a Bancos | E100: =_xlfn.XLOOKUP(C100,Códigos!$A$11:$A$415,Códigos!$B$11:$B$415,"Verificar",0) -> NOMBRE 96 | F100: 547200 | G100: Consigna Alvaro Fernandez -OJO- voy a suponer que es el pago de la admon y no una consig porque en el mvto de bancos no aparece | H100: 33 | I100: =_xlfn.XLOOKUP(H100,Códigos!$A$421:$A$483,Códigos!$B$421:$B$483,"Verificar",0) -> AJUSTE POR -Consignación - Traslado a Bancos | J100: =SUMIF(B100,H100,F100) -> 547200 | K100: Será que era el pago de la admon y no una consignac de AFR
A101: 43874 | B101: 28 | C101: 222 | D101: =_xlfn.XLOOKUP(B101,Códigos!$A$421:$A$483,Códigos!$B$421:$B$483,"Verificar",0) -> Préstamos a: | E101: =_xlfn.XLOOKUP(C101,Códigos!$A$11:$A$415,Códigos!$B$11:$B$415,"Verificar",0) -> NOMBRE 101 | F101: 254500 | H101: 28 | I101: =_xlfn.XLOOKUP(H101,Códigos!$A$421:$A$483,Códigos!$B$421:$B$483,"Verificar",0) -> Préstamos a: | J101: =SUMIF(B101,H101,F101) -> 254500
A102: 43902 | B102: 28 | C102: 222 | D102: =_xlfn.XLOOKUP(B102,Códigos!$A$421:$A$483,Códigos!$B$421:$B$483,"Verificar",0) -> Préstamos a: | E102: =_xlfn.XLOOKUP(C102,Códigos!$A$11:$A$415,Códigos!$B$11:$B$415,"Verificar",0) -> NOMBRE 101 | F102: 547200 | H102: 28 | I102: =_xlfn.XLOOKUP(H102,Códigos!$A$421:$A$483,Códigos!$B$421:$B$483,"Verificar",0) -> Préstamos a: | J102: =SUMIF(B102,H102,F102) -> 547200
I103: OJO -DUPLICA el EGRESO ? | J103: =SUM(J93:J95)-SUM(J98:J102) -> -547200 | K103: 27-ene-20: Consigna Alvaro Fernandez -OJO- voy a suponer que es el pago de la admon y no una consig porque en el mvto de bancos no aparece
C104: CARTERA del año
C105: CÓD | D105: APELLIDOS Y NOMBRES o RAZÓN SOCIAL DEL CLIENTE o TERCERO | E105: SALDOS POR COBRAR AÑOS ANTERIORES | F105: ABONOS EN EL AÑO | G105: FACTURAS y CUENTAS DE COBRO DEL AÑO | H105: INGRESOS EN EL AÑO | I105: EGRESOS EN EL AÑO | J105: SALDO TOTAL PENDIENTE POR COBRAR
C106: 222 | D106: =_xlfn.XLOOKUP(C106,Códigos!$A$11:$A$415,Códigos!$B$11:$B$415,"Verificar",0) -> NOMBRE 101 | E106: =SUMIF('CARTERA años anteriores'!$C$9:$C$133,C106,'CARTERA años anteriores'!$J$9:$J$133) -> 3280000 | F106: =SUMIF('CARTERA años anteriores'!$C$9:$C$133,C106,'CARTERA años anteriores'!$L$9:$L$133) -> 0 | G106: =SUMIF(FACTURACIÓN!$C$8:$C$1082,C106,FACTURACIÓN!$K$8:$K$1082) -> 4880000 | H106: =SUMIF('INGRESOS A CAJA'!$C$10:$C$954,C106,'INGRESOS A CAJA'!$F$10:$F$954) -> 0 | I106: =SUMIF('EGRESOS DE CAJA'!$C$10:$C$2251,C106,'EGRESOS DE CAJA'!$G$10:$G$2251) -> 2929800 | J106: =+E106-F106+G106-H106+I106 -> 11089800
A109: -Retiros y Traslados de Bancos
A110: MOVIMIENTO DE INGRESOS A CAJA DIARIO | H110: INGRESOS | I110: Cuando se retira o transfiere (Sale del banco entra a caja)
A111: 43895 | B111: I | C111: 262 | D111: =_xlfn.XLOOKUP(B111,Códigos!$A$489:$A$522,Códigos!$B$489:$B$522,"Verificar",0) -> -Retiros y Traslados de Bancos | E111: =_xlfn.XLOOKUP(C111,Códigos!$A$11:$A$415,Códigos!$B$11:$B$415,"Verificar",0) -> NOMBRE 95 | F111: 600000 | H111: I | I111: =_xlfn.XLOOKUP(H111,Códigos!$A$489:$A$522,Códigos!$B$489:$B$522,"Verificar",0) -> -Retiros y Traslados de Bancos | J111: =SUMIF(B111,H111,F111) -> 600000 | K111: Se transfiere de DAFF a GTFF
A112: 43902 | B112: I | C112: 262 | D112: =_xlfn.XLOOKUP(B112,Códigos!$A$489:$A$522,Códigos!$B$489:$B$522,"Verificar",0) -> -Retiros y Traslados de Bancos | E112: =_xlfn.XLOOKUP(C112,Códigos!$A$11:$A$415,Códigos!$B$11:$B$415,"Verificar",0) -> NOMBRE 95 | F112: 500000 | H112: I | I112: =_xlfn.XLOOKUP(H112,Códigos!$A$489:$A$522,Códigos!$B$489:$B$522,"Verificar",0) -> -Retiros y Traslados de Bancos | J112: =SUMIF(B112,H112,F112) -> 500000 | K112: OK/Efecto neutro
A114: MOVIMIENTO DE EGRESOS DE CAJA DIARIO | H114: EGRESOS | I114: Cuando va a quedar en el banco va como consignación, si se transfirie a otra cuenta va como pago (Sale de caja para otro banco o para hacer pagos)
A115: 43895 | B115: 33 | C115: 355 | D115: =_xlfn.XLOOKUP(B115,Códigos!$A$421:$A$483,Códigos!$B$421:$B$483,"Verificar",0) -> AJUSTE POR -Consignación - Traslado a Bancos | E115: =_xlfn.XLOOKUP(C115,Códigos!$A$11:$A$415,Códigos!$B$11:$B$415,"Verificar",0) -> NOMBRE 96 | F115: 600000 | H115: 33 | I115: =_xlfn.XLOOKUP(H115,Códigos!$A$421:$A$483,Códigos!$B$421:$B$483,"Verificar",0) -> AJUSTE POR -Consignación - Traslado a Bancos | J115: =SUMIF(B115,H115,F115) -> 600000 | K115: Sale de la caja para el banco para que no la infle. -Con lo transferido se pagan gastos? Hay que verificar | M115: OK/Efecto neutro
A116: 43902 | B116: 8 | C116: 283 | D116: =_xlfn.XLOOKUP(B116,Códigos!$A$421:$A$483,Códigos!$B$421:$B$483,"Verificar",0) -> Pagos de: -Cuota para alimentos y Manuntención | E116: =_xlfn.XLOOKUP(C116,Códigos!$A$11:$A$415,Códigos!$B$11:$B$415,"Verificar",0) -> NOMBRE 104 | F116: 500000 | H116: 8 | I116: =_xlfn.XLOOKUP(H116,Códigos!$A$421:$A$483,Códigos!$B$421:$B$483,"Verificar",0) -> Pagos de: -Cuota para alimentos y Manuntención | J116: =SUMIF(B116,H116,F116) -> 500000 | K116: OK/Efecto neutro
A119: RÍOS CORREA JAVIER ADOLFO
A120: MOVIMIENTO DE INGRESOS A CAJA DIARIO | H120: INGRESOS | I120: Cuando el cliente entrega la plata | K120: Concepto de DAFF
A121: 43887 | B121: F | C121: 298 | D121: =_xlfn.XLOOKUP(B121,Códigos!$A$489:$A$522,Códigos!$B$489:$B$522,"Verificar",0) -> Recibido por: -Cuentas por Cobrar | E121: =_xlfn.XLOOKUP(C121,Códigos!$A$11:$A$415,Códigos!$B$11:$B$415,"Verificar",0) -> NOMBRE 283 | F121: 253700 | G121: DUPLICADO? | H121: F | I121: =_xlfn.XLOOKUP(H121,Códigos!$A$489:$A$522,Códigos!$B$489:$B$522,"Verificar",0) -> Recibido por: -Cuentas por Cobrar | J121: =SUMIF(B121,H121,F121) -> 253700 | K121: Pago seguridad Social Javier Adolfo Rios
A122: 43888 | B122: F | C122: 298 | D122: =_xlfn.XLOOKUP(B122,Códigos!$A$489:$A$522,Códigos!$B$489:$B$522,"Verificar",0) -> Recibido por: -Cuentas por Cobrar | E122: =_xlfn.XLOOKUP(C122,Códigos!$A$11:$A$415,Códigos!$B$11:$B$415,"Verificar",0) -> NOMBRE 283 | F122: 253700 | G122: DUPLICADO? | H122: F | I122: =_xlfn.XLOOKUP(H122,Códigos!$A$489:$A$522,Códigos!$B$489:$B$522,"Verificar",0) -> Recibido por: -Cuentas por Cobrar | J122: =SUMIF(B122,H122,F122) -> 253700 | K122: pago prestamo
A124: MOVIMIENTO DE EGRESOS DE CAJA DIARIO | H124: EGRESOS | I124: Cuando se le pagó la cuenta o se le presta
A125: 43887 | B125: 30 | C125: 298 | D125: =_xlfn.XLOOKUP(B125,Códigos!$A$421:$A$483,Códigos!$B$421:$B$483,"Verificar",0) -> Egresos por Cuenta de Terceros -Seguridad social- | E125: =_xlfn.XLOOKUP(C125,Códigos!$A$11:$A$415,Códigos!$B$11:$B$415,"Verificar",0) -> NOMBRE 283 | F125: 253700 | H125: 30 | I125: =_xlfn.XLOOKUP(H125,Códigos!$A$421:$A$483,Códigos!$B$421:$B$483,"Verificar",0) -> Egresos por Cuenta de Terceros -Seguridad social- | J125: =SUMIF(B125,H125,F125) -> 253700 | K125: Pago seguridad Social Javier Adolfo Rios
J126: =SUM(J121:J123)-SUM(J125) -> 253700 | K126: Saldo final DUPLICADO
C127: CARTERA del año
C128: CÓD | D128: APELLIDOS Y NOMBRES o RAZÓN SOCIAL DEL CLIENTE o TERCERO | E128: SALDOS POR COBRAR AÑOS ANTERIORES | F128: ABONOS EN EL AÑO | G128: FACTURAS y CUENTAS DE COBRO DEL AÑO | H128: INGRESOS EN EL AÑO | I128: EGRESOS EN EL AÑO | J128: SALDO TOTAL PENDIENTE POR COBRAR
...

Sheet Códigos
A1: LIBRO DIARIO OFICINA
A2: BASE DE DATOS Y CÓDIGOS
A3: AÑO: | B3: 2025
A5: CÓDIGO | B5: APELLIDOS Y NOMBRES o RAZÓN SOCIAL DEL CLIENTE y CONCEPTO DEL CÓDIGO | C5: OBSERVACIONES
E6: Antes reorganización
A8: CLIENTES o TERCEROS
A9: CÓDIGO | B9: APELLIDOS Y NOMBRES o RAZÓN SOCIAL DEL CLIENTE o TERCERO | C9: OBSERVACIONES
A11: 0 | B11: CONSIGNACIÓN POR IDENTIFICAR
A12: 41 | B12: NOMBRE 1
A13: 346 | B13: NOMBRE 2
A14: 300 | B14: NOMBRE 3
A15: 312 | B15: NOMBRE 4
A16: 217 | B16: NOMBRE 5
A17: 42 | B17: NOMBRE 6
A18: 43 | B18: NOMBRE 7
A19: 44 | B19: NOMBRE 8
A20: 45 | B20: NOMBRE 9
A21: 172 | B21: NOMBRE 10
A22: 156 | B22: NOMBRE 11
... A37: 341 | B37: NOMBRE 26
A38: 260 | B38: NOMBRE 27 | C38: OJO -Revisar
A39: 225 | B39: NOMBRE 28
A40: 257 | B40: NOMBRE 29
A41: 56 | B41: NOMBRE 30
A42: 353 | B42: NOMBRE 31
A43: 218 | B43: NOMBRE 32
A44: 306 | B44: NOMBRE 33
A45: 270 | B45: NOMBRE 34
A46: 4 | B46: NOMBRE 35
A47: 59 | B47: NOMBRE 36
A48: 322 | B48: NOMBRE 37 | C48: OK/
A49: 271 | B49: NOMBRE 38
A50: 60 | B50: NOMBRE 39
A51: 61 | B51: NOMBRE 40
A52: 246 | B52: NOMBRE 41
A53: 62 | B53: NOMBRE 42
A54: 63 | B54: NOMBRE 43
A55: 65 | B55: NOMBRE 44
A56: 67 | B56: NOMBRE 45
A57: 279 | B57: NOMBRE 46
A58: 68 | B58: NOMBRE 47
A59: 236 | B59: NOMBRE 48
A60: 361 | B60: NOMBRE 49
... A84: 349 | B84: NOMBRE 73
A85: 227 | B85: NOMBRE 74 | C85: OJO -Revisar
A86: 250 | B86: NOMBRE 75
A87: 299 | B87: NOMBRE 76
A88: 295 | B88: NOMBRE 77
A89: 81 | B89: NOMBRE 78
A90: 39 | B90: NOMBRE 79
A91: 10 | B91: NOMBRE 80
A92: 272 | B92: NOMBRE 81
A93: 83 | B93: NOMBRE 82
A94: 84 | B94: NOMBRE 83
A95: 301 | B95: NOMBRE 84
A96: 329 | B96: NOMBRE 85
A97: 85 | B97: NOMBRE 86
... A308: 326 | B308: NOMBRE 297
A309: 243 | B309: NOMBRE 298 | C309: OJO -Revisar
A310: 175 | B310: NOMBRE 299
A311: 296 | B311: NOMBRE 300
A312: 176 | B312: NOMBRE 301
A313: 177 | B313: NOMBRE 302
A314: 234 | B314: NOMBRE 303
A315: 266 | B315: NOMBRE 304
A316: 317 | B316: NOMBRE 305
A317: 135 | B317: NOMBRE 306
A318: 178 | B318: NOMBRE 307
A319: 114 | B319: NOMBRE 308
A320: 319 | B320: NOMBRE 309
A321: 37 | B321: NOMBRE 310
... A380: 368 | B380: NOMBRE 369
A381: 369
A382: 370
A383: =+A382+1 -> 371
A384: =+A383+1 -> 372
A385: =+A384+1 -> 373
A386: =+A385+1 -> 374
A387: =+A386+1 -> 375
A388: =+A387+1 -> 376
A389: =+A388+1 -> 377
A390: =+A389+1 -> 378
A391: =+A390+1 -> 379
A392: =+A391+1 -> 380
E417: Antes reorganización
A418: EGRESOS o SALIDAS DE CAJA
A419: CÓDIGO | B419: CONCEPTO DEL CÓDIGO | C419: OBSERVACIONES
C420: Se utiliza cuando: | H420: Con MVTO:
A421: 1 | B421: Gastos personales | C421: Para gastos exclusivamente personales que no tengan que ver con la familia, la oficina y Barbosa, por ej: Pago de impuestos predial Medellín, vehículo, apartamento Ermita, mercados personales y demás. | D421: 1 | F421: 1 | G421: Germán Tulio Fernández | H421: SI | I421: IGUAL | J421: 1
A422: 2 | B422: Pago de Salarios a: | C422: Se pagan los Salarios cada semana. | D422: =+D421+1 -> 2 | F422: 2 | G422: Diego Alberto Fernández Fernández -Salarios asistente | H422: SI | I422: IGUAL | J422: =+J421+1 -> 2 | K422: OK/
A423: 3 | B423: Pago de Prestaciones sociales a: | C423: Se pagan las Liquidaciones del personal al final del año o por retiro. | D423: =+D422+1 -> 3 | F423: 3 | H423: NO | J423: =+J422+1 -> 3
A424: 4 | B424: Pago de Bonificación a: | C424: Se pagan Bonificaciones no incluidas en las liquidaciones del personal. | D424: =+D423+1 -> 4 | F424: 4 | G424: Préstamos por Nómina -Diego A. Fernández F. | H424: SI | I424: PASA AL: 5-14 | J424: =+J423+1 -> 4 | K424: OK/Actualiz
A425: 5 | B425: Préstamos por Nómina a: | C425: Se desembolsan préstamos a Diego A. Fernández F. | D425: =+D424+1 -> 5 | F425: 5 | H425: NO | J425: =+J424+1 -> 5
A426: 6 | B426: Préstamos por Nómina a: | C426: Se desembolsan préstamos a Felipe Bossio Zapata. | D426: =+D425+1 -> 6 | F426: 6 | G426: Seguridad Social | H426: SI | I426: PASA AL: 7 | J426: =+J425+1 -> 6 | K426: OK/Actualiz
A427: 7 | B427: Pagos de: -Seguridad Social | C427: Se pagan los aportes a la seguridad social de la oficina y personal cada mes. | D427: =+D426+1 -> 7 | F427: 7 | G427: Banda ancha internet UNE y servicios EPM | H427: SI | I427: PASA AL: 9-10-11 | J427: =+J426+1 -> 7 | K427: OK/Actualiz
A428: 8 | B428: Pagos de: -Cuota para alimentos y Manuntención | C428: Se hacen pagos a Libia y las niñas, a Choly, a Omar, a Juliana y DAFF (Mercado), NOTA: cualquier gasto para ALFF va a la cuenta de Gastos Barbosa (19). | D428: =+D427+1 -> 8 | F428: 8 | G428: Celulares | H428: SI | I428: PASA AL: 12 | J428: =+J427+1 -> 8 | K428: OK/Actualiz
A429: 9 | B429: Pagos de: -Servicios públicos -OFICINA- | C429: Se hacen pagos sólo de UNE y EPM que tengan que ver con la Oficina, NOTA: los de Babilonia (8) y Ermita (1) se cargan aparte a cada uno y los de Barbosa dentro de Gastos Barbosa (19). | D429: =+D428+1 -> 9 | F429: 9 | G429: CETA -Suscripción | H429: SI | I429: PASA AL: 13 | J429: =+J428+1 -> 9 | K429: OK/Actualiz
A430: 10 | B430: Pagos de: -Servicios públicos -NIÑAS- | C430: Se hacen pagos sólo de UNE y EPM de que tengan que ver con Babilonia. | D430: =+D429+1 -> 10 | F430: 10 | G430: Mantenimiento equipos | H430: NO | I430: PASA AL: 15 | J430: =+J429+1 -> 10 | K430: OK/Actualiz
A431: 11 | B431: Pagos de: -Servicios Administracion y otros Oficina | C431: Se hacen pagos sólo de UNE y EPM de que tengan que ver con la Ermita. | D431: =+D430+1 -> 11 | F431: 11 | G431: Mantenimiento Teléfonos | H431: NO | I431: PASA AL: 15 | J431: =+J430+1 -> 11 | K431: OK/Actualiz
A432: 12 | B432: Pagos de: -Celulares | C432: Se pagan los celulares de Libia y GTFF, (se debe discriminar por tercero). | D432: =+D431+1 -> 12 | F432: 12 | G432: Repuestos y reparaciones equipos oficina | H432: SI | I432: PASA AL: 15-22-32 | J432: =+J431+1 -> 12 | K432: OK/Actualiz
...

Sheet Hoja1
A1: LIBRO DIARIO OFICINA
A2: BASE DE DATOS Y CÓDIGOS
A3: AÑO: | B3: 2024
A5: CÓDIGO | B5: APELLIDOS Y NOMBRES o RAZÓN SOCIAL DEL CLIENTE y CONCEPTO DEL CÓDIGO | C5: OBSERVACIONES
E6: Antes reorganización
A8: CLIENTES o TERCEROS
A9: CÓDIGO | B9: APELLIDOS Y NOMBRES o RAZÓN SOCIAL DEL CLIENTE o TERCERO | C9: OBSERVACIONES
A11: 0 | B11: NOMBRE 1
A12: 1 | B12: NOMBRE 2
A13: 2 | B13: NOMBRE 3
A14: 3 | B14: NOMBRE 4
A15: 4 | B15: NOMBRE 5
A16: 5 | B16: NOMBRE 6
A17: 6 | B17: NOMBRE 7
A18: 7 | B18: NOMBRE 8
A19: 8 | B19: NOMBRE 9
A20: 9 | B20: NOMBRE 10
A21: 10 | B21: NOMBRE 11
A22: 11 | B22: NOMBRE 12
... A37: 27 | B37: NOMBRE 27
A38: 28 | B38: NOMBRE 28 | C38: OJO -Revisar
A39: 29 | B39: NOMBRE 29
A40: 30 | B40: NOMBRE 30
A41: 31 | B41: NOMBRE 31
A42: 32 | B42: NOMBRE 32
A43: 33 | B43: NOMBRE 33
A44: 34 | B44: NOMBRE 34
A45: 34 | B45: NOMBRE 35
A46: 35 | B46: NOMBRE 36
A47: 36 | B47: NOMBRE 37
A48: 37 | B48: NOMBRE 38 | C48: OK/
A49: 38 | B49: NOMBRE 39
A50: 39 | B50: NOMBRE 40
A51: 40 | B51: NOMBRE 41
A52: 41 | B52: NOMBRE 42
A53: 42 | B53: NOMBRE 43
A54: 43 | B54: NOMBRE 44
A55: 44 | B55: NOMBRE 45
A56: 45 | B56: NOMBRE 46
A57: 46 | B57: NOMBRE 47
A58: 47 | B58: NOMBRE 48
A59: 48 | B59: NOMBRE 49
A60: 49 | B60: NOMBRE 50
... A84: 73 | B84: NOMBRE 74
A85: 74 | B85: NOMBRE 75 | C85: OJO -Revisar
A86: 75 | B86: NOMBRE 76
A87: 76 | B87: NOMBRE 77
A88: 77 | B88: NOMBRE 78
A89: 78 | B89: NOMBRE 79
A90: 79 | B90: NOMBRE 80
A91: 80 | B91: NOMBRE 81
A92: 81 | B92: NOMBRE 82
A93: 82 | B93: NOMBRE 83
A94: 83 | B94: NOMBRE 84
A95: 84 | B95: NOMBRE 85
A96: 85 | B96: NOMBRE 86
A97: 86 | B97: NOMBRE 87
... A308: 297 | B308: NOMBRE 298
A309: 298 | B309: NOMBRE 299 | C309: OJO -Revisar
A310: 299 | B310: NOMBRE 300
A311: 300 | B311: NOMBRE 301
A312: 301 | B312: NOMBRE 302
A313: 302 | B313: NOMBRE 303
A314: 303 | B314: NOMBRE 304
A315: 304 | B315: NOMBRE 305
A316: 305 | B316: NOMBRE 306
A317: 306 | B317: NOMBRE 307
A318: 307 | B318: NOMBRE 308
A319: 308 | B319: NOMBRE 309
A320: 309 | B320: NOMBRE 310
A321: 310 | B321: NOMBRE 311
... A379: 368 | B379: NOMBRE 369
A380: 369
A381: 370
A382: =+A381+1 -> 371
A383: =+A382+1 -> 372
A384: =+A383+1 -> 373
A385: =+A384+1 -> 374
A386: =+A385+1 -> 375
A387: =+A386+1 -> 376
A388: =+A387+1 -> 377
A389: =+A388+1 -> 378
A390: =+A389+1 -> 379
A391: =+A390+1 -> 380
E416: Antes reorganización
A417: EGRESOS o SALIDAS DE CAJA
A418: CÓDIGO | B418: CONCEPTO DEL CÓDIGO | C418: OBSERVACIONES
C419: Se utiliza cuando: | H419: Con MVTO:
A420: 1 | B420: Gastos personales | C420: Para gastos exclusivamente personales que no tengan que ver con la familia, la oficina y Barbosa, por ej: Pago de impuestos predial Medellín, vehículo, apartamento Ermita, mercados personales y demás. | D420: 1 | F420: 1 | G420: Germán Tulio Fernández | H420: SI | I420: IGUAL | J420: 1
A421: 2 | B421: Pago de Salarios a: | C421: Se pagan los Salarios cada semana. | D421: =+D420+1 -> 2 | F421: 2 | G421: Diego Alberto Fernández Fernández -Salarios asistente | H421: SI | I421: IGUAL | J421: =+J420+1 -> 2 | K421: OK/
A422: 3 | B422: Pago de Prestaciones sociales a: | C422: Se pagan las Liquidaciones del personal al final del año o por retiro. | D422: =+D421+1 -> 3 | F422: 3 | H422: NO | J422: =+J421+1 -> 3
A423: 4 | B423: Pago de Bonificación a: | C423: Se pagan Bonificaciones no incluidas en las liquidaciones del personal. | D423: =+D422+1 -> 4 | F423: 4 | G423: Préstamos por Nómina -Diego A. Fernández F. | H423: SI | I423: PASA AL: 5-14 | J423: =+J422+1 -> 4 | K423: OK/Actualiz
A424: 5 | B424: Préstamos por Nómina a: | C424: Se desembolsan préstamos a Diego A. Fernández F. | D424: =+D423+1 -> 5 | F424: 5 | H424: NO | J424: =+J423+1 -> 5
A425: 6 | B425: Préstamos por Nómina a: | C425: Se desembolsan préstamos a Felipe Bossio Zapata. | D425: =+D424+1 -> 6 | F425: 6 | G425: Seguridad Social | H425: SI | I425: PASA AL: 7 | J425: =+J424+1 -> 6 | K425: OK/Actualiz
A426: 7 | B426: Pagos de: -Seguridad Social | C426: Se pagan los aportes a la seguridad social de la oficina y personal cada mes. | D426: =+D425+1 -> 7 | F426: 7 | G426: Banda ancha internet UNE y servicios EPM | H426: SI | I426: PASA AL: 9-10-11 | J426: =+J425+1 -> 7 | K426: OK/Actualiz
A427: 8 | B427: Pagos de: -Cuota para alimentos y Manuntención | C427: Se hacen pagos a Libia y las niñas, a Choly, a Omar, a Juliana y DAFF (Mercado), NOTA: cualquier gasto para ALFF va a la cuenta de Gastos Barbosa (19). | D427: =+D426+1 -> 8 | F427: 8 | G427: Celulares | H427: SI | I427: PASA AL: 12 | J427: =+J426+1 -> 8 | K427: OK/Actualiz
A428: 9 | B428: Pagos de: -Servicios públicos -OFICINA- | C428: Se hacen pagos sólo de UNE y EPM que tengan que ver con la Oficina, NOTA: los de Babilonia (8) y Ermita (1) se cargan aparte a cada uno y los de Barbosa dentro de Gastos Barbosa (19). | D428: =+D427+1 -> 9 | F428: 9 | G428: CETA -Suscripción | H428: SI | I428: PASA AL: 13 | J428: =+J427+1 -> 9 | K428: OK/Actualiz
A429: 10 | B429: Pagos de: -Servicios públicos -NIÑAS- | C429: Se hacen pagos sólo de UNE y EPM de que tengan que ver con Babilonia. | D429: =+D428+1 -> 10 | F429: 10 | G429: Mantenimiento equipos | H429: NO | I429: PASA AL: 15 | J429: =+J428+1 -> 10 | K429: OK/Actualiz
A430: 11 | B430: Pagos de: -Servicios públicos -ERMITA- | C430: Se hacen pagos sólo de UNE y EPM de que tengan que ver con la Ermita. | D430: =+D429+1 -> 11 | F430: 11 | G430: Mantenimiento Teléfonos | H430: NO | I430: PASA AL: 15 | J430: =+J429+1 -> 11 | K430: OK/Actualiz
A431: 12 | B431: Pagos de: -Celulares | C431: Se pagan los celulares de Libia y GTFF, (se debe discriminar por tercero). | D431: =+D430+1 -> 12 | F431: 12 | G431: Repuestos y reparaciones equipos oficina | H431: SI | I431: PASA AL: 15-22-32 | J431: =+J430+1 -> 12 | K431: OK/Actualiz
...

Sheet INGRESOS A CAJA
A1: =+Códigos!$A$1 -> LIBRO DIARIO OFICINA | F1: SALDO CRÉDITO ACUMULADO | G1: SALDO ACUMULADO | H1: La diferencia debe ser CERO (0). Si existe diferencia quiere decir que hay ERROR de formulas.
A2: MOVIMIENTO DE INGRESOS A CAJA DIARIO | F2: =F956 -> 634239583 | G2: =G956 -> 634239583 | H2: =+F2-G2 -> 0
A3: =+Códigos!$A$3 -> AÑO: | B3: 2025
A4: DESDE: | D4: 45658 | H4: =IF(H2=0,"OK Saldos","ERROR EN LAS OPERACIONES Verificar formulas") -> OK Saldos
A5: HASTA: | D5: 46022
A7: FECHA | B7: CÓDIGO DEL INGRESO | C7: CÓDIGO DEL TERCERO | D7: CONCEPTO DEL INGRESO | E7: APELLIDOS Y NOMBRES o RAZÓN SOCIAL DEL CLIENTE o TERCERO | F7: CRÉDITOS | G7: SALDO ACUMULADO | H7: DETALLE | I7: REVISIÓN
A10: =+D4 -> 45658 | F10: 0 | G10: =F10 -> 0
A12: 45659 | B12: I | C12: 5 | D12: =_xlfn.XLOOKUP(B12,Códigos!$A$489:$A$522,Códigos!$B$489:$B$522,"Verificar",0) -> -Retiros y Traslados de Bancos | E12: =_xlfn.XLOOKUP(C12,Códigos!$A$11:$A$415,Códigos!$B$11:$B$415,"Verificar",0) -> NOMBRE 25 | F12: 50000 | G12: =+G11+F12 -> 50000 | H12: Recarga Flypass Barbosa
A13: 45660 | B13: I | C13: 5 | D13: =_xlfn.XLOOKUP(B13,Códigos!$A$489:$A$522,Códigos!$B$489:$B$522,"Verificar",0) -> -Retiros y Traslados de Bancos | E13: =_xlfn.XLOOKUP(C13,Códigos!$A$11:$A$415,Códigos!$B$11:$B$415,"Verificar",0) -> NOMBRE 25 | F13: 500000 | G13: =+G12+F13 -> 550000 | H13: Traslado pedro pago camaras
A14: 45660 | B14: C | C14: 182 | D14: =_xlfn.XLOOKUP(B14,Códigos!$A$489:$A$522,Códigos!$B$489:$B$522,"Verificar",0) -> Recibido por: -Cuentas de cobro -DAFF | E14: =_xlfn.XLOOKUP(C14,Códigos!$A$11:$A$415,Códigos!$B$11:$B$415,"Verificar",0) -> NOMBRE 317 | F14: 1800000 | G14: =+G13+F14 -> 2350000 | H14: Pago Cuenta 24-105
A15: 45666 | B15: I | C15: 5 | D15: =_xlfn.XLOOKUP(B15,Códigos!$A$489:$A$522,Códigos!$B$489:$B$522,"Verificar",0) -> -Retiros y Traslados de Bancos | E15: =_xlfn.XLOOKUP(C15,Códigos!$A$11:$A$415,Códigos!$B$11:$B$415,"Verificar",0) -> NOMBRE 25 | F15: 47500 | G15: =+G14+F15 -> 2397500 | H15: Pago Movistar Diego
A16: 45670 | B16: I | C16: 5 | D16: =_xlfn.XLOOKUP(B16,Códigos!$A$489:$A$522,Códigos!$B$489:$B$522,"Verificar",0) -> -Retiros y Traslados de Bancos | E16: =_xlfn.XLOOKUP(C16,Códigos!$A$11:$A$415,Códigos!$B$11:$B$415,"Verificar",0) -> NOMBRE 25 | F16: 125800 | G16: =+G15+F16 -> 2523300 | H16: Pago Tigo Babilonia enero
A17: 45671 | B17: I | C17: 5 | D17: =_xlfn.XLOOKUP(B17,Códigos!$A$489:$A$522,Códigos!$B$489:$B$522,"Verificar",0) -> -Retiros y Traslados de Bancos | E17: =_xlfn.XLOOKUP(C17,Códigos!$A$11:$A$415,Códigos!$B$11:$B$415,"Verificar",0) -> NOMBRE 25 | F17: 1000600 | G17: =+G16+F17 -> 3523900 | H17: Pago Seguridad Social Empleados febrero
A18: 45671 | B18: I | C18: 5 | D18: =_xlfn.XLOOKUP(B18,Códigos!$A$489:$A$522,Códigos!$B$489:$B$522,"Verificar",0) -> -Retiros y Traslados de Bancos | E18: =_xlfn.XLOOKUP(C18,Códigos!$A$11:$A$415,Códigos!$B$11:$B$415,"Verificar",0) -> NOMBRE 25 | F18: 897800 | G18: =+G17+F18 -> 4421700 | H18: Pago Seguridad Social Independiente enero
A19: 45671 | B19: I | C19: 5 | D19: =_xlfn.XLOOKUP(B19,Códigos!$A$489:$A$522,Códigos!$B$489:$B$522,"Verificar",0) -> -Retiros y Traslados de Bancos | E19: =_xlfn.XLOOKUP(C19,Códigos!$A$11:$A$415,Códigos!$B$11:$B$415,"Verificar",0) -> NOMBRE 25 | F19: 350000 | G19: =+G18+F19 -> 4771700 | H19: Abono intererses cuota enero 2025
A20: 45671 | B20: I | C20: 5 | D20: =_xlfn.XLOOKUP(B20,Códigos!$A$489:$A$522,Códigos!$B$489:$B$522,"Verificar",0) -> -Retiros y Traslados de Bancos | E20: =_xlfn.XLOOKUP(C20,Códigos!$A$11:$A$415,Códigos!$B$11:$B$415,"Verificar",0) -> NOMBRE 25 | F20: 200000 | G20: =+G19+F20 -> 4971700 | H20: Abono a deuda enero 2025
A21: 45671 | B21: I | C21: 5 | D21: =_xlfn.XLOOKUP(B21,Códigos!$A$489:$A$522,Códigos!$B$489:$B$522,"Verificar",0) -> -Retiros y Traslados de Bancos | E21: =_xlfn.XLOOKUP(C21,Códigos!$A$11:$A$415,Códigos!$B$11:$B$415,"Verificar",0) -> NOMBRE 25 | F21: 89300 | G21: =+G20+F21 -> 5061000 | H21: Pago EPM Barbosa
A22: 45671 | B22: I | C22: 5 | D22: =_xlfn.XLOOKUP(B22,Códigos!$A$489:$A$522,Códigos!$B$489:$B$522,"Verificar",0) -> -Retiros y Traslados de Bancos | E22: =_xlfn.XLOOKUP(C22,Códigos!$A$11:$A$415,Códigos!$B$11:$B$415,"Verificar",0) -> NOMBRE 25 | F22: 67800 | G22: =+G21+F22 -> 5128800 | H22: Pago EPM Carolina
A23: 45671 | B23: I | C23: 5 | D23: =_xlfn.XLOOKUP(B23,Códigos!$A$489:$A$522,Códigos!$B$489:$B$522,"Verificar",0) -> -Retiros y Traslados de Bancos | E23: =_xlfn.XLOOKUP(C23,Códigos!$A$11:$A$415,Códigos!$B$11:$B$415,"Verificar",0) -> NOMBRE 25 | F23: =1030000-F25-F24 -> 170000 | G23: =+G22+F23 -> 5298800 | H23: Pago cita perros
A24: 45671 | B24: I | C24: 5 | D24: =_xlfn.XLOOKUP(B24,Códigos!$A$489:$A$522,Códigos!$B$489:$B$522,"Verificar",0) -> -Retiros y Traslados de Bancos | E24: =_xlfn.XLOOKUP(C24,Códigos!$A$11:$A$415,Códigos!$B$11:$B$415,"Verificar",0) -> NOMBRE 25 | F24: 200000 | G24: =+G23+F24 -> 5498800 | H24: Pago mesada tranporte U de A
A25: 45671 | B25: I | C25: 5 | D25: =_xlfn.XLOOKUP(B25,Códigos!$A$489:$A$522,Códigos!$B$489:$B$522,"Verificar",0) -> -Retiros y Traslados de Bancos | E25: =_xlfn.XLOOKUP(C25,Códigos!$A$11:$A$415,Códigos!$B$11:$B$415,"Verificar",0) -> NOMBRE 25 | F25: 660000 | G25: =+G24+F25 -> 6158800 | H25: Mesada Semana 13 al 19 enero
A26: 45671 | B26: A | C26: 25 | D26: =_xlfn.XLOOKUP(B26,Códigos!$A$489:$A$522,Códigos!$B$489:$B$522,"Verificar",0) -> Recibido por: -FACTURAS -GTFF | E26: =_xlfn.XLOOKUP(C26,Códigos!$A$11:$A$415,Códigos!$B$11:$B$415,"Verificar",0) -> NOMBRE 178 | F26: 5164600 | G26: =+G25+F26 -> 11323400 | H26: Pago factura GTFF-126
A27: 45671 | B27: A | C27: 158 | D27: =_xlfn.XLOOKUP(B27,Códigos!$A$489:$A$522,Códigos!$B$489:$B$522,"Verificar",0) -> Recibido por: -FACTURAS -GTFF | E27: =_xlfn.XLOOKUP(C27,Códigos!$A$11:$A$415,Códigos!$B$11:$B$415,"Verificar",0) -> NOMBRE 262 | F27: 3308200 | G27: =+G26+F27 -> 14631600 | H27: Pago factura GTFF-128
A28: 45671 | B28: A | C28: 296 | D28: =_xlfn.XLOOKUP(B28,Códigos!$A$489:$A$522,Códigos!$B$489:$B$522,"Verificar",0) -> Recibido por: -FACTURAS -GTFF | E28: =_xlfn.XLOOKUP(C28,Códigos!$A$11:$A$415,Códigos!$B$11:$B$415,"Verificar",0) -> NOMBRE 300 | F28: 1035300 | G28: =+G27+F28 -> 15666900 | H28: Pago factura GTFF-129
A29: 45671 | B29: A | C29: 25 | D29: =_xlfn.XLOOKUP(B29,Códigos!$A$489:$A$522,Códigos!$B$489:$B$522,"Verificar",0) -> Recibido por: -FACTURAS -GTFF | E29: =_xlfn.XLOOKUP(C29,Códigos!$A$11:$A$415,Códigos!$B$11:$B$415,"Verificar",0) -> NOMBRE 178 | F29: 4611600 | G29: =+G28+F29 -> 20278500 | H29: Pago factura GTFF-159
A30: 45671 | B30: A | C30: 158 | D30: =_xlfn.XLOOKUP(B30,Códigos!$A$489:$A$522,Códigos!$B$489:$B$522,"Verificar",0) -> Recibido por: -FACTURAS -GTFF | E30: =_xlfn.XLOOKUP(C30,Códigos!$A$11:$A$415,Códigos!$B$11:$B$415,"Verificar",0) -> NOMBRE 262 | F30: 3629500 | G30: =+G29+F30 -> 23908000 | H30: Pago factura GTFF-161
A31: 45671 | B31: A | C31: 296 | D31: =_xlfn.XLOOKUP(B31,Códigos!$A$489:$A$522,Códigos!$B$489:$B$522,"Verificar",0) -> Recibido por: -FACTURAS -GTFF | E31: =_xlfn.XLOOKUP(C31,Códigos!$A$11:$A$415,Códigos!$B$11:$B$415,"Verificar",0) -> NOMBRE 300 | F31: 1130500 | G31: =+G30+F31 -> 25038500 | H31: Pago factura GTFF-162
A32: 45671 | B32: I | C32: 3 | D32: =_xlfn.XLOOKUP(B32,Códigos!$A$489:$A$522,Códigos!$B$489:$B$522,"Verificar",0) -> -Retiros y Traslados de Bancos | E32: =_xlfn.XLOOKUP(C32,Códigos!$A$11:$A$415,Códigos!$B$11:$B$415,"Verificar",0) -> NOMBRE 24 | F32: 35000000 | G32: =+G31+F32 -> 60038500 | H32: Abono a deuda consignado Inversion Virtual
A33: 45672 | B33: C | C33: 133 | D33: =_xlfn.XLOOKUP(B33,Códigos!$A$489:$A$522,Códigos!$B$489:$B$522,"Verificar",0) -> Recibido por: -Cuentas de cobro -DAFF | E33: =_xlfn.XLOOKUP(C33,Códigos!$A$11:$A$415,Códigos!$B$11:$B$415,"Verificar",0) -> NOMBRE 216 | F33: 1160000 | G33: =+G32+F33 -> 61198500 | H33: Pago Cuenta 24-146
A34: 45672 | B34: I | C34: 3 | D34: =_xlfn.XLOOKUP(B34,Códigos!$A$489:$A$522,Códigos!$B$489:$B$522,"Verificar",0) -> -Retiros y Traslados de Bancos | E34: =_xlfn.XLOOKUP(C34,Códigos!$A$11:$A$415,Códigos!$B$11:$B$415,"Verificar",0) -> NOMBRE 24 | F34: 2000000 | G34: =+G33+F34 -> 63198500 | H34: Retiro por cajero
A35: 45673 | B35: I | C35: 5 | D35: =_xlfn.XLOOKUP(B35,Códigos!$A$489:$A$522,Códigos!$B$489:$B$522,"Verificar",0) -> -Retiros y Traslados de Bancos | E35: =_xlfn.XLOOKUP(C35,Códigos!$A$11:$A$415,Códigos!$B$11:$B$415,"Verificar",0) -> NOMBRE 25 | F35: 1026800 | G35: =+G34+F35 -> 64225300 | H35: Pago credito hipotecario
... A229: 45792 | B229: I | C229: 5 | D229: =_xlfn.XLOOKUP(B229,Códigos!$A$489:$A$522,Códigos!$B$489:$B$522,"Verificar",0) -> -Retiros y Traslados de Bancos | E229: =_xlfn.XLOOKUP(C229,Códigos!$A$11:$A$415,Códigos!$B$11:$B$415,"Verificar",0) -> NOMBRE 25 | F229: 660000 | G229: =+G228+F229 -> 404661294 | H229: Pago Nomina 12 al 18 mayo
A230: 45792 | B230: I | C230: 5 | D230: =_xlfn.XLOOKUP(B230,Códigos!$A$489:$A$522,Códigos!$B$489:$B$522,"Verificar",0) -> -Retiros y Traslados de Bancos | E230: =_xlfn.XLOOKUP(C230,Códigos!$A$11:$A$415,Códigos!$B$11:$B$415,"Verificar",0) -> NOMBRE 25 | F230: =1320000-F229-F228-2000 -> 438000 | G230: =+G229+F230 -> 405099294 | H230: Pago IMP PATR 2025
A231: 45793 | B231: I | C231: 5 | D231: =_xlfn.XLOOKUP(B231,Códigos!$A$489:$A$522,Códigos!$B$489:$B$522,"Verificar",0) -> -Retiros y Traslados de Bancos | E231: =_xlfn.XLOOKUP(C231,Códigos!$A$11:$A$415,Códigos!$B$11:$B$415,"Verificar",0) -> NOMBRE 25 | F231: 2000000 | G231: =+G230+F231 -> 407099294 | H231: Retiro por cajero
A232: 45793 | B232: I | C232: 5 | D232: =_xlfn.XLOOKUP(B232,Códigos!$A$489:$A$522,Códigos!$B$489:$B$522,"Verificar",0) -> -Retiros y Traslados de Bancos | E232: =_xlfn.XLOOKUP(C232,Códigos!$A$11:$A$415,Códigos!$B$11:$B$415,"Verificar",0) -> NOMBRE 25 | F232: 1026800 | G232: =+G231+F232 -> 408126094 | H232: Pago credito hipotecario
A233: 45797 | B233: I | C233: 5 | D233: =_xlfn.XLOOKUP(B233,Códigos!$A$489:$A$522,Códigos!$B$489:$B$522,"Verificar",0) -> -Retiros y Traslados de Bancos | E233: =_xlfn.XLOOKUP(C233,Códigos!$A$11:$A$415,Códigos!$B$11:$B$415,"Verificar",0) -> NOMBRE 25 | F233: =266130+383130 -> 649260 | G233: =+G232+F233 -> 408775354 | H233: Pago Administracion del Gaspar de Rodas
A234: 45799 | B234: I | C234: 5 | D234: =_xlfn.XLOOKUP(B234,Códigos!$A$489:$A$522,Códigos!$B$489:$B$522,"Verificar",0) -> -Retiros y Traslados de Bancos | E234: =_xlfn.XLOOKUP(C234,Códigos!$A$11:$A$415,Códigos!$B$11:$B$415,"Verificar",0) -> NOMBRE 25 | F234: 220000 | G234: =+G233+F234 -> 408995354 | H234: Pago mesada tranporte U de A
A235: 45799 | B235: I | C235: 5 | D235: =_xlfn.XLOOKUP(B235,Códigos!$A$489:$A$522,Códigos!$B$489:$B$522,"Verificar",0) -> -Retiros y Traslados de Bancos | E235: =_xlfn.XLOOKUP(C235,Códigos!$A$11:$A$415,Códigos!$B$11:$B$415,"Verificar",0) -> NOMBRE 25 | F235: 660000 | G235: =+G234+F235 -> 409655354 | H235: Pago Nomina 19 al 25 mayo
A236: 45799 | B236: I | C236: 5 | D236: =_xlfn.XLOOKUP(B236,Códigos!$A$489:$A$522,Códigos!$B$489:$B$522,"Verificar",0) -> -Retiros y Traslados de Bancos | E236: =_xlfn.XLOOKUP(C236,Códigos!$A$11:$A$415,Códigos!$B$11:$B$415,"Verificar",0) -> NOMBRE 25 | F236: 2000000 | G236: =+G235+F236 -> 411655354 | H236: Retiro por cajero
A237: 45805 | B237: I | C237: 5 | D237: =_xlfn.XLOOKUP(B237,Códigos!$A$489:$A$522,Códigos!$B$489:$B$522,"Verificar",0) -> -Retiros y Traslados de Bancos | E237: =_xlfn.XLOOKUP(C237,Códigos!$A$11:$A$415,Códigos!$B$11:$B$415,"Verificar",0) -> NOMBRE 25 | F237: 2000000 | G237: =+G236+F237 -> 413655354 | H237: Retiro por cajero
A238: 45805 | B238: I | C238: 5 | D238: =_xlfn.XLOOKUP(B238,Códigos!$A$489:$A$522,Códigos!$B$489:$B$522,"Verificar",0) -> -Retiros y Traslados de Bancos | E238: =_xlfn.XLOOKUP(C238,Códigos!$A$11:$A$415,Códigos!$B$11:$B$415,"Verificar",0) -> NOMBRE 25 | F238: 220000 | G238: =+G237+F238 -> 413875354 | H238: Pago mesada tranporte U de A
A239: 45805 | B239: I | C239: 5 | D239: =_xlfn.XLOOKUP(B239,Códigos!$A$489:$A$522,Códigos!$B$489:$B$522,"Verificar",0) -> -Retiros y Traslados de Bancos | E239: =_xlfn.XLOOKUP(C239,Códigos!$A$11:$A$415,Códigos!$B$11:$B$415,"Verificar",0) -> NOMBRE 25 | F239: 660000 | G239: =+G238+F239 -> 414535354 | H239: Pago Nomina 19 al 25 mayo
A240: 45805 | B240: I | C240: 5 | D240: =_xlfn.XLOOKUP(B240,Códigos!$A$489:$A$522,Códigos!$B$489:$B$522,"Verificar",0) -> -Retiros y Traslados de Bancos | E240: =_xlfn.XLOOKUP(C240,Códigos!$A$11:$A$415,Códigos!$B$11:$B$415,"Verificar",0) -> NOMBRE 25 | F240: 91000 | G240: =+G239+F240 -> 414626354 | H240: Pago intereses
A241: 45806 | B241: I | C241: 5 | D241: =_xlfn.XLOOKUP(B241,Códigos!$A$489:$A$522,Códigos!$B$489:$B$522,"Verificar",0) -> -Retiros y Traslados de Bancos | E241: =_xlfn.XLOOKUP(C241,Códigos!$A$11:$A$415,Códigos!$B$11:$B$415,"Verificar",0) -> NOMBRE 25 | F241: 440000 | G241: =+G240+F241 -> 415066354 | H241: Pago mesada tranporte U de A
A242: 45806 | B242: I | C242: 5 | D242: =_xlfn.XLOOKUP(B242,Códigos!$A$489:$A$522,Códigos!$B$489:$B$522,"Verificar",0) -> -Retiros y Traslados de Bancos | E242: =_xlfn.XLOOKUP(C242,Códigos!$A$11:$A$415,Códigos!$B$11:$B$415,"Verificar",0) -> NOMBRE 25 | F242: 700000 | G242: =+G241+F242 -> 415766354 | H242: Pago Nomina 26 mayo al 01 junio
A243: 45806 | B243: I | C243: 5 | D243: =_xlfn.XLOOKUP(B243,Códigos!$A$489:$A$522,Códigos!$B$489:$B$522,"Verificar",0) -> -Retiros y Traslados de Bancos | E243: =_xlfn.XLOOKUP(C243,Códigos!$A$11:$A$415,Códigos!$B$11:$B$415,"Verificar",0) -> NOMBRE 25 | F243: 36700 | G243: =+G242+F243 -> 415803054 | H243: Pago Tigo Diego mayo
A244: 45806 | B244: C | C244: 194 | D244: =_xlfn.XLOOKUP(B244,Códigos!$A$489:$A$522,Códigos!$B$489:$B$522,"Verificar",0) -> Recibido por: -Cuentas de cobro -DAFF | E244: =_xlfn.XLOOKUP(C244,Códigos!$A$11:$A$415,Códigos!$B$11:$B$415,"Verificar",0) -> NOMBRE 333 | F244: 450000 | G244: =+G243+F244 -> 416253054 | H244: Pago Cuenta Cobro 24-126
A245: 45807 | B245: I | C245: 5 | D245: =_xlfn.XLOOKUP(B245,Códigos!$A$489:$A$522,Códigos!$B$489:$B$522,"Verificar",0) -> -Retiros y Traslados de Bancos | E245: =_xlfn.XLOOKUP(C245,Códigos!$A$11:$A$415,Códigos!$B$11:$B$415,"Verificar",0) -> NOMBRE 25 | F245: 220000 | G245: =+G244+F245 -> 416473054 | H245: Pago mesada tranporte U de A
... A419: 45917 | B419: I | C419: 5 | D419: =_xlfn.XLOOKUP(B419,Códigos!$A$489:$A$522,Códigos!$B$489:$B$522,"Verificar",0) -> -Retiros y Traslados de Bancos | E419: =_xlfn.XLOOKUP(C419,Códigos!$A$11:$A$415,Códigos!$B$11:$B$415,"Verificar",0) -> NOMBRE 25 | F419: 500000 | G419: =+G418+F419 -> 596842836 | H419: Prestamo a Luis German Mesa
A420: 45918 | B420: I | C420: 5 | D420: =_xlfn.XLOOKUP(B420,Códigos!$A$489:$A$522,Códigos!$B$489:$B$522,"Verificar",0) -> -Retiros y Traslados de Bancos | E420: =_xlfn.XLOOKUP(C420,Códigos!$A$11:$A$415,Códigos!$B$11:$B$415,"Verificar",0) -> NOMBRE 25 | F420: =266130+383130+324720 -> 973980 | G420: =+G419+F420 -> 597816816 | H420: Pago Administracion del Gaspar de Rodas
A421: 45918 | B421: I | C421: 5 | D421: =_xlfn.XLOOKUP(B421,Códigos!$A$489:$A$522,Códigos!$B$489:$B$522,"Verificar",0) -> -Retiros y Traslados de Bancos | E421: =_xlfn.XLOOKUP(C421,Códigos!$A$11:$A$415,Códigos!$B$11:$B$415,"Verificar",0) -> NOMBRE 25 | F421: =65700+63980 -> 129680 | G421: =+G420+F421 -> 597946496 | H421: Pago Administracion Parqueadero San Jose
A422: 45918 | B422: I | C422: 5 | D422: =_xlfn.XLOOKUP(B422,Códigos!$A$489:$A$522,Códigos!$B$489:$B$522,"Verificar",0) -> -Retiros y Traslados de Bancos | E422: =_xlfn.XLOOKUP(C422,Códigos!$A$11:$A$415,Códigos!$B$11:$B$415,"Verificar",0) -> NOMBRE 25 | F422: 220000 | G422: =+G421+F422 -> 598166496 | H422: Pago mesada tranporte U de A | K422: =22+80+880 -> 982
A423: 45922 | B423: C | C423: 346 | D423: =_xlfn.XLOOKUP(B423,Códigos!$A$489:$A$522,Códigos!$B$489:$B$522,"Verificar",0) -> Recibido por: -Cuentas de cobro -DAFF | E423: =_xlfn.XLOOKUP(C423,Códigos!$A$11:$A$415,Códigos!$B$11:$B$415,"Verificar",0) -> NOMBRE 2 | F423: 160000 | G423: =+G422+F423 -> 598326496 | H423: Pago Cueta Cobro 25-047
A424: 45923 | B424: I | C424: 5 | D424: =_xlfn.XLOOKUP(B424,Códigos!$A$489:$A$522,Códigos!$B$489:$B$522,"Verificar",0) -> -Retiros y Traslados de Bancos | E424: =_xlfn.XLOOKUP(C424,Códigos!$A$11:$A$415,Códigos!$B$11:$B$415,"Verificar",0) -> NOMBRE 25 | F424: 430200 | G424: =+G423+F424 -> 598756696 | H424: Pago EPM varios
A425: 45925 | B425: I | C425: 5 | D425: =_xlfn.XLOOKUP(B425,Códigos!$A$489:$A$522,Códigos!$B$489:$B$522,"Verificar",0) -> -Retiros y Traslados de Bancos | E425: =_xlfn.XLOOKUP(C425,Códigos!$A$11:$A$415,Códigos!$B$11:$B$415,"Verificar",0) -> NOMBRE 25 | F425: 22000 | G425: =+G424+F425 -> 598778696 | H425: Pago WOW Libia
A426: 45925 | B426: I | C426: 5 | D426: =_xlfn.XLOOKUP(B426,Códigos!$A$489:$A$522,Códigos!$B$489:$B$522,"Verificar",0) -> -Retiros y Traslados de Bancos | E426: =_xlfn.XLOOKUP(C426,Códigos!$A$11:$A$415,Códigos!$B$11:$B$415,"Verificar",0) -> NOMBRE 25 | F426: 46073 | G426: =+G425+F426 -> 598824769 | H426: Pagom TIGO UNE
A427: 45925 | B427: I | C427: 5 | D427: =_xlfn.XLOOKUP(B427,Códigos!$A$489:$A$522,Códigos!$B$489:$B$522,"Verificar",0) -> -Retiros y Traslados de Bancos | E427: =_xlfn.XLOOKUP(C427,Códigos!$A$11:$A$415,Códigos!$B$11:$B$415,"Verificar",0) -> NOMBRE 25 | F427: 220000 | G427: =+G426+F427 -> 599044769 | H427: Pago mesada tranporte U de A
A428: 45925 | B428: I | C428: 5 | D428: =_xlfn.XLOOKUP(B428,Códigos!$A$489:$A$522,Códigos!$B$489:$B$522,"Verificar",0) -> -Retiros y Traslados de Bancos | E428: =_xlfn.XLOOKUP(C428,Códigos!$A$11:$A$415,Códigos!$B$11:$B$415,"Verificar",0) -> NOMBRE 25 | F428: 660000 | G428: =+G427+F428 -> 599704769 | H428: Pago Nomina22 al 28 septiembre
A429: 45926 | B429: I | C429: 5 | D429: =_xlfn.XLOOKUP(B429,Códigos!$A$489:$A$522,Códigos!$B$489:$B$522,"Verificar",0) -> -Retiros y Traslados de Bancos | E429: =_xlfn.XLOOKUP(C429,Códigos!$A$11:$A$415,Códigos!$B$11:$B$415,"Verificar",0) -> NOMBRE 25 | F429: 220000 | G429: =+G428+F429 -> 599924769 | H429: Pago mesada tranporte U de A
A430: 45926 | B430: C | C430: 46 | D430: =_xlfn.XLOOKUP(B430,Códigos!$A$489:$A$522,Códigos!$B$489:$B$522,"Verificar",0) -> Recibido por: -Cuentas de cobro -DAFF | E430: =_xlfn.XLOOKUP(C430,Códigos!$A$11:$A$415,Códigos!$B$11:$B$415,"Verificar",0) -> NOMBRE 116 | F430: 400000 | G430: =+G429+F430 -> 600324769 | H430: Pago Cueta Cobro 25-005
A431: 45930 | B431: I | C431: 5 | D431: =_xlfn.XLOOKUP(B431,Códigos!$A$489:$A$522,Códigos!$B$489:$B$522,"Verificar",0) -> -Retiros y Traslados de Bancos | E431: =_xlfn.XLOOKUP(C431,Códigos!$A$11:$A$415,Códigos!$B$11:$B$415,"Verificar",0) -> NOMBRE 25 | F431: 2000000 | G431: =+G430+F431 -> 602324769 | H431: Retiro por cajero
A432: 45932 | B432: I | C432: 5 | D432: =_xlfn.XLOOKUP(B432,Códigos!$A$489:$A$522,Códigos!$B$489:$B$522,"Verificar",0) -> -Retiros y Traslados de Bancos | E432: =_xlfn.XLOOKUP(C432,Códigos!$A$11:$A$415,Códigos!$B$11:$B$415,"Verificar",0) -> NOMBRE 25 | F432: 139900 | G432: =+G431+F432 -> 602464669 | H432: Pago TIGO German
A433: 45932 | B433: I | C433: 5 | D433: =_xlfn.XLOOKUP(B433,Códigos!$A$489:$A$522,Códigos!$B$489:$B$522,"Verificar",0) -> -Retiros y Traslados de Bancos | E433: =_xlfn.XLOOKUP(C433,Códigos!$A$11:$A$415,Códigos!$B$11:$B$415,"Verificar",0) -> NOMBRE 25 | F433: 220000 | G433: =+G432+F433 -> 602684669 | H433: Pago mesada tranporte U de A
A434: 45932 | B434: I | C434: 5 | D434: =_xlfn.XLOOKUP(B434,Códigos!$A$489:$A$522,Códigos!$B$489:$B$522,"Verificar",0) -> -Retiros y Traslados de Bancos | E434: =_xlfn.XLOOKUP(C434,Códigos!$A$11:$A$415,Códigos!$B$11:$B$415,"Verificar",0) -> NOMBRE 25 | F434: 660000 | G434: =+G433+F434 -> 603344669 | H434: Pago Nomina 29 septiembre al 05 octubre
... A463: 45951 | B463: I | C463: 5 | D463: =_xlfn.XLOOKUP(B463,Códigos!$A$489:$A$522,Códigos!$B$489:$B$522,"Verificar",0) -> -Retiros y Traslados de Bancos | E463: =_xlfn.XLOOKUP(C463,Códigos!$A$11:$A$415,Códigos!$B$11:$B$415,"Verificar",0) -> NOMBRE 25 | F463: 603000 | G463: =+G462+F463 -> 622065269 | H463: Pago administracion Babilonia
A464: 45951 | B464: I | C464: 5 | D464: =_xlfn.XLOOKUP(B464,Códigos!$A$489:$A$522,Códigos!$B$489:$B$522,"Verificar",0) -> -Retiros y Traslados de Bancos | E464: =_xlfn.XLOOKUP(C464,Códigos!$A$11:$A$415,Códigos!$B$11:$B$415,"Verificar",0) -> NOMBRE 25 | F464: =295700+425700+360800 -> 1082200 | G464: =+G463+F464 -> 623147469 | H464: Pago Administracion del Gaspar de Rodas
A465: 45951 | B465: C | C465: 252 | D465: =_xlfn.XLOOKUP(B465,Códigos!$A$489:$A$522,Códigos!$B$489:$B$522,"Verificar",0) -> Recibido por: -Cuentas de cobro -DAFF | E465: =_xlfn.XLOOKUP(C465,Códigos!$A$11:$A$415,Códigos!$B$11:$B$415,"Verificar",0) -> NOMBRE 219 | F465: 160000 | G465: =+G464+F465 -> 623307469 | H465: Pago Cueta Cobro 25-082
A466: 45952 | B466: I | C466: 5 | D466: =_xlfn.XLOOKUP(B466,Códigos!$A$489:$A$522,Códigos!$B$489:$B$522,"Verificar",0) -> -Retiros y Traslados de Bancos | E466: =_xlfn.XLOOKUP(C466,Códigos!$A$11:$A$415,Códigos!$B$11:$B$415,"Verificar",0) -> NOMBRE 25 | F466: 129700 | G466: =+G465+F466 -> 623437169 | H466: Pago administracion Parqueadero San Jose
A467: 45953 | B467: I | C467: 5 | D467: =_xlfn.XLOOKUP(B467,Códigos!$A$489:$A$522,Códigos!$B$489:$B$522,"Verificar",0) -> -Retiros y Traslados de Bancos | E467: =_xlfn.XLOOKUP(C467,Códigos!$A$11:$A$415,Códigos!$B$11:$B$415,"Verificar",0) -> NOMBRE 25 | F467: 464341 | G467: =+G466+F467 -> 623901510 | H467: Pago EPM varios
A468: 45953 | B468: I | C468: 5 | D468: =_xlfn.XLOOKUP(B468,Códigos!$A$489:$A$522,Códigos!$B$489:$B$522,"Verificar",0) -> -Retiros y Traslados de Bancos | E468: =_xlfn.XLOOKUP(C468,Códigos!$A$11:$A$415,Códigos!$B$11:$B$415,"Verificar",0) -> NOMBRE 25 | F468: 350000 | G468: =+G467+F468 -> 624251510 | H468: Abono intererses cuota septiembre 2025
A469: 45953 | B469: I | C469: 5 | D469: =_xlfn.XLOOKUP(B469,Códigos!$A$489:$A$522,Códigos!$B$489:$B$522,"Verificar",0) -> -Retiros y Traslados de Bancos | E469: =_xlfn.XLOOKUP(C469,Códigos!$A$11:$A$415,Códigos!$B$11:$B$415,"Verificar",0) -> NOMBRE 25 | F469: 200000 | G469: =+G468+F469 -> 624451510 | H469: Abono a deuda 2025
A470: 45953 | B470: I | C470: 3 | D470: =_xlfn.XLOOKUP(B470,Códigos!$A$489:$A$522,Códigos!$B$489:$B$522,"Verificar",0) -> -Retiros y Traslados de Bancos | E470: =_xlfn.XLOOKUP(C470,Códigos!$A$11:$A$415,Códigos!$B$11:$B$415,"Verificar",0) -> NOMBRE 24 | F470: 220000 | G470: =+G469+F470 -> 624671510 | H470: Pago mesada tranporte U de A
A471: 45953 | B471: I | C471: 3 | D471: =_xlfn.XLOOKUP(B471,Códigos!$A$489:$A$522,Códigos!$B$489:$B$522,"Verificar",0) -> -Retiros y Traslados de Bancos | E471: =_xlfn.XLOOKUP(C471,Códigos!$A$11:$A$415,Códigos!$B$11:$B$415,"Verificar",0) -> NOMBRE 24 | F471: 530000 | G471: =+G470+F471 -> 625201510 | H471: Pago Nomina 20 al 26 octubre
A472: 45953 | B472: I | C472: 3 | D472: =_xlfn.XLOOKUP(B472,Códigos!$A$489:$A$522,Códigos!$B$489:$B$522,"Verificar",0) -> -Retiros y Traslados de Bancos | E472: =_xlfn.XLOOKUP(C472,Códigos!$A$11:$A$415,Códigos!$B$11:$B$415,"Verificar",0) -> NOMBRE 24 | F472: 22000 | G472: =+G471+F472 -> 625223510 | H472: Pago WOW Libia
A473: 45953 | B473: C | C473: 89 | D473: =_xlfn.XLOOKUP(B473,Códigos!$A$489:$A$522,Códigos!$B$489:$B$522,"Verificar",0) -> Recibido por: -Cuentas de cobro -DAFF | E473: =_xlfn.XLOOKUP(C473,Códigos!$A$11:$A$415,Códigos!$B$11:$B$415,"Verificar",0) -> NOMBRE 226 | F473: 400000 | G473: =+G472+F473 -> 625623510 | H473: Pago Cueta Cobro 25-085
A474: 45953 | B474: C | C474: 24 | D474: =_xlfn.XLOOKUP(B474,Códigos!$A$489:$A$522,Códigos!$B$489:$B$522,"Verificar",0) -> Recibido por: -Cuentas de cobro -DAFF | E474: =_xlfn.XLOOKUP(C474,Códigos!$A$11:$A$415,Códigos!$B$11:$B$415,"Verificar",0) -> NOMBRE 132 | F474: 470000 | G474: =+G473+F474 -> 626093510 | H474: Pago Cueta Cobro 25-035
A475: 45955 | B475: C | C475: 351 | D475: =_xlfn.XLOOKUP(B475,Códigos!$A$489:$A$522,Códigos!$B$489:$B$522,"Verificar",0) -> Recibido por: -Cuentas de cobro -DAFF | E475: =_xlfn.XLOOKUP(C475,Códigos!$A$11:$A$415,Códigos!$B$11:$B$415,"Verificar",0) -> NOMBRE 198 | F475: 890000 | G475: =+G474+F475 -> 626983510 | H475: Pago Cueta Cobro 25-049
A476: 45957 | B476: I | C476: 5 | D476: =_xlfn.XLOOKUP(B476,Códigos!$A$489:$A$522,Códigos!$B$489:$B$522,"Verificar",0) -> -Retiros y Traslados de Bancos | E476: =_xlfn.XLOOKUP(C476,Códigos!$A$11:$A$415,Códigos!$B$11:$B$415,"Verificar",0) -> NOMBRE 25 | F476: 220000 | G476: =+G475+F476 -> 627203510 | H476: Pago mesada tranporte U de A
... A488: 45959 | B488: C | C488: 295 | D488: =_xlfn.XLOOKUP(B488,Códigos!$A$489:$A$522,Códigos!$B$489:$B$522,"Verificar",0) -> Recibido por: -Cuentas de cobro -DAFF | E488: =_xlfn.XLOOKUP(C488,Códigos!$A$11:$A$415,Códigos!$B$11:$B$415,"Verificar",0) -> NOMBRE 77 | F488: 900000 | G488: =+G487+F488 -> 634239583 | H488: Pago Cueta Cobro 25-134
A489: 45959 | D489: =_xlfn.XLOOKUP(B489,Códigos!$A$489:$A$522,Códigos!$B$489:$B$522,"Verificar",0) -> 0 | E489: =_xlfn.XLOOKUP(C489,Códigos!$A$11:$A$415,Códigos!$B$11:$B$415,"Verificar",0) -> 0 | G489: =+G488+F489 -> 634239583
A490: 45959 | D490: =_xlfn.XLOOKUP(B490,Códigos!$A$489:$A$522,Códigos!$B$489:$B$522,"Verificar",0) -> 0 | E490: =_xlfn.XLOOKUP(C490,Códigos!$A$11:$A$415,Códigos!$B$11:$B$415,"Verificar",0) -> 0 | G490: =+G489+F490 -> 634239583
D491: =_xlfn.XLOOKUP(B491,Códigos!$A$489:$A$522,Códigos!$B$489:$B$522,"Verificar",0) -> 0 | E491: =_xlfn.XLOOKUP(C491,Códigos!$A$11:$A$415,Códigos!$B$11:$B$415,"Verificar",0) -> 0 | G491: =+G490+F491 -> 634239583
D492: =_xlfn.XLOOKUP(B492,Códigos!$A$489:$A$522,Códigos!$B$489:$B$522,"Verificar",0) -> 0 | E492: =_xlfn.XLOOKUP(C492,Códigos!$A$11:$A$415,Códigos!$B$11:$B$415,"Verificar",0) -> 0 | G492: =+G491+F492 -> 634239583
D493: =_xlfn.XLOOKUP(B493,Códigos!$A$489:$A$522,Códigos!$B$489:$B$522,"Verificar",0) -> 0 | E493: =_xlfn.XLOOKUP(C493,Códigos!$A$11:$A$415,Códigos!$B$11:$B$415,"Verificar",0) -> 0 | G493: =+G492+F493 -> 634239583
D494: =_xlfn.XLOOKUP(B494,Códigos!$A$489:$A$522,Códigos!$B$489:$B$522,"Verificar",0) -> 0 | E494: =_xlfn.XLOOKUP(C494,Códigos!$A$11:$A$415,Códigos!$B$11:$B$415,"Verificar",0) -> 0 | G494: =+G493+F494 -> 634239583
D495: =_xlfn.XLOOKUP(B495,Códigos!$A$489:$A$522,Códigos!$B$489:$B$522,"Verificar",0) -> 0 | E495: =_xlfn.XLOOKUP(C495,Códigos!$A$11:$A$415,Códigos!$B$11:$B$415,"Verificar",0) -> 0 | G495: =+G494+F495 -> 634239583
D496: =_xlfn.XLOOKUP(B496,Códigos!$A$489:$A$522,Códigos!$B$489:$B$522,"Verificar",0) -> 0 | E496: =_xlfn.XLOOKUP(C496,Códigos!$A$11:$A$415,Códigos!$B$11:$B$415,"Verificar",0) -> 0 | G496: =+G495+F496 -> 634239583
D497: =_xlfn.XLOOKUP(B497,Códigos!$A$489:$A$522,Códigos!$B$489:$B$522,"Verificar",0) -> 0 | E497: =_xlfn.XLOOKUP(C497,Códigos!$A$11:$A$415,Códigos!$B$11:$B$415,"Verificar",0) -> 0 | G497: =+G496+F497 -> 634239583
D498: =_xlfn.XLOOKUP(B498,Códigos!$A$489:$A$522,Códigos!$B$489:$B$522,"Verificar",0) -> 0 | E498: =_xlfn.XLOOKUP(C498,Códigos!$A$11:$A$415,Códigos!$B$11:$B$415,"Verificar",0) -> 0 | G498: =+G497+F498 -> 634239583
D499: =_xlfn.XLOOKUP(B499,Códigos!$A$489:$A$522,Códigos!$B$489:$B$522,"Verificar",0) -> 0 | E499: =_xlfn.XLOOKUP(C499,Códigos!$A$11:$A$415,Códigos!$B$11:$B$415,"Verificar",0) -> 0 | G499: =+G498+F499 -> 634239583
D500: =_xlfn.XLOOKUP(B500,Códigos!$A$489:$A$522,Códigos!$B$489:$B$522,"Verificar",0) -> 0 | E500: =_xlfn.XLOOKUP(C500,Códigos!$A$11:$A$415,Códigos!$B$11:$B$415,"Verificar",0) -> 0 | G500: =+G499+F500 -> 634239583
D501: =_xlfn.XLOOKUP(B501,Códigos!$A$489:$A$522,Códigos!$B$489:$B$522,"Verificar",0) -> 0 | E501: =_xlfn.XLOOKUP(C501,Códigos!$A$11:$A$415,Códigos!$B$11:$B$415,"Verificar",0) -> 0 | G501: =+G500+F501 -> 634239583
D502: =_xlfn.XLOOKUP(B502,Códigos!$A$489:$A$522,Códigos!$B$489:$B$522,"Verificar",0) -> 0 | E502: =_xlfn.XLOOKUP(C502,Códigos!$A$11:$A$415,Códigos!$B$11:$B$415,"Verificar",0) -> 0 | G502: =+G501+F502 -> 634239583
... D533: =_xlfn.XLOOKUP(B533,Códigos!$A$489:$A$522,Códigos!$B$489:$B$522,"Verificar",0) -> 0 | E533: =_xlfn.XLOOKUP(C533,Códigos!$A$11:$A$415,Códigos!$B$11:$B$415,"Verificar",0) -> 0 | G533: =+G532+F533 -> 634239583
D534: =_xlfn.XLOOKUP(B534,Códigos!$A$489:$A$522,Códigos!$B$489:$B$522,"Verificar",0) -> 0 | E534: =_xlfn.XLOOKUP(C534,Códigos!$A$11:$A$415,Códigos!$B$11:$B$415,"Verificar",0) -> 0 | G534: =+G532+F534 -> 634239583
D535: =_xlfn.XLOOKUP(B535,Códigos!$A$489:$A$522,Códigos!$B$489:$B$522,"Verificar",0) -> 0 | E535: =_xlfn.XLOOKUP(C535,Códigos!$A$11:$A$415,Códigos!$B$11:$B$415,"Verificar",0) -> 0 | G535: =+G534+F535 -> 634239583
D536: =_xlfn.XLOOKUP(B536,Códigos!$A$489:$A$522,Códigos!$B$489:$B$522,"Verificar",0) -> 0 | E536: =_xlfn.XLOOKUP(C536,Códigos!$A$11:$A$415,Códigos!$B$11:$B$415,"Verificar",0) -> 0 | G536: =+G535+F536 -> 634239583
D537: =_xlfn.XLOOKUP(B537,Códigos!$A$489:$A$522,Códigos!$B$489:$B$522,"Verificar",0) -> 0 | E537: =_xlfn.XLOOKUP(C537,Códigos!$A$11:$A$415,Códigos!$B$11:$B$415,"Verificar",0) -> 0 | G537: =+G536+F537 -> 634239583
D538: =_xlfn.XLOOKUP(B538,Códigos!$A$489:$A$522,Códigos!$B$489:$B$522,"Verificar",0) -> 0 | E538: =_xlfn.XLOOKUP(C538,Códigos!$A$11:$A$415,Códigos!$B$11:$B$415,"Verificar",0) -> 0 | G538: =+G537+F538 -> 634239583
D539: =_xlfn.XLOOKUP(B539,Códigos!$A$489:$A$522,Códigos!$B$489:$B$522,"Verificar",0) -> 0 | E539: =_xlfn.XLOOKUP(C539,Códigos!$A$11:$A$415,Códigos!$B$11:$B$415,"Verificar",0) -> 0 | G539: =+G538+F539 -> 634239583
...

Sheet EGRESOS DE CAJA
A1: =+Códigos!$A$1 -> LIBRO DIARIO OFICINA | G1: SALDO DÉBITO ACUMULADO | H1: SALDO ACUMULADO | I1: La diferencia debe ser CERO (0). Si existe diferencia quiere decir que hay ERROR de formulas.
A2: MOVIMIENTO DE EGRESOS DE CAJA DIARIO | G2: =+G2253 -> 633732083 | H2: =+H2253 -> 633732083 | I2: =+G2-H2 -> 0
A3: =+Códigos!$A$3 -> AÑO: | B3: 2025
A4: DESDE: | D4: =+'INGRESOS A CAJA'!D4 -> 45658 | I4: =IF(I2=0,"OK Saldos","ERROR EN LAS OPERACIONES Verificar formulas") -> OK Saldos
A5: HASTA: | D5: =+'INGRESOS A CAJA'!D5 -> 46022
A7: FECHA | B7: CÓDIGO DEL EGRESO | C7: CÓDIGO DEL TERCERO | D7: CONCEPTO DEL EGRESO | E7: APELLIDOS Y NOMBRES o RAZÓN SOCIAL DEL CLIENTE o TERCERO | F7: ETIQUETA | G7: DÉBITOS | H7: SALDO ACUMULADO | I7: OBSERVACIONES | J7: REVISIÓN
A12: 45659 | B12: 37 | C12: 359 | D12: =_xlfn.XLOOKUP(B12,Códigos!$A$421:$A$483,Códigos!$B$421:$B$483,"Verificar",0) -> Gastos Barbosa | E12: =_xlfn.XLOOKUP(C12,Códigos!$A$11:$A$415,Códigos!$B$11:$B$415,"Verificar",0) -> NOMBRE 232 | F12: GTFF | G12: 50000 | H12: =+H11+G12 -> 50000 | I12: Recarga Flypass Barbosa
A13: 45660 | B13: 22 | C13: 359 | D13: =_xlfn.XLOOKUP(B13,Códigos!$A$421:$A$483,Códigos!$B$421:$B$483,"Verificar",0) -> Compra de: -Equipos, dotaciones y repuestos para oficina | E13: =_xlfn.XLOOKUP(C13,Códigos!$A$11:$A$415,Códigos!$B$11:$B$415,"Verificar",0) -> NOMBRE 232 | F13: OFICINA | G13: 500000 | H13: =+H12+G13 -> 550000 | I13: Traslado pedro pago camaras
A14: 45660 | B14: 33 | C14: 3 | D14: =_xlfn.XLOOKUP(B14,Códigos!$A$421:$A$483,Códigos!$B$421:$B$483,"Verificar",0) -> AJUSTE POR -Consignación - Traslado a Bancos | E14: =_xlfn.XLOOKUP(C14,Códigos!$A$11:$A$415,Códigos!$B$11:$B$415,"Verificar",0) -> NOMBRE 24 | G14: 1800000 | H14: =+H13+G14 -> 2350000 | I14: Pago Cuenta 24-105
A15: 45666 | B15: 12 | C15: 359 | D15: =_xlfn.XLOOKUP(B15,Códigos!$A$421:$A$483,Códigos!$B$421:$B$483,"Verificar",0) -> Pagos de: -Celulares | E15: =_xlfn.XLOOKUP(C15,Códigos!$A$11:$A$415,Códigos!$B$11:$B$415,"Verificar",0) -> NOMBRE 232 | F15: GTFF | G15: 47500 | H15: =+H14+G15 -> 2397500 | I15: Pago Movistar Diego
A16: 45670 | B16: 10 | C16: 359 | D16: =_xlfn.XLOOKUP(B16,Códigos!$A$421:$A$483,Códigos!$B$421:$B$483,"Verificar",0) -> Pagos de: -Servicios públicos -NIÑAS- | E16: =_xlfn.XLOOKUP(C16,Códigos!$A$11:$A$415,Códigos!$B$11:$B$415,"Verificar",0) -> NOMBRE 232 | F16: GTFF | G16: 125800 | H16: =+H15+G16 -> 2523300 | I16: Pago Tigo Babilonia enero
A17: 45671 | B17: 7 | C17: 359 | D17: =_xlfn.XLOOKUP(B17,Códigos!$A$421:$A$483,Códigos!$B$421:$B$483,"Verificar",0) -> Pagos de: -Seguridad Social | E17: =_xlfn.XLOOKUP(C17,Códigos!$A$11:$A$415,Códigos!$B$11:$B$415,"Verificar",0) -> NOMBRE 232 | F17: OFICINA | G17: 1000600 | H17: =+H16+G17 -> 3523900 | I17: Pago Seguridad Social Empleados febrero
A18: 45671 | B18: 7 | C18: 359 | D18: =_xlfn.XLOOKUP(B18,Códigos!$A$421:$A$483,Códigos!$B$421:$B$483,"Verificar",0) -> Pagos de: -Seguridad Social | E18: =_xlfn.XLOOKUP(C18,Códigos!$A$11:$A$415,Códigos!$B$11:$B$415,"Verificar",0) -> NOMBRE 232 | F18: OFICINA | G18: 897800 | H18: =+H17+G18 -> 4421700 | I18: Pago Seguridad Social Independiente enero
A19: 45671 | B19: 39 | C19: 362 | D19: =_xlfn.XLOOKUP(B19,Códigos!$A$421:$A$483,Códigos!$B$421:$B$483,"Verificar",0) -> Pago intereses préstamo Juliana | E19: =_xlfn.XLOOKUP(C19,Códigos!$A$11:$A$415,Códigos!$B$11:$B$415,"Verificar",0) -> NOMBRE 97 | F19: OFICINA | G19: 350000 | H19: =+H18+G19 -> 4771700 | I19: Abono intererses cuota enero 2025
A20: 45671 | B20: 21 | C20: 362 | D20: =_xlfn.XLOOKUP(B20,Códigos!$A$421:$A$483,Códigos!$B$421:$B$483,"Verificar",0) -> Pagos de: -Cuentas por Pagar a: | E20: =_xlfn.XLOOKUP(C20,Códigos!$A$11:$A$415,Códigos!$B$11:$B$415,"Verificar",0) -> NOMBRE 97 | F20: OFICINA | G20: 200000 | H20: =+H19+G20 -> 4971700 | I20: Abono a deuda enero 2025
A21: 45671 | B21: 9 | C21: 359 | D21: =_xlfn.XLOOKUP(B21,Códigos!$A$421:$A$483,Códigos!$B$421:$B$483,"Verificar",0) -> Pagos de: -Servicios públicos -OFICINA- | E21: =_xlfn.XLOOKUP(C21,Códigos!$A$11:$A$415,Códigos!$B$11:$B$415,"Verificar",0) -> NOMBRE 232 | F21: OFICINA | G21: 89300 | H21: =+H20+G21 -> 5061000 | I21: Pago EPM Barbosa
A22: 45671 | B22: 9 | C22: 359 | D22: =_xlfn.XLOOKUP(B22,Códigos!$A$421:$A$483,Códigos!$B$421:$B$483,"Verificar",0) -> Pagos de: -Servicios públicos -OFICINA- | E22: =_xlfn.XLOOKUP(C22,Códigos!$A$11:$A$415,Códigos!$B$11:$B$415,"Verificar",0) -> NOMBRE 232 | F22: OFICINA | G22: 67800 | H22: =+H21+G22 -> 5128800 | I22: Pago EPM Carolina
A23: 45671 | B23: 8 | C23: 357 | D23: =_xlfn.XLOOKUP(B23,Códigos!$A$421:$A$483,Códigos!$B$421:$B$483,"Verificar",0) -> Pagos de: -Cuota para alimentos y Manuntención | E23: =_xlfn.XLOOKUP(C23,Códigos!$A$11:$A$415,Códigos!$B$11:$B$415,"Verificar",0) -> NOMBRE 107 | F23: GTFF | G23: =1030000-G25-G24 -> 150000 | H23: =+H22+G23 -> 5278800 | I23: Pago cita perros
A24: 45671 | B24: 8 | C24: 357 | D24: =_xlfn.XLOOKUP(B24,Códigos!$A$421:$A$483,Códigos!$B$421:$B$483,"Verificar",0) -> Pagos de: -Cuota para alimentos y Manuntención | E24: =_xlfn.XLOOKUP(C24,Códigos!$A$11:$A$415,Códigos!$B$11:$B$415,"Verificar",0) -> NOMBRE 107 | F24: GTFF | G24: 220000 | H24: =+H23+G24 -> 5498800 | I24: Pago mesada tranporte U de A
A25: 45671 | B25: 2 | C25: 353 | D25: =_xlfn.XLOOKUP(B25,Códigos!$A$421:$A$483,Códigos!$B$421:$B$483,"Verificar",0) -> Pago de Salarios a: | E25: =_xlfn.XLOOKUP(C25,Códigos!$A$11:$A$415,Códigos!$B$11:$B$415,"Verificar",0) -> NOMBRE 31 | F25: OFICINA | G25: 660000 | H25: =+H24+G25 -> 6158800 | I25: Pago Nomina 13 al 19 enero
A26: 45671 | B26: 33 | C26: 5 | D26: =_xlfn.XLOOKUP(B26,Códigos!$A$421:$A$483,Códigos!$B$421:$B$483,"Verificar",0) -> AJUSTE POR -Consignación - Traslado a Bancos | E26: =_xlfn.XLOOKUP(C26,Códigos!$A$11:$A$415,Códigos!$B$11:$B$415,"Verificar",0) -> NOMBRE 25 | G26: 5164600 | H26: =+H25+G26 -> 11323400 | I26: Pago factura GTFF-126
A27: 45671 | B27: 33 | C27: 5 | D27: =_xlfn.XLOOKUP(B27,Códigos!$A$421:$A$483,Códigos!$B$421:$B$483,"Verificar",0) -> AJUSTE POR -Consignación - Traslado a Bancos | E27: =_xlfn.XLOOKUP(C27,Códigos!$A$11:$A$415,Códigos!$B$11:$B$415,"Verificar",0) -> NOMBRE 25 | G27: 3308200 | H27: =+H26+G27 -> 14631600 | I27: Pago factura GTFF-128
A28: 45671 | B28: 33 | C28: 5 | D28: =_xlfn.XLOOKUP(B28,Códigos!$A$421:$A$483,Códigos!$B$421:$B$483,"Verificar",0) -> AJUSTE POR -Consignación - Traslado a Bancos | E28: =_xlfn.XLOOKUP(C28,Códigos!$A$11:$A$415,Códigos!$B$11:$B$415,"Verificar",0) -> NOMBRE 25 | G28: 1035300 | H28: =+H27+G28 -> 15666900 | I28: Pago factura GTFF-129
A29: 45671 | B29: 33 | C29: 3 | D29: =_xlfn.XLOOKUP(B29,Códigos!$A$421:$A$483,Códigos!$B$421:$B$483,"Verificar",0) -> AJUSTE POR -Consignación - Traslado a Bancos | E29: =_xlfn.XLOOKUP(C29,Códigos!$A$11:$A$415,Códigos!$B$11:$B$415,"Verificar",0) -> NOMBRE 24 | G29: 35000000 | H29: =+H28+G29 -> 50666900 | I29: Abono a deuda consignado Inversion Virtual
A30: 45671 | B30: 33 | C30: 5 | D30: =_xlfn.XLOOKUP(B30,Códigos!$A$421:$A$483,Códigos!$B$421:$B$483,"Verificar",0) -> AJUSTE POR -Consignación - Traslado a Bancos | E30: =_xlfn.XLOOKUP(C30,Códigos!$A$11:$A$415,Códigos!$B$11:$B$415,"Verificar",0) -> NOMBRE 25 | G30: 4611600 | H30: =+H29+G30 -> 55278500 | I30: Pago factura GTFF-159
A31: 45671 | B31: 33 | C31: 5 | D31: =_xlfn.XLOOKUP(B31,Códigos!$A$421:$A$483,Códigos!$B$421:$B$483,"Verificar",0) -> AJUSTE POR -Consignación - Traslado a Bancos | E31: =_xlfn.XLOOKUP(C31,Códigos!$A$11:$A$415,Códigos!$B$11:$B$415,"Verificar",0) -> NOMBRE 25 | G31: 3629500 | H31: =+H30+G31 -> 58908000 | I31: Pago factura GTFF-161
A32: 45671 | B32: 33 | C32: 5 | D32: =_xlfn.XLOOKUP(B32,Códigos!$A$421:$A$483,Códigos!$B$421:$B$483,"Verificar",0) -> AJUSTE POR -Consignación - Traslado a Bancos | E32: =_xlfn.XLOOKUP(C32,Códigos!$A$11:$A$415,Códigos!$B$11:$B$415,"Verificar",0) -> NOMBRE 25 | G32: 1130500 | H32: =+H31+G32 -> 60038500 | I32: Pago factura GTFF-162
A33: 45672 | B33: 27 | C33: 359 | D33: =_xlfn.XLOOKUP(B33,Códigos!$A$421:$A$483,Códigos!$B$421:$B$483,"Verificar",0) -> Compra de: -Restaurante y cafetería | E33: =_xlfn.XLOOKUP(C33,Códigos!$A$11:$A$415,Códigos!$B$11:$B$415,"Verificar",0) -> NOMBRE 232 | F33: OFICINA | G33: 400000 | H33: =+H32+G33 -> 60438500 | I33: Cuota del Mercado -DAFF-
A34: 45672 | B34: 33 | C34: 3 | D34: =_xlfn.XLOOKUP(B34,Códigos!$A$421:$A$483,Códigos!$B$421:$B$483,"Verificar",0) -> AJUSTE POR -Consignación - Traslado a Bancos | E34: =_xlfn.XLOOKUP(C34,Códigos!$A$11:$A$415,Códigos!$B$11:$B$415,"Verificar",0) -> NOMBRE 24 | G34: 1160000 | H34: =+H33+G34 -> 61598500 | I34: Pago Cuenta 24-146
A35: 45672 | B35: 1 | C35: 355 | D35: =_xlfn.XLOOKUP(B35,Códigos!$A$421:$A$483,Códigos!$B$421:$B$483,"Verificar",0) -> Gastos personales | E35: =_xlfn.XLOOKUP(C35,Códigos!$A$11:$A$415,Códigos!$B$11:$B$415,"Verificar",0) -> NOMBRE 96 | F35: GTFF | G35: 200000 | H35: =+H34+G35 -> 61798500 | I35: Gastos combustible Barbosa
A36: 45672 | B36: 23 | C36: 359 | D36: =_xlfn.XLOOKUP(B36,Códigos!$A$421:$A$483,Códigos!$B$421:$B$483,"Verificar",0) -> Compra de: -Útiles de aseo | E36: =_xlfn.XLOOKUP(C36,Códigos!$A$11:$A$415,Códigos!$B$11:$B$415,"Verificar",0) -> NOMBRE 232 | F36: OFICINA | G36: 80000 | H36: =+H35+G36 -> 61878500 | I36: Pago Aseo oficinas 604 al 608
A37: 45673 | B37: 8 | C37: 359 | D37: =_xlfn.XLOOKUP(B37,Códigos!$A$421:$A$483,Códigos!$B$421:$B$483,"Verificar",0) -> Pagos de: -Cuota para alimentos y Manuntención | E37: =_xlfn.XLOOKUP(C37,Códigos!$A$11:$A$415,Códigos!$B$11:$B$415,"Verificar",0) -> NOMBRE 232 | F37: OFICINA | G37: 198000 | H37: =+H36+G37 -> 62076500 | I37: Pago administracion Babilonia enero
A38: 45673 | B38: 1 | C38: 359 | D38: =_xlfn.XLOOKUP(B38,Códigos!$A$421:$A$483,Códigos!$B$421:$B$483,"Verificar",0) -> Gastos personales | E38: =_xlfn.XLOOKUP(C38,Códigos!$A$11:$A$415,Códigos!$B$11:$B$415,"Verificar",0) -> NOMBRE 232 | F38: OFICINA | G38: 690000 | H38: =+H37+G38 -> 62766500 | I38: Pago matricula Maria Jose
A39: 45673 | B39: 33 | C39: 3 | D39: =_xlfn.XLOOKUP(B39,Códigos!$A$421:$A$483,Códigos!$B$421:$B$483,"Verificar",0) -> AJUSTE POR -Consignación - Traslado a Bancos | E39: =_xlfn.XLOOKUP(C39,Códigos!$A$11:$A$415,Códigos!$B$11:$B$415,"Verificar",0) -> NOMBRE 24 | F39: OFICINA | G39: 50000 | H39: =+H38+G39 -> 62816500 | I39: Consignados a Diego de Ivan Velez
A40: 45673 | B40: 43 | C40: 359 | D40: =_xlfn.XLOOKUP(B40,Códigos!$A$421:$A$483,Códigos!$B$421:$B$483,"Verificar",0) -> Pago Hipotecario BANCOLOMBIA | E40: =_xlfn.XLOOKUP(C40,Códigos!$A$11:$A$415,Códigos!$B$11:$B$415,"Verificar",0) -> NOMBRE 232 | F40: OFICINA | G40: 1026800 | H40: =+H39+G40 -> 63843300 | I40: Pago credito hipotecario
A41: 45674 | B41: 27 | C41: 359 | D41: =_xlfn.XLOOKUP(B41,Códigos!$A$421:$A$483,Códigos!$B$421:$B$483,"Verificar",0) -> Compra de: -Restaurante y cafetería | E41: =_xlfn.XLOOKUP(C41,Códigos!$A$11:$A$415,Códigos!$B$11:$B$415,"Verificar",0) -> NOMBRE 232 | F41: OFICINA | G41: 38000 | H41: =+H40+G41 -> 63881300 | I41: Compra dispensador agua
A42: 45674 | B42: 27 | C42: 359 | D42: =_xlfn.XLOOKUP(B42,Códigos!$A$421:$A$483,Códigos!$B$421:$B$483,"Verificar",0) -> Compra de: -Restaurante y cafetería | E42: =_xlfn.XLOOKUP(C42,Códigos!$A$11:$A$415,Códigos!$B$11:$B$415,"Verificar",0) -> NOMBRE 232 | F42: OFICINA | G42: 88000 | H42: =+H41+G42 -> 63969300 | I42: Compra almuerzos oficinay Tintos
A43: 45674 | B43: 33 | C43: 5 | D43: =_xlfn.XLOOKUP(B43,Códigos!$A$421:$A$483,Códigos!$B$421:$B$483,"Verificar",0) -> AJUSTE POR -Consignación - Traslado a Bancos | E43: =_xlfn.XLOOKUP(C43,Códigos!$A$11:$A$415,Códigos!$B$11:$B$415,"Verificar",0) -> NOMBRE 25 | G43: 11983300 | H43: =+H42+G43 -> 75952600 | I43: Pago factura GTFF-127 y abono factura GTFF-160
A44: 45674 | B44: 33 | C44: 5 | D44: =_xlfn.XLOOKUP(B44,Códigos!$A$421:$A$483,Códigos!$B$421:$B$483,"Verificar",0) -> AJUSTE POR -Consignación - Traslado a Bancos | E44: =_xlfn.XLOOKUP(C44,Códigos!$A$11:$A$415,Códigos!$B$11:$B$415,"Verificar",0) -> NOMBRE 25 | G44: 5000000 | H44: =+H43+G44 -> 80952600 | I44: Pago factura GTFF-156 y abono factura GTFF-157
A45: 45674 | B45: 8 | C45: 356 | D45: =_xlfn.XLOOKUP(B45,Códigos!$A$421:$A$483,Códigos!$B$421:$B$483,"Verificar",0) -> Pagos de: -Cuota para alimentos y Manuntención | E45: =_xlfn.XLOOKUP(C45,Códigos!$A$11:$A$415,Códigos!$B$11:$B$415,"Verificar",0) -> NOMBRE 108 | F45: GTFF | G45: 220000 | H45: =+H44+G45 -> 81172600 | I45: Transporte U de A susana
A46: 45674 | B46: 8 | C46: 358 | D46: =_xlfn.XLOOKUP(B46,Códigos!$A$421:$A$483,Códigos!$B$421:$B$483,"Verificar",0) -> Pagos de: -Cuota para alimentos y Manuntención | E46: =_xlfn.XLOOKUP(C46,Códigos!$A$11:$A$415,Códigos!$B$11:$B$415,"Verificar",0) -> NOMBRE 338 | F46: GTFF | G46: 380000 | H46: =+H45+G46 -> 81552600 | I46: Mesada Semana 13 al 19 enero
A47: 45674 | B47: 2 | C47: 262 | D47: =_xlfn.XLOOKUP(B47,Códigos!$A$421:$A$483,Códigos!$B$421:$B$483,"Verificar",0) -> Pago de Salarios a: | E47: =_xlfn.XLOOKUP(C47,Códigos!$A$11:$A$415,Códigos!$B$11:$B$415,"Verificar",0) -> NOMBRE 95 | F47: OFICINA | G47: 660000 | H47: =+H46+G47 -> 82212600 | I47: Pago Nomina 13 al 19 enero
A48: 45674 | B48: 1 | C48: 355 | D48: =_xlfn.XLOOKUP(B48,Códigos!$A$421:$A$483,Códigos!$B$421:$B$483,"Verificar",0) -> Gastos personales | E48: =_xlfn.XLOOKUP(C48,Códigos!$A$11:$A$415,Códigos!$B$11:$B$415,"Verificar",0) -> NOMBRE 96 | F48: GTFF | G48: 500000 | H48: =+H47+G48 -> 82712600 | I48: Gastos personales
A49: 45674 | B49: 25 | C49: 359 | D49: =_xlfn.XLOOKUP(B49,Códigos!$A$421:$A$483,Códigos!$B$421:$B$483,"Verificar",0) -> Compra de: -Manuales, Libros y formularios | E49: =_xlfn.XLOOKUP(C49,Códigos!$A$11:$A$415,Códigos!$B$11:$B$415,"Verificar",0) -> NOMBRE 232 | F49: OFICINA | G49: 196400 | H49: =+H48+G49 -> 82909000 | I49: Pago seminario CETA
A50: 45677 | B50: 9 | C50: 359 | D50: =_xlfn.XLOOKUP(B50,Códigos!$A$421:$A$483,Códigos!$B$421:$B$483,"Verificar",0) -> Pagos de: -Servicios públicos -OFICINA- | E50: =_xlfn.XLOOKUP(C50,Códigos!$A$11:$A$415,Códigos!$B$11:$B$415,"Verificar",0) -> NOMBRE 232 | F50: OFICINA | G50: 242500 | H50: =+H49+G50 -> 83151500 | I50: Pago Tigo UNE oficina 604
A51: 45677 | B51: 9 | C51: 359 | D51: =_xlfn.XLOOKUP(B51,Códigos!$A$421:$A$483,Códigos!$B$421:$B$483,"Verificar",0) -> Pagos de: -Servicios públicos -OFICINA- | E51: =_xlfn.XLOOKUP(C51,Códigos!$A$11:$A$415,Códigos!$B$11:$B$415,"Verificar",0) -> NOMBRE 232 | F51: OFICINA | G51: 303900 | H51: =+H50+G51 -> 83455400 | I51: Pago Tigo UNE oficina Internet
A52: 21 | B52: 28 | C52: 249 | D52: =_xlfn.XLOOKUP(B52,Códigos!$A$421:$A$483,Códigos!$B$421:$B$483,"Verificar",0) -> Préstamos a: | E52: =_xlfn.XLOOKUP(C52,Códigos!$A$11:$A$415,Códigos!$B$11:$B$415,"Verificar",0) -> NOMBRE 220 | F52: OFICINA | G52: 1185000 | H52: =+H51+G52 -> 84640400 | I52: Pago Administracion del Gaspar de Rodas
A53: 21 | B53: 33 | C53: 5 | D53: =_xlfn.XLOOKUP(B53,Códigos!$A$421:$A$483,Códigos!$B$421:$B$483,"Verificar",0) -> AJUSTE POR -Consignación - Traslado a Bancos | E53: =_xlfn.XLOOKUP(C53,Códigos!$A$11:$A$415,Códigos!$B$11:$B$415,"Verificar",0) -> NOMBRE 25 | F53: OFICINA | G53: 1096000 | H53: =+H52+G53 -> 85736400 | I53: Pago IVA 3er CUATR Libardo Gaviria
A54: 21 | B54: 29 | C54: 101 | D54: =_xlfn.XLOOKUP(B54,Códigos!$A$421:$A$483,Códigos!$B$421:$B$483,"Verificar",0) -> Egresos por Cuenta de Terceros -Pagos impuestos- | E54: =_xlfn.XLOOKUP(C54,Códigos!$A$11:$A$415,Códigos!$B$11:$B$415,"Verificar",0) -> NOMBRE 126 | F54: OFICINA | G54: 1096000 | H54: =+H53+G54 -> 86832400 | I54: Pago IVA 3er CUATR Libardo Gaviria
A55: 45681 | B55: 8 | C55: 357 | D55: =_xlfn.XLOOKUP(B55,Códigos!$A$421:$A$483,Códigos!$B$421:$B$483,"Verificar",0) -> Pagos de: -Cuota para alimentos y Manuntención | E55: =_xlfn.XLOOKUP(C55,Códigos!$A$11:$A$415,Códigos!$B$11:$B$415,"Verificar",0) -> NOMBRE 107 | F55: GTFF | G55: 220000 | H55: =+H54+G55 -> 87052400 | I55: Pago mesada tranporte U de A
A56: 45681 | B56: 2 | C56: 353 | D56: =_xlfn.XLOOKUP(B56,Códigos!$A$421:$A$483,Códigos!$B$421:$B$483,"Verificar",0) -> Pago de Salarios a: | E56: =_xlfn.XLOOKUP(C56,Códigos!$A$11:$A$415,Códigos!$B$11:$B$415,"Verificar",0) -> NOMBRE 31 | F56: OFICINA | G56: 660000 | H56: =+H55+G56 -> 87712400 | I56: Pago Nomina 20 al 26 enero
... A62: 45684 | B62: 28 | C62: 249 | D62: =_xlfn.XLOOKUP(B62,Códigos!$A$421:$A$483,Códigos!$B$421:$B$483,"Verificar",0) -> Préstamos a: | E62: =_xlfn.XLOOKUP(C62,Códigos!$A$11:$A$415,Códigos!$B$11:$B$415,"Verificar",0) -> NOMBRE 220 | F62: OFICINA | G62: 130000 | H62: =+H61+G62 -> 89582400 | I62: Pago Administracion Parqueadero San Jose
A63: 45684 | B63: 22 | C63: 359 | D63: =_xlfn.XLOOKUP(B63,Códigos!$A$421:$A$483,Códigos!$B$421:$B$483,"Verificar",0) -> Compra de: -Equipos, dotaciones y repuestos para oficina | E63: =_xlfn.XLOOKUP(C63,Códigos!$A$11:$A$415,Códigos!$B$11:$B$415,"Verificar",0) -> NOMBRE 232 | F63: OFICINA | G63: =800000+380000 -> 1180000 | H63: =+H62+G63 -> 90762400 | I63: Pago mantenimiento computadores mes enero
A64: 45685 | B64: 9 | C64: 359 | D64: =_xlfn.XLOOKUP(B64,Códigos!$A$421:$A$483,Códigos!$B$421:$B$483,"Verificar",0) -> Pagos de: -Servicios públicos -OFICINA- | E64: =_xlfn.XLOOKUP(C64,Códigos!$A$11:$A$415,Códigos!$B$11:$B$415,"Verificar",0) -> NOMBRE 232 | F64: OFICINA | G64: 143700 | H64: =+H63+G64 -> 90906100 | I64: Pago EPM Babilonia
A65: 45685 | B65: 28 | C65: 249 | D65: =_xlfn.XLOOKUP(B65,Códigos!$A$421:$A$483,Códigos!$B$421:$B$483,"Verificar",0) -> Préstamos a: | E65: =_xlfn.XLOOKUP(C65,Códigos!$A$11:$A$415,Códigos!$B$11:$B$415,"Verificar",0) -> NOMBRE 220 | F65: OFICINA | G65: 52100 | H65: =+H64+G65 -> 90958200 | I65: Pago EPM oficina 604
A66: 45685 | B66: 9 | C66: 359 | D66: =_xlfn.XLOOKUP(B66,Códigos!$A$421:$A$483,Códigos!$B$421:$B$483,"Verificar",0) -> Pagos de: -Servicios públicos -OFICINA- | E66: =_xlfn.XLOOKUP(C66,Códigos!$A$11:$A$415,Códigos!$B$11:$B$415,"Verificar",0) -> NOMBRE 232 | F66: OFICINA | G66: 242300 | H66: =+H65+G66 -> 91200500 | I66: Pago EPM oficina 605
A67: 45685 | B67: 5 | C67: 262 | D67: =_xlfn.XLOOKUP(B67,Códigos!$A$421:$A$483,Códigos!$B$421:$B$483,"Verificar",0) -> Préstamos por Nómina a: | E67: =_xlfn.XLOOKUP(C67,Códigos!$A$11:$A$415,Códigos!$B$11:$B$415,"Verificar",0) -> NOMBRE 95 | G67: 44200 | H67: =+H66+G67 -> 91244700 | I67: Pago EPM Diego
A68: 45685 | B68: 1 | C68: 355 | D68: =_xlfn.XLOOKUP(B68,Códigos!$A$421:$A$483,Códigos!$B$421:$B$483,"Verificar",0) -> Gastos personales | E68: =_xlfn.XLOOKUP(C68,Códigos!$A$11:$A$415,Códigos!$B$11:$B$415,"Verificar",0) -> NOMBRE 96 | F68: OFICINA | G68: 400000 | H68: =+H67+G68 -> 91644700 | I68: Gastos personales
A69: 45687 | B69: 5 | C69: 262 | D69: =_xlfn.XLOOKUP(B69,Códigos!$A$421:$A$483,Códigos!$B$421:$B$483,"Verificar",0) -> Préstamos por Nómina a: | E69: =_xlfn.XLOOKUP(C69,Códigos!$A$11:$A$415,Códigos!$B$11:$B$415,"Verificar",0) -> NOMBRE 95 | G69: 200000 | H69: =+H68+G69 -> 91844700 | I69: pago operación Simur
A70: 45688 | B70: 8 | C70: 357 | D70: =_xlfn.XLOOKUP(B70,Códigos!$A$421:$A$483,Códigos!$B$421:$B$483,"Verificar",0) -> Pagos de: -Cuota para alimentos y Manuntención | E70: =_xlfn.XLOOKUP(C70,Códigos!$A$11:$A$415,Códigos!$B$11:$B$415,"Verificar",0) -> NOMBRE 107 | F70: GTFF | G70: 220000 | H70: =+H69+G70 -> 92064700 | I70: Pago mesada tranporte U de A
A71: 45688 | B71: 2 | C71: 353 | D71: =_xlfn.XLOOKUP(B71,Códigos!$A$421:$A$483,Códigos!$B$421:$B$483,"Verificar",0) -> Pago de Salarios a: | E71: =_xlfn.XLOOKUP(C71,Códigos!$A$11:$A$415,Códigos!$B$11:$B$415,"Verificar",0) -> NOMBRE 31 | F71: OFICINA | G71: 660000 | H71: =+H70+G71 -> 92724700 | I71: Pago Nomina 27 enero al 02 febrero
A72: 45688 | B72: 8 | C72: 356 | D72: =_xlfn.XLOOKUP(B72,Códigos!$A$421:$A$483,Códigos!$B$421:$B$483,"Verificar",0) -> Pagos de: -Cuota para alimentos y Manuntención | E72: =_xlfn.XLOOKUP(C72,Códigos!$A$11:$A$415,Códigos!$B$11:$B$415,"Verificar",0) -> NOMBRE 108 | F72: GTFF | G72: 220000 | H72: =+H71+G72 -> 92944700 | I72: Pago mesada tranporte U de A
A73: 45688 | B73: 8 | C73: 358 | D73: =_xlfn.XLOOKUP(B73,Códigos!$A$421:$A$483,Códigos!$B$421:$B$483,"Verificar",0) -> Pagos de: -Cuota para alimentos y Manuntención | E73: =_xlfn.XLOOKUP(C73,Códigos!$A$11:$A$415,Códigos!$B$11:$B$415,"Verificar",0) -> NOMBRE 338 | F73: GTFF | G73: 380000 | H73: =+H72+G73 -> 93324700 | I73: Mesada Semana 27 enero al 02 febrero
A74: 45688 | B74: 2 | C74: 262 | D74: =_xlfn.XLOOKUP(B74,Códigos!$A$421:$A$483,Códigos!$B$421:$B$483,"Verificar",0) -> Pago de Salarios a: | E74: =_xlfn.XLOOKUP(C74,Códigos!$A$11:$A$415,Códigos!$B$11:$B$415,"Verificar",0) -> NOMBRE 95 | F74: OFICINA | G74: 660000 | H74: =+H73+G74 -> 93984700 | I74: Pago Nomina 27 enero al 02 febrero
A75: 45688 | B75: 5 | C75: 262 | D75: =_xlfn.XLOOKUP(B75,Códigos!$A$421:$A$483,Códigos!$B$421:$B$483,"Verificar",0) -> Préstamos por Nómina a: | E75: =_xlfn.XLOOKUP(C75,Códigos!$A$11:$A$415,Códigos!$B$11:$B$415,"Verificar",0) -> NOMBRE 95 | G75: 500000 | H75: =+H74+G75 -> 94484700 | I75: Abono Compra gafas
A76: 45692 | B76: 7 | C76: 359 | D76: =_xlfn.XLOOKUP(B76,Códigos!$A$421:$A$483,Códigos!$B$421:$B$483,"Verificar",0) -> Pagos de: -Seguridad Social | E76: =_xlfn.XLOOKUP(C76,Códigos!$A$11:$A$415,Códigos!$B$11:$B$415,"Verificar",0) -> NOMBRE 232 | F76: OFICINA | G76: 1392400 | H76: =+H75+G76 -> 95877100 | I76: Pago Seguridad Social Empleados marzo
A77: 45692 | B77: 7 | C77: 359 | D77: =_xlfn.XLOOKUP(B77,Códigos!$A$421:$A$483,Códigos!$B$421:$B$483,"Verificar",0) -> Pagos de: -Seguridad Social | E77: =_xlfn.XLOOKUP(C77,Códigos!$A$11:$A$415,Códigos!$B$11:$B$415,"Verificar",0) -> NOMBRE 232 | F77: OFICINA | G77: 940500 | H77: =+H76+G77 -> 96817600 | I77: Pago Seguridad Social Independiente febrero
A78: 45692 | B78: 5 | C78: 262 | D78: =_xlfn.XLOOKUP(B78,Códigos!$A$421:$A$483,Códigos!$B$421:$B$483,"Verificar",0) -> Préstamos por Nómina a: | E78: =_xlfn.XLOOKUP(C78,Códigos!$A$11:$A$415,Códigos!$B$11:$B$415,"Verificar",0) -> NOMBRE 95 | F78: OFICINA | G78: 100000 | H78: =+H77+G78 -> 96917600 | I78: Pago consignacion a Camila Bedoya
A79: 45692 | B79: 5 | C79: 262 | D79: =_xlfn.XLOOKUP(B79,Códigos!$A$421:$A$483,Códigos!$B$421:$B$483,"Verificar",0) -> Préstamos por Nómina a: | E79: =_xlfn.XLOOKUP(C79,Códigos!$A$11:$A$415,Códigos!$B$11:$B$415,"Verificar",0) -> NOMBRE 95 | F79: OFICINA | G79: 100000 | H79: =+H78+G79 -> 97017600 | I79: Pago consignacion a Andres Zapata Bedoya
A80: 45692 | B80: 1 | C80: 355 | D80: =_xlfn.XLOOKUP(B80,Códigos!$A$421:$A$483,Códigos!$B$421:$B$483,"Verificar",0) -> Gastos personales | E80: =_xlfn.XLOOKUP(C80,Códigos!$A$11:$A$415,Códigos!$B$11:$B$415,"Verificar",0) -> NOMBRE 96 | F80: OFICINA | G80: 200000 | H80: =+H79+G80 -> 97217600 | I80: Gastos personales
A81: 45692 | B81: 9 | C81: 359 | D81: =_xlfn.XLOOKUP(B81,Códigos!$A$421:$A$483,Códigos!$B$421:$B$483,"Verificar",0) -> Pagos de: -Servicios públicos -OFICINA- | E81: =_xlfn.XLOOKUP(C81,Códigos!$A$11:$A$415,Códigos!$B$11:$B$415,"Verificar",0) -> NOMBRE 232 | F81: OFICINA | G81: 129900 | H81: =+H80+G81 -> 97347500 | I81: Pago tigo UNE German Barbosa
A82: 45693 | B82: 27 | C82: 359 | D82: =_xlfn.XLOOKUP(B82,Códigos!$A$421:$A$483,Códigos!$B$421:$B$483,"Verificar",0) -> Compra de: -Restaurante y cafetería | E82: =_xlfn.XLOOKUP(C82,Códigos!$A$11:$A$415,Códigos!$B$11:$B$415,"Verificar",0) -> NOMBRE 232 | F82: OFICINA | G82: 400000 | H82: =+H81+G82 -> 97747500 | I82: Cuota del Mercado -DAFF-
A83: 45693 | B83: 5 | C83: 262 | D83: =_xlfn.XLOOKUP(B83,Códigos!$A$421:$A$483,Códigos!$B$421:$B$483,"Verificar",0) -> Préstamos por Nómina a: | E83: =_xlfn.XLOOKUP(C83,Códigos!$A$11:$A$415,Códigos!$B$11:$B$415,"Verificar",0) -> NOMBRE 95 | G83: 300000 | H83: =+H82+G83 -> 98047500 | I83: Abono Compra gafas
A84: 45693 | B84: 12 | C84: 359 | D84: =_xlfn.XLOOKUP(B84,Códigos!$A$421:$A$483,Códigos!$B$421:$B$483,"Verificar",0) -> Pagos de: -Celulares | E84: =_xlfn.XLOOKUP(C84,Códigos!$A$11:$A$415,Códigos!$B$11:$B$415,"Verificar",0) -> NOMBRE 232 | F84: GTFF | G84: 59700 | H84: =+H83+G84 -> 98107200 | I84: Pago Movistar Diego
A85: 45693 | B85: 8 | C85: 357 | D85: =_xlfn.XLOOKUP(B85,Códigos!$A$421:$A$483,Códigos!$B$421:$B$483,"Verificar",0) -> Pagos de: -Cuota para alimentos y Manuntención | E85: =_xlfn.XLOOKUP(C85,Códigos!$A$11:$A$415,Códigos!$B$11:$B$415,"Verificar",0) -> NOMBRE 107 | F85: GTFF | G85: 220000 | H85: =+H84+G85 -> 98327200 | I85: Pago mesada tranporte U de A
A86: 45693 | B86: 2 | C86: 353 | D86: =_xlfn.XLOOKUP(B86,Códigos!$A$421:$A$483,Códigos!$B$421:$B$483,"Verificar",0) -> Pago de Salarios a: | E86: =_xlfn.XLOOKUP(C86,Códigos!$A$11:$A$415,Códigos!$B$11:$B$415,"Verificar",0) -> NOMBRE 31 | F86: OFICINA | G86: 660000 | H86: =+H85+G86 -> 98987200 | I86: Pago Nomina 03 al 09 febrero
A87: 45693 | B87: 35 | C87: 359 | D87: =_xlfn.XLOOKUP(B87,Códigos!$A$421:$A$483,Códigos!$B$421:$B$483,"Verificar",0) -> Impuestos, tasas y contribuciones -GTFF- | E87: =_xlfn.XLOOKUP(C87,Códigos!$A$11:$A$415,Códigos!$B$11:$B$415,"Verificar",0) -> NOMBRE 232 | F87: GTFF | G87: 1257200 | H87: =+H86+G87 -> 100244400 | I87: Pago Predial Barbosa
A88: 45694 | B88: 1 | C88: 355 | D88: =_xlfn.XLOOKUP(B88,Códigos!$A$421:$A$483,Códigos!$B$421:$B$483,"Verificar",0) -> Gastos personales | E88: =_xlfn.XLOOKUP(C88,Códigos!$A$11:$A$415,Códigos!$B$11:$B$415,"Verificar",0) -> NOMBRE 96 | F88: OFICINA | G88: 210000 | H88: =+H87+G88 -> 100454400 | I88: Gastos personales
A89: 45695 | B89: 8 | C89: 356 | D89: =_xlfn.XLOOKUP(B89,Códigos!$A$421:$A$483,Códigos!$B$421:$B$483,"Verificar",0) -> Pagos de: -Cuota para alimentos y Manuntención | E89: =_xlfn.XLOOKUP(C89,Códigos!$A$11:$A$415,Códigos!$B$11:$B$415,"Verificar",0) -> NOMBRE 108 | F89: GTFF | G89: 220000 | H89: =+H88+G89 -> 100674400 | I89: Pago mesada tranporte U de A
A90: 45695 | B90: 8 | C90: 358 | D90: =_xlfn.XLOOKUP(B90,Códigos!$A$421:$A$483,Códigos!$B$421:$B$483,"Verificar",0) -> Pagos de: -Cuota para alimentos y Manuntención | E90: =_xlfn.XLOOKUP(C90,Códigos!$A$11:$A$415,Códigos!$B$11:$B$415,"Verificar",0) -> NOMBRE 338 | F90: GTFF | G90: 380000 | H90: =+H89+G90 -> 101054400 | I90: Mesada Semana 02al 09 febrero
A91: 45695 | B91: 2 | C91: 262 | D91: =_xlfn.XLOOKUP(B91,Códigos!$A$421:$A$483,Códigos!$B$421:$B$483,"Verificar",0) -> Pago de Salarios a: | E91: =_xlfn.XLOOKUP(C91,Códigos!$A$11:$A$415,Códigos!$B$11:$B$415,"Verificar",0) -> NOMBRE 95 | F91: OFICINA | G91: 660000 | H91: =+H90+G91 -> 101714400 | I91: Pago Nomina 03 al 09 febrero
A92: 45695 | B92: 1 | C92: 355 | D92: =_xlfn.XLOOKUP(B92,Códigos!$A$421:$A$483,Códigos!$B$421:$B$483,"Verificar",0) -> Gastos personales | E92: =_xlfn.XLOOKUP(C92,Códigos!$A$11:$A$415,Códigos!$B$11:$B$415,"Verificar",0) -> NOMBRE 96 | F92: OFICINA | G92: 400000 | H92: =+H91+G92 -> 102114400 | I92: Gastos personales
A93: 45699 | B93: 29 | C93: 8 | D93: =_xlfn.XLOOKUP(B93,Códigos!$A$421:$A$483,Códigos!$B$421:$B$483,"Verificar",0) -> Egresos por Cuenta de Terceros -Pagos impuestos- | E93: =_xlfn.XLOOKUP(C93,Códigos!$A$11:$A$415,Códigos!$B$11:$B$415,"Verificar",0) -> NOMBRE 64 | F93: OFICINA | G93: 53000 | H93: =+H92+G93 -> 102167400 | I93: Pago RF 01 2025
A94: 45700 | B94: 10 | C94: 359 | D94: =_xlfn.XLOOKUP(B94,Códigos!$A$421:$A$483,Códigos!$B$421:$B$483,"Verificar",0) -> Pagos de: -Servicios públicos -NIÑAS- | E94: =_xlfn.XLOOKUP(C94,Códigos!$A$11:$A$415,Códigos!$B$11:$B$415,"Verificar",0) -> NOMBRE 232 | F94: GTFF | G94: 125500 | H94: =+H93+G94 -> 102292900 | I94: Pago Tigo Babilonia febrero
A95: 45700 | B95: 9 | C95: 359 | D95: =_xlfn.XLOOKUP(B95,Códigos!$A$421:$A$483,Códigos!$B$421:$B$483,"Verificar",0) -> Pagos de: -Servicios públicos -OFICINA- | E95: =_xlfn.XLOOKUP(C95,Códigos!$A$11:$A$415,Códigos!$B$11:$B$415,"Verificar",0) -> NOMBRE 232 | F95: OFICINA | G95: 106700 | H95: =+H94+G95 -> 102399600 | I95: Pago EPM Barbosa
... A108: 45702 | B108: 1 | C108: 355 | D108: =_xlfn.XLOOKUP(B108,Códigos!$A$421:$A$483,Códigos!$B$421:$B$483,"Verificar",0) -> Gastos personales | E108: =_xlfn.XLOOKUP(C108,Códigos!$A$11:$A$415,Códigos!$B$11:$B$415,"Verificar",0) -> NOMBRE 96 | F108: OFICINA | G108: 400000 | H108: =+H107+G108 -> 110744100 | I108: Gastos personales
A109: 45702 | B109: 33 | C109: 3 | D109: =_xlfn.XLOOKUP(B109,Códigos!$A$421:$A$483,Códigos!$B$421:$B$483,"Verificar",0) -> AJUSTE POR -Consignación - Traslado a Bancos | E109: =_xlfn.XLOOKUP(C109,Códigos!$A$11:$A$415,Códigos!$B$11:$B$415,"Verificar",0) -> NOMBRE 24 | G109: 320000 | H109: =+H108+G109 -> 111064100 | I109: Pago Cuenta 24-028
A110: 45702 | B110: 33 | C110: 3 | D110: =_xlfn.XLOOKUP(B110,Códigos!$A$421:$A$483,Códigos!$B$421:$B$483,"Verificar",0) -> AJUSTE POR -Consignación - Traslado a Bancos | E110: =_xlfn.XLOOKUP(C110,Códigos!$A$11:$A$415,Códigos!$B$11:$B$415,"Verificar",0) -> NOMBRE 24 | G110: 430000 | H110: =+H109+G110 -> 111494100 | I110: Pago Cuenta 24-118
A111: 45702 | B111: 33 | C111: 3 | D111: =_xlfn.XLOOKUP(B111,Códigos!$A$421:$A$483,Códigos!$B$421:$B$483,"Verificar",0) -> AJUSTE POR -Consignación - Traslado a Bancos | E111: =_xlfn.XLOOKUP(C111,Códigos!$A$11:$A$415,Códigos!$B$11:$B$415,"Verificar",0) -> NOMBRE 24 | G111: 620000 | H111: =+H110+G111 -> 112114100 | I111: Pago Cuenta 24-111
A112: 45704 | B112: 43 | C112: 359 | D112: =_xlfn.XLOOKUP(B112,Códigos!$A$421:$A$483,Códigos!$B$421:$B$483,"Verificar",0) -> Pago Hipotecario BANCOLOMBIA | E112: =_xlfn.XLOOKUP(C112,Códigos!$A$11:$A$415,Códigos!$B$11:$B$415,"Verificar",0) -> NOMBRE 232 | F112: OFICINA | G112: 1026800 | H112: =+H111+G112 -> 113140900 | I112: Pago credito hipotecario
A113: 45705 | B113: 33 | C113: 3 | D113: =_xlfn.XLOOKUP(B113,Códigos!$A$421:$A$483,Códigos!$B$421:$B$483,"Verificar",0) -> AJUSTE POR -Consignación - Traslado a Bancos | E113: =_xlfn.XLOOKUP(C113,Códigos!$A$11:$A$415,Códigos!$B$11:$B$415,"Verificar",0) -> NOMBRE 24 | G113: 330000 | H113: =+H112+G113 -> 113470900 | I113: Pago Cuenta 24-090
A114: 45706 | B114: 1 | C114: 355 | D114: =_xlfn.XLOOKUP(B114,Códigos!$A$421:$A$483,Códigos!$B$421:$B$483,"Verificar",0) -> Gastos personales | E114: =_xlfn.XLOOKUP(C114,Códigos!$A$11:$A$415,Códigos!$B$11:$B$415,"Verificar",0) -> NOMBRE 96 | F114: GTFF | G114: 100000 | H114: =+H113+G114 -> 113570900 | I114: Gastos combustible
A115: 45706 | B115: 22 | C115: 359 | D115: =_xlfn.XLOOKUP(B115,Códigos!$A$421:$A$483,Códigos!$B$421:$B$483,"Verificar",0) -> Compra de: -Equipos, dotaciones y repuestos para oficina | E115: =_xlfn.XLOOKUP(C115,Códigos!$A$11:$A$415,Códigos!$B$11:$B$415,"Verificar",0) -> NOMBRE 232 | F115: OFICINA | G115: 340000 | H115: =+H114+G115 -> 113910900 | I115: Pago Antivirus Felipe Isabel y Diego
A116: 45708 | B116: 12 | C116: 359 | D116: =_xlfn.XLOOKUP(B116,Códigos!$A$421:$A$483,Códigos!$B$421:$B$483,"Verificar",0) -> Pagos de: -Celulares | E116: =_xlfn.XLOOKUP(C116,Códigos!$A$11:$A$415,Códigos!$B$11:$B$415,"Verificar",0) -> NOMBRE 232 | F116: GTFF | G116: 2487900 | H116: =+H115+G116 -> 116398800 | I116: Pago Predial Libia Velasquez
A117: 45708 | B117: 12 | C117: 359 | D117: =_xlfn.XLOOKUP(B117,Códigos!$A$421:$A$483,Códigos!$B$421:$B$483,"Verificar",0) -> Pagos de: -Celulares | E117: =_xlfn.XLOOKUP(C117,Códigos!$A$11:$A$415,Códigos!$B$11:$B$415,"Verificar",0) -> NOMBRE 232 | F117: GTFF | G117: 117600 | H117: =+H116+G117 -> 116516400 | I117: Pago Predial German Casa de Mario
A118: 45708 | B118: 8 | C118: 359 | D118: =_xlfn.XLOOKUP(B118,Códigos!$A$421:$A$483,Códigos!$B$421:$B$483,"Verificar",0) -> Pagos de: -Cuota para alimentos y Manuntención | E118: =_xlfn.XLOOKUP(C118,Códigos!$A$11:$A$415,Códigos!$B$11:$B$415,"Verificar",0) -> NOMBRE 232 | F118: OFICINA | G118: 198000 | H118: =+H117+G118 -> 116714400 | I118: Pago administracion Babilonia febrero
A119: 45708 | B119: 8 | C119: 357 | D119: =_xlfn.XLOOKUP(B119,Códigos!$A$421:$A$483,Códigos!$B$421:$B$483,"Verificar",0) -> Pagos de: -Cuota para alimentos y Manuntención | E119: =_xlfn.XLOOKUP(C119,Códigos!$A$11:$A$415,Códigos!$B$11:$B$415,"Verificar",0) -> NOMBRE 107 | F119: GTFF | G119: 220000 | H119: =+H118+G119 -> 116934400 | I119: Pago mesada tranporte U de A
A120: 45708 | B120: 2 | C120: 353 | D120: =_xlfn.XLOOKUP(B120,Códigos!$A$421:$A$483,Códigos!$B$421:$B$483,"Verificar",0) -> Pago de Salarios a: | E120: =_xlfn.XLOOKUP(C120,Códigos!$A$11:$A$415,Códigos!$B$11:$B$415,"Verificar",0) -> NOMBRE 31 | F120: OFICINA | G120: 660000 | H120: =+H119+G120 -> 117594400 | I120: Pago Nomina 17 al 23 febrero
A121: 45708 | B121: 33 | C121: 3 | D121: =_xlfn.XLOOKUP(B121,Códigos!$A$421:$A$483,Códigos!$B$421:$B$483,"Verificar",0) -> AJUSTE POR -Consignación - Traslado a Bancos | E121: =_xlfn.XLOOKUP(C121,Códigos!$A$11:$A$415,Códigos!$B$11:$B$415,"Verificar",0) -> NOMBRE 24 | G121: 1160000 | H121: =+H120+G121 -> 118754400 | I121: Pago Cuenta 24-147
A122: 45709 | B122: 8 | C122: 356 | D122: =_xlfn.XLOOKUP(B122,Códigos!$A$421:$A$483,Códigos!$B$421:$B$483,"Verificar",0) -> Pagos de: -Cuota para alimentos y Manuntención | E122: =_xlfn.XLOOKUP(C122,Códigos!$A$11:$A$415,Códigos!$B$11:$B$415,"Verificar",0) -> NOMBRE 108 | F122: GTFF | G122: 220000 | H122: =+H121+G122 -> 118974400 | I122: Pago mesada tranporte U de A
...

Sheet ACUM CAJADIARIO
A1: =+Códigos!$A$1 -> LIBRO DIARIO OFICINA | F1: ARQUEOS DE CAJA | H1: =SUM(H4:H11) -> 807500
A2: ACUMULADOS DE CAJA
A3: =+Códigos!$A$3 -> AÑO: | B3: =+Códigos!$B$3 -> 2025 | F3: DENOMINACIÓN | G3: CANT | H3: TOTAL
A4: DESDE: | B4: =+'INGRESOS A CAJA'!D4 -> 45658 | F4: 100000 | G4: 2 | H4: =+F4*G4 -> 200000
A5: HASTA: | B5: =+'INGRESOS A CAJA'!D5 -> 46022 | F5: 50000 | G5: 12 | H5: =+F5*G5 -> 600000
F6: 20000 | G6: 0 | H6: =+F6*G6 -> 0
A7: ARQUEOS DE CAJA -Efectivo | C7: TOTAL | D7: =+H1 -> 807500 | F7: 10000 | G7: 0 | H7: =+F7*G7 -> 0
C8: SOBRANTE | D8: =IF((D15-D7)<0,-(D15-D7),0) -> 300000 | F8: 5000 | G8: 1 | H8: =+F8*G8 -> 5000
C9: FALTANTE | D9: =IF((D15-D7)>0,(D15-D7),0) -> 0 | F9: 2000 | G9: 1 | H9: =+F9*G9 -> 2000
F10: 1000 | G10: 0 | H10: =+F10*G10 -> 0
A11: CÓDIGO | B11: CONCEPTO | C11: VALOR ACUMULADO POR CÓDIGO | D11: ACUMULADO | F11: MONEDAS | H11: 500
B12: TOTALES EGRESOS | C12: =+C81 -> 633732083 | D12: =+D81 -> 633732083 | F12: =+C12-D12 -> 0 | G12: Control: Diferencia debe ser = 0
B13: TOTAL INGRESOS | C13: =+C119 -> 634239583 | D13: =+D119 -> 634239583 | F13: =+C13-D13 -> 0 | G13: Control: Diferencia debe ser = 0
A14: SALDO INICIAL EN CAJA | C14: 0
A15: SALDO ACTUAL DE CAJA | D15: =C14+C119-C81 -> 507500
A17: EGRESOS
A19: 1 | B19: =_xlfn.XLOOKUP(A19,Códigos!$A$421:$A$483,Códigos!$B$421:$B$483,"Verificar",0) -> Gastos personales | C19: =SUMIF('EGRESOS DE CAJA'!$B$9:$B$5958,A19,'EGRESOS DE CAJA'!$G$9:$G$5958) -> 193927304 | D19: =C19 -> 193927304
A20: 2 | B20: =_xlfn.XLOOKUP(A20,Códigos!$A$421:$A$483,Códigos!$B$421:$B$483,"Verificar",0) -> Pago de Salarios a: | C20: =SUMIF('EGRESOS DE CAJA'!$B$9:$B$5958,A20,'EGRESOS DE CAJA'!$G$9:$G$5958) -> 57460000 | D20: =D19+C20 -> 251387304
A21: 3 | B21: =_xlfn.XLOOKUP(A21,Códigos!$A$421:$A$483,Códigos!$B$421:$B$483,"Verificar",0) -> Pago de Prestaciones sociales a: | C21: =SUMIF('EGRESOS DE CAJA'!$B$9:$B$5958,A21,'EGRESOS DE CAJA'!$G$9:$G$5958) -> 0 | D21: =D20+C21 -> 251387304
A22: 4 | B22: =_xlfn.XLOOKUP(A22,Códigos!$A$421:$A$483,Códigos!$B$421:$B$483,"Verificar",0) -> Pago de Bonificación a: | C22: =SUMIF('EGRESOS DE CAJA'!$B$9:$B$5958,A22,'EGRESOS DE CAJA'!$G$9:$G$5958) -> 0 | D22: =D21+C22 -> 251387304
A23: 5 | B23: =_xlfn.XLOOKUP(A23,Códigos!$A$421:$A$483,Códigos!$B$421:$B$483,"Verificar",0) -> Préstamos por Nómina a: | C23: =SUMIF('EGRESOS DE CAJA'!$B$9:$B$5958,A23,'EGRESOS DE CAJA'!$G$9:$G$5958) -> 12065900 | D23: =D22+C23 -> 263453204
A24: 6 | B24: =_xlfn.XLOOKUP(A24,Códigos!$A$421:$A$483,Códigos!$B$421:$B$483,"Verificar",0) -> Préstamos por Nómina a: | C24: =SUMIF('EGRESOS DE CAJA'!$B$9:$B$5958,A24,'EGRESOS DE CAJA'!$G$9:$G$5958) -> 67737400 | D24: =D23+C24 -> 331190604
A25: 7 | B25: =_xlfn.XLOOKUP(A25,Códigos!$A$421:$A$483,Códigos!$B$421:$B$483,"Verificar",0) -> Pagos de: -Seguridad Social | C25: =SUMIF('EGRESOS DE CAJA'!$B$9:$B$5958,A25,'EGRESOS DE CAJA'!$G$9:$G$5958) -> 27296800 | D25: =D24+C25 -> 358487404
A26: 8 | B26: =_xlfn.XLOOKUP(A26,Códigos!$A$421:$A$483,Códigos!$B$421:$B$483,"Verificar",0) -> Pagos de: -Cuota para alimentos y Manuntención | C26: =SUMIF('EGRESOS DE CAJA'!$B$9:$B$5958,A26,'EGRESOS DE CAJA'!$G$9:$G$5958) -> 43358150 | D26: =D25+C26 -> 401845554
A27: 9 | B27: =_xlfn.XLOOKUP(A27,Códigos!$A$421:$A$483,Códigos!$B$421:$B$483,"Verificar",0) -> Pagos de: -Servicios públicos -OFICINA- | C27: =SUMIF('EGRESOS DE CAJA'!$B$9:$B$5958,A27,'EGRESOS DE CAJA'!$G$9:$G$5958) -> 10779655 | D27: =D26+C27 -> 412625209
A28: 10 | B28: =_xlfn.XLOOKUP(A28,Códigos!$A$421:$A$483,Códigos!$B$421:$B$483,"Verificar",0) -> Pagos de: -Servicios públicos -NIÑAS- | C28: =SUMIF('EGRESOS DE CAJA'!$B$9:$B$5958,A28,'EGRESOS DE CAJA'!$G$9:$G$5958) -> 816300 | D28: =D27+C28 -> 413441509
A29: 11 | B29: =_xlfn.XLOOKUP(A29,Códigos!$A$421:$A$483,Códigos!$B$421:$B$483,"Verificar",0) -> Pagos de: -Servicios Administracion y otros Oficina | C29: =SUMIF('EGRESOS DE CAJA'!$B$9:$B$5958,A29,'EGRESOS DE CAJA'!$G$9:$G$5958) -> 6596185 | D29: =D28+C29 -> 420037694
A30: 12 | B30: =_xlfn.XLOOKUP(A30,Códigos!$A$421:$A$483,Códigos!$B$421:$B$483,"Verificar",0) -> Pagos de: -Celulares | C30: =SUMIF('EGRESOS DE CAJA'!$B$9:$B$5958,A30,'EGRESOS DE CAJA'!$G$9:$G$5958) -> 3595890 | D30: =D29+C30 -> 423633584
A31: 13 | B31: =_xlfn.XLOOKUP(A31,Códigos!$A$421:$A$483,Códigos!$B$421:$B$483,"Verificar",0) -> Pagos de: -Suscripciones | C31: =SUMIF('EGRESOS DE CAJA'!$B$9:$B$5958,A31,'EGRESOS DE CAJA'!$G$9:$G$5958) -> 0 | D31: =D30+C31 -> 423633584
... A78: 60 | B78: =_xlfn.XLOOKUP(A78,Códigos!$A$421:$A$483,Códigos!$B$421:$B$483,"Verificar",0) -> 0 | C78: =SUMIF('EGRESOS DE CAJA'!$B$9:$B$5958,A78,'EGRESOS DE CAJA'!$G$9:$G$5958) -> 0 | D78: =D77+C78 -> 633732083
C79: =SUMIF('EGRESOS DE CAJA'!$B$9:$B$5958,A79,'EGRESOS DE CAJA'!$G$9:$G$5958) -> 0 | D79: =D78+C79 -> 633732083
A81: TOTAL EGRESOS | C81: =SUM(C19:C80) -> 633732083 | D81: =+D79 -> 633732083
A83: INGRESOS
A85: A | B85: =_xlfn.XLOOKUP(A85,Códigos!$A$489:$A$522,Códigos!$B$489:$B$522,"Verificar",0) -> Recibido por: -FACTURAS -GTFF | C85: =SUMIF('INGRESOS A CAJA'!$B$9:$B$4452,A85,'INGRESOS A CAJA'!$F$9:$F$4452) -> 45615800 | D85: =C85 -> 45615800
A86: B | B86: =_xlfn.XLOOKUP(A86,Códigos!$A$489:$A$522,Códigos!$B$489:$B$522,"Verificar",0) -> Recibido por: -Cuentas de cobro -GTFF | C86: =SUMIF('INGRESOS A CAJA'!$B$9:$B$4452,A86,'INGRESOS A CAJA'!$F$9:$F$4452) -> 0 | D86: =D85+C86 -> 45615800
A87: C | B87: =_xlfn.XLOOKUP(A87,Códigos!$A$489:$A$522,Códigos!$B$489:$B$522,"Verificar",0) -> Recibido por: -Cuentas de cobro -DAFF | C87: =SUMIF('INGRESOS A CAJA'!$B$9:$B$4452,A87,'INGRESOS A CAJA'!$F$9:$F$4452) -> 42540000 | D87: =D86+C87 -> 88155800
A88: D | B88: =_xlfn.XLOOKUP(A88,Códigos!$A$489:$A$522,Códigos!$B$489:$B$522,"Verificar",0) -> Recibido por: -Otros ingresos Sin Facturación | C88: =SUMIF('INGRESOS A CAJA'!$B$9:$B$4452,A88,'INGRESOS A CAJA'!$F$9:$F$4452) -> 0 | D88: =D87+C88 -> 88155800
A89: E | B89: =_xlfn.XLOOKUP(A89,Códigos!$A$489:$A$522,Códigos!$B$489:$B$522,"Verificar",0) -> Ingresos Recibidos de terceros para pagos | C89: =SUMIF('INGRESOS A CAJA'!$B$9:$B$4452,A89,'INGRESOS A CAJA'!$F$9:$F$4452) -> 1096000 | D89: =D88+C89 -> 89251800
A90: F | B90: =_xlfn.XLOOKUP(A90,Códigos!$A$489:$A$522,Códigos!$B$489:$B$522,"Verificar",0) -> Recibido por: -Cuentas por Cobrar | C90: =SUMIF('INGRESOS A CAJA'!$B$9:$B$4452,A90,'INGRESOS A CAJA'!$F$9:$F$4452) -> 10076800 | D90: =D89+C90 -> 99328600
A91: G | B91: =_xlfn.XLOOKUP(A91,Códigos!$A$489:$A$522,Códigos!$B$489:$B$522,"Verificar",0) -> Recibido por: -Abono a préstamos por Nómina de: | C91: =SUMIF('INGRESOS A CAJA'!$B$9:$B$4452,A91,'INGRESOS A CAJA'!$F$9:$F$4452) -> 1744200 | D91: =D90+C91 -> 101072800
A92: H | B92: =_xlfn.XLOOKUP(A92,Códigos!$A$489:$A$522,Códigos!$B$489:$B$522,"Verificar",0) -> Recibido por: -Abono a préstamos por Nómina de: | C92: =SUMIF('INGRESOS A CAJA'!$B$9:$B$4452,A92,'INGRESOS A CAJA'!$F$9:$F$4452) -> 0 | D92: =D91+C92 -> 101072800
A93: I | B93: =_xlfn.XLOOKUP(A93,Códigos!$A$489:$A$522,Códigos!$B$489:$B$522,"Verificar",0) -> -Retiros y Traslados de Bancos | C93: =SUMIF('INGRESOS A CAJA'!$B$9:$B$4452,A93,'INGRESOS A CAJA'!$F$9:$F$4452) -> 533166783 | D93: =D92+C93 -> 634239583
A94: J | B94: =_xlfn.XLOOKUP(A94,Códigos!$A$489:$A$522,Códigos!$B$489:$B$522,"Verificar",0) -> -Consignaciones pendientes de identificar | C94: =SUMIF('INGRESOS A CAJA'!$B$9:$B$4452,A94,'INGRESOS A CAJA'!$F$9:$F$4452) -> 0 | D94: =D93+C94 -> 634239583
A95: K | B95: =_xlfn.XLOOKUP(A95,Códigos!$A$489:$A$522,Códigos!$B$489:$B$522,"Verificar",0) -> Recibido por: -Préstamos a favor de la oficina | C95: =SUMIF('INGRESOS A CAJA'!$B$9:$B$4452,A95,'INGRESOS A CAJA'!$F$9:$F$4452) -> 0 | D95: =D94+C95 -> 634239583
A96: L | B96: =_xlfn.XLOOKUP(A96,Códigos!$A$489:$A$522,Códigos!$B$489:$B$522,"Verificar",0) -> Reembolsos y recuperaciones | C96: =SUMIF('INGRESOS A CAJA'!$B$9:$B$4452,A96,'INGRESOS A CAJA'!$F$9:$F$4452) -> 0 | D96: =D95+C96 -> 634239583
A97: M | B97: =_xlfn.XLOOKUP(A97,Códigos!$A$489:$A$522,Códigos!$B$489:$B$522,"Verificar",0) -> Recibido por: -Abono a préstamos | C97: =SUMIF('INGRESOS A CAJA'!$B$9:$B$4452,A97,'INGRESOS A CAJA'!$F$9:$F$4452) -> 0 | D97: =D96+C97 -> 634239583
... A116: AG | B116: =_xlfn.XLOOKUP(A116,Códigos!$A$489:$A$522,Códigos!$B$489:$B$522,"Verificar",0) -> 0 | C116: =SUMIF('INGRESOS A CAJA'!$B$9:$B$4452,A116,'INGRESOS A CAJA'!$F$9:$F$4452) -> 0 | D116: =D115+C116 -> 634239583
C117: =SUMIF('INGRESOS A CAJA'!$B$9:$B$4452,A117,'INGRESOS A CAJA'!$F$9:$F$4452) -> 0 | D117: =D116+C117 -> 634239583
A119: TOTAL INGRESOS | C119: =SUM(C85:C118) -> 634239583 | D119: =+D117 -> 634239583

Sheet FACTURACIÓN
A1: =+Códigos!$A$1 -> LIBRO DIARIO OFICINA
A2: RELACIÓN DE FACTURAS | F2: - CONTROL TOPES - DIFERENCIA | G2: =+E331 -> 0 | H2: =+G333 -> 26882000 | I2: DAFF
A3: =+Códigos!$A$3 -> AÑO: | B3: =+Códigos!$B$3 -> 2025 | F3: - CONTROL TOPES - DIFERENCIA | G3: =+E332 -> 0 | H3: =+G334 -> 11454000 | I3: DAFF
A5: DOCUMENTO No. | B5: FECHA DEL DOCUMENTO | C5: CÓDIGO DEL CLIENTE | D5: APELLIDOS Y NOMBRES o RAZÓN SOCIAL DEL CLIENTE o TERCERO | E5: HACE RET FTE | F5: DETALLE | G5: VALOR BRUTO DEL DOCUMENTO | H5: I V A | I5: VALOR TOTAL DEL DOCUMENTO | J5: RETENCIÓN EN LA FUENTE | K5: SALDO A PAGAR | L5: ABONOS | M5: DESCUENTOS | N5: SALDO POR COBRAR AL CLIENTE | O5: SALDO POR PAGAR A CARGO DE LA OFICINA | P5: FORMA DE PAGO | Q5: FECHA DE PAGO | R5: OBSERVACIONES
A8: FACTURAS -GERMÁN TULIO FERNÁNDEZ FERNÁNDEZ-
A9: GTFF-163 | B9: 45827 | C9: 10 | D9: =_xlfn.XLOOKUP(C9,Códigos!$A$11:$A$415,Códigos!$B$11:$B$415,"Verificar",0) -> NOMBRE 80 | E9: SI | F9: Asesoría tributaria año gravable 2024 | G9: 7553000 | H9: =+G9*19% -> 1435070 | I9: =+G9+H9 -> 8988070 | J9: =+G9*0.11 -> 830830 | K9: =+I9-J9 -> 8157240 | L9: 8157240 | M9: 0 | N9: =IF(+(K9-L9-M9)<0,0,(K9-L9-M9)) -> 0 | O9: =IF(+(K9-L9-M9)>0,0,(K9-L9-M9)) -> 0 | P9: Cheque 0231402-4 | Q9: 45828
A10: GTFF-164 | B10: 45827 | C10: 19 | D10: =_xlfn.XLOOKUP(C10,Códigos!$A$11:$A$415,Códigos!$B$11:$B$415,"Verificar",0) -> NOMBRE 164 | E10: SI | F10: Asesoría tributaria año gravable 2024 | G10: 11025000 | H10: =+G10*19% -> 2094750 | I10: =+G10+H10 -> 13119750 | J10: =IF(E10="SI",G10*11%,0) -> 1212750 | K10: =+I10-J10 -> 11907000 | L10: 11907000 | M10: 0 | N10: =IF(+(K10-L10-M10)<0,0,(K10-L10-M10)) -> 0 | O10: =IF(+(K10-L10-M10)>0,0,(K10-L10-M10)) -> 0 | P10: Cheque 0231402-4 | Q10: 45828
A11: GTFF-165 | B11: 45827 | C11: 28 | D11: =_xlfn.XLOOKUP(C11,Códigos!$A$11:$A$415,Códigos!$B$11:$B$415,"Verificar",0) -> NOMBRE 180 | E11: SI | F11: Asesoría tributaria año gravable 2024 | G11: 11025000 | H11: =+G11*19% -> 2094750 | I11: =+G11+H11 -> 13119750 | J11: =+G11*0.11 -> 1212750 | K11: =+I11-J11 -> 11907000 | L11: 11907000 | M11: 0 | N11: =IF(+(K11-L11-M11)<0,0,(K11-L11-M11)) -> 0 | O11: =IF(+(K11-L11-M11)>0,0,(K11-L11-M11)) -> 0 | P11: Cheque 0231402-4 | Q11: 45828
A12: GTFF-160 | D12: =_xlfn.XLOOKUP(C12,Códigos!$A$11:$A$415,Códigos!$B$11:$B$415,"Verificar",0) -> 0 | E12: SI | F12: Asesoría tributaria año gravable 2024 | H12: =+G12*19% -> 0 | I12: =+G12+H12 -> 0 | J12: =IF(E12="SI",G12*11%,0) -> 0 | K12: =+I12-J12 -> 0 | M12: 0 | N12: =IF(+(K12-L12-M12)<0,0,(K12-L12-M12)) -> 0 | O12: =IF(+(K12-L12-M12)>0,0,(K12-L12-M12)) -> 0
A13: GTFF-160 | D13: =_xlfn.XLOOKUP(C13,Códigos!$A$11:$A$415,Códigos!$B$11:$B$415,"Verificar",0) -> 0 | E13: SI | F13: Asesoría tributaria año gravable 2024 | H13: =+G13*19% -> 0 | I13: =+G13+H13 -> 0 | J13: =IF(E13="SI",G13*11%,0) -> 0 | K13: =+I13-J13 -> 0 | M13: 0 | N13: =IF(+(K13-L13-M13)<0,0,(K13-L13-M13)) -> 0 | O13: =IF(+(K13-L13-M13)>0,0,(K13-L13-M13)) -> 0
A14: GTFF-160 | D14: =_xlfn.XLOOKUP(C14,Códigos!$A$11:$A$415,Códigos!$B$11:$B$415,"Verificar",0) -> 0 | E14: SI | F14: Asesoría tributaria año gravable 2024 | H14: =+G14*19% -> 0 | I14: =+G14+H14 -> 0 | J14: =IF(E14="SI",G14*11%,0) -> 0 | K14: =+I14-J14 -> 0 | M14: 0 | N14: =IF(+(K14-L14-M14)<0,0,(K14-L14-M14)) -> 0 | O14: =IF(+(K14-L14-M14)>0,0,(K14-L14-M14)) -> 0
A15: GTFF-160 | D15: =_xlfn.XLOOKUP(C15,Códigos!$A$11:$A$415,Códigos!$B$11:$B$415,"Verificar",0) -> 0 | E15: SI | F15: Asesoría tributaria año gravable 2024 | H15: =+G15*19% -> 0 | I15: =+G15+H15 -> 0 | J15: =IF(E15="SI",G15*11%,0) -> 0 | K15: =+I15-J15 -> 0 | M15: 0 | N15: =IF(+(K15-L15-M15)<0,0,(K15-L15-M15)) -> 0 | O15: =IF(+(K15-L15-M15)>0,0,(K15-L15-M15)) -> 0
A16: GTFF-160 | D16: =_xlfn.XLOOKUP(C16,Códigos!$A$11:$A$415,Códigos!$B$11:$B$415,"Verificar",0) -> 0 | E16: SI | F16: Asesoría tributaria año gravable 2024 | H16: =+G16*19% -> 0 | I16: =+G16+H16 -> 0 | J16: =IF(E16="SI",G16*11%,0) -> 0 | K16: =+I16-J16 -> 0 | M16: 0 | N16: =IF(+(K16-L16-M16)<0,0,(K16-L16-M16)) -> 0 | O16: =IF(+(K16-L16-M16)>0,0,(K16-L16-M16)) -> 0
A17: GTFF-160 | D17: =_xlfn.XLOOKUP(C17,Códigos!$A$11:$A$415,Códigos!$B$11:$B$415,"Verificar",0) -> 0 | E17: SI | F17: Asesoría tributaria año gravable 2024 | H17: =+G17*19% -> 0 | I17: =+G17+H17 -> 0 | J17: =IF(E17="SI",G17*11%,0) -> 0 | K17: =+I17-J17 -> 0 | M17: 0 | N17: =IF(+(K17-L17-M17)<0,0,(K17-L17-M17)) -> 0 | O17: =IF(+(K17-L17-M17)>0,0,(K17-L17-M17)) -> 0
A18: GTFF-160 | D18: =_xlfn.XLOOKUP(C18,Códigos!$A$11:$A$415,Códigos!$B$11:$B$415,"Verificar",0) -> 0 | E18: SI | F18: Asesoría tributaria año gravable 2024 | H18: =+G18*19% -> 0 | I18: =+G18+H18 -> 0 | J18: =IF(E18="SI",G18*11%,0) -> 0 | K18: =+I18-J18 -> 0 | M18: 0 | N18: =IF(+(K18-L18-M18)<0,0,(K18-L18-M18)) -> 0 | O18: =IF(+(K18-L18-M18)>0,0,(K18-L18-M18)) -> 0
A19: GTFF-160 | D19: =_xlfn.XLOOKUP(C19,Códigos!$A$11:$A$415,Códigos!$B$11:$B$415,"Verificar",0) -> 0 | E19: SI | F19: Asesoría tributaria año gravable 2024 | H19: =+G19*19% -> 0 | I19: =+G19+H19 -> 0 | J19: =IF(E19="SI",G19*11%,0) -> 0 | K19: =+I19-J19 -> 0 | M19: 0 | N19: =IF(+(K19-L19-M19)<0,0,(K19-L19-M19)) -> 0 | O19: =IF(+(K19-L19-M19)>0,0,(K19-L19-M19)) -> 0
A20: GTFF-160 | D20: =_xlfn.XLOOKUP(C20,Códigos!$A$11:$A$415,Códigos!$B$11:$B$415,"Verificar",0) -> 0 | E20: SI | F20: Asesoría tributaria año gravable 2024 | H20: =+G20*19% -> 0 | I20: =+G20+H20 -> 0 | J20: =IF(E20="SI",G20*11%,0) -> 0 | K20: =+I20-J20 -> 0 | M20: 0 | N20: =IF(+(K20-L20-M20)<0,0,(K20-L20-M20)) -> 0 | O20: =IF(+(K20-L20-M20)>0,0,(K20-L20-M20)) -> 0
A21: GTFF-160 | D21: =_xlfn.XLOOKUP(C21,Códigos!$A$11:$A$415,Códigos!$B$11:$B$415,"Verificar",0) -> 0 | E21: SI | F21: Asesoría tributaria año gravable 2024 | H21: =+G21*19% -> 0 | I21: =+G21+H21 -> 0 | J21: =IF(E21="SI",G21*11%,0) -> 0 | K21: =+I21-J21 -> 0 | M21: 0 | N21: =IF(+(K21-L21-M21)<0,0,(K21-L21-M21)) -> 0 | O21: =IF(+(K21-L21-M21)>0,0,(K21-L21-M21)) -> 0
A22: GTFF-160 | D22: =_xlfn.XLOOKUP(C22,Códigos!$A$11:$A$415,Códigos!$B$11:$B$415,"Verificar",0) -> 0 | E22: SI | F22: Asesoría tributaria año gravable 2024 | H22: =+G22*19% -> 0 | I22: =+G22+H22 -> 0 | J22: =IF(E22="SI",G22*11%,0) -> 0 | K22: =+I22-J22 -> 0 | M22: 0 | N22: =IF(+(K22-L22-M22)<0,0,(K22-L22-M22)) -> 0 | O22: =IF(+(K22-L22-M22)>0,0,(K22-L22-M22)) -> 0
A23: GTFF-160 | D23: =_xlfn.XLOOKUP(C23,Códigos!$A$11:$A$415,Códigos!$B$11:$B$415,"Verificar",0) -> 0 | E23: SI | F23: Asesoría tributaria año gravable 2024 | H23: =+G23*19% -> 0 | I23: =+G23+H23 -> 0 | J23: =IF(E23="SI",G23*11%,0) -> 0 | K23: =+I23-J23 -> 0 | M23: 0 | N23: =IF(+(K23-L23-M23)<0,0,(K23-L23-M23)) -> 0 | O23: =IF(+(K23-L23-M23)>0,0,(K23-L23-M23)) -> 0
... A36: GTFF-160 | D36: =_xlfn.XLOOKUP(C36,Códigos!$A$11:$A$415,Códigos!$B$11:$B$415,"Verificar",0) -> 0 | E36: NO | F36: Asesoría tributaria año gravable 2024 | H36: =+G36*19% -> 0 | I36: =+G36+H36 -> 0 | J36: =IF(E36="SI",G36*11%,0) -> 0 | K36: =+I36-J36 -> 0 | M36: 0 | N36: =IF(+(K36-L36-M36)<0,0,(K36-L36-M36)) -> 0 | O36: =IF(+(K36-L36-M36)>0,0,(K36-L36-M36)) -> 0
A37: GTFF-160 | D37: =_xlfn.XLOOKUP(C37,Códigos!$A$11:$A$415,Códigos!$B$11:$B$415,"Verificar",0) -> 0 | E37: NO | G37: 0 | H37: =+G37*19% -> 0 | I37: =+G37+H37 -> 0 | J37: =IF(E37="SI",G37*11%,0) -> 0 | K37: =+I37-J37 -> 0 | M37: 0 | N37: =IF(+(K37-L37-M37)<0,0,(K37-L37-M37)) -> 0 | O37: =IF(+(K37-L37-M37)>0,0,(K37-L37-M37)) -> 0
A38: GTFF-160 | D38: =_xlfn.XLOOKUP(C38,Códigos!$A$11:$A$415,Códigos!$B$11:$B$415,"Verificar",0) -> 0 | E38: NO | G38: 0 | H38: =+G38*19% -> 0 | I38: =+G38+H38 -> 0 | J38: =IF(E38="SI",G38*11%,0) -> 0 | K38: =+I38-J38 -> 0 | M38: 0 | N38: =IF(+(K38-L38-M38)<0,0,(K38-L38-M38)) -> 0 | O38: =IF(+(K38-L38-M38)>0,0,(K38-L38-M38)) -> 0
A39: GTFF-160 | D39: =_xlfn.XLOOKUP(C39,Códigos!$A$11:$A$415,Códigos!$B$11:$B$415,"Verificar",0) -> 0 | E39: NO | G39: 0 | H39: =+G39*19% -> 0 | I39: =+G39+H39 -> 0 | J39: =IF(E39="SI",G39*11%,0) -> 0 | K39: =+I39-J39 -> 0 | M39: 0 | N39: =IF(+(K39-L39-M39)<0,0,(K39-L39-M39)) -> 0 | O39: =IF(+(K39-L39-M39)>0,0,(K39-L39-M39)) -> 0
A40: GTFF-160 | D40: =_xlfn.XLOOKUP(C40,Códigos!$A$11:$A$415,Códigos!$B$11:$B$415,"Verificar",0) -> 0 | E40: NO | G40: 0 | H40: =+G40*19% -> 0 | I40: =+G40+H40 -> 0 | J40: =IF(E40="SI",G40*11%,0) -> 0 | K40: =+I40-J40 -> 0 | M40: 0 | N40: =IF(+(K40-L40-M40)<0,0,(K40-L40-M40)) -> 0 | O40: =IF(+(K40-L40-M40)>0,0,(K40-L40-M40)) -> 0
A41: GTFF-160 | D41: =_xlfn.XLOOKUP(C41,Códigos!$A$11:$A$415,Códigos!$B$11:$B$415,"Verificar",0) -> 0 | E41: NO | G41: 0 | H41: =+G41*19% -> 0 | I41: =+G41+H41 -> 0 | J41: =IF(E41="SI",G41*11%,0) -> 0 | K41: =+I41-J41 -> 0 | M41: 0 | N41: =IF(+(K41-L41-M41)<0,0,(K41-L41-M41)) -> 0 | O41: =IF(+(K41-L41-M41)>0,0,(K41-L41-M41)) -> 0
A42: GTFF-160 | D42: =_xlfn.XLOOKUP(C42,Códigos!$A$11:$A$415,Códigos!$B$11:$B$415,"Verificar",0) -> 0 | E42: NO | G42: 0 | H42: =+G42*19% -> 0 | I42: =+G42+H42 -> 0 | J42: =IF(E42="SI",G42*11%,0) -> 0 | K42: =+I42-J42 -> 0 | M42: 0 | N42: =IF(+(K42-L42-M42)<0,0,(K42-L42-M42)) -> 0 | O42: =IF(+(K42-L42-M42)>0,0,(K42-L42-M42)) -> 0
A43: GTFF-160 | D43: =_xlfn.XLOOKUP(C43,Códigos!$A$11:$A$415,Códigos!$B$11:$B$415,"Verificar",0) -> 0 | E43: NO | G43: 0 | H43: =+G43*19% -> 0 | I43: =+G43+H43 -> 0 | J43: =IF(E43="SI",G43*11%,0) -> 0 | K43: =+I43-J43 -> 0 | M43: 0 | N43: =IF(+(K43-L43-M43)<0,0,(K43-L43-M43)) -> 0 | O43: =IF(+(K43-L43-M43)>0,0,(K43-L43-M43)) -> 0
A44: GTFF-160 | D44: =_xlfn.XLOOKUP(C44,Códigos!$A$11:$A$415,Códigos!$B$11:$B$415,"Verificar",0) -> 0 | E44: NO | G44: 0 | H44: =+G44*19% -> 0 | I44: =+G44+H44 -> 0 | J44: =IF(E44="SI",G44*11%,0) -> 0 | K44: =+I44-J44 -> 0 | M44: 0 | N44: =IF(+(K44-L44-M44)<0,0,(K44-L44-M44)) -> 0 | O44: =IF(+(K44-L44-M44)>0,0,(K44-L44-M44)) -> 0
A45: GTFF-160 | D45: =_xlfn.XLOOKUP(C45,Códigos!$A$11:$A$415,Códigos!$B$11:$B$415,"Verificar",0) -> 0 | E45: NO | G45: 0 | H45: =+G45*19% -> 0 | I45: =+G45+H45 -> 0 | J45: =IF(E45="SI",G45*11%,0) -> 0 | K45: =+I45-J45 -> 0 | L45: 0 | M45: 0 | N45: =IF(+(K45-L45-M45)<0,0,(K45-L45-M45)) -> 0 | O45: =IF(+(K45-L45-M45)>0,0,(K45-L45-M45)) -> 0
A46: GTFF-160 | D46: =_xlfn.XLOOKUP(C46,Códigos!$A$11:$A$415,Códigos!$B$11:$B$415,"Verificar",0) -> 0 | E46: NO | G46: 0 | H46: =+G46*19% -> 0 | I46: =+G46+H46 -> 0 | J46: =IF(E46="SI",G46*11%,0) -> 0 | K46: =+I46-J46 -> 0 | L46: 0 | M46: 0 | N46: =IF(+(K46-L46-M46)<0,0,(K46-L46-M46)) -> 0 | O46: =IF(+(K46-L46-M46)>0,0,(K46-L46-M46)) -> 0
A47: GTFF-160 | D47: =_xlfn.XLOOKUP(C47,Códigos!$A$11:$A$415,Códigos!$B$11:$B$415,"Verificar",0) -> 0 | E47: NO | G47: 0 | H47: =+G47*19% -> 0 | I47: =+G47+H47 -> 0 | J47: =IF(E47="SI",G47*11%,0) -> 0 | K47: =+I47-J47 -> 0 | L47: 0 | M47: 0 | N47: =IF(+(K47-L47-M47)<0,0,(K47-L47-M47)) -> 0 | O47: =IF(+(K47-L47-M47)>0,0,(K47-L47-M47)) -> 0
A48: GTFF-160 | D48: =_xlfn.XLOOKUP(C48,Códigos!$A$11:$A$415,Códigos!$B$11:$B$415,"Verificar",0) -> 0 | E48: NO | G48: 0 | H48: =+G48*19% -> 0 | I48: =+G48+H48 -> 0 | J48: =IF(E48="SI",G48*11%,0) -> 0 | K48: =+I48-J48 -> 0 | L48: 0 | M48: 0 | N48: =IF(+(K48-L48-M48)<0,0,(K48-L48-M48)) -> 0 | O48: =IF(+(K48-L48-M48)>0,0,(K48-L48-M48)) -> 0
A49: GTFF-160 | D49: =_xlfn.XLOOKUP(C49,Códigos!$A$11:$A$415,Códigos!$B$11:$B$415,"Verificar",0) -> 0 | E49: NO | G49: 0 | H49: =+G49*19% -> 0 | I49: =+G49+H49 -> 0 | J49: =IF(E49="SI",G49*11%,0) -> 0 | K49: =+I49-J49 -> 0 | L49: 0 | M49: 0 | N49: =IF(+(K49-L49-M49)<0,0,(K49-L49-M49)) -> 0 | O49: =IF(+(K49-L49-M49)>0,0,(K49-L49-M49)) -> 0
A50: GTFF-160 | D50: =_xlfn.XLOOKUP(C50,Códigos!$A$11:$A$415,Códigos!$B$11:$B$415,"Verificar",0) -> 0 | E50: NO | G50: 0 | H50: =+G50*19% -> 0 | I50: =+G50+H50 -> 0 | J50: =IF(E50="SI",G50*11%,0) -> 0 | K50: =+I50-J50 -> 0 | L50: 0 | M50: 0 | N50: =IF(+(K50-L50-M50)<0,0,(K50-L50-M50)) -> 0 | O50: =IF(+(K50-L50-M50)>0,0,(K50-L50-M50)) -> 0
A51: GTFF-160 | D51: =_xlfn.XLOOKUP(C51,Códigos!$A$11:$A$415,Códigos!$B$11:$B$415,"Verificar",0) -> 0 | G51: 0 | H51: =+G51*19% -> 0 | I51: =+G51+H51 -> 0 | J51: =IF(E51="SI",G51*11%,0) -> 0 | K51: =+I51-J51 -> 0 | L51: 0 | M51: 0 | N51: =IF(+(K51-L51-M51)<0,0,(K51-L51-M51)) -> 0 | O51: =IF(+(K51-L51-M51)>0,0,(K51-L51-M51)) -> 0
A52: GTFF- | D52: =_xlfn.XLOOKUP(C52,Códigos!$A$11:$A$415,Códigos!$B$11:$B$415,"Verificar",0) -> 0 | G52: 0 | H52: =+G52*19% -> 0 | I52: =+G52+H52 -> 0 | J52: =IF(E52="SI",G52*11%,0) -> 0 | K52: =+I52-J52 -> 0 | L52: 0 | M52: 0 | N52: =IF(+(K52-L52-M52)<0,0,(K52-L52-M52)) -> 0 | O52: =IF(+(K52-L52-M52)>0,0,(K52-L52-M52)) -> 0
A53: GTFF- | D53: =_xlfn.XLOOKUP(C53,Códigos!$A$11:$A$415,Códigos!$B$11:$B$415,"Verificar",0) -> 0 | G53: 0 | H53: =+G53*19% -> 0 | I53: =+G53+H53 -> 0 | J53: =IF(E53="SI",G53*11%,0) -> 0 | K53: =+I53-J53 -> 0 | L53: 0 | M53: 0 | N53: =IF(+(K53-L53-M53)<0,0,(K53-L53-M53)) -> 0 | O53: =IF(+(K53-L53-M53)>0,0,(K53-L53-M53)) -> 0
A54: GTFF- | D54: =_xlfn.XLOOKUP(C54,Códigos!$A$11:$A$415,Códigos!$B$11:$B$415,"Verificar",0) -> 0 | G54: 0 | H54: =+G54*19% -> 0 | I54: =+G54+H54 -> 0 | J54: =IF(E54="SI",G54*11%,0) -> 0 | K54: =+I54-J54 -> 0 | L54: 0 | M54: 0 | N54: =IF(+(K54-L54-M54)<0,0,(K54-L54-M54)) -> 0 | O54: =IF(+(K54-L54-M54)>0,0,(K54-L54-M54)) -> 0
A55: GTFF- | D55: =_xlfn.XLOOKUP(C55,Códigos!$A$11:$A$415,Códigos!$B$11:$B$415,"Verificar",0) -> 0 | G55: 0 | H55: =+G55*19% -> 0 | I55: =+G55+H55 -> 0 | J55: =IF(E55="SI",G55*11%,0) -> 0 | K55: =+I55-J55 -> 0 | L55: 0 | M55: 0 | N55: =IF(+(K55-L55-M55)<0,0,(K55-L55-M55)) -> 0 | O55: =IF(+(K55-L55-M55)>0,0,(K55-L55-M55)) -> 0
A56: GTFF- | D56: =_xlfn.XLOOKUP(C56,Códigos!$A$11:$A$415,Códigos!$B$11:$B$415,"Verificar",0) -> 0 | G56: 0 | H56: =+G56*19% -> 0 | I56: =+G56+H56 -> 0 | J56: =IF(E56="SI",G56*11%,0) -> 0 | K56: =+I56-J56 -> 0 | L56: 0 | M56: 0 | N56: =IF(+(K56-L56-M56)<0,0,(K56-L56-M56)) -> 0 | O56: =IF(+(K56-L56-M56)>0,0,(K56-L56-M56)) -> 0
A57: GTFF- | D57: =_xlfn.XLOOKUP(C57,Códigos!$A$11:$A$415,Códigos!$B$11:$B$415,"Verificar",0) -> 0 | G57: 0 | H57: =+G57*19% -> 0 | I57: =+G57+H57 -> 0 | J57: =IF(E57="SI",G57*11%,0) -> 0 | K57: =+I57-J57 -> 0 | L57: 0 | M57: 0 | N57: =IF(+(K57-L57-M57)<0,0,(K57-L57-M57)) -> 0 | O57: =IF(+(K57-L57-M57)>0,0,(K57-L57-M57)) -> 0
G58: 0 | H58: =+G58*19% -> 0 | I58: =+G58+H58 -> 0 | J58: =+G58*0.11 -> 0 | K58: =+I58-J58 -> 0 | L58: 0 | M58: 0 | N58: =+K58-L58-M58 -> 0
G59: 0 | H59: =+G59*19% -> 0 | I59: =+G59+H59 -> 0 | J59: =+G59*0.11 -> 0 | K59: =+I59-J59 -> 0 | L59: 0 | M59: 0 | N59: =+K59-L59-M59 -> 0
G60: 0 | H60: =+G60*19% -> 0 | I60: =+G60+H60 -> 0 | J60: =+G60*0.11 -> 0 | K60: =+I60-J60 -> 0 | L60: 0 | M60: 0 | N60: =+K60-L60-M60 -> 0
G61: 0 | H61: =+G61*19% -> 0 | I61: =+G61+H61 -> 0 | J61: =+G61*0.11 -> 0 | K61: =+I61-J61 -> 0 | L61: 0 | M61: 0 | N61: =+K61-L61-M61 -> 0
G62: 0 | H62: =+G62*19% -> 0 | I62: =+G62+H62 -> 0 | J62: =+G62*0.11 -> 0 | K62: =+I62-J62 -> 0 | L62: 0 | M62: 0 | N62: =+K62-L62-M62 -> 0
G63: 0 | H63: =+G63*19% -> 0 | I63: =+G63+H63 -> 0 | J63: =+G63*0.11 -> 0 | K63: =+I63-J63 -> 0 | L63: 0 | M63: 0 | N63: =+K63-L63-M63 -> 0
G64: 0 | H64: =+G64*19% -> 0 | I64: =+G64+H64 -> 0 | J64: =+G64*0.11 -> 0 | K64: =+I64-J64 -> 0 | L64: 0 | M64: 0 | N64: =+K64-L64-M64 -> 0
G65: 0 | H65: =+G65*19% -> 0 | I65: =+G65+H65 -> 0 | J65: =+G65*0.11 -> 0 | K65: =+I65-J65 -> 0 | L65: 0 | M65: 0 | N65: =+K65-L65-M65 -> 0
G66: 0 | H66: =+G66*19% -> 0 | I66: =+G66+H66 -> 0 | J66: =+G66*0.11 -> 0 | K66: =+I66-J66 -> 0 | L66: 0 | M66: 0 | N66: =+K66-L66-M66 -> 0
G67: 0 | H67: =+G67*19% -> 0 | I67: =+G67+H67 -> 0 | J67: =+G67*0.11 -> 0 | K67: =+I67-J67 -> 0 | L67: 0 | M67: 0 | N67: =+K67-L67-M67 -> 0
G68: 0 | H68: =+G68*19% -> 0 | I68: =+G68+H68 -> 0 | J68: =+G68*0.11 -> 0 | K68: =+I68-J68 -> 0 | L68: 0 | M68: 0 | N68: =+K68-L68-M68 -> 0
G69: 0 | H69: =+G69*19% -> 0 | I69: =+G69+H69 -> 0 | J69: =+G69*0.11 -> 0 | K69: =+I69-J69 -> 0 | L69: 0 | M69: 0 | N69: =+K69-L69-M69 -> 0
... G96: 0 | H96: =+G96*19% -> 0 | I96: =+G96+H96 -> 0 | J96: =+G96*0.11 -> 0 | K96: =+I96-J96 -> 0 | L96: 0 | M96: 0 | N96: =+K96-L96-M96 -> 0
A98: TOTAL | B98: =+A8 -> FACTURAS -GERMÁN TULIO FERNÁNDEZ FERNÁNDEZ- | G98: =SUM(G8:G97) -> 29603000 | H98: =SUM(H8:H97) -> 5624570 | I98: =SUM(I8:I97) -> 35227570 | J98: =SUM(J8:J97) -> 3256330 | K98: =SUM(K8:K97) -> 31971240 | L98: =SUM(L8:L97) -> 31971240 | M98: =SUM(M8:M97) -> 0 | N98: =SUM(N8:N97) -> 0 | O98: =SUM(O8:O97) -> 0
A102: VALOR DECLARADO | G102: 0
G103: =+G98-G102 -> 29603000
A107: OTROS COBROS -GERMÁN TULIO FERNÁNDEZ FERNÁNDEZ-
A109: 0714 | D109: =_xlfn.XLOOKUP(C109,Códigos!$A$11:$A$415,Códigos!$B$11:$B$415,"Verificar",0) -> 0 | G109: 0 | H109: N/A | I109: =+G109 -> 0 | J109: N/A | K109: =+I109 -> 0 | L109: 0 | M109: 0 | N109: =IF(+(K109-L109-M109)<0,0,(K109-L109-M109)) -> 0 | O109: =IF(+(K109-L109-M109)>0,0,(K109-L109-M109)) -> 0
A110: 0715 | D110: =_xlfn.XLOOKUP(C110,Códigos!$A$11:$A$415,Códigos!$B$11:$B$415,"Verificar",0) -> 0 | G110: 0 | H110: N/A | I110: =+G110 -> 0 | J110: N/A | K110: =+I110 -> 0 | L110: 0 | M110: 0 | N110: =IF(+(K110-L110-M110)<0,0,(K110-L110-M110)) -> 0 | O110: =IF(+(K110-L110-M110)>0,0,(K110-L110-M110)) -> 0
A111: 0716 | D111: =_xlfn.XLOOKUP(C111,Códigos!$A$11:$A$415,Códigos!$B$11:$B$415,"Verificar",0) -> 0 | G111: 0 | H111: N/A | I111: =+G111 -> 0 | J111: N/A | K111: =+I111 -> 0 | L111: 0 | M111: 0 | N111: =IF(+(K111-L111-M111)<0,0,(K111-L111-M111)) -> 0 | O111: =IF(+(K111-L111-M111)>0,0,(K111-L111-M111)) -> 0
A112: 0717 | D112: =_xlfn.XLOOKUP(C112,Códigos!$A$11:$A$415,Códigos!$B$11:$B$415,"Verificar",0) -> 0 | G112: 0 | H112: N/A | I112: =+G112 -> 0 | J112: N/A | K112: =+I112 -> 0 | L112: 0 | M112: 0 | N112: =IF(+(K112-L112-M112)<0,0,(K112-L112-M112)) -> 0 | O112: =IF(+(K112-L112-M112)>0,0,(K112-L112-M112)) -> 0
A113: 0718 | D113: =_xlfn.XLOOKUP(C113,Códigos!$A$11:$A$415,Códigos!$B$11:$B$415,"Verificar",0) -> 0 | G113: 0 | H113: N/A | I113: =+G113 -> 0 | J113: N/A | K113: =+I113 -> 0 | L113: 0 | M113: 0 | N113: =IF(+(K113-L113-M113)<0,0,(K113-L113-M113)) -> 0 | O113: =IF(+(K113-L113-M113)>0,0,(K113-L113-M113)) -> 0
A114: 0719 | D114: =_xlfn.XLOOKUP(C114,Códigos!$A$11:$A$415,Códigos!$B$11:$B$415,"Verificar",0) -> 0 | G114: 0 | H114: N/A | I114: =+G114 -> 0 | J114: N/A | K114: =+I114 -> 0 | L114: 0 | M114: 0 | N114: =IF(+(K114-L114-M114)<0,0,(K114-L114-M114)) -> 0 | O114: =IF(+(K114-L114-M114)>0,0,(K114-L114-M114)) -> 0
A115: 0720 | D115: =_xlfn.XLOOKUP(C115,Códigos!$A$11:$A$415,Códigos!$B$11:$B$415,"Verificar",0) -> 0 | G115: 0 | H115: N/A | I115: =+G115 -> 0 | J115: N/A | K115: =+I115 -> 0 | L115: 0 | M115: 0 | N115: =IF(+(K115-L115-M115)<0,0,(K115-L115-M115)) -> 0 | O115: =IF(+(K115-L115-M115)>0,0,(K115-L115-M115)) -> 0
D116: =_xlfn.XLOOKUP(C116,Códigos!$A$11:$A$415,Códigos!$B$11:$B$415,"Verificar",0) -> 0 | G116: 0 | H116: N/A | I116: =+G116 -> 0 | J116: N/A | K116: =+I116 -> 0 | L116: 0 | M116: 0 | N116: =IF(+(K116-L116-M116)<0,0,(K116-L116-M116)) -> 0 | O116: =IF(+(K116-L116-M116)>0,0,(K116-L116-M116)) -> 0
D117: =_xlfn.XLOOKUP(C117,Códigos!$A$11:$A$415,Códigos!$B$11:$B$415,"Verificar",0) -> 0 | G117: 0 | H117: N/A | I117: =+G117 -> 0 | J117: N/A | K117: =+I117 -> 0 | L117: 0 | M117: 0 | N117: =IF(+(K117-L117-M117)<0,0,(K117-L117-M117)) -> 0 | O117: =IF(+(K117-L117-M117)>0,0,(K117-L117-M117)) -> 0
D118: =_xlfn.XLOOKUP(C118,Códigos!$A$11:$A$415,Códigos!$B$11:$B$415,"Verificar",0) -> 0 | G118: 0 | H118: N/A | I118: =+G118 -> 0 | J118: N/A | K118: =+I118 -> 0 | L118: 0 | M118: 0 | N118: =IF(+(K118-L118-M118)<0,0,(K118-L118-M118)) -> 0 | O118: =IF(+(K118-L118-M118)>0,0,(K118-L118-M118)) -> 0
D119: =_xlfn.XLOOKUP(C119,Códigos!$A$11:$A$415,Códigos!$B$11:$B$415,"Verificar",0) -> 0 | G119: 0 | H119: N/A | I119: =+G119 -> 0 | J119: N/A | K119: =+I119 -> 0 | L119: 0 | M119: 0 | N119: =IF(+(K119-L119-M119)<0,0,(K119-L119-M119)) -> 0 | O119: =IF(+(K119-L119-M119)>0,0,(K119-L119-M119)) -> 0
D120: =_xlfn.XLOOKUP(C120,Códigos!$A$11:$A$415,Códigos!$B$11:$B$415,"Verificar",0) -> 0 | G120: 0 | H120: N/A | I120: =+G120 -> 0 | J120: N/A | K120: =+I120 -> 0 | L120: 0 | M120: 0 | N120: =IF(+(K121-L121-M120)<0,0,(K121-L121-M120)) -> 0 | O120: =IF(+(K121-L121-M120)>0,0,(K121-L121-M120)) -> 0
D121: =_xlfn.XLOOKUP(C121,Códigos!$A$11:$A$415,Códigos!$B$11:$B$415,"Verificar",0) -> 0 | G121: 0 | H121: N/A | I121: =+G121 -> 0 | J121: N/A | K121: =+I121 -> 0 | L121: 0 | M121: 0 | N121: =IF(+(K121-L121-M121)<0,0,(K121-L121-M121)) -> 0 | O121: =IF(+(K121-L121-M121)>0,0,(K121-L121-M121)) -> 0
D122: =_xlfn.XLOOKUP(C122,Códigos!$A$11:$A$415,Códigos!$B$11:$B$415,"Verificar",0) -> 0 | G122: 0 | H122: N/A | I122: =+G122 -> 0 | J122: N/A | K122: =+I122 -> 0 | L122: 0 | M122: 0 | N122: =IF(+(K122-L122-M122)<0,0,(K122-L122-M122)) -> 0 | O122: =IF(+(K122-L122-M122)>0,0,(K122-L122-M122)) -> 0
D123: =_xlfn.XLOOKUP(C123,Códigos!$A$11:$A$415,Códigos!$B$11:$B$415,"Verificar",0) -> 0 | G123: 0 | H123: N/A | I123: =+G123 -> 0 | J123: N/A | K123: =+I123 -> 0 | L123: 0 | M123: 0 | N123: =IF(+(K123-L123-M123)<0,0,(K123-L123-M123)) -> 0 | O123: =IF(+(K123-L123-M123)>0,0,(K123-L123-M123)) -> 0
D124: =_xlfn.XLOOKUP(C124,Códigos!$A$11:$A$415,Códigos!$B$11:$B$415,"Verificar",0) -> 0 | G124: 0 | H124: N/A | I124: =+G124 -> 0 | J124: N/A | K124: =+I124 -> 0 | L124: 0 | M124: 0 | N124: =IF(+(K124-L124-M124)<0,0,(K124-L124-M124)) -> 0 | O124: =IF(+(K124-L124-M124)>0,0,(K124-L124-M124)) -> 0
D125: =_xlfn.XLOOKUP(C125,Códigos!$A$11:$A$415,Códigos!$B$11:$B$415,"Verificar",0) -> 0 | G125: 0 | H125: N/A | I125: =+G125 -> 0 | J125: N/A | K125: =+I125 -> 0 | L125: 0 | M125: 0 | N125: =IF(+(K125-L125-M125)<0,0,(K125-L125-M125)) -> 0 | O125: =IF(+(K125-L125-M125)>0,0,(K125-L125-M125)) -> 0
D126: =_xlfn.XLOOKUP(C126,Códigos!$A$11:$A$415,Códigos!$B$11:$B$415,"Verificar",0) -> 0 | G126: 0 | H126: N/A | I126: =+G126 -> 0 | J126: N/A | K126: =+I126 -> 0 | L126: 0 | M126: 0 | N126: =IF(+(K126-L126-M126)<0,0,(K126-L126-M126)) -> 0 | O126: =IF(+(K126-L126-M126)>0,0,(K126-L126-M126)) -> 0
D127: =_xlfn.XLOOKUP(C127,Códigos!$A$11:$A$415,Códigos!$B$11:$B$415,"Verificar",0) -> 0 | G127: 0 | H127: N/A | I127: =+G127 -> 0 | J127: N/A | K127: =+I127 -> 0 | L127: 0 | M127: 0 | N127: =IF(+(K127-L127-M127)<0,0,(K127-L127-M127)) -> 0 | O127: =IF(+(K127-L127-M127)>0,0,(K127-L127-M127)) -> 0
D128: =_xlfn.XLOOKUP(C128,Códigos!$A$11:$A$415,Códigos!$B$11:$B$415,"Verificar",0) -> 0 | G128: 0 | H128: N/A | I128: =+G128 -> 0 | J128: N/A | K128: =+I128 -> 0 | L128: 0 | M128: 0 | N128: =IF(+(K128-L128-M128)<0,0,(K128-L128-M128)) -> 0 | O128: =IF(+(K128-L128-M128)>0,0,(K128-L128-M128)) -> 0
D129: =_xlfn.XLOOKUP(C129,Códigos!$A$11:$A$415,Códigos!$B$11:$B$415,"Verificar",0) -> 0 | G129: 0 | H129: N/A | I129: =+G129 -> 0 | J129: N/A | K129: =+I129 -> 0 | L129: 0 | M129: 0 | N129: =IF(+(K129-L129-M129)<0,0,(K129-L129-M129)) -> 0 | O129: =IF(+(K129-L129-M129)>0,0,(K129-L129-M129)) -> 0
D130: =_xlfn.XLOOKUP(C130,Códigos!$A$11:$A$415,Códigos!$B$11:$B$415,"Verificar",0) -> 0 | G130: 0 | H130: N/A | I130: =+G130 -> 0 | J130: N/A | K130: =+I130 -> 0 | L130: 0 | M130: 0 | N130: =IF(+(K130-L130-M130)<0,0,(K130-L130-M130)) -> 0 | O130: =IF(+(K130-L130-M130)>0,0,(K130-L130-M130)) -> 0
D131: =_xlfn.XLOOKUP(C131,Códigos!$A$11:$A$415,Códigos!$B$11:$B$415,"Verificar",0) -> 0 | G131: 0 | H131: N/A | I131: =+G131 -> 0 | J131: N/A | K131: =+I131 -> 0 | L131: 0 | M131: 0 | N131: =IF(+(K131-L131-M131)<0,0,(K131-L131-M131)) -> 0 | O131: =IF(+(K131-L131-M131)>0,0,(K131-L131-M131)) -> 0
D132: =_xlfn.XLOOKUP(C132,Códigos!$A$11:$A$415,Códigos!$B$11:$B$415,"Verificar",0) -> 0 | G132: 0 | H132: N/A | I132: =+G132 -> 0 | J132: N/A | K132: =+I132 -> 0 | L132: 0 | M132: 0 | N132: =IF(+(K132-L132-M132)<0,0,(K132-L132-M132)) -> 0 | O132: =IF(+(K132-L132-M132)>0,0,(K132-L132-M132)) -> 0
... D139: =_xlfn.XLOOKUP(C139,Códigos!$A$11:$A$415,Códigos!$B$11:$B$415,"Verificar",0) -> 0 | G139: 0 | H139: N/A | I139: =+G139 -> 0 | J139: N/A | K139: =+I139 -> 0 | L139: 0 | M139: 0 | N139: =IF(+(K139-L139-M139)<0,0,(K139-L139-M139)) -> 0 | O139: =IF(+(K139-L139-M139)>0,0,(K139-L139-M139)) -> 0
A141: TOTAL | B141: =+A107 -> OTROS COBROS -GERMÁN TULIO FERNÁNDEZ FERNÁNDEZ- | G141: =SUM(G109:G140) -> 0 | H141: =SUM(H109:H140) -> 0 | I141: =SUM(I109:I140) -> 0 | J141: =SUM(J109:J140) -> 0 | K141: =SUM(K109:K140) -> 0 | L141: =SUM(L109:L140) -> 0 | M141: =SUM(M109:M140) -> 0 | N141: =SUM(N109:N140) -> 0 | O141: =SUM(O109:O140) -> 0
A146: OTRAS CUENTAS DE COBRO
A147: CUENTAS DE COBRO -DIEGO ALBERTO FERNÁNDEZ FERNÁNDEZ-
A149: 25-001 | B149: 45701 | C149: 364 | D149: =_xlfn.XLOOKUP(C149,Códigos!$A$11:$A$415,Códigos!$B$11:$B$415,"Verificar",0) -> NOMBRE 365 | E149: NO | F149: Asesoría tributaria año gravable 2024 | G149: 150000 | H149: N/A | I149: =+G149 -> 150000 | J149: 0 | K149: =+I149-J149 -> 150000 | L149: 150000 | N149: =IF(+(K149-L149-M149)<0,0,(K149-L149-M149)) -> 0 | O149: =IF(+(K149-L149-M149)>0,0,(K149-L149-M149)) -> 0 | P149: Consignado | Q149: 45701
A150: 25-002 | B150: 45756 | C150: 366 | D150: =_xlfn.XLOOKUP(C150,Códigos!$A$11:$A$415,Códigos!$B$11:$B$415,"Verificar",0) -> NOMBRE 367 | E150: NO | F150: Asesoría tributaria año gravable 2024 | G150: 7000000 | H150: N/A | I150: =+G150 -> 7000000 | J150: 0 | K150: =+I150-J150 -> 7000000 | L150: 7000000 | N150: =IF(+(K150-L150-M150)<0,0,(K150-L150-M150)) -> 0 | O150: =IF(+(K150-L150-M150)>0,0,(K150-L150-M150)) -> 0 | P150: Consignado | Q150: 45756
A151: 25-003 | B151: 45895 | C151: 340 | D151: =_xlfn.XLOOKUP(C151,Códigos!$A$11:$A$415,Códigos!$B$11:$B$415,"Verificar",0) -> NOMBRE 72 | E151: NO | F151: Asesoría tributaria año gravable 2024 | G151: 200000 | H151: N/A | I151: =+G151 -> 200000 | J151: 0 | K151: =+I151-J151 -> 200000 | L151: 200000 | N151: =IF(+(K151-L151-M151)<0,0,(K151-L151-M151)) -> 0 | O151: =IF(+(K151-L151-M151)>0,0,(K151-L151-M151)) -> 0 | P151: Efectivo | Q151: 45895
A152: 25-004 | B152: 45912 | C152: 112 | D152: =_xlfn.XLOOKUP(C152,Códigos!$A$11:$A$415,Códigos!$B$11:$B$415,"Verificar",0) -> NOMBRE 141 | E152: NO | F152: Asesoría tributaria año gravable 2024 | G152: 410000 | H152: N/A | I152: =+G152 -> 410000 | J152: 0 | K152: =+I152-J152 -> 410000 | L152: 410000 | N152: =IF(+(K152-L152-M152)<0,0,(K152-L152-M152)) -> 0 | O152: =IF(+(K152-L152-M152)>0,0,(K152-L152-M152)) -> 0 | P152: Consignado | Q152: 45912
A153: 25-005 | B153: 45926 | C153: 46 | D153: =_xlfn.XLOOKUP(C153,Códigos!$A$11:$A$415,Códigos!$B$11:$B$415,"Verificar",0) -> NOMBRE 116 | E153: NO | F153: Asesoría tributaria año gravable 2024 | G153: 400000 | H153: N/A | I153: =+G153 -> 400000 | J153: 0 | K153: =+I153-J153 -> 400000 | L153: 400000 | N153: =IF(+(K153-L153-M153)<0,0,(K153-L153-M153)) -> 0 | O153: =IF(+(K153-L153-M153)>0,0,(K153-L153-M153)) -> 0 | P153: Consignado | Q153: 45926
A154: 25-006 | B154: 45932 | C154: 143 | D154: =_xlfn.XLOOKUP(C154,Códigos!$A$11:$A$415,Códigos!$B$11:$B$415,"Verificar",0) -> NOMBRE 236 | E154: NO | F154: Asesoría tributaria año gravable 2024 | G154: 1350000 | H154: N/A | I154: =+G154 -> 1350000 | J154: 0 | K154: =+I154-J154 -> 1350000 | N154: =IF(+(K154-L154-M154)<0,0,(K154-L154-M154)) -> 1350000 | O154: =IF(+(K154-L154-M154)>0,0,(K154-L154-M154)) -> 0
A155: 25-007 | B155: 45932 | C155: 217 | D155: =_xlfn.XLOOKUP(C155,Códigos!$A$11:$A$415,Códigos!$B$11:$B$415,"Verificar",0) -> NOMBRE 5 | E155: NO | F155: Asesoría tributaria año gravable 2024 | G155: 330000 | H155: N/A | I155: =+G155 -> 330000 | J155: 0 | K155: =+I155-J155 -> 330000 | L155: 330000 | N155: =IF(+(K155-L155-M155)<0,0,(K155-L155-M155)) -> 0 | O155: =IF(+(K155-L155-M155)>0,0,(K155-L155-M155)) -> 0 | P155: Efectivo | Q155: 45957
A156: 25-008 | B156: 45932 | C156: 65 | D156: =_xlfn.XLOOKUP(C156,Códigos!$A$11:$A$415,Códigos!$B$11:$B$415,"Verificar",0) -> NOMBRE 44 | E156: NO | F156: Asesoría tributaria año gravable 2024 | G156: 4170000 | H156: N/A | I156: =+G156 -> 4170000 | J156: 0 | K156: =+I156-J156 -> 4170000 | N156: =IF(+(K156-L156-M156)<0,0,(K156-L156-M156)) -> 4170000 | O156: =IF(+(K156-L156-M156)>0,0,(K156-L156-M156)) -> 0
A157: 25-009 | B157: 45932 | C157: 45 | D157: =_xlfn.XLOOKUP(C157,Códigos!$A$11:$A$415,Códigos!$B$11:$B$415,"Verificar",0) -> NOMBRE 9 | E157: NO | F157: Asesoría tributaria año gravable 2024 | G157: 980000 | H157: N/A | I157: =+G157 -> 980000 | J157: 0 | K157: =+I157-J157 -> 980000 | N157: =IF(+(K157-L157-M157)<0,0,(K157-L157-M157)) -> 980000 | O157: =IF(+(K157-L157-M157)>0,0,(K157-L157-M157)) -> 0
A158: 25-010 | B158: 45932 | C158: 48 | D158: =_xlfn.XLOOKUP(C158,Códigos!$A$11:$A$415,Códigos!$B$11:$B$415,"Verificar",0) -> NOMBRE 14 | E158: NO | F158: Asesoría tributaria año gravable 2024 | G158: 580000 | H158: N/A | I158: =+G158 -> 580000 | J158: 0 | K158: =+I158-J158 -> 580000 | L158: 580000 | N158: =IF(+(K158-L158-M158)<0,0,(K158-L158-M158)) -> 0 | O158: =IF(+(K158-L158-M158)>0,0,(K158-L158-M158)) -> 0 | P158: Consignado | Q158: 45948
A159: 25-011 | B159: 45932 | C159: 50 | D159: =_xlfn.XLOOKUP(C159,Códigos!$A$11:$A$415,Códigos!$B$11:$B$415,"Verificar",0) -> NOMBRE 18 | E159: NO | F159: Asesoría tributaria año gravable 2024 | G159: 350000 | H159: N/A | I159: =+G159 -> 350000 | J159: 0 | K159: =+I159-J159 -> 350000 | N159: =IF(+(K159-L159-M159)<0,0,(K159-L159-M159)) -> 350000 | O159: =IF(+(K159-L159-M159)>0,0,(K159-L159-M159)) -> 0
A160: 25-012 | B160: 45932 | C160: 366 | D160: =_xlfn.XLOOKUP(C160,Códigos!$A$11:$A$415,Códigos!$B$11:$B$415,"Verificar",0) -> NOMBRE 367 | E160: NO | F160: Asesoría tributaria año gravable 2024 | G160: 200000 | H160: N/A | I160: =+G160 -> 200000 | J160: 0 | K160: =+I160-J160 -> 200000 | N160: =IF(+(K160-L160-M160)<0,0,(K160-L160-M160)) -> 200000 | O160: =IF(+(K160-L160-M160)>0,0,(K160-L160-M160)) -> 0
A161: 25-013 | B161: 45932 | C161: 260 | D161: =_xlfn.XLOOKUP(C161,Códigos!$A$11:$A$415,Códigos!$B$11:$B$415,"Verificar",0) -> NOMBRE 27 | E161: NO | F161: Asesoría tributaria año gravable 2024 | G161: 170000 | H161: N/A | I161: =+G161 -> 170000 | J161: 0 | K161: =+I161-J161 -> 170000 | N161: =IF(+(K161-L161-M161)<0,0,(K161-L161-M161)) -> 170000 | O161: =IF(+(K161-L161-M161)>0,0,(K161-L161-M161)) -> 0
...

Sheet PASIVOS GTFF
A1: =+Códigos!$A$1 -> LIBRO DIARIO OFICINA | C1: =+C392 -> -1.0301822e+08 | D1: =+D392 -> #REF! | E1: =+E392 -> 70794200 | F1: =+F392 -> 153531240 | G1: =+G392 -> 99028600 | H1: =+H392 -> 60987200 | I1: =+I392 -> #REF! | J1: TOTALES: CUENTAS POR PAGAR
A2: CUENTAS POR PAGAR DE LA OFICINA Y PERSONALES
A3: =+Códigos!$A$3 -> AÑO: | B3: =+Códigos!$B$3 -> 2025
A4: DESDE: | B4: =+'INGRESOS A CAJA'!D4 -> 45658
A5: HASTA: | B5: =+'INGRESOS A CAJA'!D5 -> 46022
D6: Viene de: CARTERA años anteriores | F6: Viene de: FACTURACIÓN del año | G6: Viene de: INGRESOS del año | H6: Viene de: EGRESOS del año
A7: CÓDIGO DEL TERCERO | B7: APELLIDOS Y NOMBRES o RAZÓN SOCIAL DEL CLIENTE o TERCERO | C7: SALDOS POR PAGAR AÑOS ANTERIORES | D7: SALDOS POR COBRAR AÑOS ANTERIORES | E7: ABONOS EN EL AÑO | F7: FACTURAS y CUENTAS DE COBRO DEL AÑO | G7: INGRESOS EN EL AÑO | H7: EGRESOS EN EL AÑO | I7: SALDO TOTAL PENDIENTE POR PAGAR | J7: OBSERVACIONES
A10: 1 | B10: =_xlfn.XLOOKUP(A10,Códigos!$A$11:$A$415,Códigos!$B$11:$B$415,"Verificar",0) -> NOMBRE 21 | D10: =SUMIF('CARTERA años anteriores'!$C$9:$C$234,A10,'CARTERA años anteriores'!$J$9:$J$234) -> 0 | E10: =SUMIF('CARTERA años anteriores'!$C$9:$C$234,A10,'CARTERA años anteriores'!$L$9:$L$234) -> 0 | F10: =SUMIF(FACTURACIÓN!$C$8:$C$1082,A10,FACTURACIÓN!$K$8:$K$1082) -> 0 | G10: =SUMIF('INGRESOS A CAJA'!$C$10:$C$954,A10,'INGRESOS A CAJA'!$F$10:$F$954) -> 0 | H10: =SUMIF('EGRESOS DE CAJA'!$C$10:$C$2251,A10,'EGRESOS DE CAJA'!$G$10:$G$2251) -> 0 | I10: =IF((+C10+D10-E10+F10+G10*0+H10)<0,(+C10+D10-E10+F10+G10*0+H10),0) -> 0
A11: 2 | B11: =_xlfn.XLOOKUP(A11,Códigos!$A$11:$A$415,Códigos!$B$11:$B$415,"Verificar",0) -> NOMBRE 23 | D11: =SUMIF('CARTERA años anteriores'!$C$9:$C$234,A11,'CARTERA años anteriores'!$J$9:$J$234) -> 4310000 | E11: =SUMIF('CARTERA años anteriores'!$C$9:$C$234,A11,'CARTERA años anteriores'!$L$9:$L$234) -> 0 | F11: =SUMIF(FACTURACIÓN!$C$8:$C$1082,A11,FACTURACIÓN!$K$8:$K$1082) -> 0 | G11: =SUMIF('INGRESOS A CAJA'!$C$10:$C$954,A11,'INGRESOS A CAJA'!$F$10:$F$954) -> 0 | H11: =SUMIF('EGRESOS DE CAJA'!$C$10:$C$2251,A11,'EGRESOS DE CAJA'!$G$10:$G$2251) -> 0 | I11: =IF((+C11+D11-E11+F11+G11*0+H11)<0,(+C11+D11-E11+F11+G11*0+H11),0) -> 0
A12: 3 | B12: =_xlfn.XLOOKUP(A12,Códigos!$A$11:$A$415,Códigos!$B$11:$B$415,"Verificar",0) -> NOMBRE 24 | D12: =SUMIF('CARTERA años anteriores'!$C$9:$C$234,A12,'CARTERA años anteriores'!$J$9:$J$234) -> 0 | E12: =SUMIF('CARTERA años anteriores'!$C$9:$C$234,A12,'CARTERA años anteriores'!$L$9:$L$234) -> 0 | F12: =SUMIF(FACTURACIÓN!$C$8:$C$1082,A12,FACTURACIÓN!$K$8:$K$1082)*0 -> 0 | G12: =SUMIF('INGRESOS A CAJA'!$C$10:$C$954,A12,'INGRESOS A CAJA'!$F$10:$F$954)*0 -> 0 | H12: =SUMIF('EGRESOS DE CAJA'!$C$10:$C$2251,A12,'EGRESOS DE CAJA'!$G$10:$G$2251)*0 -> 0 | I12: =IF((+C12+D12-E12+F12+G12*0+H12)<0,(+C12+D12-E12+F12+G12*0+H12),0) -> 0 | J12: N/A
A13: 4 | B13: =_xlfn.XLOOKUP(A13,Códigos!$A$11:$A$415,Códigos!$B$11:$B$415,"Verificar",0) -> NOMBRE 35 | D13: =SUMIF('CARTERA años anteriores'!$C$9:$C$234,A13,'CARTERA años anteriores'!$J$9:$J$234) -> 0 | E13: =SUMIF('CARTERA años anteriores'!$C$9:$C$234,A13,'CARTERA años anteriores'!$L$9:$L$234) -> 0 | F13: =SUMIF(FACTURACIÓN!$C$8:$C$1082,A13,FACTURACIÓN!$K$8:$K$1082) -> 0 | G13: =SUMIF('INGRESOS A CAJA'!$C$10:$C$954,A13,'INGRESOS A CAJA'!$F$10:$F$954) -> 0 | H13: =SUMIF('EGRESOS DE CAJA'!$C$10:$C$2251,A13,'EGRESOS DE CAJA'!$G$10:$G$2251) -> 0 | I13: =IF((+C13+D13-E13+F13+G13*0+H13)<0,(+C13+D13-E13+F13+G13*0+H13),0) -> 0
A14: 5 | B14: =_xlfn.XLOOKUP(A14,Códigos!$A$11:$A$415,Códigos!$B$11:$B$415,"Verificar",0) -> NOMBRE 25 | D14: =SUMIF('CARTERA años anteriores'!$C$9:$C$234,A14,'CARTERA años anteriores'!$J$9:$J$234) -> 0 | E14: =SUMIF('CARTERA años anteriores'!$C$9:$C$234,A14,'CARTERA años anteriores'!$L$9:$L$234) -> 0 | F14: =SUMIF(FACTURACIÓN!$C$8:$C$1082,A14,FACTURACIÓN!$K$8:$K$1082)*0 -> 0 | G14: =SUMIF('INGRESOS A CAJA'!$C$10:$C$954,A14,'INGRESOS A CAJA'!$F$10:$F$954)*0 -> 0 | H14: =SUMIF('EGRESOS DE CAJA'!$C$10:$C$2251,A14,'EGRESOS DE CAJA'!$G$10:$G$2251)*0 -> 0 | I14: =IF((+C14+D14-E14+F14+G14*0+H14)<0,(+C14+D14-E14+F14+G14*0+H14),0) -> 0 | J14: N/A
A15: 6 | B15: =_xlfn.XLOOKUP(A15,Códigos!$A$11:$A$415,Códigos!$B$11:$B$415,"Verificar",0) -> NOMBRE 57 | D15: =SUMIF('CARTERA años anteriores'!$C$9:$C$234,A15,'CARTERA años anteriores'!$J$9:$J$234) -> 0 | E15: =SUMIF('CARTERA años anteriores'!$C$9:$C$234,A15,'CARTERA años anteriores'!$L$9:$L$234) -> 0 | F15: =SUMIF(FACTURACIÓN!$C$8:$C$1082,A15,FACTURACIÓN!$K$8:$K$1082) -> 0 | G15: =SUMIF('INGRESOS A CAJA'!$C$10:$C$954,A15,'INGRESOS A CAJA'!$F$10:$F$954) -> 0 | H15: =SUMIF('EGRESOS DE CAJA'!$C$10:$C$2251,A15,'EGRESOS DE CAJA'!$G$10:$G$2251) -> 0 | I15: =IF((+C15+D15-E15+F15+G15*0+H15)<0,(+C15+D15-E15+F15+G15*0+H15),0) -> 0
A16: 7 | B16: =_xlfn.XLOOKUP(A16,Códigos!$A$11:$A$415,Códigos!$B$11:$B$415,"Verificar",0) -> NOMBRE 59 | D16: =SUMIF('CARTERA años anteriores'!$C$9:$C$234,A16,'CARTERA años anteriores'!$J$9:$J$234) -> 0 | E16: =SUMIF('CARTERA años anteriores'!$C$9:$C$234,A16,'CARTERA años anteriores'!$L$9:$L$234) -> 0 | F16: =SUMIF(FACTURACIÓN!$C$8:$C$1082,A16,FACTURACIÓN!$K$8:$K$1082)*0 -> 0 | G16: =SUMIF('INGRESOS A CAJA'!$C$10:$C$954,A16,'INGRESOS A CAJA'!$F$10:$F$954)*0 -> 0 | H16: =SUMIF('EGRESOS DE CAJA'!$C$10:$C$2251,A16,'EGRESOS DE CAJA'!$G$10:$G$2251)*0 -> 0 | I16: =IF((+C16+D16-E16+F16+G16*0+H16)<0,(+C16+D16-E16+F16+G16*0+H16),0) -> 0 | J16: N/A
A17: 8 | B17: =_xlfn.XLOOKUP(A17,Códigos!$A$11:$A$415,Códigos!$B$11:$B$415,"Verificar",0) -> NOMBRE 64 | D17: =SUMIF('CARTERA años anteriores'!$C$9:$C$234,A17,'CARTERA años anteriores'!$J$9:$J$234) -> 252000 | E17: =SUMIF('CARTERA años anteriores'!$C$9:$C$234,A17,'CARTERA años anteriores'!$L$9:$L$234) -> 0 | F17: =SUMIF(FACTURACIÓN!$C$8:$C$1082,A17,FACTURACIÓN!$K$8:$K$1082) -> 0 | G17: =SUMIF('INGRESOS A CAJA'!$C$10:$C$954,A17,'INGRESOS A CAJA'!$F$10:$F$954) -> 0 | H17: =SUMIF('EGRESOS DE CAJA'!$C$10:$C$2251,A17,'EGRESOS DE CAJA'!$G$10:$G$2251) -> 900100 | I17: =IF((+C17+D17-E17+F17+G17*0+H17)<0,(+C17+D17-E17+F17+G17*0+H17),0) -> 0
A18: 9 | B18: =_xlfn.XLOOKUP(A18,Códigos!$A$11:$A$415,Códigos!$B$11:$B$415,"Verificar",0) -> NOMBRE 65 | D18: =SUMIF('CARTERA años anteriores'!$C$9:$C$234,A18,'CARTERA años anteriores'!$J$9:$J$234) -> 8661600 | E18: =SUMIF('CARTERA años anteriores'!$C$9:$C$234,A18,'CARTERA años anteriores'!$L$9:$L$234) -> 0 | F18: =SUMIF(FACTURACIÓN!$C$8:$C$1082,A18,FACTURACIÓN!$K$8:$K$1082) -> 0 | G18: =SUMIF('INGRESOS A CAJA'!$C$10:$C$954,A18,'INGRESOS A CAJA'!$F$10:$F$954) -> 0 | H18: =SUMIF('EGRESOS DE CAJA'!$C$10:$C$2251,A18,'EGRESOS DE CAJA'!$G$10:$G$2251) -> 0 | I18: =IF((+C18+D18-E18+F18+G18*0+H18)<0,(+C18+D18-E18+F18+G18*0+H18),0) -> 0
A19: 10 | B19: =_xlfn.XLOOKUP(A19,Códigos!$A$11:$A$415,Códigos!$B$11:$B$415,"Verificar",0) -> NOMBRE 80 | D19: =SUMIF('CARTERA años anteriores'!$C$9:$C$234,A19,'CARTERA años anteriores'!$J$9:$J$234) -> 0 | E19: =SUMIF('CARTERA años anteriores'!$C$9:$C$234,A19,'CARTERA años anteriores'!$L$9:$L$234) -> 0 | F19: =SUMIF(FACTURACIÓN!$C$8:$C$1082,A19,FACTURACIÓN!$K$8:$K$1082) -> 8157240 | G19: =SUMIF('INGRESOS A CAJA'!$C$10:$C$954,A19,'INGRESOS A CAJA'!$F$10:$F$954) -> 0 | H19: =SUMIF('EGRESOS DE CAJA'!$C$10:$C$2251,A19,'EGRESOS DE CAJA'!$G$10:$G$2251) -> 0 | I19: =IF((+C19+D19-E19+F19+G19*0+H19)<0,(+C19+D19-E19+F19+G19*0+H19),0) -> 0
A20: 11 | B20: =_xlfn.XLOOKUP(A20,Códigos!$A$11:$A$415,Códigos!$B$11:$B$415,"Verificar",0) -> NOMBRE 92 | D20: =SUMIF('CARTERA años anteriores'!$C$9:$C$234,A20,'CARTERA años anteriores'!$J$9:$J$234) -> 0 | E20: =SUMIF('CARTERA años anteriores'!$C$9:$C$234,A20,'CARTERA años anteriores'!$L$9:$L$234) -> 0 | F20: =SUMIF(FACTURACIÓN!$C$8:$C$1082,A20,FACTURACIÓN!$K$8:$K$1082) -> 0 | G20: =SUMIF('INGRESOS A CAJA'!$C$10:$C$954,A20,'INGRESOS A CAJA'!$F$10:$F$954) -> 0 | H20: =SUMIF('EGRESOS DE CAJA'!$C$10:$C$2251,A20,'EGRESOS DE CAJA'!$G$10:$G$2251) -> 0 | I20: =IF((+C20+D20-E20+F20+G20*0+H20)<0,(+C20+D20-E20+F20+G20*0+H20),0) -> 0
A21: 12 | B21: =_xlfn.XLOOKUP(A21,Códigos!$A$11:$A$415,Códigos!$B$11:$B$415,"Verificar",0) -> NOMBRE 115 | D21: =SUMIF('CARTERA años anteriores'!$C$9:$C$234,A21,'CARTERA años anteriores'!$J$9:$J$234) -> 0 | E21: =SUMIF('CARTERA años anteriores'!$C$9:$C$234,A21,'CARTERA años anteriores'!$L$9:$L$234) -> 0 | F21: =SUMIF(FACTURACIÓN!$C$8:$C$1082,A21,FACTURACIÓN!$K$8:$K$1082) -> 0 | G21: =SUMIF('INGRESOS A CAJA'!$C$10:$C$954,A21,'INGRESOS A CAJA'!$F$10:$F$954) -> 0 | H21: =SUMIF('EGRESOS DE CAJA'!$C$10:$C$2251,A21,'EGRESOS DE CAJA'!$G$10:$G$2251) -> 0 | I21: =IF((+C21+D21-E21+F21+G21*0+H21)<0,(+C21+D21-E21+F21+G21*0+H21),0) -> 0
A22: 13 | B22: =_xlfn.XLOOKUP(A22,Códigos!$A$11:$A$415,Códigos!$B$11:$B$415,"Verificar",0) -> NOMBRE 50 | D22: =SUMIF('CARTERA años anteriores'!$C$9:$C$234,A22,'CARTERA años anteriores'!$J$9:$J$234) -> 0 | E22: =SUMIF('CARTERA años anteriores'!$C$9:$C$234,A22,'CARTERA años anteriores'!$L$9:$L$234) -> 0 | F22: =SUMIF(FACTURACIÓN!$C$8:$C$1082,A22,FACTURACIÓN!$K$8:$K$1082) -> 0 | G22: =SUMIF('INGRESOS A CAJA'!$C$10:$C$954,A22,'INGRESOS A CAJA'!$F$10:$F$954) -> 0 | H22: =SUMIF('EGRESOS DE CAJA'!$C$10:$C$2251,A22,'EGRESOS DE CAJA'!$G$10:$G$2251) -> 0 | I22: =IF((+C22+D22-E22+F22+G22*0+H22)<0,(+C22+D22-E22+F22+G22*0+H22),0) -> 0
A23: 14 | B23: =_xlfn.XLOOKUP(A23,Códigos!$A$11:$A$415,Códigos!$B$11:$B$415,"Verificar",0) -> NOMBRE 158 | D23: =SUMIF('CARTERA años anteriores'!$C$9:$C$234,A23,'CARTERA años anteriores'!$J$9:$J$234) -> 0 | E23: =SUMIF('CARTERA años anteriores'!$C$9:$C$234,A23,'CARTERA años anteriores'!$L$9:$L$234) -> 0 | F23: =SUMIF(FACTURACIÓN!$C$8:$C$1082,A23,FACTURACIÓN!$K$8:$K$1082) -> 0 | G23: =SUMIF('INGRESOS A CAJA'!$C$10:$C$954,A23,'INGRESOS A CAJA'!$F$10:$F$954) -> 0 | H23: =SUMIF('EGRESOS DE CAJA'!$C$10:$C$2251,A23,'EGRESOS DE CAJA'!$G$10:$G$2251) -> 0 | I23: =IF((+C23+D23-E23+F23+G23*0+H23)<0,(+C23+D23-E23+F23+G23*0+H23),0) -> 0
A24: 15 | B24: =_xlfn.XLOOKUP(A24,Códigos!$A$11:$A$415,Códigos!$B$11:$B$415,"Verificar",0) -> NOMBRE 159 | D24: =SUMIF('CARTERA años anteriores'!$C$9:$C$234,A24,'CARTERA años anteriores'!$J$9:$J$234) -> 0 | E24: =SUMIF('CARTERA años anteriores'!$C$9:$C$234,A24,'CARTERA años anteriores'!$L$9:$L$234) -> 0 | F24: =SUMIF(FACTURACIÓN!$C$8:$C$1082,A24,FACTURACIÓN!$K$8:$K$1082) -> 0 | G24: =SUMIF('INGRESOS A CAJA'!$C$10:$C$954,A24,'INGRESOS A CAJA'!$F$10:$F$954) -> 0 | H24: =SUMIF('EGRESOS DE CAJA'!$C$10:$C$2251,A24,'EGRESOS DE CAJA'!$G$10:$G$2251) -> 0 | I24: =IF((+C24+D24-E24+F24+G24*0+H24)<0,(+C24+D24-E24+F24+G24*0+H24),0) -> 0
A25: 16 | B25: =_xlfn.XLOOKUP(A25,Códigos!$A$11:$A$415,Códigos!$B$11:$B$415,"Verificar",0) -> NOMBRE 105 | D25: =SUMIF('CARTERA años anteriores'!$C$9:$C$234,A25,'CARTERA años anteriores'!$J$9:$J$234) -> 0 | E25: =SUMIF('CARTERA años anteriores'!$C$9:$C$234,A25,'CARTERA años anteriores'!$L$9:$L$234) -> 0 | F25: =SUMIF(FACTURACIÓN!$C$8:$C$1082,A25,FACTURACIÓN!$K$8:$K$1082) -> 0 | G25: =SUMIF('INGRESOS A CAJA'!$C$10:$C$954,A25,'INGRESOS A CAJA'!$F$10:$F$954) -> 0 | H25: =SUMIF('EGRESOS DE CAJA'!$C$10:$C$2251,A25,'EGRESOS DE CAJA'!$G$10:$G$2251) -> 0 | I25: =IF((+C25+D25-E25+F25+G25*0+H25)<0,(+C25+D25-E25+F25+G25*0+H25),0) -> 0
A26: 17 | B26: =_xlfn.XLOOKUP(A26,Códigos!$A$11:$A$415,Códigos!$B$11:$B$415,"Verificar",0) -> NOMBRE 160 | D26: =SUMIF('CARTERA años anteriores'!$C$9:$C$234,A26,'CARTERA años anteriores'!$J$9:$J$234) -> 0 | E26: =SUMIF('CARTERA años anteriores'!$C$9:$C$234,A26,'CARTERA años anteriores'!$L$9:$L$234) -> 0 | F26: =SUMIF(FACTURACIÓN!$C$8:$C$1082,A26,FACTURACIÓN!$K$8:$K$1082) -> 0 | G26: =SUMIF('INGRESOS A CAJA'!$C$10:$C$954,A26,'INGRESOS A CAJA'!$F$10:$F$954) -> 0 | H26: =SUMIF('EGRESOS DE CAJA'!$C$10:$C$2251,A26,'EGRESOS DE CAJA'!$G$10:$G$2251) -> 0 | I26: =IF((+C26+D26-E26+F26+G26*0+H26)<0,(+C26+D26-E26+F26+G26*0+H26),0) -> 0
A27: 18 | B27: =_xlfn.XLOOKUP(A27,Códigos!$A$11:$A$415,Códigos!$B$11:$B$415,"Verificar",0) -> NOMBRE 161 | D27: =SUMIF('CARTERA años anteriores'!$C$9:$C$234,A27,'CARTERA años anteriores'!$J$9:$J$234) -> 0 | E27: =SUMIF('CARTERA años anteriores'!$C$9:$C$234,A27,'CARTERA años anteriores'!$L$9:$L$234) -> 0 | F27: =SUMIF(FACTURACIÓN!$C$8:$C$1082,A27,FACTURACIÓN!$K$8:$K$1082) -> 0 | G27: =SUMIF('INGRESOS A CAJA'!$C$10:$C$954,A27,'INGRESOS A CAJA'!$F$10:$F$954) -> 0 | H27: =SUMIF('EGRESOS DE CAJA'!$C$10:$C$2251,A27,'EGRESOS DE CAJA'!$G$10:$G$2251) -> 0 | I27: =IF((+C27+D27-E27+F27+G27*0+H27)<0,(+C27+D27-E27+F27+G27*0+H27),0) -> 0
A28: 19 | B28: =_xlfn.XLOOKUP(A28,Códigos!$A$11:$A$415,Códigos!$B$11:$B$415,"Verificar",0) -> NOMBRE 164 | D28: =SUMIF('CARTERA años anteriores'!$C$9:$C$234,A28,'CARTERA años anteriores'!$J$9:$J$234) -> 0 | E28: =SUMIF('CARTERA años anteriores'!$C$9:$C$234,A28,'CARTERA años anteriores'!$L$9:$L$234) -> 0 | F28: =SUMIF(FACTURACIÓN!$C$8:$C$1082,A28,FACTURACIÓN!$K$8:$K$1082) -> 11907000 | G28: =SUMIF('INGRESOS A CAJA'!$C$10:$C$954,A28,'INGRESOS A CAJA'!$F$10:$F$954) -> 0 | H28: =SUMIF('EGRESOS DE CAJA'!$C$10:$C$2251,A28,'EGRESOS DE CAJA'!$G$10:$G$2251) -> 0 | I28: =IF((+C28+D28-E28+F28+G28*0+H28)<0,(+C28+D28-E28+F28+G28*0+H28),0) -> 0
... A270: 261 | B270: =_xlfn.XLOOKUP(A270,Códigos!$A$11:$A$415,Códigos!$B$11:$B$415,"Verificar",0) -> NOMBRE 153 | D270: =SUMIF('CARTERA años anteriores'!$C$9:$C$234,A270,'CARTERA años anteriores'!$J$9:$J$234) -> 0 | E270: =SUMIF('CARTERA años anteriores'!$C$9:$C$234,A270,'CARTERA años anteriores'!$L$9:$L$234) -> 0 | F270: =SUMIF(FACTURACIÓN!$C$8:$C$1082,A270,FACTURACIÓN!$K$8:$K$1082) -> 0 | G270: =SUMIF('INGRESOS A CAJA'!$C$10:$C$954,A270,'INGRESOS A CAJA'!$F$10:$F$954) -> 0 | H270: =SUMIF('EGRESOS DE CAJA'!$C$10:$C$2251,A270,'EGRESOS DE CAJA'!$G$10:$G$2251) -> 0 | I270: =IF((+C270+D270-E270+F270+G270*0+H270)<0,(+C270+D270-E270+F270+G270*0+H270),0) -> 0
A271: 262 | B271: =_xlfn.XLOOKUP(A271,Códigos!$A$11:$A$415,Códigos!$B$11:$B$415,"Verificar",0) -> NOMBRE 95 | D271: =SUMIF('CARTERA años anteriores'!$C$9:$C$234,A271,'CARTERA años anteriores'!$J$9:$J$234) -> 43100984 | E271: =SUMIF('CARTERA años anteriores'!$C$9:$C$234,A271,'CARTERA años anteriores'!$L$9:$L$234) -> 1744200 | H271: =+'EMPLEADO 2'!E14 -> 12065900 | I271: =IF((+C271+D271-E271+F271+G271*0+H271)<0,(+C271+D271-E271+F271+G271*0+H271),0) -> 0
A272: 263 | B272: =_xlfn.XLOOKUP(A272,Códigos!$A$11:$A$415,Códigos!$B$11:$B$415,"Verificar",0) -> NOMBRE 128 | D272: =SUMIF('CARTERA años anteriores'!$C$9:$C$234,A272,'CARTERA años anteriores'!$J$9:$J$234) -> 0 | E272: =SUMIF('CARTERA años anteriores'!$C$9:$C$234,A272,'CARTERA años anteriores'!$L$9:$L$234) -> 0 | F272: =SUMIF(FACTURACIÓN!$C$8:$C$1082,A272,FACTURACIÓN!$K$8:$K$1082) -> 0 | G272: =SUMIF('INGRESOS A CAJA'!$C$10:$C$954,A272,'INGRESOS A CAJA'!$F$10:$F$954) -> 0 | H272: =SUMIF('EGRESOS DE CAJA'!$C$10:$C$2251,A272,'EGRESOS DE CAJA'!$G$10:$G$2251) -> 0 | I272: =IF((+C272+D272-E272+F272+G272*0+H272)<0,(+C272+D272-E272+F272+G272*0+H272),0) -> 0
A273: 264 | B273: =_xlfn.XLOOKUP(A273,Códigos!$A$11:$A$415,Códigos!$B$11:$B$415,"Verificar",0) -> NOMBRE 312 | D273: =SUMIF('CARTERA años anteriores'!$C$9:$C$234,A273,'CARTERA años anteriores'!$J$9:$J$234) -> 0 | E273: =SUMIF('CARTERA años anteriores'!$C$9:$C$234,A273,'CARTERA años anteriores'!$L$9:$L$234) -> 0 | F273: =SUMIF(FACTURACIÓN!$C$8:$C$1082,A273,FACTURACIÓN!$K$8:$K$1082) -> 350000 | G273: =SUMIF('INGRESOS A CAJA'!$C$10:$C$954,A273,'INGRESOS A CAJA'!$F$10:$F$954) -> 0 | H273: =SUMIF('EGRESOS DE CAJA'!$C$10:$C$2251,A273,'EGRESOS DE CAJA'!$G$10:$G$2251) -> 0 | I273: =IF((+C273+D273-E273+F273+G273*0+H273)<0,(+C273+D273-E273+F273+G273*0+H273),0) -> 0
A274: 265 | B274: =_xlfn.XLOOKUP(A274,Códigos!$A$11:$A$415,Códigos!$B$11:$B$415,"Verificar",0) -> NOMBRE 246 | D274: =SUMIF('CARTERA años anteriores'!$C$9:$C$234,A274,'CARTERA años anteriores'!$J$9:$J$234) -> 320000 | E274: =SUMIF('CARTERA años anteriores'!$C$9:$C$234,A274,'CARTERA años anteriores'!$L$9:$L$234) -> 0 | F274: =SUMIF(FACTURACIÓN!$C$8:$C$1082,A274,FACTURACIÓN!$K$8:$K$1082) -> 370000 | G274: =SUMIF('INGRESOS A CAJA'!$C$10:$C$954,A274,'INGRESOS A CAJA'!$F$10:$F$954) -> 0 | H274: =SUMIF('EGRESOS DE CAJA'!$C$10:$C$2251,A274,'EGRESOS DE CAJA'!$G$10:$G$2251) -> 0 | I274: =IF((+C274+D274-E274+F274+G274*0+H274)<0,(+C274+D274-E274+F274+G274*0+H274),0) -> 0
A275: 266 | B275: =_xlfn.XLOOKUP(A275,Códigos!$A$11:$A$415,Códigos!$B$11:$B$415,"Verificar",0) -> NOMBRE 304 | D275: =SUMIF('CARTERA años anteriores'!$C$9:$C$234,A275,'CARTERA años anteriores'!$J$9:$J$234) -> 0 | E275: =SUMIF('CARTERA años anteriores'!$C$9:$C$234,A275,'CARTERA años anteriores'!$L$9:$L$234) -> 0 | F275: =SUMIF(FACTURACIÓN!$C$8:$C$1082,A275,FACTURACIÓN!$K$8:$K$1082) -> 310000 | G275: =SUMIF('INGRESOS A CAJA'!$C$10:$C$954,A275,'INGRESOS A CAJA'!$F$10:$F$954) -> 0 | H275: =SUMIF('EGRESOS DE CAJA'!$C$10:$C$2251,A275,'EGRESOS DE CAJA'!$G$10:$G$2251) -> 0 | I275: =IF((+C275+D275-E275+F275+G275*0+H275)<0,(+C275+D275-E275+F275+G275*0+H275),0) -> 0
A276: 267 | B276: =_xlfn.XLOOKUP(A276,Códigos!$A$11:$A$415,Códigos!$B$11:$B$415,"Verificar",0) -> NOMBRE 224 | D276: =SUMIF('CARTERA años anteriores'!$C$9:$C$234,A276,'CARTERA años anteriores'!$J$9:$J$234) -> 0 | E276: =SUMIF('CARTERA años anteriores'!$C$9:$C$234,A276,'CARTERA años anteriores'!$L$9:$L$234) -> 0 | F276: =SUMIF(FACTURACIÓN!$C$8:$C$1082,A276,FACTURACIÓN!$K$8:$K$1082) -> 310000 | G276: =SUMIF('INGRESOS A CAJA'!$C$10:$C$954,A276,'INGRESOS A CAJA'!$F$10:$F$954) -> 0 | H276: =SUMIF('EGRESOS DE CAJA'!$C$10:$C$2251,A276,'EGRESOS DE CAJA'!$G$10:$G$2251) -> 0 | I276: =IF((+C276+D276-E276+F276+G276*0+H276)<0,(+C276+D276-E276+F276+G276*0+H276),0) -> 0
A277: 268 | B277: =_xlfn.XLOOKUP(A277,Códigos!$A$11:$A$415,Códigos!$B$11:$B$415,"Verificar",0) -> NOMBRE 326 | D277: =SUMIF('CARTERA años anteriores'!$C$9:$C$234,A277,'CARTERA años anteriores'!$J$9:$J$234) -> 0 | E277: =SUMIF('CARTERA años anteriores'!$C$9:$C$234,A277,'CARTERA años anteriores'!$L$9:$L$234) -> 0 | F277: =SUMIF(FACTURACIÓN!$C$8:$C$1082,A277,FACTURACIÓN!$K$8:$K$1082) -> 0 | G277: =SUMIF('INGRESOS A CAJA'!$C$10:$C$954,A277,'INGRESOS A CAJA'!$F$10:$F$954) -> 0 | H277: =SUMIF('EGRESOS DE CAJA'!$C$10:$C$2251,A277,'EGRESOS DE CAJA'!$G$10:$G$2251) -> 0 | I277: =IF((+C277+D277-E277+F277+G277*0+H277)<0,(+C277+D277-E277+F277+G277*0+H277),0) -> 0
A278: 269 | B278: =_xlfn.XLOOKUP(A278,Códigos!$A$11:$A$415,Códigos!$B$11:$B$415,"Verificar",0) -> NOMBRE 218 | D278: =SUMIF('CARTERA años anteriores'!$C$9:$C$234,A278,'CARTERA años anteriores'!$J$9:$J$234) -> 0 | E278: =SUMIF('CARTERA años anteriores'!$C$9:$C$234,A278,'CARTERA años anteriores'!$L$9:$L$234) -> 0 | F278: =SUMIF(FACTURACIÓN!$C$8:$C$1082,A278,FACTURACIÓN!$K$8:$K$1082) -> 320000 | G278: =SUMIF('INGRESOS A CAJA'!$C$10:$C$954,A278,'INGRESOS A CAJA'!$F$10:$F$954) -> 0 | H278: =SUMIF('EGRESOS DE CAJA'!$C$10:$C$2251,A278,'EGRESOS DE CAJA'!$G$10:$G$2251) -> 0 | I278: =IF((+C278+D278-E278+F278+G278*0+H278)<0,(+C278+D278-E278+F278+G278*0+H278),0) -> 0
A279: 270 | B279: =_xlfn.XLOOKUP(A279,Códigos!$A$11:$A$415,Códigos!$B$11:$B$415,"Verificar",0) -> NOMBRE 34 | D279: =SUMIF('CARTERA años anteriores'!$C$9:$C$234,A279,'CARTERA años anteriores'!$J$9:$J$234) -> 0 | E279: =SUMIF('CARTERA años anteriores'!$C$9:$C$234,A279,'CARTERA años anteriores'!$L$9:$L$234) -> 0 | F279: =SUMIF(FACTURACIÓN!$C$8:$C$1082,A279,FACTURACIÓN!$K$8:$K$1082) -> 0 | G279: =SUMIF('INGRESOS A CAJA'!$C$10:$C$954,A279,'INGRESOS A CAJA'!$F$10:$F$954) -> 0 | H279: =SUMIF('EGRESOS DE CAJA'!$C$10:$C$2251,A279,'EGRESOS DE CAJA'!$G$10:$G$2251) -> 0 | I279: =IF((+C279+D279-E279+F279+G279*0+H279)<0,(+C279+D279-E279+F279+G279*0+H279),0) -> 0
A280: 271 | B280: =_xlfn.XLOOKUP(A280,Códigos!$A$11:$A$415,Códigos!$B$11:$B$415,"Verificar",0) -> NOMBRE 38 | D280: =SUMIF('CARTERA años anteriores'!$C$9:$C$234,A280,'CARTERA años anteriores'!$J$9:$J$234) -> 0 | E280: =SUMIF('CARTERA años anteriores'!$C$9:$C$234,A280,'CARTERA años anteriores'!$L$9:$L$234) -> 0 | F280: =SUMIF(FACTURACIÓN!$C$8:$C$1082,A280,FACTURACIÓN!$K$8:$K$1082) -> 330000 | G280: =SUMIF('INGRESOS A CAJA'!$C$10:$C$954,A280,'INGRESOS A CAJA'!$F$10:$F$954) -> 0 | H280: =SUMIF('EGRESOS DE CAJA'!$C$10:$C$2251,A280,'EGRESOS DE CAJA'!$G$10:$G$2251) -> 0 | I280: =IF((+C280+D280-E280+F280+G280*0+H280)<0,(+C280+D280-E280+F280+G280*0+H280),0) -> 0
A281: 272 | B281: =_xlfn.XLOOKUP(A281,Códigos!$A$11:$A$415,Códigos!$B$11:$B$415,"Verificar",0) -> NOMBRE 81 | D281: =SUMIF('CARTERA años anteriores'!$C$9:$C$234,A281,'CARTERA años anteriores'!$J$9:$J$234) -> 0 | E281: =SUMIF('CARTERA años anteriores'!$C$9:$C$234,A281,'CARTERA años anteriores'!$L$9:$L$234) -> 0 | F281: =SUMIF(FACTURACIÓN!$C$8:$C$1082,A281,FACTURACIÓN!$K$8:$K$1082) -> 350000 | G281: =SUMIF('INGRESOS A CAJA'!$C$10:$C$954,A281,'INGRESOS A CAJA'!$F$10:$F$954) -> 350000 | H281: =SUMIF('EGRESOS DE CAJA'!$C$10:$C$2251,A281,'EGRESOS DE CAJA'!$G$10:$G$2251) -> 0 | I281: =IF((+C281+D281-E281+F281+G281*0+H281)<0,(+C281+D281-E281+F281+G281*0+H281),0) -> 0
A282: 273 | B282: =_xlfn.XLOOKUP(A282,Códigos!$A$11:$A$415,Códigos!$B$11:$B$415,"Verificar",0) -> NOMBRE 88 | D282: =SUMIF('CARTERA años anteriores'!$C$9:$C$234,A282,'CARTERA años anteriores'!$J$9:$J$234) -> 580000 | E282: =SUMIF('CARTERA años anteriores'!$C$9:$C$234,A282,'CARTERA años anteriores'!$L$9:$L$234) -> 580000 | F282: =SUMIF(FACTURACIÓN!$C$8:$C$1082,A282,FACTURACIÓN!$K$8:$K$1082) -> 610000 | G282: =SUMIF('INGRESOS A CAJA'!$C$10:$C$954,A282,'INGRESOS A CAJA'!$F$10:$F$954) -> 580000 | H282: =SUMIF('EGRESOS DE CAJA'!$C$10:$C$2251,A282,'EGRESOS DE CAJA'!$G$10:$G$2251) -> 0 | I282: =IF((+C282+D282-E282+F282+G282*0+H282)<0,(+C282+D282-E282+F282+G282*0+H282),0) -> 0
A283: 274 | B283: =_xlfn.XLOOKUP(A283,Códigos!$A$11:$A$415,Códigos!$B$11:$B$415,"Verificar",0) -> NOMBRE 280 | D283: =SUMIF('CARTERA años anteriores'!$C$9:$C$234,A283,'CARTERA años anteriores'!$J$9:$J$234) -> 0 | E283: =SUMIF('CARTERA años anteriores'!$C$9:$C$234,A283,'CARTERA años anteriores'!$L$9:$L$234) -> 0 | F283: =SUMIF(FACTURACIÓN!$C$8:$C$1082,A283,FACTURACIÓN!$K$8:$K$1082) -> 0 | G283: =SUMIF('INGRESOS A CAJA'!$C$10:$C$954,A283,'INGRESOS A CAJA'!$F$10:$F$954) -> 0 | H283: =SUMIF('EGRESOS DE CAJA'!$C$10:$C$2251,A283,'EGRESOS DE CAJA'!$G$10:$G$2251) -> 0 | I283: =IF((+C283+D283-E283+F283+G283*0+H283)<0,(+C283+D283-E283+F283+G283*0+H283),0) -> 0
... A292: 283 | B292: =_xlfn.XLOOKUP(A292,Códigos!$A$11:$A$415,Códigos!$B$11:$B$415,"Verificar",0) -> NOMBRE 104 | D292: =SUMIF('CARTERA años anteriores'!$C$9:$C$234,A292,'CARTERA años anteriores'!$J$9:$J$234) -> #REF! | E292: =SUMIF('CARTERA años anteriores'!$C$9:$C$234,A292,'CARTERA años anteriores'!$L$9:$L$234) -> 0 | F292: =SUMIF(FACTURACIÓN!$C$8:$C$1082,A292,FACTURACIÓN!$K$8:$K$1082) -> 0 | G292: =SUMIF('INGRESOS A CAJA'!$C$10:$C$954,A292,'INGRESOS A CAJA'!$F$10:$F$954) -> 0 | H292: =SUMIF('EGRESOS DE CAJA'!$C$10:$C$2251,A292,'EGRESOS DE CAJA'!$G$10:$G$2251) -> 0 | I292: =IF((+C292+D292-E292+F292+G292*0+H292)<0,(+C292+D292-E292+F292+G292*0+H292),0) -> #REF!
A293: 284 | B293: =_xlfn.XLOOKUP(A293,Códigos!$A$11:$A$415,Códigos!$B$11:$B$415,"Verificar",0) -> NOMBRE 103 | C293: -75575217 | D293: =SUMIF('CARTERA años anteriores'!$C$9:$C$234,A293,'CARTERA años anteriores'!$J$9:$J$234) -> 0 | E293: =SUMIF('CARTERA años anteriores'!$C$9:$C$234,A293,'CARTERA años anteriores'!$L$9:$L$234) -> 0 | F293: =SUMIF(FACTURACIÓN!$C$8:$C$1082,A293,FACTURACIÓN!$K$8:$K$1082) -> 0 | G293: =SUMIF('INGRESOS A CAJA'!$C$10:$C$954,A293,'INGRESOS A CAJA'!$F$10:$F$954) -> 0 | H293: =SUMIF('EGRESOS DE CAJA'!$C$10:$C$2251,A293,'EGRESOS DE CAJA'!$G$10:$G$2251) -> 0 | I293: =IF((+C293+D293-E293+F293+G293*0+H293)<0,(+C293+D293-E293+F293+G293*0+H293),0) -> -75575217
A294: 285 | B294: =_xlfn.XLOOKUP(A294,Códigos!$A$11:$A$415,Códigos!$B$11:$B$415,"Verificar",0) -> NOMBRE 99 | D294: =SUMIF('CARTERA años anteriores'!$C$9:$C$234,A294,'CARTERA años anteriores'!$J$9:$J$234) -> 0 | E294: =SUMIF('CARTERA años anteriores'!$C$9:$C$234,A294,'CARTERA años anteriores'!$L$9:$L$234) -> 0 | F294: =SUMIF(FACTURACIÓN!$C$8:$C$1082,A294,FACTURACIÓN!$K$8:$K$1082) -> 0 | G294: =SUMIF('INGRESOS A CAJA'!$C$10:$C$954,A294,'INGRESOS A CAJA'!$F$10:$F$954) -> 0 | H294: =SUMIF('EGRESOS DE CAJA'!$C$10:$C$2251,A294,'EGRESOS DE CAJA'!$G$10:$G$2251) -> 0 | I294: =IF((+C294+D294-E294+F294+G294*0+H294)<0,(+C294+D294-E294+F294+G294*0+H294),0) -> 0
A295: 286 | B295: =_xlfn.XLOOKUP(A295,Códigos!$A$11:$A$415,Códigos!$B$11:$B$415,"Verificar",0) -> NOMBRE 129 | D295: =SUMIF('CARTERA años anteriores'!$C$9:$C$234,A295,'CARTERA años anteriores'!$J$9:$J$234) -> 0 | E295: =SUMIF('CARTERA años anteriores'!$C$9:$C$234,A295,'CARTERA años anteriores'!$L$9:$L$234) -> 0 | F295: =SUMIF(FACTURACIÓN!$C$8:$C$1082,A295,FACTURACIÓN!$K$8:$K$1082) -> 0 | G295: =SUMIF('INGRESOS A CAJA'!$C$10:$C$954,A295,'INGRESOS A CAJA'!$F$10:$F$954) -> 0 | H295: =SUMIF('EGRESOS DE CAJA'!$C$10:$C$2251,A295,'EGRESOS DE CAJA'!$G$10:$G$2251) -> 0 | I295: =IF((+C295+D295-E295+F295+G295*0+H295)<0,(+C295+D295-E295+F295+G295*0+H295),0) -> 0
A296: 287 | B296: =_xlfn.XLOOKUP(A296,Códigos!$A$11:$A$415,Códigos!$B$11:$B$415,"Verificar",0) -> NOMBRE 109 | D296: =SUMIF('CARTERA años anteriores'!$C$9:$C$234,A296,'CARTERA años anteriores'!$J$9:$J$234) -> 150000 | E296: =SUMIF('CARTERA años anteriores'!$C$9:$C$234,A296,'CARTERA años anteriores'!$L$9:$L$234) -> 150000 | F296: =SUMIF(FACTURACIÓN!$C$8:$C$1082,A296,FACTURACIÓN!$K$8:$K$1082) -> 160000 | G296: =SUMIF('INGRESOS A CAJA'!$C$10:$C$954,A296,'INGRESOS A CAJA'!$F$10:$F$954) -> 150000 | H296: =SUMIF('EGRESOS DE CAJA'!$C$10:$C$2251,A296,'EGRESOS DE CAJA'!$G$10:$G$2251) -> 0 | I296: =IF((+C296+D296-E296+F296+G296*0+H296)<0,(+C296+D296-E296+F296+G296*0+H296),0) -> 0
A297: 288 | B297: =_xlfn.XLOOKUP(A297,Códigos!$A$11:$A$415,Códigos!$B$11:$B$415,"Verificar",0) -> NOMBRE 182 | D297: =SUMIF('CARTERA años anteriores'!$C$9:$C$234,A297,'CARTERA años anteriores'!$J$9:$J$234) -> 0 | E297: =SUMIF('CARTERA años anteriores'!$C$9:$C$234,A297,'CARTERA años anteriores'!$L$9:$L$234) -> 0 | F297: =SUMIF(FACTURACIÓN!$C$8:$C$1082,A297,FACTURACIÓN!$K$8:$K$1082) -> 0 | G297: =SUMIF('INGRESOS A CAJA'!$C$10:$C$954,A297,'INGRESOS A CAJA'!$F$10:$F$954) -> 0 | H297: =SUMIF('EGRESOS DE CAJA'!$C$10:$C$2251,A297,'EGRESOS DE CAJA'!$G$10:$G$2251) -> 0 | I297: =IF((+C297+D297-E297+F297+G297*0+H297)<0,(+C297+D297-E297+F297+G297*0+H297),0) -> 0
A298: 289 | B298: =_xlfn.XLOOKUP(A298,Códigos!$A$11:$A$415,Códigos!$B$11:$B$415,"Verificar",0) -> NOMBRE 140 | D298: =SUMIF('CARTERA años anteriores'!$C$9:$C$234,A298,'CARTERA años anteriores'!$J$9:$J$234) -> 430000 | E298: =SUMIF('CARTERA años anteriores'!$C$9:$C$234,A298,'CARTERA años anteriores'!$L$9:$L$234) -> 0 | F298: =SUMIF(FACTURACIÓN!$C$8:$C$1082,A298,FACTURACIÓN!$K$8:$K$1082) -> 450000 | G298: =SUMIF('INGRESOS A CAJA'!$C$10:$C$954,A298,'INGRESOS A CAJA'!$F$10:$F$954) -> 0 | H298: =SUMIF('EGRESOS DE CAJA'!$C$10:$C$2251,A298,'EGRESOS DE CAJA'!$G$10:$G$2251) -> 0 | I298: =IF((+C298+D298-E298+F298+G298*0+H298)<0,(+C298+D298-E298+F298+G298*0+H298),0) -> 0
A299: 290 | B299: =_xlfn.XLOOKUP(A299,Códigos!$A$11:$A$415,Códigos!$B$11:$B$415,"Verificar",0) -> NOMBRE 170 | D299: =SUMIF('CARTERA años anteriores'!$C$9:$C$234,A299,'CARTERA años anteriores'!$J$9:$J$234) -> 15957100 | E299: =SUMIF('CARTERA años anteriores'!$C$9:$C$234,A299,'CARTERA años anteriores'!$L$9:$L$234) -> 11983300 | F299: =SUMIF(FACTURACIÓN!$C$8:$C$1082,A299,FACTURACIÓN!$K$8:$K$1082) -> 0 | G299: =SUMIF('INGRESOS A CAJA'!$C$10:$C$954,A299,'INGRESOS A CAJA'!$F$10:$F$954) -> 11983300 | H299: =SUMIF('EGRESOS DE CAJA'!$C$10:$C$2251,A299,'EGRESOS DE CAJA'!$G$10:$G$2251) -> 0 | I299: =IF((+C299+D299-E299+F299+G299*0+H299)<0,(+C299+D299-E299+F299+G299*0+H299),0) -> 0
A300: 291 | B300: =_xlfn.XLOOKUP(A300,Códigos!$A$11:$A$415,Códigos!$B$11:$B$415,"Verificar",0) -> NOMBRE 173 | D300: =SUMIF('CARTERA años anteriores'!$C$9:$C$234,A300,'CARTERA años anteriores'!$J$9:$J$234) -> 0 | E300: =SUMIF('CARTERA años anteriores'!$C$9:$C$234,A300,'CARTERA años anteriores'!$L$9:$L$234) -> 0 | F300: =SUMIF(FACTURACIÓN!$C$8:$C$1082,A300,FACTURACIÓN!$K$8:$K$1082) -> 0 | G300: =SUMIF('INGRESOS A CAJA'!$C$10:$C$954,A300,'INGRESOS A CAJA'!$F$10:$F$954) -> 0 | H300: =SUMIF('EGRESOS DE CAJA'!$C$10:$C$2251,A300,'EGRESOS DE CAJA'!$G$10:$G$2251) -> 0 | I300: =IF((+C300+D300-E300+F300+G300*0+H300)<0,(+C300+D300-E300+F300+G300*0+H300),0) -> 0
A301: 292 | B301: =_xlfn.XLOOKUP(A301,Códigos!$A$11:$A$415,Códigos!$B$11:$B$415,"Verificar",0) -> NOMBRE 174 | D301: =SUMIF('CARTERA años anteriores'!$C$9:$C$234,A301,'CARTERA años anteriores'!$J$9:$J$234) -> 0 | E301: =SUMIF('CARTERA años anteriores'!$C$9:$C$234,A301,'CARTERA años anteriores'!$L$9:$L$234) -> 0 | F301: =SUMIF(FACTURACIÓN!$C$8:$C$1082,A301,FACTURACIÓN!$K$8:$K$1082) -> 0 | G301: =SUMIF('INGRESOS A CAJA'!$C$10:$C$954,A301,'INGRESOS A CAJA'!$F$10:$F$954) -> 0 | H301: =SUMIF('EGRESOS DE CAJA'!$C$10:$C$2251,A301,'EGRESOS DE CAJA'!$G$10:$G$2251) -> 0 | I301: =IF((+C301+D301-E301+F301+G301*0+H301)<0,(+C301+D301-E301+F301+G301*0+H301),0) -> 0
A302: 293 | B302: =_xlfn.XLOOKUP(A302,Códigos!$A$11:$A$415,Códigos!$B$11:$B$415,"Verificar",0) -> NOMBRE 175 | D302: =SUMIF('CARTERA años anteriores'!$C$9:$C$234,A302,'CARTERA años anteriores'!$J$9:$J$234) -> 0 | E302: =SUMIF('CARTERA años anteriores'!$C$9:$C$234,A302,'CARTERA años anteriores'!$L$9:$L$234) -> 0 | F302: =SUMIF(FACTURACIÓN!$C$8:$C$1082,A302,FACTURACIÓN!$K$8:$K$1082) -> 0 | G302: =SUMIF('INGRESOS A CAJA'!$C$10:$C$954,A302,'INGRESOS A CAJA'!$F$10:$F$954) -> 0 | H302: =SUMIF('EGRESOS DE CAJA'!$C$10:$C$2251,A302,'EGRESOS DE CAJA'!$G$10:$G$2251) -> 0 | I302: =IF((+C302+D302-E302+F302+G302*0+H302)<0,(+C302+D302-E302+F302+G302*0+H302),0) -> 0
A303: 294 | B303: =_xlfn.XLOOKUP(A303,Códigos!$A$11:$A$415,Códigos!$B$11:$B$415,"Verificar",0) -> NOMBRE 296 | D303: =SUMIF('CARTERA años anteriores'!$C$9:$C$234,A303,'CARTERA años anteriores'!$J$9:$J$234) -> 0 | E303: =SUMIF('CARTERA años anteriores'!$C$9:$C$234,A303,'CARTERA años anteriores'!$L$9:$L$234) -> 0 | F303: =SUMIF(FACTURACIÓN!$C$8:$C$1082,A303,FACTURACIÓN!$K$8:$K$1082) -> 0 | G303: =SUMIF('INGRESOS A CAJA'!$C$10:$C$954,A303,'INGRESOS A CAJA'!$F$10:$F$954) -> 0 | H303: =SUMIF('EGRESOS DE CAJA'!$C$10:$C$2251,A303,'EGRESOS DE CAJA'!$G$10:$G$2251) -> 0 | I303: =IF((+C303+D303-E303+F303+G303*0+H303)<0,(+C303+D303-E303+F303+G303*0+H303),0) -> 0
A304: 295 | B304: =_xlfn.XLOOKUP(A304,Códigos!$A$11:$A$415,Códigos!$B$11:$B$415,"Verificar",0) -> NOMBRE 77 | D304: =SUMIF('CARTERA años anteriores'!$C$9:$C$234,A304,'CARTERA años anteriores'!$J$9:$J$234) -> 0 | E304: =SUMIF('CARTERA años anteriores'!$C$9:$C$234,A304,'CARTERA años anteriores'!$L$9:$L$234) -> 0 | F304: =SUMIF(FACTURACIÓN!$C$8:$C$1082,A304,FACTURACIÓN!$K$8:$K$1082) -> 900000 | G304: =SUMIF('INGRESOS A CAJA'!$C$10:$C$954,A304,'INGRESOS A CAJA'!$F$10:$F$954) -> 900000 | H304: =SUMIF('EGRESOS DE CAJA'!$C$10:$C$2251,A304,'EGRESOS DE CAJA'!$G$10:$G$2251) -> 0 | I304: =IF((+C304+D304-E304+F304+G304*0+H304)<0,(+C304+D304-E304+F304+G304*0+H304),0) -> 0
A305: 296 | B305: =_xlfn.XLOOKUP(A305,Códigos!$A$11:$A$415,Códigos!$B$11:$B$415,"Verificar",0) -> NOMBRE 300 | D305: =SUMIF('CARTERA años anteriores'!$C$9:$C$234,A305,'CARTERA años anteriores'!$J$9:$J$234) -> 2701300 | E305: =SUMIF('CARTERA años anteriores'!$C$9:$C$234,A305,'CARTERA años anteriores'!$L$9:$L$234) -> 2165800 | F305: =SUMIF(FACTURACIÓN!$C$8:$C$1082,A305,FACTURACIÓN!$K$8:$K$1082) -> 0 | G305: =SUMIF('INGRESOS A CAJA'!$C$10:$C$954,A305,'INGRESOS A CAJA'!$F$10:$F$954) -> 2165800 | H305: =SUMIF('EGRESOS DE CAJA'!$C$10:$C$2251,A305,'EGRESOS DE CAJA'!$G$10:$G$2251) -> 0 | I305: =IF((+C305+D305-E305+F305+G305*0+H305)<0,(+C305+D305-E305+F305+G305*0+H305),0) -> 0
... A361: 352 | B361: =_xlfn.XLOOKUP(A361,Códigos!$A$11:$A$415,Códigos!$B$11:$B$415,"Verificar",0) -> NOMBRE 227 | D361: =SUMIF('CARTERA años anteriores'!$C$9:$C$234,A361,'CARTERA años anteriores'!$J$9:$J$234) -> 0 | E361: =SUMIF('CARTERA años anteriores'!$C$9:$C$234,A361,'CARTERA años anteriores'!$L$9:$L$234) -> 0 | F361: =SUMIF(FACTURACIÓN!$C$8:$C$1082,A361,FACTURACIÓN!$K$8:$K$1082) -> 0 | G361: =SUMIF('INGRESOS A CAJA'!$C$10:$C$954,A361,'INGRESOS A CAJA'!$F$10:$F$954) -> 0 | H361: =SUMIF('EGRESOS DE CAJA'!$C$10:$C$2251,A361,'EGRESOS DE CAJA'!$G$10:$G$2251) -> 0 | I361: =IF((+C361+D361-E361+F361+G361*0+H361)<0,(+C361+D361-E361+F361+G361*0+H361),0) -> 0
A362: 353 | B362: =_xlfn.XLOOKUP(A362,Códigos!$A$11:$A$415,Códigos!$B$11:$B$415,"Verificar",0) -> NOMBRE 31 | D362: =SUMIF('CARTERA años anteriores'!$C$9:$C$234,A362,'CARTERA años anteriores'!$J$9:$J$234) -> 0 | E362: =SUMIF('CARTERA años anteriores'!$C$9:$C$234,A362,'CARTERA años anteriores'!$L$9:$L$234) -> 0 | H362: =+'EMPLEADO 2'!E106 -> 0 | I362: =IF((+C362+D362-E362+F362+G362*0+H362)<0,(+C362+D362-E362+F362+G362*0+H362),0) -> 0
A363: 354 | B363: =_xlfn.XLOOKUP(A363,Códigos!$A$11:$A$415,Códigos!$B$11:$B$415,"Verificar",0) -> NOMBRE 318 | D363: =SUMIF('CARTERA años anteriores'!$C$9:$C$234,A363,'CARTERA años anteriores'!$J$9:$J$234) -> 0 | E363: =SUMIF('CARTERA años anteriores'!$C$9:$C$234,A363,'CARTERA años anteriores'!$L$9:$L$234) -> 0 | F363: =SUMIF(FACTURACIÓN!$C$8:$C$1082,A363,FACTURACIÓN!$K$8:$K$1082) -> 0 | G363: =SUMIF('INGRESOS A CAJA'!$C$10:$C$954,A363,'INGRESOS A CAJA'!$F$10:$F$954) -> 0 | H363: =SUMIF('EGRESOS DE CAJA'!$C$10:$C$2251,A363,'EGRESOS DE CAJA'!$G$10:$G$2251) -> 0 | I363: =IF((+C363+D363-E363+F363+G363*0+H363)<0,(+C363+D363-E363+F363+G363*0+H363),0) -> 0
A364: 355 | B364: =_xlfn.XLOOKUP(A364,Códigos!$A$11:$A$415,Códigos!$B$11:$B$415,"Verificar",0) -> NOMBRE 96 | D364: =SUMIF('CARTERA años anteriores'!$C$9:$C$234,A364,'CARTERA años anteriores'!$J$9:$J$234) -> 0 | E364: =SUMIF('CARTERA años anteriores'!$C$9:$C$234,A364,'CARTERA años anteriores'!$L$9:$L$234) -> 0 | F364: =SUMIF(FACTURACIÓN!$C$8:$C$1082,A364,FACTURACIÓN!$K$8:$K$1082)*0 -> 0 | G364: =SUMIF('INGRESOS A CAJA'!$C$10:$C$954,A364,'INGRESOS A CAJA'!$F$10:$F$954)*0 -> 0 | H364: =SUMIF('EGRESOS DE CAJA'!$C$10:$C$2251,A364,'EGRESOS DE CAJA'!$G$10:$G$2251)*0 -> 0 | I364: =IF((+C364+D364-E364+F364+G364*0+H364)<0,(+C364+D364-E364+F364+G364*0+H364),0) -> 0 | J364: N/A
A365: 356 | B365: =_xlfn.XLOOKUP(A365,Códigos!$A$11:$A$415,Códigos!$B$11:$B$415,"Verificar",0) -> NOMBRE 108 | D365: =SUMIF('CARTERA años anteriores'!$C$9:$C$234,A365,'CARTERA años anteriores'!$J$9:$J$234) -> 0 | E365: =SUMIF('CARTERA años anteriores'!$C$9:$C$234,A365,'CARTERA años anteriores'!$L$9:$L$234) -> 0 | F365: =SUMIF(FACTURACIÓN!$C$8:$C$1082,A365,FACTURACIÓN!$K$8:$K$1082)*0 -> 0 | G365: =SUMIF('INGRESOS A CAJA'!$C$10:$C$954,A365,'INGRESOS A CAJA'!$F$10:$F$954)*0 -> 0 | H365: =SUMIF('EGRESOS DE CAJA'!$C$10:$C$2251,A365,'EGRESOS DE CAJA'!$G$10:$G$2251)*0 -> 0 | I365: =IF((+C365+D365-E365+F365+G365*0+H365)<0,(+C365+D365-E365+F365+G365*0+H365),0) -> 0 | J365: N/A
A366: 357 | B366: =_xlfn.XLOOKUP(A366,Códigos!$A$11:$A$415,Códigos!$B$11:$B$415,"Verificar",0) -> NOMBRE 107 | D366: =SUMIF('CARTERA años anteriores'!$C$9:$C$234,A366,'CARTERA años anteriores'!$J$9:$J$234) -> 0 | E366: =SUMIF('CARTERA años anteriores'!$C$9:$C$234,A366,'CARTERA años anteriores'!$L$9:$L$234) -> 0 | F366: =SUMIF(FACTURACIÓN!$C$8:$C$1082,A366,FACTURACIÓN!$K$8:$K$1082)*0 -> 0 | G366: =SUMIF('INGRESOS A CAJA'!$C$10:$C$954,A366,'INGRESOS A CAJA'!$F$10:$F$954)*0 -> 0 | H366: =SUMIF('EGRESOS DE CAJA'!$C$10:$C$2251,A366,'EGRESOS DE CAJA'!$G$10:$G$2251)*0 -> 0 | I366: =IF((+C366+D366-E366+F366+G366*0+H366)<0,(+C366+D366-E366+F366+G366*0+H366),0) -> 0 | J366: N/A
A367: 358 | B367: =_xlfn.XLOOKUP(A367,Códigos!$A$11:$A$415,Códigos!$B$11:$B$415,"Verificar",0) -> NOMBRE 338 | D367: =SUMIF('CARTERA años anteriores'!$C$9:$C$234,A367,'CARTERA años anteriores'!$J$9:$J$234) -> 0 | E367: =SUMIF('CARTERA años anteriores'!$C$9:$C$234,A367,'CARTERA años anteriores'!$L$9:$L$234) -> 0 | F367: =SUMIF(FACTURACIÓN!$C$8:$C$1082,A367,FACTURACIÓN!$K$8:$K$1082)*0 -> 0 | G367: =SUMIF('INGRESOS A CAJA'!$C$10:$C$954,A367,'INGRESOS A CAJA'!$F$10:$F$954)*0 -> 0 | H367: =SUMIF('EGRESOS DE CAJA'!$C$10:$C$2251,A367,'EGRESOS DE CAJA'!$G$10:$G$2251)*0 -> 0 | I367: =IF((+C367+D367-E367+F367+G367*0+H367)<0,(+C367+D367-E367+F367+G367*0+H367),0) -> 0 | J367: N/A
A368: 359 | B368: =_xlfn.XLOOKUP(A368,Códigos!$A$11:$A$415,Códigos!$B$11:$B$415,"Verificar",0) -> NOMBRE 232 | D368: =SUMIF('CARTERA años anteriores'!$C$9:$C$234,A368,'CARTERA años anteriores'!$J$9:$J$234) -> 7200 | E368: =SUMIF('CARTERA años anteriores'!$C$9:$C$234,A368,'CARTERA años anteriores'!$L$9:$L$234) -> 0 | F368: =SUMIF(FACTURACIÓN!$C$8:$C$1082,A368,FACTURACIÓN!$K$8:$K$1082)*0 -> 0 | G368: =SUMIF('INGRESOS A CAJA'!$C$10:$C$954,A368,'INGRESOS A CAJA'!$F$10:$F$954)*0 -> 0 | H368: =SUMIF('EGRESOS DE CAJA'!$C$10:$C$2251,A368,'EGRESOS DE CAJA'!$G$10:$G$2251)*0 -> 0 | I368: =IF((+C368+D368-E368+F368+G368*0+H368)<0,(+C368+D368-E368+F368+G368*0+H368),0) -> 0 | J368: N/A
A369: 360 | B369: =_xlfn.XLOOKUP(A369,Códigos!$A$11:$A$415,Códigos!$B$11:$B$415,"Verificar",0) -> NOMBRE 94 | D369: =SUMIF('CARTERA años anteriores'!$C$9:$C$234,A369,'CARTERA años anteriores'!$J$9:$J$234) -> 0 | E369: =SUMIF('CARTERA años anteriores'!$C$9:$C$234,A369,'CARTERA años anteriores'!$L$9:$L$234) -> 0 | F369: =SUMIF(FACTURACIÓN!$C$8:$C$1082,A369,FACTURACIÓN!$K$8:$K$1082)*0 -> 0 | G369: =SUMIF('INGRESOS A CAJA'!$C$10:$C$954,A369,'INGRESOS A CAJA'!$F$10:$F$954)*0 -> 0 | H369: =SUMIF('EGRESOS DE CAJA'!$C$10:$C$2251,A369,'EGRESOS DE CAJA'!$G$10:$G$2251)*0 -> 0 | I369: =IF((+C369+D369-E369+F369+G369*0+H369)<0,(+C369+D369-E369+F369+G369*0+H369),0) -> 0 | J369: N/A
A370: 361 | B370: =_xlfn.XLOOKUP(A370,Códigos!$A$11:$A$415,Códigos!$B$11:$B$415,"Verificar",0) -> NOMBRE 49 | D370: =SUMIF('CARTERA años anteriores'!$C$9:$C$234,A370,'CARTERA años anteriores'!$J$9:$J$234) -> 0 | E370: =SUMIF('CARTERA años anteriores'!$C$9:$C$234,A370,'CARTERA años anteriores'!$L$9:$L$234) -> 0 | F370: =SUMIF(FACTURACIÓN!$C$8:$C$1082,A370,FACTURACIÓN!$K$8:$K$1082)*0 -> 0 | G370: =SUMIF('INGRESOS A CAJA'!$C$10:$C$954,A370,'INGRESOS A CAJA'!$F$10:$F$954)*0 -> 0 | H370: =SUMIF('EGRESOS DE CAJA'!$C$10:$C$2251,A370,'EGRESOS DE CAJA'!$G$10:$G$2251)*0 -> 0 | I370: =IF((+C370+D370-E370+F370+G370*0+H370)<0,(+C370+D370-E370+F370+G370*0+H370),0) -> 0 | J370: N/A
A371: 362 | B371: =_xlfn.XLOOKUP(A371,Códigos!$A$11:$A$415,Códigos!$B$11:$B$415,"Verificar",0) -> NOMBRE 97 | C371: -27443000 | D371: =SUMIF('CARTERA años anteriores'!$C$9:$C$234,A371,'CARTERA años anteriores'!$J$9:$J$234) -> 0 | E371: =SUMIF('CARTERA años anteriores'!$C$9:$C$234,A371,'CARTERA años anteriores'!$L$9:$L$234) -> 0 | F371: =SUMIF(FACTURACIÓN!$C$8:$C$1082,A371,FACTURACIÓN!$K$8:$K$1082) -> 0 | G371: =SUMIF('INGRESOS A CAJA'!$C$10:$C$954,A371,'INGRESOS A CAJA'!$F$10:$F$954) -> 0 | H371: =SUMIF('EGRESOS DE CAJA'!$C$10:$C$2251,A371,'EGRESOS DE CAJA'!$G$10:$G$2251) -> 6000000 | I371: =IF((+C371+D371-E371+F371+G371*0+H371)<0,(+C371+D371-E371+F371+G371*0+H371),0) -> -21443000
A372: 363 | B372: =_xlfn.XLOOKUP(A372,Códigos!$A$11:$A$415,Códigos!$B$11:$B$415,"Verificar",0) -> NOMBRE 358 | D372: =SUMIF('CARTERA años anteriores'!$C$9:$C$234,A372,'CARTERA años anteriores'!$J$9:$J$234) -> 0 | E372: =SUMIF('CARTERA años anteriores'!$C$9:$C$234,A372,'CARTERA años anteriores'!$L$9:$L$234) -> 0 | F372: =SUMIF(FACTURACIÓN!$C$8:$C$1082,A372,FACTURACIÓN!$K$8:$K$1082) -> 260000 | G372: =SUMIF('INGRESOS A CAJA'!$C$10:$C$954,A372,'INGRESOS A CAJA'!$F$10:$F$954) -> 0 | H372: =SUMIF('EGRESOS DE CAJA'!$C$10:$C$2251,A372,'EGRESOS DE CAJA'!$G$10:$G$2251) -> 0 | I372: =IF((+C372+D372-E372+F372+G372*0+H372)<0,(+C372+D372-E372+F372+G372*0+H372),0) -> 0
A373: 364 | B373: =_xlfn.XLOOKUP(A373,Códigos!$A$11:$A$415,Códigos!$B$11:$B$415,"Verificar",0) -> NOMBRE 365 | D373: =SUMIF('CARTERA años anteriores'!$C$9:$C$234,A373,'CARTERA años anteriores'!$J$9:$J$234) -> 0 | E373: =SUMIF('CARTERA años anteriores'!$C$9:$C$234,A373,'CARTERA años anteriores'!$L$9:$L$234) -> 0 | F373: =SUMIF(FACTURACIÓN!$C$8:$C$1082,A373,FACTURACIÓN!$K$8:$K$1082) -> 150000 | G373: =SUMIF('INGRESOS A CAJA'!$C$10:$C$954,A373,'INGRESOS A CAJA'!$F$10:$F$954) -> 0 | H373: =SUMIF('EGRESOS DE CAJA'!$C$10:$C$2251,A373,'EGRESOS DE CAJA'!$G$10:$G$2251) -> 0 | I373: =IF((+C373+D373-E373+F373+G373*0+H373)<0,(+C373+D373-E373+F373+G373*0+H373),0) -> 0
A374: 365 | B374: =_xlfn.XLOOKUP(A374,Códigos!$A$11:$A$415,Códigos!$B$11:$B$415,"Verificar",0) -> NOMBRE 366 | D374: =SUMIF('CARTERA años anteriores'!$C$9:$C$234,A374,'CARTERA años anteriores'!$J$9:$J$234) -> 0 | E374: =SUMIF('CARTERA años anteriores'!$C$9:$C$234,A374,'CARTERA años anteriores'!$L$9:$L$234) -> 0 | F374: =SUMIF(FACTURACIÓN!$C$8:$C$1082,A374,FACTURACIÓN!$K$8:$K$1082) -> 0 | G374: =SUMIF('INGRESOS A CAJA'!$C$10:$C$954,A374,'INGRESOS A CAJA'!$F$10:$F$954) -> 0 | H374: =SUMIF('EGRESOS DE CAJA'!$C$10:$C$2251,A374,'EGRESOS DE CAJA'!$G$10:$G$2251) -> 0 | I374: =IF((+C374+D374-E374+F374+G374*0+H374)<0,(+C374+D374-E374+F374+G374*0+H374),0) -> 0
A375: 366 | B375: =_xlfn.XLOOKUP(A375,Códigos!$A$11:$A$415,Códigos!$B$11:$B$415,"Verificar",0) -> NOMBRE 367 | D375: =SUMIF('CARTERA años anteriores'!$C$9:$C$234,A375,'CARTERA años anteriores'!$J$9:$J$234) -> 0 | E375: =SUMIF('CARTERA años anteriores'!$C$9:$C$234,A375,'CARTERA años anteriores'!$L$9:$L$234) -> 0 | F375: =SUMIF(FACTURACIÓN!$C$8:$C$1082,A375,FACTURACIÓN!$K$8:$K$1082) -> 7200000 | G375: =SUMIF('INGRESOS A CAJA'!$C$10:$C$954,A375,'INGRESOS A CAJA'!$F$10:$F$954) -> 7000000 | H375: =SUMIF('EGRESOS DE CAJA'!$C$10:$C$2251,A375,'EGRESOS DE CAJA'!$G$10:$G$2251) -> 0 | I375: =IF((+C375+D375-E375+F375+G375*0+H375)<0,(+C375+D375-E375+F375+G375*0+H375),0) -> 0
A376: 367 | B376: =_xlfn.XLOOKUP(A376,Códigos!$A$11:$A$415,Códigos!$B$11:$B$415,"Verificar",0) -> NOMBRE 368 | D376: =SUMIF('CARTERA años anteriores'!$C$9:$C$234,A376,'CARTERA años anteriores'!$J$9:$J$234) -> 0 | E376: =SUMIF('CARTERA años anteriores'!$C$9:$C$234,A376,'CARTERA años anteriores'!$L$9:$L$234) -> 0 | F376: =SUMIF(FACTURACIÓN!$C$8:$C$1082,A376,FACTURACIÓN!$K$8:$K$1082) -> 100000 | G376: =SUMIF('INGRESOS A CAJA'!$C$10:$C$954,A376,'INGRESOS A CAJA'!$F$10:$F$954) -> 100000 | H376: =SUMIF('EGRESOS DE CAJA'!$C$10:$C$2251,A376,'EGRESOS DE CAJA'!$G$10:$G$2251) -> 0 | I376: =IF((+C376+D376-E376+F376+G376*0+H376)<0,(+C376+D376-E376+F376+G376*0+H376),0) -> 0
A377: 368 | B377: =_xlfn.XLOOKUP(A377,Códigos!$A$11:$A$415,Códigos!$B$11:$B$415,"Verificar",0) -> NOMBRE 369 | D377: =SUMIF('CARTERA años anteriores'!$C$9:$C$234,A377,'CARTERA años anteriores'!$J$9:$J$234) -> 0 | E377: =SUMIF('CARTERA años anteriores'!$C$9:$C$234,A377,'CARTERA años anteriores'!$L$9:$L$234) -> 0 | F377: =SUMIF(FACTURACIÓN!$C$8:$C$1082,A377,FACTURACIÓN!$K$8:$K$1082) -> 0 | G377: =SUMIF('INGRESOS A CAJA'!$C$10:$C$954,A377,'INGRESOS A CAJA'!$F$10:$F$954) -> 0 | H377: =SUMIF('EGRESOS DE CAJA'!$C$10:$C$2251,A377,'EGRESOS DE CAJA'!$G$10:$G$2251) -> 0 | I377: =IF((+C377+D377-E377+F377+G377*0+H377)<0,(+C377+D377-E377+F377+G377*0+H377),0) -> 0
A378: 369 | B378: =_xlfn.XLOOKUP(A378,Códigos!$A$11:$A$415,Códigos!$B$11:$B$415,"Verificar",0) -> 0 | D378: =SUMIF('CARTERA años anteriores'!$C$9:$C$133,A378,'CARTERA años anteriores'!$J$9:$J$133) -> 0 | E378: =SUMIF('CARTERA años anteriores'!$C$9:$C$234,A378,'CARTERA años anteriores'!$L$9:$L$234) -> 0 | F378: =SUMIF(FACTURACIÓN!$C$8:$C$1082,A378,FACTURACIÓN!$K$8:$K$1082) -> 0 | G378: =SUMIF('INGRESOS A CAJA'!$C$10:$C$954,A378,'INGRESOS A CAJA'!$F$10:$F$954) -> 0 | H378: =SUMIF('EGRESOS DE CAJA'!$C$10:$C$2251,A378,'EGRESOS DE CAJA'!$G$10:$G$2251) -> 0 | I378: =IF((+C378+D378-E378+F378+G378*0+H378)<0,(+C378+D378-E378+F378+G378*0+H378),0) -> 0
A379: 370 | B379: =_xlfn.XLOOKUP(A379,Códigos!$A$11:$A$415,Códigos!$B$11:$B$415,"Verificar",0) -> 0 | D379: =SUMIF('CARTERA años anteriores'!$C$9:$C$133,A379,'CARTERA años anteriores'!$J$9:$J$133) -> 0 | E379: =SUMIF('CARTERA años anteriores'!$C$9:$C$234,A379,'CARTERA años anteriores'!$L$9:$L$234) -> 0 | F379: =SUMIF(FACTURACIÓN!$C$8:$C$1082,A379,FACTURACIÓN!$K$8:$K$1082) -> 0 | G379: =SUMIF('INGRESOS A CAJA'!$C$10:$C$954,A379,'INGRESOS A CAJA'!$F$10:$F$954) -> 0 | H379: =SUMIF('EGRESOS DE CAJA'!$C$10:$C$2251,A379,'EGRESOS DE CAJA'!$G$10:$G$2251) -> 0 | I379: =IF((+C379+D379-E379+F379+G379*0+H379)<0,(+C379+D379-E379+F379+G379*0+H379),0) -> 0
A380: 371 | B380: =_xlfn.XLOOKUP(A380,Códigos!$A$11:$A$415,Códigos!$B$11:$B$415,"Verificar",0) -> 0 | D380: =SUMIF('CARTERA años anteriores'!$C$9:$C$133,A380,'CARTERA años anteriores'!$J$9:$J$133) -> 0 | E380: =SUMIF('CARTERA años anteriores'!$C$9:$C$234,A380,'CARTERA años anteriores'!$L$9:$L$234) -> 0 | F380: =SUMIF(FACTURACIÓN!$C$8:$C$1082,A380,FACTURACIÓN!$K$8:$K$1082) -> 0 | G380: =SUMIF('INGRESOS A CAJA'!$C$10:$C$954,A380,'INGRESOS A CAJA'!$F$10:$F$954) -> 0 | H380: =SUMIF('EGRESOS DE CAJA'!$C$10:$C$2251,A380,'EGRESOS DE CAJA'!$G$10:$G$2251) -> 0 | I380: =IF((+C380+D380-E380+F380+G380*0+H380)<0,(+C380+D380-E380+F380+G380*0+H380),0) -> 0
A381: 372 | B381: =_xlfn.XLOOKUP(A381,Códigos!$A$11:$A$415,Códigos!$B$11:$B$415,"Verificar",0) -> 0 | D381: =SUMIF('CARTERA años anteriores'!$C$9:$C$133,A381,'CARTERA años anteriores'!$J$9:$J$133) -> 0 | E381: =SUMIF('CARTERA años anteriores'!$C$9:$C$234,A381,'CARTERA años anteriores'!$L$9:$L$234) -> 0 | F381: =SUMIF(FACTURACIÓN!$C$8:$C$1082,A381,FACTURACIÓN!$K$8:$K$1082) -> 0 | G381: =SUMIF('INGRESOS A CAJA'!$C$10:$C$954,A381,'INGRESOS A CAJA'!$F$10:$F$954) -> 0 | H381: =SUMIF('EGRESOS DE CAJA'!$C$10:$C$2251,A381,'EGRESOS DE CAJA'!$G$10:$G$2251) -> 0 | I381: =IF((+C381+D381-E381+F381+G381*0+H381)<0,(+C381+D381-E381+F381+G381*0+H381),0) -> 0
A382: 373 | B382: =_xlfn.XLOOKUP(A382,Códigos!$A$11:$A$415,Códigos!$B$11:$B$415,"Verificar",0) -> 0 | D382: =SUMIF('CARTERA años anteriores'!$C$9:$C$133,A382,'CARTERA años anteriores'!$J$9:$J$133) -> 0 | E382: =SUMIF('CARTERA años anteriores'!$C$9:$C$234,A382,'CARTERA años anteriores'!$L$9:$L$234) -> 0 | F382: =SUMIF(FACTURACIÓN!$C$8:$C$1082,A382,FACTURACIÓN!$K$8:$K$1082) -> 0 | G382: =SUMIF('INGRESOS A CAJA'!$C$10:$C$954,A382,'INGRESOS A CAJA'!$F$10:$F$954) -> 0 | H382: =SUMIF('EGRESOS DE CAJA'!$C$10:$C$2251,A382,'EGRESOS DE CAJA'!$G$10:$G$2251) -> 0 | I382: =IF((+C382+D382-E382+F382+G382*0+H382)<0,(+C382+D382-E382+F382+G382*0+H382),0) -> 0
A383: 374 | B383: =_xlfn.XLOOKUP(A383,Códigos!$A$11:$A$415,Códigos!$B$11:$B$415,"Verificar",0) -> 0 | D383: =SUMIF('CARTERA años anteriores'!$C$9:$C$133,A383,'CARTERA años anteriores'!$J$9:$J$133) -> 0 | E383: =SUMIF('CARTERA años anteriores'!$C$9:$C$234,A383,'CARTERA años anteriores'!$L$9:$L$234) -> 0 | F383: =SUMIF(FACTURACIÓN!$C$8:$C$1082,A383,FACTURACIÓN!$K$8:$K$1082) -> 0 | G383: =SUMIF('INGRESOS A CAJA'!$C$10:$C$954,A383,'INGRESOS A CAJA'!$F$10:$F$954) -> 0 | H383: =SUMIF('EGRESOS DE CAJA'!$C$10:$C$2251,A383,'EGRESOS DE CAJA'!$G$10:$G$2251) -> 0 | I383: =IF((+C383+D383-E383+F383+G383*0+H383)<0,(+C383+D383-E383+F383+G383*0+H383),0) -> 0
A384: 375 | B384: =_xlfn.XLOOKUP(A384,Códigos!$A$11:$A$415,Códigos!$B$11:$B$415,"Verificar",0) -> 0 | D384: =SUMIF('CARTERA años anteriores'!$C$9:$C$133,A384,'CARTERA años anteriores'!$J$9:$J$133) -> 0 | E384: =SUMIF('CARTERA años anteriores'!$C$9:$C$234,A384,'CARTERA años anteriores'!$L$9:$L$234) -> 0 | F384: =SUMIF(FACTURACIÓN!$C$8:$C$1082,A384,FACTURACIÓN!$K$8:$K$1082) -> 0 | G384: =SUMIF('INGRESOS A CAJA'!$C$10:$C$954,A384,'INGRESOS A CAJA'!$F$10:$F$954) -> 0 | H384: =SUMIF('EGRESOS DE CAJA'!$C$10:$C$2251,A384,'EGRESOS DE CAJA'!$G$10:$G$2251) -> 0 | I384: =IF((+C384+D384-E384+F384+G384*0+H384)<0,(+C384+D384-E384+F384+G384*0+H384),0) -> 0
A385: 376 | B385: =_xlfn.XLOOKUP(A385,Códigos!$A$11:$A$415,Códigos!$B$11:$B$415,"Verificar",0) -> 0 | D385: =SUMIF('CARTERA años anteriores'!$C$9:$C$133,A385,'CARTERA años anteriores'!$J$9:$J$133) -> 0 | E385: =SUMIF('CARTERA años anteriores'!$C$9:$C$234,A385,'CARTERA años anteriores'!$L$9:$L$234) -> 0 | F385: =SUMIF(FACTURACIÓN!$C$8:$C$1082,A385,FACTURACIÓN!$K$8:$K$1082) -> 0 | G385: =SUMIF('INGRESOS A CAJA'!$C$10:$C$954,A385,'INGRESOS A CAJA'!$F$10:$F$954) -> 0 | H385: =SUMIF('EGRESOS DE CAJA'!$C$10:$C$2251,A385,'EGRESOS DE CAJA'!$G$10:$G$2251) -> 0 | I385: =IF((+C385+D385-E385+F385+G385*0+H385)<0,(+C385+D385-E385+F385+G385*0+H385),0) -> 0
