Workbook
Name _Toc464338185: 'TABLA RetFte'!$A$16

Sheet Grupos Familiares
A2: GRUPOS FAMILIARES | L2: RETENCIÓN EN LA FUENTE
A3: PRESUPUESTO DE COBROS
A4: AÑO GRAVABLE 2024 | O4: RETENCIÓN FUENTE -Honorarios- | P4: UVT 2025
B5: =+A583 -> GRAN TOTAL | C5: =+C583 -> 0 | D5: =+D583 -> 0 | E5: =+E583 -> 0 | F5: =+F583 -> 0 | G5: =+G583 -> 0 | H5: =+H583 -> 0 | I5: =+I583 -> 0 | O5: 0.11 | P5: 49799
A6: No. | B6: APELLIDOS Y NOMBRES o RAZÓN SOCIAL | C6: VALOR FACTURA | D6: I V A | E6: RETENCIÓN EN LA FUENTE | F6: VALOR FACTURA antes de RTE FTE | G6: VALOR TOTAL NETO DE LA FACTURA | H6: VALOR CUENTA DE COBRO | I6: VALOR NETO TOTAL FRAS + C DE C | J6: OBSERVACIONES | L6: SEGURIDAD SOCIAL | M6: Ingreso Base RetFte | N6: AGENTE RETENEDOR | O6: RETENCIÓN EN LA FUENTE | P6: Vr Ingreso Base RetFte EN UVT
L7: =12.5%+16% -> 0.285
A8: FAMILIA RESTREPO POSADA
A11: 1
A12: SUB TOTAL | L12: =+C12*$L$7 -> 0 | M12: =+C12-L12*0 -> 0 | N12: N | O12: =IF(N12="S",M12*$O$5,"NO RETENCIÓN") -> NO RETENCIÓN | P12: =+M12/$P$5 -> 0
A15: 1
A16: =A15+1 -> 2
A17: SUB TOTAL | L17: =+C17*$L$7 -> 0 | M17: =+C17-L17*0 -> 0 | N17: S | O17: =IF(N17="S",M17*$O$5,"NO RETENCIÓN") -> 0 | P17: =+M17/$P$5 -> 0
A21: 1
A22: SUB TOTAL | L22: =+C22*$L$7 -> 0 | M22: =+C22-L22*0 -> 0 | N22: N | O22: =IF(N22="S",M22*$O$5,"NO RETENCIÓN") -> NO RETENCIÓN | P22: =+M22/$P$5 -> 0
A25: =A21+1 -> 2
A26: SUB TOTAL | L26: =+C26*$L$7 -> 0 | M26: =+C26-L26*0 -> 0 | N26: N | O26: =IF(N26="S",M26*$O$5,"NO RETENCIÓN") -> NO RETENCIÓN | P26: =+M26/$P$5 -> 0
A29: =A25+1 -> 3
A30: =A29+1 -> 4
A31: SUB TOTAL | L31: =+C31*$L$7 -> 0 | M31: =+C31-L31*0 -> 0 | N31: S | O31: =IF(N31="S",M31*$O$5,"NO RETENCIÓN") -> 0 | P31: =+M31/$P$5 -> 0
A33: TOTAL DOÑA SILVIA ELENA
A37: 1
A38: =A37+1 -> 2
A39: SUB TOTAL | L39: =+C39*$L$7 -> 0 | M39: =+C39-L39*0 -> 0 | N39: S | O39: =IF(N39="S",M39*$O$5,"NO RETENCIÓN") -> 0 | P39: =+M39/$P$5 -> 0
A42: 1
A43: =A42+1 -> 2
A44: =+A43+1 -> 3
A45: SUB TOTAL | L45: =+C45*$L$7 -> 0 | M45: =+C45-L45*0 -> 0 | N45: N | O45: =IF(N45="S",M45*$O$5,"NO RETENCIÓN") -> NO RETENCIÓN | P45: =+M45/$P$5 -> 0
A48: =+A44+1 -> 4
A49: SUB TOTAL | L49: =+C49*$L$7 -> 0 | M49: =+C49-L49*0 -> 0 | N49: N | O49: =IF(N49="S",M49*$O$5,"NO RETENCIÓN") -> NO RETENCIÓN | P49: =+M49/$P$5 -> 0
A53: 1
A54: =+A53+1 -> 2
A55: =A54+1 -> 3
A56: =+A55+1 -> 4
A57: SUB TOTAL | L57: =+C57*$L$7 -> 0 | M57: =+C57-L57*0 -> 0 | N57: S | O57: =IF(N57="S",M57*$O$5,"NO RETENCIÓN") -> 0 | P57: =+M57/$P$5 -> 0
A60: =A58+1 -> 1
A61: =+A60+1 -> 2
A62: =+A61+1 -> 3
A63: =A62+1 -> 4
A64: =A63+1 -> 5
A65: SUB TOTAL | L65: =+C65*$L$7 -> 0 | M65: =+C65-L65*0 -> 0 | N65: S | O65: =IF(N65="S",M65*$O$5,"NO RETENCIÓN") -> 0 | P65: =+M65/$P$5 -> 0
A69: =+A64+1 -> 6
A70: SUB TOTAL | L70: =+C70*$L$7 -> 0 | M70: =+C70-L70*0 -> 0 | N70: S | O70: =IF(N70="S",M70*$O$5,"NO RETENCIÓN") -> 0 | P70: =+M70/$P$5 -> 0
A73: =+A69+1 -> 7
A74: SUB TOTAL | L74: =+C74*$L$7 -> 0 | M74: =+C74-L74*0 -> 0 | N74: S | O74: =IF(N74="S",M74*$O$5,"NO RETENCIÓN") -> 0 | P74: =+M74/$P$5 -> 0
A77: 1 | L77: =+C77*$L$7 -> 0 | M77: =+C77-L77*0 -> 0 | N77: S | O77: =IF(N77="S",M77*$O$5,"NO RETENCIÓN") -> 0 | P77: =+M77/$P$5 -> 0
A78: =A77+1 -> 2 | L78: =+C78*$L$7 -> 0 | M78: =+C78-L78*0 -> 0 | N78: S | O78: =IF(N78="S",M78*$O$5,"NO RETENCIÓN") -> 0 | P78: =+M78/$P$5 -> 0
A79: =A78+1 -> 3
A80: =A79+1 -> 4 | L80: =+C80*$L$7 -> 0 | M80: =+C80-L80*0 -> 0 | N80: S | O80: =IF(N80="S",M80*$O$5,"NO RETENCIÓN") -> 0 | P80: =+M80/$P$5 -> 0
A81: =A80+1 -> 5 | L81: =+C81*$L$7 -> 0 | M81: =+C81-L81*0 -> 0 | N81: S | O81: =IF(N81="S",M81*$O$5,"NO RETENCIÓN") -> 0 | P81: =+M81/$P$5 -> 0
A82: =A81+1 -> 6 | L82: =+C82*$L$7 -> 0 | M82: =+C82-L82*0 -> 0 | N82: S | O82: =IF(N82="S",M82*$O$5,"NO RETENCIÓN") -> 0 | P82: =+M82/$P$5 -> 0
A83: SUB TOTAL PERSONAS JURÍDICAS | L83: =+C83*$L$7 -> 0 | M83: =+C83-L83*0 -> 0 | O83: =SUM(O77:O82) -> 0
A86: LINABI SAS
A87: 1
A88: SUB TOTAL | L88: =+C88*$L$7 -> 0 | M88: =+C88-L88*0 -> 0 | N88: S | O88: =IF(N88="S",M88*$O$5,"NO RETENCIÓN") -> 0 | P88: =+M88/$P$5 -> 0
A91: TOTAL ACUMULADO FAMILIA RESTREPO POSADA | L91: =+L12+L17+L39+L45+L49+L57+L33+L65+L70+L74+L83+L88 -> 0 | M91: =+M12+M17+M39+M45+M49+M57+M33+M65+M70+M74+M83+M88 -> 0
A95: DR. ESTEBAN ECHAVARRÍA
A96: 1
A97: SUB TOTAL
A99: FAMILIA ECHAVARRÍA
A100: 1 | L100: =+C100*$L$7 -> 0 | M100: =+C100-L100*0 -> 0 | N100: S | O100: =IF(N100="S",M100*$O$5,"NO RETENCIÓN") -> 0 | P100: =+M100/$P$5 -> 0
A101: =A100+1 -> 2 | L101: =+C101*$L$7 -> 0 | M101: =+C101-L101*0 -> 0 | N101: S | O101: =IF(N101="S",M101*$O$5,"NO RETENCIÓN") -> 0 | P101: =+M101/$P$5 -> 0
A102: =A101+1 -> 3 | L102: =+C102*$L$7 -> 0 | M102: =+C102-L102*0 -> 0 | N102: S | O102: =IF(N102="S",M102*$O$5,"NO RETENCIÓN") -> 0 | P102: =+M102/$P$5 -> 0
A103: SUB TOTAL | Q103: =SUM(O100:O102) -> 0
Q104: =+E105+Q103 -> 0
A105: TOTAL ACUMULADO DR ESTEBAN
A109: JAVIER RÍOS
A110: 1
A111: =A110+1 -> 2
A112: =A111+1 -> 3
A113: SUB TOTAL | L113: =+C113*$L$7 -> 0 | M113: =+C113-L113*0 -> 0 | N113: S | O113: =IF(N113="S",M113*$O$5,"NO RETENCIÓN") -> 0 | P113: =+M113/$P$5 -> 0
A117: =A112+1 -> 4
A118: SUB TOTAL
A120: TOTAL ACUMULADO FAMILIA RÍOS CORREA
A124: CARLI FLURY
A125: 1
A126: =A125+1 -> 2
A127: =A126+1 -> 3
A128: =A127+1 -> 4
A129: =A128+1 -> 5
A130: =A129+1 -> 6
A131: SUB TOTAL
A133: =+A130+1 -> 7
A134: SUB TOTAL
A136: TOTAL ACUMULADO FAMILIA FLURY VALENCIA
A140: LUÍS H. VILLEGAS LONDOÑO
A141: 1
A142: =A141+1 -> 2
A143: =A142+1 -> 3
A144: =A143+1 -> 4
A145: TOTAL | L145: =+C145*$L$7 -> 0 | M145: =+C145-L145*0 -> 0 | N145: S | O145: =IF(N145="S",M145*$O$5,"NO RETENCIÓN") -> 0 | P145: =+M145/$P$5 -> 0
A149: SERGIO CÁRDENAS GUTIÉRREZ
A150: 1
A151: =+A150+1 -> 2
A152: =A151+1 -> 3
A153: SUB TOTAL
A155: =A154+1 -> 1
A156: =A152+1 -> 4
A157: =A156+1 -> 5
A158: SUB TOTAL
A160: TOTAL ACUMULADO FAMILIA SERGIO CÁRDENAS GUTIÉRREZ
...

Sheet Facturas
A2: =+'Grupos Familiares'!$A$3 -> PRESUPUESTO DE COBROS | Q2: Mínima Mvto | S2: Mínima 1° Vez | U2: PARA CALCULAR EL VALOR A COBRAR POR EL PRESENTE AÑO | AO2: IPC 2024 | AP2: Mínima Mvto -año anterior- | AQ2: Mínima 1° Vez -Año anterior-
A3: FACTURACIÓN ELECTRÓNICA | Q3: =ROUND(AP3*(100%+$AO$3),-4) -> 230000 | S3: =ROUND(AQ3*(100%+$AO$3),-4) -> 370000 | AO3: 0.052 | AP3: 220000 | AQ3: 350000
A4: =+'Grupos Familiares'!$A$4 -> AÑO GRAVABLE 2024 | F4: VALORES A FACTURAR -PRESENTE AÑO- | U4: PRESUPUESTOS DE COBRO: | Y4: =+$A$3 -> FACTURACIÓN ELECTRÓNICA | AO4: Vr Incrementado | AP4: =(AP3*(100%+$AO$3)) -> 231440 | AQ4: =(AQ3*(100%+$AO$3)) -> 368200
A5: PERSONAS NATURALES Y PERSONAS JURÍDICAS | G5: 0.19 | I5: 0.11 | U5: IPC | V5: =+AO3 -> 0.052 | X5: 0.5 | Z5: =75%+80%*0 -> 0.75 | AB5: 0.15 | AD5: 0.2 | AF5: 0.1 | AH5: 0.2 | AJ5: 0.3
A6: No. | B6: APELLIDOS Y NOMBRES o RAZÓN SOCIAL | C6: CÓDIGO | D6: NIT No. | E6: D. V. | F6: VALOR BRUTO A ELABORAR LA FACTURA | G6: I V A | H6: AGENTE RETENEDOR | I6: RETENCIÓN EN LA FUENTE | J6: VALOR FACTURA antes de RTE FTE | K6: VALOR A PAGAR NETO DE LA FACTURA | L6: VoBo ELABORAR Fra. | M6: FACTURA No. | N6: MEDIO | O6: FECHA | P6: ESTADO | Q6: VALOR CUENTA DE COBRO -POR PRÉSTAMOS- | R6: CUENTA DE COBRO No. | S6: OBSERVACIONES | U6: SI o NO | V6: VALOR DECLARACIÓN RENTA | W6: SI o NO | X6: VALOR DECLARACIÓN I AL P 2023 | Y6: SI o NO | Z6: VALOR MEDIOS MAGNÉTICOS | AA6: SI o NO | AB6: EXÓGENA MPIO MEDELLÍN | AC6: SI o NO | AD6: REG ÚNICO de BENEFICIARIOS | AE6: SI o NO | AF6: VALOR FORMATO 2516 CONSERVAR | AG6: SI o NO | AH6: VALOR FORMATO 2516 TRANSMITIR | AI6: SI o NO | AJ6: VALOR DECLARACIÓN ACTIVOS EN EL EXTERIOR | AK6: VALOR OTRAS ASESORÍAS | AL6: PRÉSTAMOS | AM6: TOTAL PRESUPUESTADO | AO6: FACTURAS y C de C
A8: PERSONAS NATURALES
A9: 1 | B9: NOMBRE 1 | C9: =_xlfn.XLOOKUP(B9,Códigos!$B$8:$B$406,Códigos!$A$8:$A$406,"Verificar",0) -> 41 | D9: =_xlfn.XLOOKUP(B9,'Consolidado Cobros'!$B$10:$B$268,'Consolidado Cobros'!$C$10:$C$268,"Verificar",0) -> 22126399 | E9: =IF((MOD((VALUE(MID(TEXT(D9,"000000000000000"),15,1))*3+VALUE(MID(TEXT(D9,"000000000000000"),14,1))*7+VALUE(MID(TEXT(D9,"000000000000000"),13,1))*13+VALUE(MID(TEXT(D9,"000000000000000"),12,1))*17+VALUE(MID(TEXT(D9,"000000000000000"),11,1))*19+VALUE(MID(TEXT(D9,"000000000000000"),10,1))*23+VALUE(MID(TEXT(D9,"000000000000000"),9,1))*29+VALUE(MID(TEXT(D9,"000000000000000"),8,1))*37+VALUE(MID(TEXT(D9,"000000000000000"),7,1))*41+VALUE(MID(TEXT(D9,"000000000000000"),6,1))*43+VALUE(MID(TEXT(D9,"000000000000000"),5,1))*47+VALUE(MID(TEXT(D9,"000000000000000"),4,1))*53+VALUE(MID(TEXT(D9,"000000000000000"),3,1))*59+VALUE(MID(TEXT(D9,"000000000000000"),2,1))*67+VALUE(MID(TEXT(D9,"000000000000000"),1,1))*71),11))=0,0,IF((MOD((VALUE(MID(TEXT(D9,"000000000000000"),15,1))*3+VALUE(MID(TEXT(D9,"000000000000000"),14,1))*7+VALUE(MID(TEXT(D9,"000000000000000"),13,1))*13+VALUE(MID(TEXT(D9,"000000000000000"),12,1))*17+VALUE(MID(TEXT(D9,"000000000000000"),11,1))*19+VALUE(MID(TEXT(D9,"000000000000000"),10,1))*23+VALUE(MID(TEXT(D9,"000000000000000"),9,1))*29+VALUE(MID(TEXT(D9,"000000000000000"),8,1))*37+VALUE(MID(TEXT(D9,"000000000000000"),7,1))*41+VALUE(MID(TEXT(D9,"000000000000000"),6,1))*43+VALUE(MID(TEXT(D9,"000000000000000"),5,1))*47+VALUE(MID(TEXT(D9,"000000000000000"),4,1))*53+VALUE(MID(TEXT(D9,"000000000000000"),3,1))*59+VALUE(MID(TEXT(D9,"000000000000000"),2,1))*67+VALUE(MID(TEXT(D9,"000000000000000"),1,1))*71),11))=1,1,11-(MOD((VALUE(MID(TEXT(D9,"000000000000000"),15,1))*3+VALUE(MID(TEXT(D9,"000000000000000"),14,1))*7+VALUE(MID(TEXT(D9,"000000000000000"),13,1))*13+VALUE(MID(TEXT(D9,"000000000000000"),12,1))*17+VALUE(MID(TEXT(D9,"000000000000000"),11,1))*19+VALUE(MID(TEXT(D9,"000000000000000"),10,1))*23+VALUE(MID(TEXT(D9,"000000000000000"),9,1))*29+VALUE(MID(TEXT(D9,"000000000000000"),8,1))*37+VALUE(MID(TEXT(D9,"000000000000000"),7,1))*41+VALUE(MID(TEXT(D9,"000000000000000"),6,1))*43+VALUE(MID(TEXT(D9,"000000000000000"),5,1))*47+VALUE(MID(TEXT(D9,"000000000000000"),4,1))*53+VALUE(MID(TEXT(D9,"000000000000000"),3,1))*59+VALUE(MID(TEXT(D9,"000000000000000"),2,1))*67+VALUE(MID(TEXT(D9,"000000000000000"),1,1))*71),11)))) -> 5 | F9: =+AM9 -> 870000 | G9: =+F9*$G$5 -> 165300 | H9: S | I9: =IF(H9="S",-F9*$I$5,"NO RETENCIÓN") -> -95700 | J9: =+F9+G9 -> 1035300 | K9: =SUM(F9:I9) -> 939600 | Q9: =+AL9 -> 0 | U9: SI | V9: =ROUND(IF(U9="SI",SUMIF('Facturas año anterior'!$B$8:$B$81,B9,'Facturas año anterior'!$V$8:$V$81)*(100%+$V$5),0),-3)+ROUND(IF(U9="SI",SUMIF('C de C año anterior'!$B$8:$B$210,B9,'C de C año anterior'!$Q$8:$Q$210)*(100%+$V$5),0),-3) -> 871000 | X9: =ROUND(IF(W9="SI",V9*$X$5,0),-3) -> 0 | Z9: =ROUND(IF(Y9="SI",V9*$Z$5,0),-3) -> 0 | AB9: =ROUND(IF(AA9="SI",V9*$AB$5,0),-3) -> 0 | AD9: =ROUND(IF(AC9="SI",V9*$AD$5,0),-3) -> 0 | AF9: =ROUND(IF(AE9="SI",V9*$AF$5,0),-3) -> 0 | AH9: =ROUND(IF(AG9="SI",V9*$AH$5,0),-3) -> 0 | AJ9: =IF(AI9="SI",V9*$AJ$5,0) -> 0 | AK9: =SUMIF('Otras Asesorías y Préstamos'!$B$7:$B$242,B9,'Otras Asesorías y Préstamos'!$F$7:$F$242) -> 0 | AL9: =SUMIF('Otras Asesorías y Préstamos'!$B$7:$B$242,B9,'Otras Asesorías y Préstamos'!$V$7:$V$242) -> 0 | AM9: =ROUND(SUM(V9:AK9),-4) -> 870000
A10: =+A9+1 -> 2 | B10: NOMBRE 2 | C10: =_xlfn.XLOOKUP(B10,Códigos!$B$8:$B$406,Códigos!$A$8:$A$406,"Verificar",0) -> 346 | D10: =_xlfn.XLOOKUP(B10,'Consolidado Cobros'!$B$10:$B$268,'Consolidado Cobros'!$C$10:$C$268,"Verificar",0) -> 71581755 | E10: =IF((MOD((VALUE(MID(TEXT(D10,"000000000000000"),15,1))*3+VALUE(MID(TEXT(D10,"000000000000000"),14,1))*7+VALUE(MID(TEXT(D10,"000000000000000"),13,1))*13+VALUE(MID(TEXT(D10,"000000000000000"),12,1))*17+VALUE(MID(TEXT(D10,"000000000000000"),11,1))*19+VALUE(MID(TEXT(D10,"000000000000000"),10,1))*23+VALUE(MID(TEXT(D10,"000000000000000"),9,1))*29+VALUE(MID(TEXT(D10,"000000000000000"),8,1))*37+VALUE(MID(TEXT(D10,"000000000000000"),7,1))*41+VALUE(MID(TEXT(D10,"000000000000000"),6,1))*43+VALUE(MID(TEXT(D10,"000000000000000"),5,1))*47+VALUE(MID(TEXT(D10,"000000000000000"),4,1))*53+VALUE(MID(TEXT(D10,"000000000000000"),3,1))*59+VALUE(MID(TEXT(D10,"000000000000000"),2,1))*67+VALUE(MID(TEXT(D10,"000000000000000"),1,1))*71),11))=0,0,IF((MOD((VALUE(MID(TEXT(D10,"000000000000000"),15,1))*3+VALUE(MID(TEXT(D10,"000000000000000"),14,1))*7+VALUE(MID(TEXT(D10,"000000000000000"),13,1))*13+VALUE(MID(TEXT(D10,"000000000000000"),12,1))*17+VALUE(MID(TEXT(D10,"000000000000000"),11,1))*19+VALUE(MID(TEXT(D10,"000000000000000"),10,1))*23+VALUE(MID(TEXT(D10,"000000000000000"),9,1))*29+VALUE(MID(TEXT(D10,"000000000000000"),8,1))*37+VALUE(MID(TEXT(D10,"000000000000000"),7,1))*41+VALUE(MID(TEXT(D10,"000000000000000"),6,1))*43+VALUE(MID(TEXT(D10,"000000000000000"),5,1))*47+VALUE(MID(TEXT(D10,"000000000000000"),4,1))*53+VALUE(MID(TEXT(D10,"000000000000000"),3,1))*59+VALUE(MID(TEXT(D10,"000000000000000"),2,1))*67+VALUE(MID(TEXT(D10,"000000000000000"),1,1))*71),11))=1,1,11-(MOD((VALUE(MID(TEXT(D10,"000000000000000"),15,1))*3+VALUE(MID(TEXT(D10,"000000000000000"),14,1))*7+VALUE(MID(TEXT(D10,"000000000000000"),13,1))*13+VALUE(MID(TEXT(D10,"000000000000000"),12,1))*17+VALUE(MID(TEXT(D10,"000000000000000"),11,1))*19+VALUE(MID(TEXT(D10,"000000000000000"),10,1))*23+VALUE(MID(TEXT(D10,"000000000000000"),9,1))*29+VALUE(MID(TEXT(D10,"000000000000000"),8,1))*37+VALUE(MID(TEXT(D10,"000000000000000"),7,1))*41+VALUE(MID(TEXT(D10,"000000000000000"),6,1))*43+VALUE(MID(TEXT(D10,"000000000000000"),5,1))*47+VALUE(MID(TEXT(D10,"000000000000000"),4,1))*53+VALUE(MID(TEXT(D10,"000000000000000"),3,1))*59+VALUE(MID(TEXT(D10,"000000000000000"),2,1))*67+VALUE(MID(TEXT(D10,"000000000000000"),1,1))*71),11)))) -> 2 | F10: =+AM10 -> 1000000 | G10: =+F10*$G$5 -> 190000 | H10: NO | I10: =IF(H10="S",-F10*$I$5,"NO RETENCIÓN") -> NO RETENCIÓN | J10: =+F10+G10 -> 1190000 | K10: =SUM(F10:I10) -> 1190000 | Q10: =+AL10 -> 0 | U10: SI | V10: =ROUND(IF(U10="SI",SUMIF('Facturas año anterior'!$B$8:$B$81,B10,'Facturas año anterior'!$V$8:$V$81)*(100%+$V$5),0),-3)+ROUND(IF(U10="SI",SUMIF('C de C año anterior'!$B$8:$B$210,B10,'C de C año anterior'!$Q$8:$Q$210)*(100%+$V$5),0),-3) -> 773000 | X10: =ROUND(IF(W10="SI",V10*$X$5,0),-3) -> 0 | Z10: =ROUND(IF(Y10="SI",V10*$Z$5,0),-3) -> 0 | AB10: =ROUND(IF(AA10="SI",V10*$AB$5,0),-3) -> 0 | AD10: =ROUND(IF(AC10="SI",V10*$AD$5,0),-3) -> 0 | AF10: =ROUND(IF(AE10="SI",V10*$AF$5,0),-3) -> 0 | AH10: =ROUND(IF(AG10="SI",V10*$AH$5,0),-3) -> 0 | AI10: SI | AJ10: =IF(AI10="SI",V10*$AJ$5,0) -> 231900 | AK10: =SUMIF('Otras Asesorías y Préstamos'!$B$7:$B$242,B10,'Otras Asesorías y Préstamos'!$F$7:$F$242) -> 0 | AL10: =SUMIF('Otras Asesorías y Préstamos'!$B$7:$B$242,B10,'Otras Asesorías y Préstamos'!$V$7:$V$242) -> 0 | AM10: =ROUND(SUM(V10:AK10),-4) -> 1000000
A11: =+A10+1 -> 3 | B11: NOMBRE 3 | C11: =_xlfn.XLOOKUP(B11,Códigos!$B$8:$B$406,Códigos!$A$8:$A$406,"Verificar",0) -> 300 | D11: =_xlfn.XLOOKUP(B11,'Consolidado Cobros'!$B$10:$B$268,'Consolidado Cobros'!$C$10:$C$268,"Verificar",0) -> 70116694 | E11: =IF((MOD((VALUE(MID(TEXT(D11,"000000000000000"),15,1))*3+VALUE(MID(TEXT(D11,"000000000000000"),14,1))*7+VALUE(MID(TEXT(D11,"000000000000000"),13,1))*13+VALUE(MID(TEXT(D11,"000000000000000"),12,1))*17+VALUE(MID(TEXT(D11,"000000000000000"),11,1))*19+VALUE(MID(TEXT(D11,"000000000000000"),10,1))*23+VALUE(MID(TEXT(D11,"000000000000000"),9,1))*29+VALUE(MID(TEXT(D11,"000000000000000"),8,1))*37+VALUE(MID(TEXT(D11,"000000000000000"),7,1))*41+VALUE(MID(TEXT(D11,"000000000000000"),6,1))*43+VALUE(MID(TEXT(D11,"000000000000000"),5,1))*47+VALUE(MID(TEXT(D11,"000000000000000"),4,1))*53+VALUE(MID(TEXT(D11,"000000000000000"),3,1))*59+VALUE(MID(TEXT(D11,"000000000000000"),2,1))*67+VALUE(MID(TEXT(D11,"000000000000000"),1,1))*71),11))=0,0,IF((MOD((VALUE(MID(TEXT(D11,"000000000000000"),15,1))*3+VALUE(MID(TEXT(D11,"000000000000000"),14,1))*7+VALUE(MID(TEXT(D11,"000000000000000"),13,1))*13+VALUE(MID(TEXT(D11,"000000000000000"),12,1))*17+VALUE(MID(TEXT(D11,"000000000000000"),11,1))*19+VALUE(MID(TEXT(D11,"000000000000000"),10,1))*23+VALUE(MID(TEXT(D11,"000000000000000"),9,1))*29+VALUE(MID(TEXT(D11,"000000000000000"),8,1))*37+VALUE(MID(TEXT(D11,"000000000000000"),7,1))*41+VALUE(MID(TEXT(D11,"000000000000000"),6,1))*43+VALUE(MID(TEXT(D11,"000000000000000"),5,1))*47+VALUE(MID(TEXT(D11,"000000000000000"),4,1))*53+VALUE(MID(TEXT(D11,"000000000000000"),3,1))*59+VALUE(MID(TEXT(D11,"000000000000000"),2,1))*67+VALUE(MID(TEXT(D11,"000000000000000"),1,1))*71),11))=1,1,11-(MOD((VALUE(MID(TEXT(D11,"000000000000000"),15,1))*3+VALUE(MID(TEXT(D11,"000000000000000"),14,1))*7+VALUE(MID(TEXT(D11,"000000000000000"),13,1))*13+VALUE(MID(TEXT(D11,"000000000000000"),12,1))*17+VALUE(MID(TEXT(D11,"000000000000000"),11,1))*19+VALUE(MID(TEXT(D11,"000000000000000"),10,1))*23+VALUE(MID(TEXT(D11,"000000000000000"),9,1))*29+VALUE(MID(TEXT(D11,"000000000000000"),8,1))*37+VALUE(MID(TEXT(D11,"000000000000000"),7,1))*41+VALUE(MID(TEXT(D11,"000000000000000"),6,1))*43+VALUE(MID(TEXT(D11,"000000000000000"),5,1))*47+VALUE(MID(TEXT(D11,"000000000000000"),4,1))*53+VALUE(MID(TEXT(D11,"000000000000000"),3,1))*59+VALUE(MID(TEXT(D11,"000000000000000"),2,1))*67+VALUE(MID(TEXT(D11,"000000000000000"),1,1))*71),11)))) -> 5 | F11: =+AM11 -> 1080000 | G11: =+F11*$G$5 -> 205200 | H11: S | I11: =IF(H11="S",-F11*$I$5,"NO RETENCIÓN") -> -118800 | J11: =+F11+G11 -> 1285200 | K11: =SUM(F11:I11) -> 1166400 | Q11: =+AL11 -> 0 | U11: SI | V11: =ROUND(IF(U11="SI",SUMIF('Facturas año anterior'!$B$8:$B$81,B11,'Facturas año anterior'!$V$8:$V$81)*(100%+$V$5),0),-3)+ROUND(IF(U11="SI",SUMIF('C de C año anterior'!$B$8:$B$210,B11,'C de C año anterior'!$Q$8:$Q$210)*(100%+$V$5),0),-3) -> 1083000 | X11: =ROUND(IF(W11="SI",V11*$X$5,0),-3) -> 0 | Z11: =ROUND(IF(Y11="SI",V11*$Z$5,0),-3) -> 0 | AB11: =ROUND(IF(AA11="SI",V11*$AB$5,0),-3) -> 0 | AD11: =ROUND(IF(AC11="SI",V11*$AD$5,0),-3) -> 0 | AF11: =ROUND(IF(AE11="SI",V11*$AF$5,0),-3) -> 0 | AH11: =ROUND(IF(AG11="SI",V11*$AH$5,0),-3) -> 0 | AJ11: =IF(AI11="SI",V11*$AJ$5,0) -> 0 | AK11: =SUMIF('Otras Asesorías y Préstamos'!$B$7:$B$242,B11,'Otras Asesorías y Préstamos'!$F$7:$F$242) -> 0 | AL11: =SUMIF('Otras Asesorías y Préstamos'!$B$7:$B$242,B11,'Otras Asesorías y Préstamos'!$V$7:$V$242) -> 0 | AM11: =ROUND(SUM(V11:AK11),-4) -> 1080000
A12: =+A11+1 -> 4 | B12: NOMBRE 4 | C12: =_xlfn.XLOOKUP(B12,Códigos!$B$8:$B$406,Códigos!$A$8:$A$406,"Verificar",0) -> 312 | D12: =_xlfn.XLOOKUP(B12,'Consolidado Cobros'!$B$10:$B$268,'Consolidado Cobros'!$C$10:$C$268,"Verificar",0) -> 3349249 | E12: =IF((MOD((VALUE(MID(TEXT(D12,"000000000000000"),15,1))*3+VALUE(MID(TEXT(D12,"000000000000000"),14,1))*7+VALUE(MID(TEXT(D12,"000000000000000"),13,1))*13+VALUE(MID(TEXT(D12,"000000000000000"),12,1))*17+VALUE(MID(TEXT(D12,"000000000000000"),11,1))*19+VALUE(MID(TEXT(D12,"000000000000000"),10,1))*23+VALUE(MID(TEXT(D12,"000000000000000"),9,1))*29+VALUE(MID(TEXT(D12,"000000000000000"),8,1))*37+VALUE(MID(TEXT(D12,"000000000000000"),7,1))*41+VALUE(MID(TEXT(D12,"000000000000000"),6,1))*43+VALUE(MID(TEXT(D12,"000000000000000"),5,1))*47+VALUE(MID(TEXT(D12,"000000000000000"),4,1))*53+VALUE(MID(TEXT(D12,"000000000000000"),3,1))*59+VALUE(MID(TEXT(D12,"000000000000000"),2,1))*67+VALUE(MID(TEXT(D12,"000000000000000"),1,1))*71),11))=0,0,IF((MOD((VALUE(MID(TEXT(D12,"000000000000000"),15,1))*3+VALUE(MID(TEXT(D12,"000000000000000"),14,1))*7+VALUE(MID(TEXT(D12,"000000000000000"),13,1))*13+VALUE(MID(TEXT(D12,"000000000000000"),12,1))*17+VALUE(MID(TEXT(D12,"000000000000000"),11,1))*19+VALUE(MID(TEXT(D12,"000000000000000"),10,1))*23+VALUE(MID(TEXT(D12,"000000000000000"),9,1))*29+VALUE(MID(TEXT(D12,"000000000000000"),8,1))*37+VALUE(MID(TEXT(D12,"000000000000000"),7,1))*41+VALUE(MID(TEXT(D12,"000000000000000"),6,1))*43+VALUE(MID(TEXT(D12,"000000000000000"),5,1))*47+VALUE(MID(TEXT(D12,"000000000000000"),4,1))*53+VALUE(MID(TEXT(D12,"000000000000000"),3,1))*59+VALUE(MID(TEXT(D12,"000000000000000"),2,1))*67+VALUE(MID(TEXT(D12,"000000000000000"),1,1))*71),11))=1,1,11-(MOD((VALUE(MID(TEXT(D12,"000000000000000"),15,1))*3+VALUE(MID(TEXT(D12,"000000000000000"),14,1))*7+VALUE(MID(TEXT(D12,"000000000000000"),13,1))*13+VALUE(MID(TEXT(D12,"000000000000000"),12,1))*17+VALUE(MID(TEXT(D12,"000000000000000"),11,1))*19+VALUE(MID(TEXT(D12,"000000000000000"),10,1))*23+VALUE(MID(TEXT(D12,"000000000000000"),9,1))*29+VALUE(MID(TEXT(D12,"000000000000000"),8,1))*37+VALUE(MID(TEXT(D12,"000000000000000"),7,1))*41+VALUE(MID(TEXT(D12,"000000000000000"),6,1))*43+VALUE(MID(TEXT(D12,"000000000000000"),5,1))*47+VALUE(MID(TEXT(D12,"000000000000000"),4,1))*53+VALUE(MID(TEXT(D12,"000000000000000"),3,1))*59+VALUE(MID(TEXT(D12,"000000000000000"),2,1))*67+VALUE(MID(TEXT(D12,"000000000000000"),1,1))*71),11)))) -> 7 | F12: =+AM12 -> 2990000 | G12: =+F12*$G$5 -> 568100 | H12: S | I12: =IF(H12="S",-F12*$I$5,"NO RETENCIÓN") -> -328900 | J12: =+F12+G12 -> 3558100 | K12: =SUM(F12:I12) -> 3229200 | Q12: =+AL12 -> 0 | U12: SI | V12: =ROUND(IF(U12="SI",SUMIF('Facturas año anterior'!$B$8:$B$81,B12,'Facturas año anterior'!$V$8:$V$81)*(100%+$V$5),0),-3)+ROUND(IF(U12="SI",SUMIF('C de C año anterior'!$B$8:$B$210,B12,'C de C año anterior'!$Q$8:$Q$210)*(100%+$V$5),0),-3) -> 1328000 | W12: SI | X12: =ROUND(IF(W12="SI",V12*$X$5,0),-3) -> 664000 | Y12: SI | Z12: =ROUND(IF(Y12="SI",V12*$Z$5,0),-3) -> 996000 | AB12: =ROUND(IF(AA12="SI",V12*$AB$5,0),-3) -> 0 | AD12: =ROUND(IF(AC12="SI",V12*$AD$5,0),-3) -> 0 | AF12: =ROUND(IF(AE12="SI",V12*$AF$5,0),-3) -> 0 | AH12: =ROUND(IF(AG12="SI",V12*$AH$5,0),-3) -> 0 | AJ12: =IF(AI12="SI",V12*$AJ$5,0) -> 0 | AK12: =SUMIF('Otras Asesorías y Préstamos'!$B$7:$B$242,B12,'Otras Asesorías y Préstamos'!$F$7:$F$242) -> 0 | AL12: =SUMIF('Otras Asesorías y Préstamos'!$B$7:$B$242,B12,'Otras Asesorías y Préstamos'!$V$7:$V$242) -> 0 | AM12: =ROUND(SUM(V12:AK12),-4) -> 2990000
A13: =+A12+1 -> 5 | B13: NOMBRE 5 | C13: =_xlfn.XLOOKUP(B13,Códigos!$B$8:$B$406,Códigos!$A$8:$A$406,"Verificar",0) -> 217 | D13: =_xlfn.XLOOKUP(B13,'Consolidado Cobros'!$B$10:$B$268,'Consolidado Cobros'!$C$10:$C$268,"Verificar",0) -> 71632774 | E13: =IF((MOD((VALUE(MID(TEXT(D13,"000000000000000"),15,1))*3+VALUE(MID(TEXT(D13,"000000000000000"),14,1))*7+VALUE(MID(TEXT(D13,"000000000000000"),13,1))*13+VALUE(MID(TEXT(D13,"000000000000000"),12,1))*17+VALUE(MID(TEXT(D13,"000000000000000"),11,1))*19+VALUE(MID(TEXT(D13,"000000000000000"),10,1))*23+VALUE(MID(TEXT(D13,"000000000000000"),9,1))*29+VALUE(MID(TEXT(D13,"000000000000000"),8,1))*37+VALUE(MID(TEXT(D13,"000000000000000"),7,1))*41+VALUE(MID(TEXT(D13,"000000000000000"),6,1))*43+VALUE(MID(TEXT(D13,"000000000000000"),5,1))*47+VALUE(MID(TEXT(D13,"000000000000000"),4,1))*53+VALUE(MID(TEXT(D13,"000000000000000"),3,1))*59+VALUE(MID(TEXT(D13,"000000000000000"),2,1))*67+VALUE(MID(TEXT(D13,"000000000000000"),1,1))*71),11))=0,0,IF((MOD((VALUE(MID(TEXT(D13,"000000000000000"),15,1))*3+VALUE(MID(TEXT(D13,"000000000000000"),14,1))*7+VALUE(MID(TEXT(D13,"000000000000000"),13,1))*13+VALUE(MID(TEXT(D13,"000000000000000"),12,1))*17+VALUE(MID(TEXT(D13,"000000000000000"),11,1))*19+VALUE(MID(TEXT(D13,"000000000000000"),10,1))*23+VALUE(MID(TEXT(D13,"000000000000000"),9,1))*29+VALUE(MID(TEXT(D13,"000000000000000"),8,1))*37+VALUE(MID(TEXT(D13,"000000000000000"),7,1))*41+VALUE(MID(TEXT(D13,"000000000000000"),6,1))*43+VALUE(MID(TEXT(D13,"000000000000000"),5,1))*47+VALUE(MID(TEXT(D13,"000000000000000"),4,1))*53+VALUE(MID(TEXT(D13,"000000000000000"),3,1))*59+VALUE(MID(TEXT(D13,"000000000000000"),2,1))*67+VALUE(MID(TEXT(D13,"000000000000000"),1,1))*71),11))=1,1,11-(MOD((VALUE(MID(TEXT(D13,"000000000000000"),15,1))*3+VALUE(MID(TEXT(D13,"000000000000000"),14,1))*7+VALUE(MID(TEXT(D13,"000000000000000"),13,1))*13+VALUE(MID(TEXT(D13,"000000000000000"),12,1))*17+VALUE(MID(TEXT(D13,"000000000000000"),11,1))*19+VALUE(MID(TEXT(D13,"000000000000000"),10,1))*23+VALUE(MID(TEXT(D13,"000000000000000"),9,1))*29+VALUE(MID(TEXT(D13,"000000000000000"),8,1))*37+VALUE(MID(TEXT(D13,"000000000000000"),7,1))*41+VALUE(MID(TEXT(D13,"000000000000000"),6,1))*43+VALUE(MID(TEXT(D13,"000000000000000"),5,1))*47+VALUE(MID(TEXT(D13,"000000000000000"),4,1))*53+VALUE(MID(TEXT(D13,"000000000000000"),3,1))*59+VALUE(MID(TEXT(D13,"000000000000000"),2,1))*67+VALUE(MID(TEXT(D13,"000000000000000"),1,1))*71),11)))) -> 2 | F13: =+AM13 -> 2430000 | G13: =+F13*$G$5 -> 461700 | H13: S | I13: =IF(H13="S",-F13*$I$5,"NO RETENCIÓN") -> -267300 | J13: =+F13+G13 -> 2891700 | K13: =SUM(F13:I13) -> 2624400 | Q13: =+AL13 -> 0 | U13: SI | V13: =ROUND(IF(U13="SI",SUMIF('Facturas año anterior'!$B$8:$B$81,B13,'Facturas año anterior'!$V$8:$V$81)*(100%+$V$5),0),-3)+ROUND(IF(U13="SI",SUMIF('C de C año anterior'!$B$8:$B$210,B13,'C de C año anterior'!$Q$8:$Q$210)*(100%+$V$5),0),-3) -> 2332000 | X13: =ROUND(IF(W13="SI",V13*$X$5,0),-3) -> 0 | Z13: =ROUND(IF(Y13="SI",V13*$Z$5,0),-3) -> 0 | AB13: =ROUND(IF(AA13="SI",V13*$AB$5,0),-3) -> 0 | AD13: =ROUND(IF(AC13="SI",V13*$AD$5,0),-3) -> 0 | AF13: =ROUND(IF(AE13="SI",V13*$AF$5,0),-3) -> 0 | AH13: =ROUND(IF(AG13="SI",V13*$AH$5,0),-3) -> 0 | AJ13: =IF(AI13="SI",V13*$AJ$5,0) -> 0 | AK13: =SUMIF('Otras Asesorías y Préstamos'!$B$7:$B$242,B13,'Otras Asesorías y Préstamos'!$F$7:$F$242) -> 100000 | AL13: =SUMIF('Otras Asesorías y Préstamos'!$B$7:$B$242,B13,'Otras Asesorías y Préstamos'!$V$7:$V$242) -> 0 | AM13: =ROUND(SUM(V13:AK13),-4) -> 2430000
A14: =+A13+1 -> 6 | B14: NOMBRE 6 | C14: =_xlfn.XLOOKUP(B14,Códigos!$B$8:$B$406,Códigos!$A$8:$A$406,"Verificar",0) -> 42 | D14: =_xlfn.XLOOKUP(B14,'Consolidado Cobros'!$B$10:$B$268,'Consolidado Cobros'!$C$10:$C$268,"Verificar",0) -> 21315528 | E14: =IF((MOD((VALUE(MID(TEXT(D14,"000000000000000"),15,1))*3+VALUE(MID(TEXT(D14,"000000000000000"),14,1))*7+VALUE(MID(TEXT(D14,"000000000000000"),13,1))*13+VALUE(MID(TEXT(D14,"000000000000000"),12,1))*17+VALUE(MID(TEXT(D14,"000000000000000"),11,1))*19+VALUE(MID(TEXT(D14,"000000000000000"),10,1))*23+VALUE(MID(TEXT(D14,"000000000000000"),9,1))*29+VALUE(MID(TEXT(D14,"000000000000000"),8,1))*37+VALUE(MID(TEXT(D14,"000000000000000"),7,1))*41+VALUE(MID(TEXT(D14,"000000000000000"),6,1))*43+VALUE(MID(TEXT(D14,"000000000000000"),5,1))*47+VALUE(MID(TEXT(D14,"000000000000000"),4,1))*53+VALUE(MID(TEXT(D14,"000000000000000"),3,1))*59+VALUE(MID(TEXT(D14,"000000000000000"),2,1))*67+VALUE(MID(TEXT(D14,"000000000000000"),1,1))*71),11))=0,0,IF((MOD((VALUE(MID(TEXT(D14,"000000000000000"),15,1))*3+VALUE(MID(TEXT(D14,"000000000000000"),14,1))*7+VALUE(MID(TEXT(D14,"000000000000000"),13,1))*13+VALUE(MID(TEXT(D14,"000000000000000"),12,1))*17+VALUE(MID(TEXT(D14,"000000000000000"),11,1))*19+VALUE(MID(TEXT(D14,"000000000000000"),10,1))*23+VALUE(MID(TEXT(D14,"000000000000000"),9,1))*29+VALUE(MID(TEXT(D14,"000000000000000"),8,1))*37+VALUE(MID(TEXT(D14,"000000000000000"),7,1))*41+VALUE(MID(TEXT(D14,"000000000000000"),6,1))*43+VALUE(MID(TEXT(D14,"000000000000000"),5,1))*47+VALUE(MID(TEXT(D14,"000000000000000"),4,1))*53+VALUE(MID(TEXT(D14,"000000000000000"),3,1))*59+VALUE(MID(TEXT(D14,"000000000000000"),2,1))*67+VALUE(MID(TEXT(D14,"000000000000000"),1,1))*71),11))=1,1,11-(MOD((VALUE(MID(TEXT(D14,"000000000000000"),15,1))*3+VALUE(MID(TEXT(D14,"000000000000000"),14,1))*7+VALUE(MID(TEXT(D14,"000000000000000"),13,1))*13+VALUE(MID(TEXT(D14,"000000000000000"),12,1))*17+VALUE(MID(TEXT(D14,"000000000000000"),11,1))*19+VALUE(MID(TEXT(D14,"000000000000000"),10,1))*23+VALUE(MID(TEXT(D14,"000000000000000"),9,1))*29+VALUE(MID(TEXT(D14,"000000000000000"),8,1))*37+VALUE(MID(TEXT(D14,"000000000000000"),7,1))*41+VALUE(MID(TEXT(D14,"000000000000000"),6,1))*43+VALUE(MID(TEXT(D14,"000000000000000"),5,1))*47+VALUE(MID(TEXT(D14,"000000000000000"),4,1))*53+VALUE(MID(TEXT(D14,"000000000000000"),3,1))*59+VALUE(MID(TEXT(D14,"000000000000000"),2,1))*67+VALUE(MID(TEXT(D14,"000000000000000"),1,1))*71),11)))) -> 6 | F14: =+AM14 -> 1830000 | G14: =+F14*$G$5 -> 347700 | H14: S | I14: =IF(H14="S",-F14*$I$5,"NO RETENCIÓN") -> -201300 | J14: =+F14+G14 -> 2177700 | K14: =SUM(F14:I14) -> 1976400 | Q14: =+AL14 -> 0 | S14: Fra con -San Antonio de la Almería | U14: SI | V14: =ROUND(IF(U14="SI",SUMIF('Facturas año anterior'!$B$8:$B$81,B14,'Facturas año anterior'!$V$8:$V$81)*(100%+$V$5),0),-3)+ROUND(IF(U14="SI",SUMIF('C de C año anterior'!$B$8:$B$210,B14,'C de C año anterior'!$Q$8:$Q$210)*(100%+$V$5),0),-3) -> 1830000 | X14: =ROUND(IF(W14="SI",V14*$X$5,0),-3) -> 0 | Z14: =ROUND(IF(Y14="SI",V14*$Z$5,0),-3) -> 0 | AB14: =ROUND(IF(AA14="SI",V14*$AB$5,0),-3) -> 0 | AD14: =ROUND(IF(AC14="SI",V14*$AD$5,0),-3) -> 0 | AF14: =ROUND(IF(AE14="SI",V14*$AF$5,0),-3) -> 0 | AH14: =ROUND(IF(AG14="SI",V14*$AH$5,0),-3) -> 0 | AJ14: =IF(AI14="SI",V14*$AJ$5,0) -> 0 | AK14: =SUMIF('Otras Asesorías y Préstamos'!$B$7:$B$242,B14,'Otras Asesorías y Préstamos'!$F$7:$F$242) -> 0 | AL14: =SUMIF('Otras Asesorías y Préstamos'!$B$7:$B$242,B14,'Otras Asesorías y Préstamos'!$V$7:$V$242) -> 0 | AM14: =ROUND(SUM(V14:AK14),-4) -> 1830000
A15: =+A14+1 -> 7 | B15: NOMBRE 7 | C15: =_xlfn.XLOOKUP(B15,Códigos!$B$8:$B$406,Códigos!$A$8:$A$406,"Verificar",0) -> 43 | D15: =_xlfn.XLOOKUP(B15,'Consolidado Cobros'!$B$10:$B$268,'Consolidado Cobros'!$C$10:$C$268,"Verificar",0) -> 32336950 | E15: =IF((MOD((VALUE(MID(TEXT(D15,"000000000000000"),15,1))*3+VALUE(MID(TEXT(D15,"000000000000000"),14,1))*7+VALUE(MID(TEXT(D15,"000000000000000"),13,1))*13+VALUE(MID(TEXT(D15,"000000000000000"),12,1))*17+VALUE(MID(TEXT(D15,"000000000000000"),11,1))*19+VALUE(MID(TEXT(D15,"000000000000000"),10,1))*23+VALUE(MID(TEXT(D15,"000000000000000"),9,1))*29+VALUE(MID(TEXT(D15,"000000000000000"),8,1))*37+VALUE(MID(TEXT(D15,"000000000000000"),7,1))*41+VALUE(MID(TEXT(D15,"000000000000000"),6,1))*43+VALUE(MID(TEXT(D15,"000000000000000"),5,1))*47+VALUE(MID(TEXT(D15,"000000000000000"),4,1))*53+VALUE(MID(TEXT(D15,"000000000000000"),3,1))*59+VALUE(MID(TEXT(D15,"000000000000000"),2,1))*67+VALUE(MID(TEXT(D15,"000000000000000"),1,1))*71),11))=0,0,IF((MOD((VALUE(MID(TEXT(D15,"000000000000000"),15,1))*3+VALUE(MID(TEXT(D15,"000000000000000"),14,1))*7+VALUE(MID(TEXT(D15,"000000000000000"),13,1))*13+VALUE(MID(TEXT(D15,"000000000000000"),12,1))*17+VALUE(MID(TEXT(D15,"000000000000000"),11,1))*19+VALUE(MID(TEXT(D15,"000000000000000"),10,1))*23+VALUE(MID(TEXT(D15,"000000000000000"),9,1))*29+VALUE(MID(TEXT(D15,"000000000000000"),8,1))*37+VALUE(MID(TEXT(D15,"000000000000000"),7,1))*41+VALUE(MID(TEXT(D15,"000000000000000"),6,1))*43+VALUE(MID(TEXT(D15,"000000000000000"),5,1))*47+VALUE(MID(TEXT(D15,"000000000000000"),4,1))*53+VALUE(MID(TEXT(D15,"000000000000000"),3,1))*59+VALUE(MID(TEXT(D15,"000000000000000"),2,1))*67+VALUE(MID(TEXT(D15,"000000000000000"),1,1))*71),11))=1,1,11-(MOD((VALUE(MID(TEXT(D15,"000000000000000"),15,1))*3+VALUE(MID(TEXT(D15,"000000000000000"),14,1))*7+VALUE(MID(TEXT(D15,"000000000000000"),13,1))*13+VALUE(MID(TEXT(D15,"000000000000000"),12,1))*17+VALUE(MID(TEXT(D15,"000000000000000"),11,1))*19+VALUE(MID(TEXT(D15,"000000000000000"),10,1))*23+VALUE(MID(TEXT(D15,"000000000000000"),9,1))*29+VALUE(MID(TEXT(D15,"000000000000000"),8,1))*37+VALUE(MID(TEXT(D15,"000000000000000"),7,1))*41+VALUE(MID(TEXT(D15,"000000000000000"),6,1))*43+VALUE(MID(TEXT(D15,"000000000000000"),5,1))*47+VALUE(MID(TEXT(D15,"000000000000000"),4,1))*53+VALUE(MID(TEXT(D15,"000000000000000"),3,1))*59+VALUE(MID(TEXT(D15,"000000000000000"),2,1))*67+VALUE(MID(TEXT(D15,"000000000000000"),1,1))*71),11)))) -> 1 | F15: =+AM15 -> 2390000 | G15: =+F15*$G$5 -> 454100 | H15: S | I15: =IF(H15="S",-F15*$I$5,"NO RETENCIÓN") -> -262900 | J15: =+F15+G15 -> 2844100 | K15: =SUM(F15:I15) -> 2581200 | Q15: =+AL15 -> 0 | S15: Fra con -San Antonio de la Almería | U15: SI | V15: =ROUND(IF(U15="SI",SUMIF('Facturas año anterior'!$B$8:$B$81,B15,'Facturas año anterior'!$V$8:$V$81)*(100%+$V$5),0),-3)+ROUND(IF(U15="SI",SUMIF('C de C año anterior'!$B$8:$B$210,B15,'C de C año anterior'!$Q$8:$Q$210)*(100%+$V$5),0),-3) -> 2010000 | X15: =ROUND(IF(W15="SI",V15*$X$5,0),-3) -> 0 | Z15: =ROUND(IF(Y15="SI",V15*$Z$5,0),-3) -> 0 | AB15: =ROUND(IF(AA15="SI",V15*$AB$5,0),-3) -> 0 | AD15: =ROUND(IF(AC15="SI",V15*$AD$5,0),-3) -> 0 | AF15: =ROUND(IF(AE15="SI",V15*$AF$5,0),-3) -> 0 | AH15: =ROUND(IF(AG15="SI",V15*$AH$5,0),-3) -> 0 | AJ15: =IF(AI15="SI",V15*$AJ$5,0) -> 0 | AK15: =SUMIF('Otras Asesorías y Préstamos'!$B$7:$B$242,B15,'Otras Asesorías y Préstamos'!$F$7:$F$242) -> 384948.68 | AL15: =SUMIF('Otras Asesorías y Préstamos'!$B$7:$B$242,B15,'Otras Asesorías y Préstamos'!$V$7:$V$242) -> 0 | AM15: =ROUND(SUM(V15:AK15),-4) -> 2390000
A16: =+A15+1 -> 8 | B16: NOMBRE 8 | C16: =_xlfn.XLOOKUP(B16,Códigos!$B$8:$B$406,Códigos!$A$8:$A$406,"Verificar",0) -> 44 | D16: =_xlfn.XLOOKUP(B16,'Consolidado Cobros'!$B$10:$B$268,'Consolidado Cobros'!$C$10:$C$268,"Verificar",0) -> 1152450831 | E16: =IF((MOD((VALUE(MID(TEXT(D16,"000000000000000"),15,1))*3+VALUE(MID(TEXT(D16,"000000000000000"),14,1))*7+VALUE(MID(TEXT(D16,"000000000000000"),13,1))*13+VALUE(MID(TEXT(D16,"000000000000000"),12,1))*17+VALUE(MID(TEXT(D16,"000000000000000"),11,1))*19+VALUE(MID(TEXT(D16,"000000000000000"),10,1))*23+VALUE(MID(TEXT(D16,"000000000000000"),9,1))*29+VALUE(MID(TEXT(D16,"000000000000000"),8,1))*37+VALUE(MID(TEXT(D16,"000000000000000"),7,1))*41+VALUE(MID(TEXT(D16,"000000000000000"),6,1))*43+VALUE(MID(TEXT(D16,"000000000000000"),5,1))*47+VALUE(MID(TEXT(D16,"000000000000000"),4,1))*53+VALUE(MID(TEXT(D16,"000000000000000"),3,1))*59+VALUE(MID(TEXT(D16,"000000000000000"),2,1))*67+VALUE(MID(TEXT(D16,"000000000000000"),1,1))*71),11))=0,0,IF((MOD((VALUE(MID(TEXT(D16,"000000000000000"),15,1))*3+VALUE(MID(TEXT(D16,"000000000000000"),14,1))*7+VALUE(MID(TEXT(D16,"000000000000000"),13,1))*13+VALUE(MID(TEXT(D16,"000000000000000"),12,1))*17+VALUE(MID(TEXT(D16,"000000000000000"),11,1))*19+VALUE(MID(TEXT(D16,"000000000000000"),10,1))*23+VALUE(MID(TEXT(D16,"000000000000000"),9,1))*29+VALUE(MID(TEXT(D16,"000000000000000"),8,1))*37+VALUE(MID(TEXT(D16,"000000000000000"),7,1))*41+VALUE(MID(TEXT(D16,"000000000000000"),6,1))*43+VALUE(MID(TEXT(D16,"000000000000000"),5,1))*47+VALUE(MID(TEXT(D16,"000000000000000"),4,1))*53+VALUE(MID(TEXT(D16,"000000000000000"),3,1))*59+VALUE(MID(TEXT(D16,"000000000000000"),2,1))*67+VALUE(MID(TEXT(D16,"000000000000000"),1,1))*71),11))=1,1,11-(MOD((VALUE(MID(TEXT(D16,"000000000000000"),15,1))*3+VALUE(MID(TEXT(D16,"000000000000000"),14,1))*7+VALUE(MID(TEXT(D16,"000000000000000"),13,1))*13+VALUE(MID(TEXT(D16,"000000000000000"),12,1))*17+VALUE(MID(TEXT(D16,"000000000000000"),11,1))*19+VALUE(MID(TEXT(D16,"000000000000000"),10,1))*23+VALUE(MID(TEXT(D16,"000000000000000"),9,1))*29+VALUE(MID(TEXT(D16,"000000000000000"),8,1))*37+VALUE(MID(TEXT(D16,"000000000000000"),7,1))*41+VALUE(MID(TEXT(D16,"000000000000000"),6,1))*43+VALUE(MID(TEXT(D16,"000000000000000"),5,1))*47+VALUE(MID(TEXT(D16,"000000000000000"),4,1))*53+VALUE(MID(TEXT(D16,"000000000000000"),3,1))*59+VALUE(MID(TEXT(D16,"000000000000000"),2,1))*67+VALUE(MID(TEXT(D16,"000000000000000"),1,1))*71),11)))) -> 7 | F16: =+AM16 -> 220000 | G16: =+F16*$G$5 -> 41800 | H16: S | I16: =IF(H16="S",-F16*$I$5,"NO RETENCIÓN") -> -24200 | J16: =+F16+G16 -> 261800 | K16: =SUM(F16:I16) -> 237600 | Q16: =+AL16 -> 0 | S16: Fra con -Ruiz González Álvaro H. | U16: SI | V16: =ROUND(IF(U16="SI",SUMIF('Facturas año anterior'!$B$8:$B$81,B16,'Facturas año anterior'!$V$8:$V$81)*(100%+$V$5),0),-3)+ROUND(IF(U16="SI",SUMIF('C de C año anterior'!$B$8:$B$210,B16,'C de C año anterior'!$Q$8:$Q$210)*(100%+$V$5),0),-3) -> 221000 | X16: =ROUND(IF(W16="SI",V16*$X$5,0),-3) -> 0 | Z16: =ROUND(IF(Y16="SI",V16*$Z$5,0),-3) -> 0 | AB16: =ROUND(IF(AA16="SI",V16*$AB$5,0),-3) -> 0 | AD16: =ROUND(IF(AC16="SI",V16*$AD$5,0),-3) -> 0 | AF16: =ROUND(IF(AE16="SI",V16*$AF$5,0),-3) -> 0 | AH16: =ROUND(IF(AG16="SI",V16*$AH$5,0),-3) -> 0 | AJ16: =IF(AI16="SI",V16*$AJ$5,0) -> 0 | AK16: =SUMIF('Otras Asesorías y Préstamos'!$B$7:$B$242,B16,'Otras Asesorías y Préstamos'!$F$7:$F$242) -> 0 | AL16: =SUMIF('Otras Asesorías y Préstamos'!$B$7:$B$242,B16,'Otras Asesorías y Préstamos'!$V$7:$V$242) -> 0 | AM16: =ROUND(SUM(V16:AK16),-4) -> 220000
A17: =+A16+1 -> 9 | U17: SI | V17: =ROUND(IF(U17="SI",SUMIF('Facturas año anterior'!$B$8:$B$81,B17,'Facturas año anterior'!$V$8:$V$81)*(100%+$V$5),0),-3)+ROUND(IF(U17="SI",SUMIF('C de C año anterior'!$B$8:$B$210,B17,'C de C año anterior'!$Q$8:$Q$210)*(100%+$V$5),0),-3) -> 0 | X17: =ROUND(IF(W17="SI",V17*$X$5,0),-3) -> 0 | Z17: =ROUND(IF(Y17="SI",V17*$Z$5,0),-3) -> 0 | AB17: =ROUND(IF(AA17="SI",V17*$AB$5,0),-3) -> 0 | AD17: =ROUND(IF(AC17="SI",V17*$AD$5,0),-3) -> 0 | AF17: =ROUND(IF(AE17="SI",V17*$AF$5,0),-3) -> 0 | AH17: =ROUND(IF(AG17="SI",V17*$AH$5,0),-3) -> 0 | AJ17: =IF(AI17="SI",V17*$AJ$5,0) -> 0 | AK17: =SUMIF('Otras Asesorías y Préstamos'!$B$7:$B$242,B17,'Otras Asesorías y Préstamos'!$F$7:$F$242) -> 0 | AL17: =SUMIF('Otras Asesorías y Préstamos'!$B$7:$B$242,B17,'Otras Asesorías y Préstamos'!$V$7:$V$242) -> 0 | AM17: =ROUND(SUM(V17:AK17),-4) -> 0
A18: =+A17+1 -> 10 | Q18: =+AL18 -> 0 | U18: SI | V18: =ROUND(IF(U18="SI",SUMIF('Facturas año anterior'!$B$8:$B$81,B18,'Facturas año anterior'!$V$8:$V$81)*(100%+$V$5),0),-3)+ROUND(IF(U18="SI",SUMIF('C de C año anterior'!$B$8:$B$210,B18,'C de C año anterior'!$Q$8:$Q$210)*(100%+$V$5),0),-3) -> 0 | X18: =ROUND(IF(W18="SI",V18*$X$5,0),-3) -> 0 | Z18: =ROUND(IF(Y18="SI",V18*$Z$5,0),-3) -> 0 | AB18: =ROUND(IF(AA18="SI",V18*$AB$5,0),-3) -> 0 | AD18: =ROUND(IF(AC18="SI",V18*$AD$5,0),-3) -> 0 | AF18: =ROUND(IF(AE18="SI",V18*$AF$5,0),-3) -> 0 | AH18: =ROUND(IF(AG18="SI",V18*$AH$5,0),-3) -> 0 | AI18: SI | AJ18: =IF(AI18="SI",V18*$AJ$5,0) -> 0 | AK18: =SUMIF('Otras Asesorías y Préstamos'!$B$7:$B$242,B18,'Otras Asesorías y Préstamos'!$F$7:$F$242) -> 0 | AL18: =SUMIF('Otras Asesorías y Préstamos'!$B$7:$B$242,B18,'Otras Asesorías y Préstamos'!$V$7:$V$242) -> 0 | AM18: =ROUND(SUM(V18:AK18),-4) -> 0
A19: =+A18+1 -> 11 | Q19: =+AL19 -> 0 | U19: SI | V19: =ROUND(IF(U19="SI",SUMIF('Facturas año anterior'!$B$8:$B$81,B19,'Facturas año anterior'!$V$8:$V$81)*(100%+$V$5),0),-3)+ROUND(IF(U19="SI",SUMIF('C de C año anterior'!$B$8:$B$210,B19,'C de C año anterior'!$Q$8:$Q$210)*(100%+$V$5),0),-3) -> 0 | X19: =ROUND(IF(W19="SI",V19*$X$5,0),-3) -> 0 | Z19: =ROUND(IF(Y19="SI",V19*$Z$5,0),-3) -> 0 | AB19: =ROUND(IF(AA19="SI",V19*$AB$5,0),-3) -> 0 | AD19: =ROUND(IF(AC19="SI",V19*$AD$5,0),-3) -> 0 | AF19: =ROUND(IF(AE19="SI",V19*$AF$5,0),-3) -> 0 | AH19: =ROUND(IF(AG19="SI",V19*$AH$5,0),-3) -> 0 | AJ19: =IF(AI19="SI",V19*$AJ$5,0) -> 0 | AK19: =SUMIF('Otras Asesorías y Préstamos'!$B$7:$B$242,B19,'Otras Asesorías y Préstamos'!$F$7:$F$242) -> 0 | AL19: =SUMIF('Otras Asesorías y Préstamos'!$B$7:$B$242,B19,'Otras Asesorías y Préstamos'!$V$7:$V$242) -> 0 | AM19: =ROUND(SUM(V19:AK19),-4) -> 0
A20: =+A19+1 -> 12 | Q20: =+AL20 -> 0 | U20: SI | V20: =ROUND(IF(U20="SI",SUMIF('Facturas año anterior'!$B$8:$B$81,B20,'Facturas año anterior'!$V$8:$V$81)*(100%+$V$5),0),-3)+ROUND(IF(U20="SI",SUMIF('C de C año anterior'!$B$8:$B$210,B20,'C de C año anterior'!$Q$8:$Q$210)*(100%+$V$5),0),-3) -> 0 | X20: =ROUND(IF(W20="SI",V20*$X$5,0),-3) -> 0 | Z20: =ROUND(IF(Y20="SI",V20*$Z$5,0),-3) -> 0 | AB20: =ROUND(IF(AA20="SI",V20*$AB$5,0),-3) -> 0 | AD20: =ROUND(IF(AC20="SI",V20*$AD$5,0),-3) -> 0 | AF20: =ROUND(IF(AE20="SI",V20*$AF$5,0),-3) -> 0 | AH20: =ROUND(IF(AG20="SI",V20*$AH$5,0),-3) -> 0 | AJ20: =IF(AI20="SI",V20*$AJ$5,0) -> 0 | AK20: =SUMIF('Otras Asesorías y Préstamos'!$B$7:$B$242,B20,'Otras Asesorías y Préstamos'!$F$7:$F$242) -> 0 | AL20: =SUMIF('Otras Asesorías y Préstamos'!$B$7:$B$242,B20,'Otras Asesorías y Préstamos'!$V$7:$V$242) -> 0 | AM20: =ROUND(SUM(V20:AK20),-4) -> 0
A21: =+A20+1 -> 13 | Q21: =+AL21 -> 0 | U21: SI | V21: =ROUND(IF(U21="SI",SUMIF('Facturas año anterior'!$B$8:$B$81,B21,'Facturas año anterior'!$V$8:$V$81)*(100%+$V$5),0),-3)+ROUND(IF(U21="SI",SUMIF('C de C año anterior'!$B$8:$B$210,B21,'C de C año anterior'!$Q$8:$Q$210)*(100%+$V$5),0),-3) -> 0 | X21: =ROUND(IF(W21="SI",V21*$X$5,0),-3) -> 0 | Z21: =ROUND(IF(Y21="SI",V21*$Z$5,0),-3) -> 0 | AB21: =ROUND(IF(AA21="SI",V21*$AB$5,0),-3) -> 0 | AD21: =ROUND(IF(AC21="SI",V21*$AD$5,0),-3) -> 0 | AF21: =ROUND(IF(AE21="SI",V21*$AF$5,0),-3) -> 0 | AH21: =ROUND(IF(AG21="SI",V21*$AH$5,0),-3) -> 0 | AI21: SI | AJ21: =IF(AI21="SI",V21*$AJ$5,0) -> 0 | AK21: =SUMIF('Otras Asesorías y Préstamos'!$B$7:$B$242,B21,'Otras Asesorías y Préstamos'!$F$7:$F$242) -> 0 | AL21: =SUMIF('Otras Asesorías y Préstamos'!$B$7:$B$242,B21,'Otras Asesorías y Préstamos'!$V$7:$V$242) -> 0 | AM21: =ROUND(SUM(V21:AK21),-4) -> 0
A22: =+A21+1 -> 14 | Q22: =+AL22 -> 0 | U22: SI | V22: =ROUND(IF(U22="SI",SUMIF('Facturas año anterior'!$B$8:$B$81,B22,'Facturas año anterior'!$V$8:$V$81)*(100%+$V$5),0),-3)+ROUND(IF(U22="SI",SUMIF('C de C año anterior'!$B$8:$B$210,B22,'C de C año anterior'!$Q$8:$Q$210)*(100%+$V$5),0),-3) -> 0 | X22: =ROUND(IF(W22="SI",V22*$X$5,0),-3) -> 0 | Z22: =ROUND(IF(Y22="SI",V22*$Z$5,0),-3) -> 0 | AB22: =ROUND(IF(AA22="SI",V22*$AB$5,0),-3) -> 0 | AD22: =ROUND(IF(AC22="SI",V22*$AD$5,0),-3) -> 0 | AF22: =ROUND(IF(AE22="SI",V22*$AF$5,0),-3) -> 0 | AH22: =ROUND(IF(AG22="SI",V22*$AH$5,0),-3) -> 0 | AI22: SI | AJ22: =IF(AI22="SI",V22*$AJ$5,0) -> 0 | AK22: =SUMIF('Otras Asesorías y Préstamos'!$B$7:$B$242,B22,'Otras Asesorías y Préstamos'!$F$7:$F$242) -> 0 | AL22: =SUMIF('Otras Asesorías y Préstamos'!$B$7:$B$242,B22,'Otras Asesorías y Préstamos'!$V$7:$V$242) -> 0 | AM22: =ROUND(SUM(V22:AK22),-4) -> 0
A23: =+A22+1 -> 15 | Q23: =+AL23 -> 0 | U23: SI | V23: =ROUND(IF(U23="SI",SUMIF('Facturas año anterior'!$B$8:$B$81,B23,'Facturas año anterior'!$V$8:$V$81)*(100%+$V$5),0),-3)+ROUND(IF(U23="SI",SUMIF('C de C año anterior'!$B$8:$B$210,B23,'C de C año anterior'!$Q$8:$Q$210)*(100%+$V$5),0),-3) -> 0 | X23: =ROUND(IF(W23="SI",V23*$X$5,0),-3) -> 0 | Z23: =ROUND(IF(Y23="SI",V23*$Z$5,0),-3) -> 0 | AB23: =ROUND(IF(AA23="SI",V23*$AB$5,0),-3) -> 0 | AD23: =ROUND(IF(AC23="SI",V23*$AD$5,0),-3) -> 0 | AF23: =ROUND(IF(AE23="SI",V23*$AF$5,0),-3) -> 0 | AH23: =ROUND(IF(AG23="SI",V23*$AH$5,0),-3) -> 0 | AI23: SI | AJ23: =IF(AI23="SI",V23*$AJ$5,0) -> 0 | AK23: =SUMIF('Otras Asesorías y Préstamos'!$B$7:$B$242,B23,'Otras Asesorías y Préstamos'!$F$7:$F$242) -> 0 | AL23: =SUMIF('Otras Asesorías y Préstamos'!$B$7:$B$242,B23,'Otras Asesorías y Préstamos'!$V$7:$V$242) -> 0 | AM23: =ROUND(SUM(V23:AK23),-4) -> 0
A24: =+A23+1 -> 16 | Q24: =+AL24 -> 0 | U24: SI | V24: =ROUND(IF(U24="SI",SUMIF('Facturas año anterior'!$B$8:$B$81,B24,'Facturas año anterior'!$V$8:$V$81)*(100%+$V$5),0),-3)+ROUND(IF(U24="SI",SUMIF('C de C año anterior'!$B$8:$B$210,B24,'C de C año anterior'!$Q$8:$Q$210)*(100%+$V$5),0),-3) -> 0 | X24: =ROUND(IF(W24="SI",V24*$X$5,0),-3) -> 0 | Z24: =ROUND(IF(Y24="SI",V24*$Z$5,0),-3) -> 0 | AB24: =ROUND(IF(AA24="SI",V24*$AB$5,0),-3) -> 0 | AD24: =ROUND(IF(AC24="SI",V24*$AD$5,0),-3) -> 0 | AF24: =ROUND(IF(AE24="SI",V24*$AF$5,0),-3) -> 0 | AH24: =ROUND(IF(AG24="SI",V24*$AH$5,0),-3) -> 0 | AJ24: =IF(AI24="SI",V24*$AJ$5,0) -> 0 | AK24: =SUMIF('Otras Asesorías y Préstamos'!$B$7:$B$242,B24,'Otras Asesorías y Préstamos'!$F$7:$F$242) -> 0 | AL24: =SUMIF('Otras Asesorías y Préstamos'!$B$7:$B$242,B24,'Otras Asesorías y Préstamos'!$V$7:$V$242) -> 0 | AM24: =ROUND(SUM(V24:AK24),-4) -> 0
A25: =+A24+1 -> 17 | Q25: =+AL25 -> 0 | U25: SI | V25: =ROUND(IF(U25="SI",SUMIF('Facturas año anterior'!$B$8:$B$81,B25,'Facturas año anterior'!$V$8:$V$81)*(100%+$V$5),0),-3)+ROUND(IF(U25="SI",SUMIF('C de C año anterior'!$B$8:$B$210,B25,'C de C año anterior'!$Q$8:$Q$210)*(100%+$V$5),0),-3) -> 0 | X25: =ROUND(IF(W25="SI",V25*$X$5,0),-3) -> 0 | Z25: =ROUND(IF(Y25="SI",V25*$Z$5,0),-3) -> 0 | AB25: =ROUND(IF(AA25="SI",V25*$AB$5,0),-3) -> 0 | AD25: =ROUND(IF(AC25="SI",V25*$AD$5,0),-3) -> 0 | AF25: =ROUND(IF(AE25="SI",V25*$AF$5,0),-3) -> 0 | AH25: =ROUND(IF(AG25="SI",V25*$AH$5,0),-3) -> 0 | AI25: SI | AJ25: =IF(AI25="SI",V25*$AJ$5,0) -> 0 | AK25: =SUMIF('Otras Asesorías y Préstamos'!$B$7:$B$242,B25,'Otras Asesorías y Préstamos'!$F$7:$F$242) -> 0 | AL25: =SUMIF('Otras Asesorías y Préstamos'!$B$7:$B$242,B25,'Otras Asesorías y Préstamos'!$V$7:$V$242) -> 0 | AM25: =ROUND(SUM(V25:AK25),-4) -> 0
A26: =+A25+1 -> 18 | Q26: =+AL26 -> 0 | U26: SI | V26: =ROUND(IF(U26="SI",SUMIF('Facturas año anterior'!$B$8:$B$81,B26,'Facturas año anterior'!$V$8:$V$81)*(100%+$V$5),0),-3)+ROUND(IF(U26="SI",SUMIF('C de C año anterior'!$B$8:$B$210,B26,'C de C año anterior'!$Q$8:$Q$210)*(100%+$V$5),0),-3) -> 0 | X26: =ROUND(IF(W26="SI",V26*$X$5,0),-3) -> 0 | Z26: =ROUND(IF(Y26="SI",V26*$Z$5,0),-3) -> 0 | AB26: =ROUND(IF(AA26="SI",V26*$AB$5,0),-3) -> 0 | AD26: =ROUND(IF(AC26="SI",V26*$AD$5,0),-3) -> 0 | AF26: =ROUND(IF(AE26="SI",V26*$AF$5,0),-3) -> 0 | AH26: =ROUND(IF(AG26="SI",V26*$AH$5,0),-3) -> 0 | AJ26: =IF(AI26="SI",V26*$AJ$5,0) -> 0 | AK26: =SUMIF('Otras Asesorías y Préstamos'!$B$7:$B$242,B26,'Otras Asesorías y Préstamos'!$F$7:$F$242) -> 0 | AL26: =SUMIF('Otras Asesorías y Préstamos'!$B$7:$B$242,B26,'Otras Asesorías y Préstamos'!$V$7:$V$242) -> 0 | AM26: =ROUND(SUM(V26:AK26),-4) -> 0
A27: =+A26+1 -> 19 | Q27: =+AL27 -> 0 | U27: SI | V27: =ROUND(IF(U27="SI",SUMIF('Facturas año anterior'!$B$8:$B$81,B27,'Facturas año anterior'!$V$8:$V$81)*(100%+$V$5),0),-3)+ROUND(IF(U27="SI",SUMIF('C de C año anterior'!$B$8:$B$210,B27,'C de C año anterior'!$Q$8:$Q$210)*(100%+$V$5),0),-3) -> 0 | X27: =ROUND(IF(W27="SI",V27*$X$5,0),-3) -> 0 | Z27: =ROUND(IF(Y27="SI",V27*$Z$5,0),-3) -> 0 | AB27: =ROUND(IF(AA27="SI",V27*$AB$5,0),-3) -> 0 | AD27: =ROUND(IF(AC27="SI",V27*$AD$5,0),-3) -> 0 | AF27: =ROUND(IF(AE27="SI",V27*$AF$5,0),-3) -> 0 | AH27: =ROUND(IF(AG27="SI",V27*$AH$5,0),-3) -> 0 | AJ27: =IF(AI27="SI",V27*$AJ$5,0) -> 0 | AK27: =SUMIF('Otras Asesorías y Préstamos'!$B$7:$B$242,B27,'Otras Asesorías y Préstamos'!$F$7:$F$242) -> 0 | AL27: =SUMIF('Otras Asesorías y Préstamos'!$B$7:$B$242,B27,'Otras Asesorías y Préstamos'!$V$7:$V$242) -> 0 | AM27: =ROUND(SUM(V27:AK27),-4) -> 0
A28: =+A27+1 -> 20 | Q28: =+AL28 -> 0 | U28: SI | V28: =ROUND(IF(U28="SI",SUMIF('Facturas año anterior'!$B$8:$B$81,B28,'Facturas año anterior'!$V$8:$V$81)*(100%+$V$5),0),-3)+ROUND(IF(U28="SI",SUMIF('C de C año anterior'!$B$8:$B$210,B28,'C de C año anterior'!$Q$8:$Q$210)*(100%+$V$5),0),-3) -> 0 | X28: =ROUND(IF(W28="SI",V28*$X$5,0),-3) -> 0 | Z28: =ROUND(IF(Y28="SI",V28*$Z$5,0),-3) -> 0 | AB28: =ROUND(IF(AA28="SI",V28*$AB$5,0),-3) -> 0 | AD28: =ROUND(IF(AC28="SI",V28*$AD$5,0),-3) -> 0 | AF28: =ROUND(IF(AE28="SI",V28*$AF$5,0),-3) -> 0 | AH28: =ROUND(IF(AG28="SI",V28*$AH$5,0),-3) -> 0 | AJ28: =IF(AI28="SI",V28*$AJ$5,0) -> 0 | AK28: =SUMIF('Otras Asesorías y Préstamos'!$B$7:$B$242,B28,'Otras Asesorías y Préstamos'!$F$7:$F$242) -> 0 | AL28: =SUMIF('Otras Asesorías y Préstamos'!$B$7:$B$242,B28,'Otras Asesorías y Préstamos'!$V$7:$V$242) -> 0 | AM28: =ROUND(SUM(V28:AK28),-4) -> 0
A29: =+A28+1 -> 21 | Q29: =+AL29 -> 0 | U29: SI | V29: =ROUND(IF(U29="SI",SUMIF('Facturas año anterior'!$B$8:$B$81,B29,'Facturas año anterior'!$V$8:$V$81)*(100%+$V$5),0),-3)+ROUND(IF(U29="SI",SUMIF('C de C año anterior'!$B$8:$B$210,B29,'C de C año anterior'!$Q$8:$Q$210)*(100%+$V$5),0),-3) -> 0 | X29: =ROUND(IF(W29="SI",V29*$X$5,0),-3) -> 0 | Y29: SI | Z29: =ROUND(IF(Y29="SI",V29*$Z$5,0),-3) -> 0 | AB29: =ROUND(IF(AA29="SI",V29*$AB$5,0),-3) -> 0 | AD29: =ROUND(IF(AC29="SI",V29*$AD$5,0),-3) -> 0 | AF29: =ROUND(IF(AE29="SI",V29*$AF$5,0),-3) -> 0 | AH29: =ROUND(IF(AG29="SI",V29*$AH$5,0),-3) -> 0 | AJ29: =IF(AI29="SI",V29*$AJ$5,0) -> 0 | AK29: =SUMIF('Otras Asesorías y Préstamos'!$B$7:$B$242,B29,'Otras Asesorías y Préstamos'!$F$7:$F$242) -> 0 | AL29: =SUMIF('Otras Asesorías y Préstamos'!$B$7:$B$242,B29,'Otras Asesorías y Préstamos'!$V$7:$V$242) -> 0 | AM29: =ROUND(SUM(V29:AK29),-4) -> 0
A30: =+A29+1 -> 22 | Q30: =+AL30 -> 0 | U30: SI | V30: =ROUND(IF(U30="SI",SUMIF('Facturas año anterior'!$B$8:$B$81,B30,'Facturas año anterior'!$V$8:$V$81)*(100%+$V$5),0),-3)+ROUND(IF(U30="SI",SUMIF('C de C año anterior'!$B$8:$B$210,B30,'C de C año anterior'!$Q$8:$Q$210)*(100%+$V$5),0),-3) -> 0 | X30: =ROUND(IF(W30="SI",V30*$X$5,0),-3) -> 0 | Z30: =ROUND(IF(Y30="SI",V30*$Z$5,0),-3) -> 0 | AB30: =ROUND(IF(AA30="SI",V30*$AB$5,0),-3) -> 0 | AD30: =ROUND(IF(AC30="SI",V30*$AD$5,0),-3) -> 0 | AF30: =ROUND(IF(AE30="SI",V30*$AF$5,0),-3) -> 0 | AH30: =ROUND(IF(AG30="SI",V30*$AH$5,0),-3) -> 0 | AI30: SI | AJ30: =IF(AI30="SI",V30*$AJ$5,0) -> 0 | AK30: =SUMIF('Otras Asesorías y Préstamos'!$B$7:$B$242,B30,'Otras Asesorías y Préstamos'!$F$7:$F$242) -> 0 | AL30: =SUMIF('Otras Asesorías y Préstamos'!$B$7:$B$242,B30,'Otras Asesorías y Préstamos'!$V$7:$V$242) -> 0 | AM30: =ROUND(SUM(V30:AK30),-4) -> 0
A31: =+A30+1 -> 23 | Q31: =+AL31 -> 0 | U31: SI | V31: =ROUND(IF(U31="SI",SUMIF('Facturas año anterior'!$B$8:$B$81,B31,'Facturas año anterior'!$V$8:$V$81)*(100%+$V$5),0),-3)+ROUND(IF(U31="SI",SUMIF('C de C año anterior'!$B$8:$B$210,B31,'C de C año anterior'!$Q$8:$Q$210)*(100%+$V$5),0),-3) -> 0 | X31: =ROUND(IF(W31="SI",V31*$X$5,0),-3) -> 0 | Z31: =ROUND(IF(Y31="SI",V31*$Z$5,0),-3) -> 0 | AB31: =ROUND(IF(AA31="SI",V31*$AB$5,0),-3) -> 0 | AD31: =ROUND(IF(AC31="SI",V31*$AD$5,0),-3) -> 0 | AF31: =ROUND(IF(AE31="SI",V31*$AF$5,0),-3) -> 0 | AH31: =ROUND(IF(AG31="SI",V31*$AH$5,0),-3) -> 0 | AJ31: =IF(AI31="SI",V31*$AJ$5,0) -> 0 | AK31: =SUMIF('Otras Asesorías y Préstamos'!$B$7:$B$242,B31,'Otras Asesorías y Préstamos'!$F$7:$F$242) -> 0 | AL31: =SUMIF('Otras Asesorías y Préstamos'!$B$7:$B$242,B31,'Otras Asesorías y Préstamos'!$V$7:$V$242) -> 0 | AM31: =ROUND(SUM(V31:AK31),-4) -> 0
A32: =+A31+1 -> 24 | Q32: =+AL32 -> 0 | U32: NO | V32: =ROUND(IF(U32="SI",SUMIF('Facturas año anterior'!$B$8:$B$81,B32,'Facturas año anterior'!$V$8:$V$81)*(100%+$V$5),0),-3)+ROUND(IF(U32="SI",SUMIF('C de C año anterior'!$B$8:$B$210,B32,'C de C año anterior'!$Q$8:$Q$210)*(100%+$V$5),0),-3) -> 0 | X32: =ROUND(IF(W32="SI",V32*$X$5,0),-3) -> 0 | Z32: =ROUND(IF(Y32="SI",V32*$Z$5,0),-3) -> 0 | AB32: =ROUND(IF(AA32="SI",V32*$AB$5,0),-3) -> 0 | AD32: =ROUND(IF(AC32="SI",V32*$AD$5,0),-3) -> 0 | AF32: =ROUND(IF(AE32="SI",V32*$AF$5,0),-3) -> 0 | AH32: =ROUND(IF(AG32="SI",V32*$AH$5,0),-3) -> 0 | AJ32: =IF(AI32="SI",V32*$AJ$5,0) -> 0 | AK32: =SUMIF('Otras Asesorías y Préstamos'!$B$7:$B$242,B32,'Otras Asesorías y Préstamos'!$F$7:$F$242) -> 0 | AL32: =SUMIF('Otras Asesorías y Préstamos'!$B$7:$B$242,B32,'Otras Asesorías y Préstamos'!$V$7:$V$242) -> 0 | AM32: =ROUND(SUM(V32:AK32),-4) -> 0
A33: =+A32+1 -> 25 | Q33: =+AL33 -> 0 | U33: SI | V33: =ROUND(IF(U33="SI",SUMIF('Facturas año anterior'!$B$8:$B$81,B33,'Facturas año anterior'!$V$8:$V$81)*(100%+$V$5),0),-3)+ROUND(IF(U33="SI",SUMIF('C de C año anterior'!$B$8:$B$210,B33,'C de C año anterior'!$Q$8:$Q$210)*(100%+$V$5),0),-3) -> 0 | X33: =ROUND(IF(W33="SI",V33*$X$5,0),-3) -> 0 | Z33: =ROUND(IF(Y33="SI",V33*$Z$5,0),-3) -> 0 | AB33: =ROUND(IF(AA33="SI",V33*$AB$5,0),-3) -> 0 | AD33: =ROUND(IF(AC33="SI",V33*$AD$5,0),-3) -> 0 | AF33: =ROUND(IF(AE33="SI",V33*$AF$5,0),-3) -> 0 | AH33: =ROUND(IF(AG33="SI",V33*$AH$5,0),-3) -> 0 | AJ33: =IF(AI33="SI",V33*$AJ$5,0) -> 0 | AK33: =SUMIF('Otras Asesorías y Préstamos'!$B$7:$B$242,B33,'Otras Asesorías y Préstamos'!$F$7:$F$242) -> 0 | AL33: =SUMIF('Otras Asesorías y Préstamos'!$B$7:$B$242,B33,'Otras Asesorías y Préstamos'!$V$7:$V$242) -> 0 | AM33: =ROUND(SUM(V33:AK33),-4) -> 0
A34: =+A33+1 -> 26 | U34: SI | V34: =ROUND(IF(U34="SI",SUMIF('Facturas año anterior'!$B$8:$B$81,B34,'Facturas año anterior'!$V$8:$V$81)*(100%+$V$5),0),-3)+ROUND(IF(U34="SI",SUMIF('C de C año anterior'!$B$8:$B$210,B34,'C de C año anterior'!$Q$8:$Q$210)*(100%+$V$5),0),-3) -> 0 | X34: =ROUND(IF(W34="SI",V34*$X$5,0),-3) -> 0 | Z34: =ROUND(IF(Y34="SI",V34*$Z$5,0),-3) -> 0 | AB34: =ROUND(IF(AA34="SI",V34*$AB$5,0),-3) -> 0 | AD34: =ROUND(IF(AC34="SI",V34*$AD$5,0),-3) -> 0 | AF34: =ROUND(IF(AE34="SI",V34*$AF$5,0),-3) -> 0 | AH34: =ROUND(IF(AG34="SI",V34*$AH$5,0),-3) -> 0 | AI34: SI | AJ34: =IF(AI34="SI",V34*$AJ$5,0) -> 0 | AK34: =SUMIF('Otras Asesorías y Préstamos'!$B$7:$B$242,B34,'Otras Asesorías y Préstamos'!$F$7:$F$242) -> 0 | AL34: =SUMIF('Otras Asesorías y Préstamos'!$B$7:$B$242,B34,'Otras Asesorías y Préstamos'!$V$7:$V$242) -> 0 | AM34: =ROUND(SUM(V34:AK34),-4) -> 0
A35: =+A34+1 -> 27 | Q35: =+AL35 -> 0 | U35: SI | V35: =ROUND(IF(U35="SI",SUMIF('Facturas año anterior'!$B$8:$B$81,B35,'Facturas año anterior'!$V$8:$V$81)*(100%+$V$5),0),-3)+ROUND(IF(U35="SI",SUMIF('C de C año anterior'!$B$8:$B$210,B35,'C de C año anterior'!$Q$8:$Q$210)*(100%+$V$5),0),-3) -> 0 | X35: =ROUND(IF(W35="SI",V35*$X$5,0),-3) -> 0 | Z35: =ROUND(IF(Y35="SI",V35*$Z$5,0),-3) -> 0 | AB35: =ROUND(IF(AA35="SI",V35*$AB$5,0),-3) -> 0 | AD35: =ROUND(IF(AC35="SI",V35*$AD$5,0),-3) -> 0 | AF35: =ROUND(IF(AE35="SI",V35*$AF$5,0),-3) -> 0 | AH35: =ROUND(IF(AG35="SI",V35*$AH$5,0),-3) -> 0 | AJ35: =IF(AI35="SI",V35*$AJ$5,0) -> 0 | AK35: =SUMIF('Otras Asesorías y Préstamos'!$B$7:$B$242,B35,'Otras Asesorías y Préstamos'!$F$7:$F$242) -> 0 | AL35: =SUMIF('Otras Asesorías y Préstamos'!$B$7:$B$242,B35,'Otras Asesorías y Préstamos'!$V$7:$V$242) -> 0 | AM35: =ROUND(SUM(V35:AK35),-4) -> 0
A36: =+A35+1 -> 28 | Q36: =+AL36 -> 0 | U36: SI | V36: =ROUND(IF(U36="SI",SUMIF('Facturas año anterior'!$B$8:$B$81,B36,'Facturas año anterior'!$V$8:$V$81)*(100%+$V$5),0),-3)+ROUND(IF(U36="SI",SUMIF('C de C año anterior'!$B$8:$B$210,B36,'C de C año anterior'!$Q$8:$Q$210)*(100%+$V$5),0),-3) -> 0 | X36: =ROUND(IF(W36="SI",V36*$X$5,0),-3) -> 0 | Z36: =ROUND(IF(Y36="SI",V36*$Z$5,0),-3) -> 0 | AB36: =ROUND(IF(AA36="SI",V36*$AB$5,0),-3) -> 0 | AD36: =ROUND(IF(AC36="SI",V36*$AD$5,0),-3) -> 0 | AF36: =ROUND(IF(AE36="SI",V36*$AF$5,0),-3) -> 0 | AH36: =ROUND(IF(AG36="SI",V36*$AH$5,0),-3) -> 0 | AJ36: =IF(AI36="SI",V36*$AJ$5,0) -> 0 | AK36: =SUMIF('Otras Asesorías y Préstamos'!$B$7:$B$242,B36,'Otras Asesorías y Préstamos'!$F$7:$F$242) -> 0 | AL36: =SUMIF('Otras Asesorías y Préstamos'!$B$7:$B$242,B36,'Otras Asesorías y Préstamos'!$V$7:$V$242) -> 0 | AM36: =ROUND(SUM(V36:AK36),-4) -> 0
A37: =+A36+1 -> 29 | Q37: =+AL37 -> 0 | U37: SI | V37: =ROUND(IF(U37="SI",SUMIF('Facturas año anterior'!$B$8:$B$81,B37,'Facturas año anterior'!$V$8:$V$81)*(100%+$V$5),0),-3)+ROUND(IF(U37="SI",SUMIF('C de C año anterior'!$B$8:$B$210,B37,'C de C año anterior'!$Q$8:$Q$210)*(100%+$V$5),0),-3) -> 0 | X37: =ROUND(IF(W37="SI",V37*$X$5,0),-3) -> 0 | Z37: =ROUND(IF(Y37="SI",V37*$Z$5,0),-3) -> 0 | AB37: =ROUND(IF(AA37="SI",V37*$AB$5,0),-3) -> 0 | AD37: =ROUND(IF(AC37="SI",V37*$AD$5,0),-3) -> 0 | AF37: =ROUND(IF(AE37="SI",V37*$AF$5,0),-3) -> 0 | AH37: =ROUND(IF(AG37="SI",V37*$AH$5,0),-3) -> 0 | AJ37: =IF(AI37="SI",V37*$AJ$5,0) -> 0 | AK37: =SUMIF('Otras Asesorías y Préstamos'!$B$7:$B$242,B37,'Otras Asesorías y Préstamos'!$F$7:$F$242) -> 0 | AL37: =SUMIF('Otras Asesorías y Préstamos'!$B$7:$B$242,B37,'Otras Asesorías y Préstamos'!$V$7:$V$242) -> 0 | AM37: =ROUND(SUM(V37:AK37),-4) -> 0
V38: =ROUND(IF(U38="SI",SUMIF('Facturas año anterior'!$B$8:$B$81,B38,'Facturas año anterior'!$V$8:$V$81)*(100%+$V$5),0),-3)+ROUND(IF(U38="SI",SUMIF('C de C año anterior'!$B$8:$B$210,B38,'C de C año anterior'!$F$8:$F$210)*(100%+$V$5),0),-3) -> 0 | X38: =ROUND(IF(W38="SI",V38*$X$5,0),-3) -> 0 | Z38: =ROUND(IF(Y38="SI",V38*$Z$5,0),-3) -> 0 | AB38: =ROUND(IF(AA38="SI",V38*$AB$5,0),-3) -> 0 | AD38: =ROUND(IF(AC38="SI",V38*$AD$5,0),-3) -> 0 | AF38: =ROUND(IF(AE38="SI",V38*$AF$5,0),-3) -> 0 | AH38: =ROUND(IF(AG38="SI",V38*$AH$5,0),-3) -> 0 | AJ38: =IF(AI38="SI",V38*$AJ$5,0) -> 0 | AK38: =SUMIF('Otras Asesorías y Préstamos'!$B$7:$B$242,B38,'Otras Asesorías y Préstamos'!$F$7:$F$242) -> 0 | AL38: =SUMIF('Otras Asesorías y Préstamos'!$B$7:$B$242,B38,'Otras Asesorías y Préstamos'!$V$7:$V$242) -> 0 | AM38: =ROUND(SUM(V38:AK38),-4) -> 0
V39: =ROUND(IF(U39="SI",SUMIF('Facturas año anterior'!$B$8:$B$81,B39,'Facturas año anterior'!$V$8:$V$81)*(100%+$V$5),0),-3)+ROUND(IF(U39="SI",SUMIF('C de C año anterior'!$B$8:$B$210,B39,'C de C año anterior'!$F$8:$F$210)*(100%+$V$5),0),-3) -> 0 | X39: =ROUND(IF(W39="SI",V39*$X$5,0),-3) -> 0 | Z39: =ROUND(IF(Y39="SI",V39*$Z$5,0),-3) -> 0 | AB39: =ROUND(IF(AA39="SI",V39*$AB$5,0),-3) -> 0 | AD39: =ROUND(IF(AC39="SI",V39*$AD$5,0),-3) -> 0 | AF39: =ROUND(IF(AE39="SI",V39*$AF$5,0),-3) -> 0 | AH39: =ROUND(IF(AG39="SI",V39*$AH$5,0),-3) -> 0 | AJ39: =IF(AI39="SI",V39*$AJ$5,0) -> 0 | AK39: =SUMIF('Otras Asesorías y Préstamos'!$B$7:$B$242,B39,'Otras Asesorías y Préstamos'!$F$7:$F$242) -> 0 | AL39: =SUMIF('Otras Asesorías y Préstamos'!$B$7:$B$242,B39,'Otras Asesorías y Préstamos'!$V$7:$V$242) -> 0 | AM39: =ROUND(SUM(V39:AK39),-4) -> 0
V40: =ROUND(IF(U40="SI",SUMIF('Facturas año anterior'!$B$8:$B$81,B40,'Facturas año anterior'!$V$8:$V$81)*(100%+$V$5),0),-3)+ROUND(IF(U40="SI",SUMIF('C de C año anterior'!$B$8:$B$210,B40,'C de C año anterior'!$F$8:$F$210)*(100%+$V$5),0),-3) -> 0 | X40: =ROUND(IF(W40="SI",V40*$X$5,0),-3) -> 0 | Z40: =ROUND(IF(Y40="SI",V40*$Z$5,0),-3) -> 0 | AB40: =ROUND(IF(AA40="SI",V40*$AB$5,0),-3) -> 0 | AD40: =ROUND(IF(AC40="SI",V40*$AD$5,0),-3) -> 0 | AF40: =ROUND(IF(AE40="SI",V40*$AF$5,0),-3) -> 0 | AH40: =ROUND(IF(AG40="SI",V40*$AH$5,0),-3) -> 0 | AJ40: =IF(AI40="SI",V40*$AJ$5,0) -> 0 | AK40: =SUMIF('Otras Asesorías y Préstamos'!$B$7:$B$242,B40,'Otras Asesorías y Préstamos'!$F$7:$F$242) -> 0 | AL40: =SUMIF('Otras Asesorías y Préstamos'!$B$7:$B$242,B40,'Otras Asesorías y Préstamos'!$V$7:$V$242) -> 0 | AM40: =ROUND(SUM(V40:AK40),-4) -> 0
V41: =ROUND(IF(U41="SI",SUMIF('Facturas año anterior'!$B$8:$B$81,B41,'Facturas año anterior'!$V$8:$V$81)*(100%+$V$5),0),-3)+ROUND(IF(U41="SI",SUMIF('C de C año anterior'!$B$8:$B$210,B41,'C de C año anterior'!$F$8:$F$210)*(100%+$V$5),0),-3) -> 0 | X41: =ROUND(IF(W41="SI",V41*$X$5,0),-3) -> 0 | Z41: =ROUND(IF(Y41="SI",V41*$Z$5,0),-3) -> 0 | AB41: =ROUND(IF(AA41="SI",V41*$AB$5,0),-3) -> 0 | AD41: =ROUND(IF(AC41="SI",V41*$AD$5,0),-3) -> 0 | AF41: =ROUND(IF(AE41="SI",V41*$AF$5,0),-3) -> 0 | AH41: =ROUND(IF(AG41="SI",V41*$AH$5,0),-3) -> 0 | AJ41: =IF(AI41="SI",V41*$AJ$5,0) -> 0 | AK41: =SUMIF('Otras Asesorías y Préstamos'!$B$7:$B$242,B41,'Otras Asesorías y Préstamos'!$F$7:$F$242) -> 0 | AL41: =SUMIF('Otras Asesorías y Préstamos'!$B$7:$B$242,B41,'Otras Asesorías y Préstamos'!$V$7:$V$242) -> 0 | AM41: =ROUND(SUM(V41:AK41),-4) -> 0
V42: =ROUND(IF(U42="SI",SUMIF('Facturas año anterior'!$B$8:$B$81,B42,'Facturas año anterior'!$V$8:$V$81)*(100%+$V$5),0),-3)+ROUND(IF(U42="SI",SUMIF('C de C año anterior'!$B$8:$B$210,B42,'C de C año anterior'!$F$8:$F$210)*(100%+$V$5),0),-3) -> 0 | X42: =ROUND(IF(W42="SI",V42*$X$5,0),-3) -> 0 | Z42: =ROUND(IF(Y42="SI",V42*$Z$5,0),-3) -> 0 | AB42: =ROUND(IF(AA42="SI",V42*$AB$5,0),-3) -> 0 | AD42: =ROUND(IF(AC42="SI",V42*$AD$5,0),-3) -> 0 | AF42: =ROUND(IF(AE42="SI",V42*$AF$5,0),-3) -> 0 | AH42: =ROUND(IF(AG42="SI",V42*$AH$5,0),-3) -> 0 | AJ42: =IF(AI42="SI",V42*$AJ$5,0) -> 0 | AK42: =SUMIF('Otras Asesorías y Préstamos'!$B$7:$B$242,B42,'Otras Asesorías y Préstamos'!$F$7:$F$242) -> 0 | AL42: =SUMIF('Otras Asesorías y Préstamos'!$B$7:$B$242,B42,'Otras Asesorías y Préstamos'!$V$7:$V$242) -> 0 | AM42: =ROUND(SUM(V42:AK42),-4) -> 0
V43: =ROUND(IF(U43="SI",SUMIF('Facturas año anterior'!$B$8:$B$81,B43,'Facturas año anterior'!$V$8:$V$81)*(100%+$V$5),0),-3)+ROUND(IF(U43="SI",SUMIF('C de C año anterior'!$B$8:$B$210,B43,'C de C año anterior'!$F$8:$F$210)*(100%+$V$5),0),-3) -> 0 | X43: =ROUND(IF(W43="SI",V43*$X$5,0),-3) -> 0 | Z43: =ROUND(IF(Y43="SI",V43*$Z$5,0),-3) -> 0 | AB43: =ROUND(IF(AA43="SI",V43*$AB$5,0),-3) -> 0 | AD43: =ROUND(IF(AC43="SI",V43*$AD$5,0),-3) -> 0 | AF43: =ROUND(IF(AE43="SI",V43*$AF$5,0),-3) -> 0 | AH43: =ROUND(IF(AG43="SI",V43*$AH$5,0),-3) -> 0 | AJ43: =IF(AI43="SI",V43*$AJ$5,0) -> 0 | AK43: =SUMIF('Otras Asesorías y Préstamos'!$B$7:$B$242,B43,'Otras Asesorías y Préstamos'!$F$7:$F$242) -> 0 | AL43: =SUMIF('Otras Asesorías y Préstamos'!$B$7:$B$242,B43,'Otras Asesorías y Préstamos'!$V$7:$V$242) -> 0 | AM43: =ROUND(SUM(V43:AK43),-4) -> 0
V44: =ROUND(IF(U44="SI",SUMIF('Facturas año anterior'!$B$8:$B$81,B44,'Facturas año anterior'!$V$8:$V$81)*(100%+$V$5),0),-3)+ROUND(IF(U44="SI",SUMIF('C de C año anterior'!$B$8:$B$210,B44,'C de C año anterior'!$F$8:$F$210)*(100%+$V$5),0),-3) -> 0 | X44: =ROUND(IF(W44="SI",V44*$X$5,0),-3) -> 0 | Z44: =ROUND(IF(Y44="SI",V44*$Z$5,0),-3) -> 0 | AB44: =ROUND(IF(AA44="SI",V44*$AB$5,0),-3) -> 0 | AD44: =ROUND(IF(AC44="SI",V44*$AD$5,0),-3) -> 0 | AF44: =ROUND(IF(AE44="SI",V44*$AF$5,0),-3) -> 0 | AH44: =ROUND(IF(AG44="SI",V44*$AH$5,0),-3) -> 0 | AJ44: =IF(AI44="SI",V44*$AJ$5,0) -> 0 | AK44: =SUMIF('Otras Asesorías y Préstamos'!$B$7:$B$242,B44,'Otras Asesorías y Préstamos'!$F$7:$F$242) -> 0 | AL44: =SUMIF('Otras Asesorías y Préstamos'!$B$7:$B$242,B44,'Otras Asesorías y Préstamos'!$V$7:$V$242) -> 0 | AM44: =ROUND(SUM(V44:AK44),-4) -> 0
V45: =ROUND(IF(U45="SI",SUMIF('Facturas año anterior'!$B$8:$B$81,B45,'Facturas año anterior'!$V$8:$V$81)*(100%+$V$5),0),-3)+ROUND(IF(U45="SI",SUMIF('C de C año anterior'!$B$8:$B$210,B45,'C de C año anterior'!$F$8:$F$210)*(100%+$V$5),0),-3) -> 0 | X45: =ROUND(IF(W45="SI",V45*$X$5,0),-3) -> 0 | Z45: =ROUND(IF(Y45="SI",V45*$Z$5,0),-3) -> 0 | AB45: =ROUND(IF(AA45="SI",V45*$AB$5,0),-3) -> 0 | AD45: =ROUND(IF(AC45="SI",V45*$AD$5,0),-3) -> 0 | AF45: =ROUND(IF(AE45="SI",V45*$AF$5,0),-3) -> 0 | AH45: =ROUND(IF(AG45="SI",V45*$AH$5,0),-3) -> 0 | AJ45: =IF(AI45="SI",V45*$AJ$5,0) -> 0 | AK45: =SUMIF('Otras Asesorías y Préstamos'!$B$7:$B$242,B45,'Otras Asesorías y Préstamos'!$F$7:$F$242) -> 0 | AL45: =SUMIF('Otras Asesorías y Préstamos'!$B$7:$B$242,B45,'Otras Asesorías y Préstamos'!$V$7:$V$242) -> 0 | AM45: =ROUND(SUM(V45:AK45),-4) -> 0
V46: =ROUND(IF(U46="SI",SUMIF('Facturas año anterior'!$B$8:$B$81,B46,'Facturas año anterior'!$V$8:$V$81)*(100%+$V$5),0),-3)+ROUND(IF(U46="SI",SUMIF('C de C año anterior'!$B$8:$B$210,B46,'C de C año anterior'!$F$8:$F$210)*(100%+$V$5),0),-3) -> 0 | X46: =ROUND(IF(W46="SI",V46*$X$5,0),-3) -> 0 | Z46: =ROUND(IF(Y46="SI",V46*$Z$5,0),-3) -> 0 | AB46: =ROUND(IF(AA46="SI",V46*$AB$5,0),-3) -> 0 | AD46: =ROUND(IF(AC46="SI",V46*$AD$5,0),-3) -> 0 | AF46: =ROUND(IF(AE46="SI",V46*$AF$5,0),-3) -> 0 | AH46: =ROUND(IF(AG46="SI",V46*$AH$5,0),-3) -> 0 | AJ46: =IF(AI46="SI",V46*$AJ$5,0) -> 0 | AK46: =SUMIF('Otras Asesorías y Préstamos'!$B$7:$B$242,B46,'Otras Asesorías y Préstamos'!$F$7:$F$242) -> 0 | AL46: =SUMIF('Otras Asesorías y Préstamos'!$B$7:$B$242,B46,'Otras Asesorías y Préstamos'!$V$7:$V$242) -> 0 | AM46: =ROUND(SUM(V46:AK46),-4) -> 0
A49: TOTAL PERSONAS NATURALES | F49: =SUM(F9:F47) -> 12810000 | G49: =SUM(G9:G47) -> 2433900 | I49: =SUM(I9:I47) -> -1299100 | J49: =SUM(J9:J47) -> 15243900 | K49: =SUM(K9:K47) -> 13944800 | V49: =SUM(V9:V47) -> 10448000 | X49: =SUM(X9:X47) -> 664000 | Z49: =SUM(Z9:Z47) -> 996000 | AB49: =SUM(AB9:AB47) -> 0 | AD49: =SUM(AD9:AD47) -> 0 | AF49: =SUM(AF9:AF47) -> 0 | AH49: =SUM(AH9:AH47) -> 0 | AJ49: =SUM(AJ9:AJ47) -> 231900 | AK49: =SUM(AK9:AK47) -> 484948.68 | AL49: =SUM(AL9:AL47) -> 0 | AM49: =SUM(AM9:AM47) -> 12810000
C51: =+A37 -> 29
A53: PERSONAS JURÍDICAS
V75: =ROUND(IF(U75="SI",SUMIF('Facturas año anterior'!$B$8:$B$81,B75,'Facturas año anterior'!$V$8:$V$81)*(100%+$V$5),0),-3)+ROUND(IF(U75="SI",SUMIF('C de C año anterior'!$B$8:$B$210,B75,'C de C año anterior'!$Q$8:$Q$210)*(100%+$V$5),0),-3) -> 0 | X75: =ROUND(IF(W75="SI",V75*$X$5,0),-3) -> 0 | Z75: =ROUND(IF(Y75="SI",V75*$Z$5,0),-3) -> 0 | AF75: =ROUND(IF(AE75="SI",V75*$AF$5,0),-3) -> 0 | AH75: =ROUND(IF(AG75="SI",V75*$AH$5,0),-3) -> 0 | AJ75: =IF(AI75="SI",V75*$AJ$5,0) -> 0 | AK75: =SUMIF('Otras Asesorías y Préstamos'!$B$7:$B$242,B75,'Otras Asesorías y Préstamos'!$F$7:$F$242) -> 0 | AL75: =SUMIF('Otras Asesorías y Préstamos'!$B$7:$B$242,B75,'Otras Asesorías y Préstamos'!$V$7:$V$242) -> 0 | AM75: =ROUND(SUM(V75:AK75),-3) -> 0
V76: =ROUND(IF(U76="SI",SUMIF('Facturas año anterior'!$B$8:$B$81,B76,'Facturas año anterior'!$V$8:$V$81)*(100%+$V$5),0),-3)+ROUND(IF(U76="SI",SUMIF('C de C año anterior'!$B$8:$B$210,B76,'C de C año anterior'!$Q$8:$Q$210)*(100%+$V$5),0),-3) -> 0 | X76: =ROUND(IF(W76="SI",V76*$X$5,0),-3) -> 0 | Z76: =ROUND(IF(Y76="SI",V76*$Z$5,0),-3) -> 0 | AF76: =ROUND(IF(AE76="SI",V76*$AF$5,0),-3) -> 0 | AH76: =ROUND(IF(AG76="SI",V76*$AH$5,0),-3) -> 0 | AJ76: =IF(AI76="SI",V76*$AJ$5,0) -> 0 | AK76: =SUMIF('Otras Asesorías y Préstamos'!$B$7:$B$242,B76,'Otras Asesorías y Préstamos'!$F$7:$F$242) -> 0 | AL76: =SUMIF('Otras Asesorías y Préstamos'!$B$7:$B$242,B76,'Otras Asesorías y Préstamos'!$V$7:$V$242) -> 0 | AM76: =ROUND(SUM(V76:AK76),-3) -> 0
V77: =ROUND(IF(U77="SI",SUMIF('Facturas año anterior'!$B$8:$B$81,B77,'Facturas año anterior'!$V$8:$V$81)*(100%+$V$5),0),-3)+ROUND(IF(U77="SI",SUMIF('C de C año anterior'!$B$8:$B$210,B77,'C de C año anterior'!$Q$8:$Q$210)*(100%+$V$5),0),-3) -> 0 | X77: =ROUND(IF(W77="SI",V77*$X$5,0),-3) -> 0 | Z77: =ROUND(IF(Y77="SI",V77*$Z$5,0),-3) -> 0 | AF77: =ROUND(IF(AE77="SI",V77*$AF$5,0),-3) -> 0 | AH77: =ROUND(IF(AG77="SI",V77*$AH$5,0),-3) -> 0 | AJ77: =IF(AI77="SI",V77*$AJ$5,0) -> 0 | AK77: =SUMIF('Otras Asesorías y Préstamos'!$B$7:$B$242,B77,'Otras Asesorías y Préstamos'!$F$7:$F$242) -> 0 | AL77: =SUMIF('Otras Asesorías y Préstamos'!$B$7:$B$242,B77,'Otras Asesorías y Préstamos'!$V$7:$V$242) -> 0 | AM77: =ROUND(SUM(V77:AK77),-3) -> 0
A80: TOTAL PERSONAS JURÍDICAS | F80: =SUM(F54:F77) -> 0 | G80: =SUM(G54:G77) -> 0 | I80: =SUM(I54:I77) -> 0 | J80: =SUM(J54:J77) -> 0 | K80: =SUM(K54:K77) -> 0 | V80: =SUM(V54:V77) -> 0 | X80: =SUM(X54:X77) -> 0 | Z80: =SUM(Z54:Z77) -> 0 | AB80: =SUM(AB54:AB77) -> 0 | AD80: =SUM(AD54:AD77) -> 0 | AF80: =SUM(AF54:AF77) -> 0 | AH80: =SUM(AH54:AH77) -> 0 | AJ80: =SUM(AJ54:AJ77) -> 0 | AK80: =SUM(AK54:AK77) -> 0 | AL80: =SUM(AL54:AL77) -> 0 | AM80: =SUM(AM54:AM77) -> 0
A82: ACUMULADO CLIENTES | C82: =+A38+A72 -> 0 | D82: =+C82+C51 -> 29 | F82: =F49+F80 -> 12810000 | G82: =G49+G80 -> 2433900 | I82: =I49+I80 -> -1299100 | J82: =J49+J80 -> 15243900 | K82: =K49+K80 -> 13944800 | M82: =M49+M80 -> 0 | V82: =V49+V80 -> 10448000 | X82: =X49+X80 -> 664000 | Z82: =Z49+Z80 -> 996000 | AB82: =AB49+AB80 -> 0 | AD82: =AD49+AD80 -> 0 | AF82: =AF49+AF80 -> 0 | AH82: =AH49+AH80 -> 0 | AJ82: =AJ49+AJ80 -> 231900 | AK82: =AK49+AK80 -> 484948.68 | AL82: =AL49+AL80 -> 0 | AM82: =AM49+AM80 -> 12810000

Sheet Cuentas de Cobro
A1: =+'Grupos Familiares'!$A$1 -> 0
A2: =+'Grupos Familiares'!$A$3 -> PRESUPUESTO DE COBROS | M2: Mínima Mvto | N2: Mínima 1° Vez | P2: PARA CALCULAR EL VALOR A COBRAR POR EL PRESENTE AÑO
A3: CUENTAS DE COBRO | D3: 42684082 | M3: =(+Facturas!Q3) -> 230000 | N3: =+Facturas!S3 -> 370000
A4: =+'Grupos Familiares'!$A$4 -> AÑO GRAVABLE 2024 | F4: VALORES CUENTAS DE COBRO 2023 | P4: PRESUPUESTOS DE COBRO: | T4: =+$A$3 -> CUENTAS DE COBRO
A5: PERSONAS NATURALES Y PERSONAS JURÍDICAS | P5: IPC | Q5: =+Facturas!V5 -> 0.052 | S5: 0.5 | U5: =75%+80%*0 -> 0.75 | W5: 0.15 | Y5: 0.2 | AA5: 0.1 | AC5: 0.2 | AE5: 0.3
A6: No. | B6: APELLIDOS Y NOMBRES o RAZÓN SOCIAL | C6: CÓDIGO | D6: NIT No. | E6: D. V. | F6: VALOR A ELABORAR LA CUENTA DE COBRO | G6: CUENTA DE COBRO No. | H6: ENVIADA | I6: FECHA ENVIO | J6: ESTADO DEL COBRO | K6: MEDIO DE PAGO | L6: FECHA DE PAGO | M6: OBSERVACIONES-1 | N6: OBSERVACIONES-2 | P6: SI o NO | Q6: VALOR DECLARACIÓN RENTA | R6: SI o NO | S6: VALOR DECLARACIÓN I AL P | T6: SI o NO | U6: VALOR MEDIOS MAGNÉTICOS | V6: SI o NO | W6: EXÓGENA MPIO MEDELLÍN | X6: SI o NO | Y6: REG ÚNICO de BENEFICIARIOS | Z6: SI o NO | AA6: VALOR FORMATO 2516 CONSERVAR | AB6: SI o NO | AC6: VALOR FORMATO 2516 TRANSMITIR | AD6: SI o NO | AE6: VALOR DECLARACIÓN ACTIVOS EN EL EXTERIOR | AF6: VALOR ASESORÍAS | AG6: VALOR PRÉSTAMOS | AH6: TOTAL PRESUPUESTADO
A8: PERSONAS NATURALES
A9: 1 | B9: NOMBRE 1 | C9: =_xlfn.XLOOKUP(B9,Códigos!$B$8:$B$406,Códigos!$A$8:$A$406,"Verificar",0) -> 41 | D9: =_xlfn.XLOOKUP(B9,'Consolidado Cobros'!$B$10:$B$268,'Consolidado Cobros'!$C$10:$C$268,"Verificar",0) -> 22126399 | E9: =IF((MOD((VALUE(MID(TEXT(D9,"000000000000000"),15,1))*3+VALUE(MID(TEXT(D9,"000000000000000"),14,1))*7+VALUE(MID(TEXT(D9,"000000000000000"),13,1))*13+VALUE(MID(TEXT(D9,"000000000000000"),12,1))*17+VALUE(MID(TEXT(D9,"000000000000000"),11,1))*19+VALUE(MID(TEXT(D9,"000000000000000"),10,1))*23+VALUE(MID(TEXT(D9,"000000000000000"),9,1))*29+VALUE(MID(TEXT(D9,"000000000000000"),8,1))*37+VALUE(MID(TEXT(D9,"000000000000000"),7,1))*41+VALUE(MID(TEXT(D9,"000000000000000"),6,1))*43+VALUE(MID(TEXT(D9,"000000000000000"),5,1))*47+VALUE(MID(TEXT(D9,"000000000000000"),4,1))*53+VALUE(MID(TEXT(D9,"000000000000000"),3,1))*59+VALUE(MID(TEXT(D9,"000000000000000"),2,1))*67+VALUE(MID(TEXT(D9,"000000000000000"),1,1))*71),11))=0,0,IF((MOD((VALUE(MID(TEXT(D9,"000000000000000"),15,1))*3+VALUE(MID(TEXT(D9,"000000000000000"),14,1))*7+VALUE(MID(TEXT(D9,"000000000000000"),13,1))*13+VALUE(MID(TEXT(D9,"000000000000000"),12,1))*17+VALUE(MID(TEXT(D9,"000000000000000"),11,1))*19+VALUE(MID(TEXT(D9,"000000000000000"),10,1))*23+VALUE(MID(TEXT(D9,"000000000000000"),9,1))*29+VALUE(MID(TEXT(D9,"000000000000000"),8,1))*37+VALUE(MID(TEXT(D9,"000000000000000"),7,1))*41+VALUE(MID(TEXT(D9,"000000000000000"),6,1))*43+VALUE(MID(TEXT(D9,"000000000000000"),5,1))*47+VALUE(MID(TEXT(D9,"000000000000000"),4,1))*53+VALUE(MID(TEXT(D9,"000000000000000"),3,1))*59+VALUE(MID(TEXT(D9,"000000000000000"),2,1))*67+VALUE(MID(TEXT(D9,"000000000000000"),1,1))*71),11))=1,1,11-(MOD((VALUE(MID(TEXT(D9,"000000000000000"),15,1))*3+VALUE(MID(TEXT(D9,"000000000000000"),14,1))*7+VALUE(MID(TEXT(D9,"000000000000000"),13,1))*13+VALUE(MID(TEXT(D9,"000000000000000"),12,1))*17+VALUE(MID(TEXT(D9,"000000000000000"),11,1))*19+VALUE(MID(TEXT(D9,"000000000000000"),10,1))*23+VALUE(MID(TEXT(D9,"000000000000000"),9,1))*29+VALUE(MID(TEXT(D9,"000000000000000"),8,1))*37+VALUE(MID(TEXT(D9,"000000000000000"),7,1))*41+VALUE(MID(TEXT(D9,"000000000000000"),6,1))*43+VALUE(MID(TEXT(D9,"000000000000000"),5,1))*47+VALUE(MID(TEXT(D9,"000000000000000"),4,1))*53+VALUE(MID(TEXT(D9,"000000000000000"),3,1))*59+VALUE(MID(TEXT(D9,"000000000000000"),2,1))*67+VALUE(MID(TEXT(D9,"000000000000000"),1,1))*71),11)))) -> 5 | F9: =+AH9 -> 900000 | G9: 25-118 | P9: SI | Q9: =ROUND(IF(P9="SI",SUMIF('C de C año anterior'!$B$8:$B$229,B9,'C de C año anterior'!$Q$8:$Q$229)*(100%+$Q$5),0),-3)+ROUND(IF(P9="SI",SUMIF('Facturas año anterior'!$B$8:$B$86,B9,'Facturas año anterior'!$V$8:$V$86)*(100%+$AA$5),0),-3) -> 895000 | S9: =ROUND(IF(R9="SI",Q9*$S$5,0),-3) -> 0 | U9: =ROUND(IF(T9="SI",Q9*$U$5,0),-3) -> 0 | W9: =ROUND(IF(V9="SI",Q9*$W$5,0),-3) -> 0 | Y9: =ROUND(IF(X9="SI",Q9*$Y$5,0),-3) -> 0 | AA9: =ROUND(IF(Z9="SI",Q9*$AA$5,0),-3) -> 0 | AC9: =ROUND(IF(AB9="SI",Q9*$AC$5,0),-3) -> 0 | AE9: =IF(AD9="SI",Q9*$AE$5,0) -> 0 | AF9: =SUMIF('Otras Asesorías y Préstamos'!$B$7:$B$242,B9,'Otras Asesorías y Préstamos'!$F$7:$F$242) -> 0 | AG9: =SUMIF('Otras Asesorías y Préstamos'!$B$7:$B$242,B9,'Otras Asesorías y Préstamos'!$V$7:$V$242) -> 0 | AH9: =ROUND(SUM(Q9:AG9),-4) -> 900000
A10: =+A9+1 -> 2 | B10: NOMBRE 2 | C10: =_xlfn.XLOOKUP(B10,Códigos!$B$8:$B$406,Códigos!$A$8:$A$406,"Verificar",0) -> 346 | D10: =_xlfn.XLOOKUP(B10,'Consolidado Cobros'!$B$10:$B$268,'Consolidado Cobros'!$C$10:$C$268,"Verificar",0) -> 71581755 | E10: =IF((MOD((VALUE(MID(TEXT(D10,"000000000000000"),15,1))*3+VALUE(MID(TEXT(D10,"000000000000000"),14,1))*7+VALUE(MID(TEXT(D10,"000000000000000"),13,1))*13+VALUE(MID(TEXT(D10,"000000000000000"),12,1))*17+VALUE(MID(TEXT(D10,"000000000000000"),11,1))*19+VALUE(MID(TEXT(D10,"000000000000000"),10,1))*23+VALUE(MID(TEXT(D10,"000000000000000"),9,1))*29+VALUE(MID(TEXT(D10,"000000000000000"),8,1))*37+VALUE(MID(TEXT(D10,"000000000000000"),7,1))*41+VALUE(MID(TEXT(D10,"000000000000000"),6,1))*43+VALUE(MID(TEXT(D10,"000000000000000"),5,1))*47+VALUE(MID(TEXT(D10,"000000000000000"),4,1))*53+VALUE(MID(TEXT(D10,"000000000000000"),3,1))*59+VALUE(MID(TEXT(D10,"000000000000000"),2,1))*67+VALUE(MID(TEXT(D10,"000000000000000"),1,1))*71),11))=0,0,IF((MOD((VALUE(MID(TEXT(D10,"000000000000000"),15,1))*3+VALUE(MID(TEXT(D10,"000000000000000"),14,1))*7+VALUE(MID(TEXT(D10,"000000000000000"),13,1))*13+VALUE(MID(TEXT(D10,"000000000000000"),12,1))*17+VALUE(MID(TEXT(D10,"000000000000000"),11,1))*19+VALUE(MID(TEXT(D10,"000000000000000"),10,1))*23+VALUE(MID(TEXT(D10,"000000000000000"),9,1))*29+VALUE(MID(TEXT(D10,"000000000000000"),8,1))*37+VALUE(MID(TEXT(D10,"000000000000000"),7,1))*41+VALUE(MID(TEXT(D10,"000000000000000"),6,1))*43+VALUE(MID(TEXT(D10,"000000000000000"),5,1))*47+VALUE(MID(TEXT(D10,"000000000000000"),4,1))*53+VALUE(MID(TEXT(D10,"000000000000000"),3,1))*59+VALUE(MID(TEXT(D10,"000000000000000"),2,1))*67+VALUE(MID(TEXT(D10,"000000000000000"),1,1))*71),11))=1,1,11-(MOD((VALUE(MID(TEXT(D10,"000000000000000"),15,1))*3+VALUE(MID(TEXT(D10,"000000000000000"),14,1))*7+VALUE(MID(TEXT(D10,"000000000000000"),13,1))*13+VALUE(MID(TEXT(D10,"000000000000000"),12,1))*17+VALUE(MID(TEXT(D10,"000000000000000"),11,1))*19+VALUE(MID(TEXT(D10,"000000000000000"),10,1))*23+VALUE(MID(TEXT(D10,"000000000000000"),9,1))*29+VALUE(MID(TEXT(D10,"000000000000000"),8,1))*37+VALUE(MID(TEXT(D10,"000000000000000"),7,1))*41+VALUE(MID(TEXT(D10,"000000000000000"),6,1))*43+VALUE(MID(TEXT(D10,"000000000000000"),5,1))*47+VALUE(MID(TEXT(D10,"000000000000000"),4,1))*53+VALUE(MID(TEXT(D10,"000000000000000"),3,1))*59+VALUE(MID(TEXT(D10,"000000000000000"),2,1))*67+VALUE(MID(TEXT(D10,"000000000000000"),1,1))*71),11)))) -> 2 | F10: =+AH10 -> 800000 | G10: 25-047 | J10: OK/ | K10: CONSIGNACIÓN | L10: 45922 | M10: Falta elaborar cuenta de cobro | P10: SI | Q10: =ROUND(IF(P10="SI",SUMIF('C de C año anterior'!$B$8:$B$229,B10,'C de C año anterior'!$Q$8:$Q$229)*(100%+$Q$5),0),-3)+ROUND(IF(P10="SI",SUMIF('Facturas año anterior'!$B$8:$B$86,B10,'Facturas año anterior'!$V$8:$V$86)*(100%+$AA$5),0),-3) -> 801000 | S10: =ROUND(IF(R10="SI",Q10*$S$5,0),-3) -> 0 | U10: =ROUND(IF(T10="SI",Q10*$U$5,0),-3) -> 0 | W10: =ROUND(IF(V10="SI",Q10*$W$5,0),-3) -> 0 | Y10: =ROUND(IF(X10="SI",Q10*$Y$5,0),-3) -> 0 | AA10: =ROUND(IF(Z10="SI",Q10*$AA$5,0),-3) -> 0 | AC10: =ROUND(IF(AB10="SI",Q10*$AC$5,0),-3) -> 0 | AE10: =IF(AD10="SI",Q10*$AE$5,0) -> 0 | AF10: =SUMIF('Otras Asesorías y Préstamos'!$B$7:$B$242,B10,'Otras Asesorías y Préstamos'!$F$7:$F$242) -> 0 | AG10: =SUMIF('Otras Asesorías y Préstamos'!$B$7:$B$242,B10,'Otras Asesorías y Préstamos'!$V$7:$V$242) -> 0 | AH10: =ROUND(SUM(Q10:AG10),-4) -> 800000
A11: =+A10+1 -> 3 | B11: NOMBRE 3 | C11: =_xlfn.XLOOKUP(B11,Códigos!$B$8:$B$406,Códigos!$A$8:$A$406,"Verificar",0) -> 300 | D11: =_xlfn.XLOOKUP(B11,'Consolidado Cobros'!$B$10:$B$268,'Consolidado Cobros'!$C$10:$C$268,"Verificar",0) -> 70116694 | E11: =IF((MOD((VALUE(MID(TEXT(D11,"000000000000000"),15,1))*3+VALUE(MID(TEXT(D11,"000000000000000"),14,1))*7+VALUE(MID(TEXT(D11,"000000000000000"),13,1))*13+VALUE(MID(TEXT(D11,"000000000000000"),12,1))*17+VALUE(MID(TEXT(D11,"000000000000000"),11,1))*19+VALUE(MID(TEXT(D11,"000000000000000"),10,1))*23+VALUE(MID(TEXT(D11,"000000000000000"),9,1))*29+VALUE(MID(TEXT(D11,"000000000000000"),8,1))*37+VALUE(MID(TEXT(D11,"000000000000000"),7,1))*41+VALUE(MID(TEXT(D11,"000000000000000"),6,1))*43+VALUE(MID(TEXT(D11,"000000000000000"),5,1))*47+VALUE(MID(TEXT(D11,"000000000000000"),4,1))*53+VALUE(MID(TEXT(D11,"000000000000000"),3,1))*59+VALUE(MID(TEXT(D11,"000000000000000"),2,1))*67+VALUE(MID(TEXT(D11,"000000000000000"),1,1))*71),11))=0,0,IF((MOD((VALUE(MID(TEXT(D11,"000000000000000"),15,1))*3+VALUE(MID(TEXT(D11,"000000000000000"),14,1))*7+VALUE(MID(TEXT(D11,"000000000000000"),13,1))*13+VALUE(MID(TEXT(D11,"000000000000000"),12,1))*17+VALUE(MID(TEXT(D11,"000000000000000"),11,1))*19+VALUE(MID(TEXT(D11,"000000000000000"),10,1))*23+VALUE(MID(TEXT(D11,"000000000000000"),9,1))*29+VALUE(MID(TEXT(D11,"000000000000000"),8,1))*37+VALUE(MID(TEXT(D11,"000000000000000"),7,1))*41+VALUE(MID(TEXT(D11,"000000000000000"),6,1))*43+VALUE(MID(TEXT(D11,"000000000000000"),5,1))*47+VALUE(MID(TEXT(D11,"000000000000000"),4,1))*53+VALUE(MID(TEXT(D11,"000000000000000"),3,1))*59+VALUE(MID(TEXT(D11,"000000000000000"),2,1))*67+VALUE(MID(TEXT(D11,"000000000000000"),1,1))*71),11))=1,1,11-(MOD((VALUE(MID(TEXT(D11,"000000000000000"),15,1))*3+VALUE(MID(TEXT(D11,"000000000000000"),14,1))*7+VALUE(MID(TEXT(D11,"000000000000000"),13,1))*13+VALUE(MID(TEXT(D11,"000000000000000"),12,1))*17+VALUE(MID(TEXT(D11,"000000000000000"),11,1))*19+VALUE(MID(TEXT(D11,"000000000000000"),10,1))*23+VALUE(MID(TEXT(D11,"000000000000000"),9,1))*29+VALUE(MID(TEXT(D11,"000000000000000"),8,1))*37+VALUE(MID(TEXT(D11,"000000000000000"),7,1))*41+VALUE(MID(TEXT(D11,"000000000000000"),6,1))*43+VALUE(MID(TEXT(D11,"000000000000000"),5,1))*47+VALUE(MID(TEXT(D11,"000000000000000"),4,1))*53+VALUE(MID(TEXT(D11,"000000000000000"),3,1))*59+VALUE(MID(TEXT(D11,"000000000000000"),2,1))*67+VALUE(MID(TEXT(D11,"000000000000000"),1,1))*71),11)))) -> 5 | F11: =+AH11 -> 1110000 | G11: 25-119 | P11: SI | Q11: =ROUND(IF(P11="SI",SUMIF('C de C año anterior'!$B$8:$B$229,B11,'C de C año anterior'!$Q$8:$Q$229)*(100%+$Q$5),0),-3)+ROUND(IF(P11="SI",SUMIF('Facturas año anterior'!$B$8:$B$86,B11,'Facturas año anterior'!$V$8:$V$86)*(100%+$AA$5),0),-3) -> 1111000 | S11: =ROUND(IF(R11="SI",Q11*$S$5,0),-3) -> 0 | U11: =ROUND(IF(T11="SI",Q11*$U$5,0),-3) -> 0 | W11: =ROUND(IF(V11="SI",Q11*$W$5,0),-3) -> 0 | Y11: =ROUND(IF(X11="SI",Q11*$Y$5,0),-3) -> 0 | AA11: =ROUND(IF(Z11="SI",Q11*$AA$5,0),-3) -> 0 | AC11: =ROUND(IF(AB11="SI",Q11*$AC$5,0),-3) -> 0 | AE11: =IF(AD11="SI",Q11*$AE$5,0) -> 0 | AF11: =SUMIF('Otras Asesorías y Préstamos'!$B$7:$B$242,B11,'Otras Asesorías y Préstamos'!$F$7:$F$242) -> 0 | AG11: =SUMIF('Otras Asesorías y Préstamos'!$B$7:$B$242,B11,'Otras Asesorías y Préstamos'!$V$7:$V$242) -> 0 | AH11: =ROUND(SUM(Q11:AG11),-4) -> 1110000
A12: =+A11+1 -> 4 | B12: NOMBRE 4 | C12: =_xlfn.XLOOKUP(B12,Códigos!$B$8:$B$406,Códigos!$A$8:$A$406,"Verificar",0) -> 312 | D12: =_xlfn.XLOOKUP(B12,'Consolidado Cobros'!$B$10:$B$268,'Consolidado Cobros'!$C$10:$C$268,"Verificar",0) -> 3349249 | E12: =IF((MOD((VALUE(MID(TEXT(D12,"000000000000000"),15,1))*3+VALUE(MID(TEXT(D12,"000000000000000"),14,1))*7+VALUE(MID(TEXT(D12,"000000000000000"),13,1))*13+VALUE(MID(TEXT(D12,"000000000000000"),12,1))*17+VALUE(MID(TEXT(D12,"000000000000000"),11,1))*19+VALUE(MID(TEXT(D12,"000000000000000"),10,1))*23+VALUE(MID(TEXT(D12,"000000000000000"),9,1))*29+VALUE(MID(TEXT(D12,"000000000000000"),8,1))*37+VALUE(MID(TEXT(D12,"000000000000000"),7,1))*41+VALUE(MID(TEXT(D12,"000000000000000"),6,1))*43+VALUE(MID(TEXT(D12,"000000000000000"),5,1))*47+VALUE(MID(TEXT(D12,"000000000000000"),4,1))*53+VALUE(MID(TEXT(D12,"000000000000000"),3,1))*59+VALUE(MID(TEXT(D12,"000000000000000"),2,1))*67+VALUE(MID(TEXT(D12,"000000000000000"),1,1))*71),11))=0,0,IF((MOD((VALUE(MID(TEXT(D12,"000000000000000"),15,1))*3+VALUE(MID(TEXT(D12,"000000000000000"),14,1))*7+VALUE(MID(TEXT(D12,"000000000000000"),13,1))*13+VALUE(MID(TEXT(D12,"000000000000000"),12,1))*17+VALUE(MID(TEXT(D12,"000000000000000"),11,1))*19+VALUE(MID(TEXT(D12,"000000000000000"),10,1))*23+VALUE(MID(TEXT(D12,"000000000000000"),9,1))*29+VALUE(MID(TEXT(D12,"000000000000000"),8,1))*37+VALUE(MID(TEXT(D12,"000000000000000"),7,1))*41+VALUE(MID(TEXT(D12,"000000000000000"),6,1))*43+VALUE(MID(TEXT(D12,"000000000000000"),5,1))*47+VALUE(MID(TEXT(D12,"000000000000000"),4,1))*53+VALUE(MID(TEXT(D12,"000000000000000"),3,1))*59+VALUE(MID(TEXT(D12,"000000000000000"),2,1))*67+VALUE(MID(TEXT(D12,"000000000000000"),1,1))*71),11))=1,1,11-(MOD((VALUE(MID(TEXT(D12,"000000000000000"),15,1))*3+VALUE(MID(TEXT(D12,"000000000000000"),14,1))*7+VALUE(MID(TEXT(D12,"000000000000000"),13,1))*13+VALUE(MID(TEXT(D12,"000000000000000"),12,1))*17+VALUE(MID(TEXT(D12,"000000000000000"),11,1))*19+VALUE(MID(TEXT(D12,"000000000000000"),10,1))*23+VALUE(MID(TEXT(D12,"000000000000000"),9,1))*29+VALUE(MID(TEXT(D12,"000000000000000"),8,1))*37+VALUE(MID(TEXT(D12,"000000000000000"),7,1))*41+VALUE(MID(TEXT(D12,"000000000000000"),6,1))*43+VALUE(MID(TEXT(D12,"000000000000000"),5,1))*47+VALUE(MID(TEXT(D12,"000000000000000"),4,1))*53+VALUE(MID(TEXT(D12,"000000000000000"),3,1))*59+VALUE(MID(TEXT(D12,"000000000000000"),2,1))*67+VALUE(MID(TEXT(D12,"000000000000000"),1,1))*71),11)))) -> 7 | F12: =+AH12 -> 1370000 | G12: 25-007 | M12: Se puede elaborar y enviar | P12: SI | Q12: =ROUND(IF(P12="SI",SUMIF('C de C año anterior'!$B$8:$B$229,B12,'C de C año anterior'!$Q$8:$Q$229)*(100%+$Q$5),0),-3)+ROUND(IF(P12="SI",SUMIF('Facturas año anterior'!$B$8:$B$86,B12,'Facturas año anterior'!$V$8:$V$86)*(100%+$AA$5),0),-3) -> 1374000 | S12: =ROUND(IF(R12="SI",Q12*$S$5,0),-3) -> 0 | U12: =ROUND(IF(T12="SI",Q12*$U$5,0),-3) -> 0 | W12: =ROUND(IF(V12="SI",Q12*$W$5,0),-3) -> 0 | Y12: =ROUND(IF(X12="SI",Q12*$Y$5,0),-3) -> 0 | AA12: =ROUND(IF(Z12="SI",Q12*$AA$5,0),-3) -> 0 | AC12: =ROUND(IF(AB12="SI",Q12*$AC$5,0),-3) -> 0 | AE12: =IF(AD12="SI",Q12*$AE$5,0) -> 0 | AF12: =SUMIF('Otras Asesorías y Préstamos'!$B$7:$B$242,B12,'Otras Asesorías y Préstamos'!$F$7:$F$242) -> 0 | AG12: =SUMIF('Otras Asesorías y Préstamos'!$B$7:$B$242,B12,'Otras Asesorías y Préstamos'!$V$7:$V$242) -> 0 | AH12: =ROUND(SUM(Q12:AG12),-4) -> 1370000
A13: =+A12+1 -> 5 | B13: NOMBRE 5 | C13: =_xlfn.XLOOKUP(B13,Códigos!$B$8:$B$406,Códigos!$A$8:$A$406,"Verificar",0) -> 217 | D13: =_xlfn.XLOOKUP(B13,'Consolidado Cobros'!$B$10:$B$268,'Consolidado Cobros'!$C$10:$C$268,"Verificar",0) -> 71632774 | E13: =IF((MOD((VALUE(MID(TEXT(D13,"000000000000000"),15,1))*3+VALUE(MID(TEXT(D13,"000000000000000"),14,1))*7+VALUE(MID(TEXT(D13,"000000000000000"),13,1))*13+VALUE(MID(TEXT(D13,"000000000000000"),12,1))*17+VALUE(MID(TEXT(D13,"000000000000000"),11,1))*19+VALUE(MID(TEXT(D13,"000000000000000"),10,1))*23+VALUE(MID(TEXT(D13,"000000000000000"),9,1))*29+VALUE(MID(TEXT(D13,"000000000000000"),8,1))*37+VALUE(MID(TEXT(D13,"000000000000000"),7,1))*41+VALUE(MID(TEXT(D13,"000000000000000"),6,1))*43+VALUE(MID(TEXT(D13,"000000000000000"),5,1))*47+VALUE(MID(TEXT(D13,"000000000000000"),4,1))*53+VALUE(MID(TEXT(D13,"000000000000000"),3,1))*59+VALUE(MID(TEXT(D13,"000000000000000"),2,1))*67+VALUE(MID(TEXT(D13,"000000000000000"),1,1))*71),11))=0,0,IF((MOD((VALUE(MID(TEXT(D13,"000000000000000"),15,1))*3+VALUE(MID(TEXT(D13,"000000000000000"),14,1))*7+VALUE(MID(TEXT(D13,"000000000000000"),13,1))*13+VALUE(MID(TEXT(D13,"000000000000000"),12,1))*17+VALUE(MID(TEXT(D13,"000000000000000"),11,1))*19+VALUE(MID(TEXT(D13,"000000000000000"),10,1))*23+VALUE(MID(TEXT(D13,"000000000000000"),9,1))*29+VALUE(MID(TEXT(D13,"000000000000000"),8,1))*37+VALUE(MID(TEXT(D13,"000000000000000"),7,1))*41+VALUE(MID(TEXT(D13,"000000000000000"),6,1))*43+VALUE(MID(TEXT(D13,"000000000000000"),5,1))*47+VALUE(MID(TEXT(D13,"000000000000000"),4,1))*53+VALUE(MID(TEXT(D13,"000000000000000"),3,1))*59+VALUE(MID(TEXT(D13,"000000000000000"),2,1))*67+VALUE(MID(TEXT(D13,"000000000000000"),1,1))*71),11))=1,1,11-(MOD((VALUE(MID(TEXT(D13,"000000000000000"),15,1))*3+VALUE(MID(TEXT(D13,"000000000000000"),14,1))*7+VALUE(MID(TEXT(D13,"000000000000000"),13,1))*13+VALUE(MID(TEXT(D13,"000000000000000"),12,1))*17+VALUE(MID(TEXT(D13,"000000000000000"),11,1))*19+VALUE(MID(TEXT(D13,"000000000000000"),10,1))*23+VALUE(MID(TEXT(D13,"000000000000000"),9,1))*29+VALUE(MID(TEXT(D13,"000000000000000"),8,1))*37+VALUE(MID(TEXT(D13,"000000000000000"),7,1))*41+VALUE(MID(TEXT(D13,"000000000000000"),6,1))*43+VALUE(MID(TEXT(D13,"000000000000000"),5,1))*47+VALUE(MID(TEXT(D13,"000000000000000"),4,1))*53+VALUE(MID(TEXT(D13,"000000000000000"),3,1))*59+VALUE(MID(TEXT(D13,"000000000000000"),2,1))*67+VALUE(MID(TEXT(D13,"000000000000000"),1,1))*71),11)))) -> 2 | F13: =+AH13 -> 2520000 | G13: 25-050 | H13: WhatsApp | I13: 45944 | P13: si | Q13: =ROUND(IF(P13="SI",SUMIF('C de C año anterior'!$B$8:$B$229,B13,'C de C año anterior'!$Q$8:$Q$229)*(100%+$Q$5),0),-3)+ROUND(IF(P13="SI",SUMIF('Facturas año anterior'!$B$8:$B$86,B13,'Facturas año anterior'!$V$8:$V$86)*(100%+$AA$5),0),-3) -> 2419000 | S13: =ROUND(IF(R13="SI",Q13*$S$5,0),-3) -> 0 | U13: =ROUND(IF(T13="SI",Q13*$U$5,0),-3) -> 0 | W13: =ROUND(IF(V13="SI",Q13*$W$5,0),-3) -> 0 | Y13: =ROUND(IF(X13="SI",Q13*$Y$5,0),-3) -> 0 | AA13: =ROUND(IF(Z13="SI",Q13*$AA$5,0),-3) -> 0 | AC13: =ROUND(IF(AB13="SI",Q13*$AC$5,0),-3) -> 0 | AE13: =IF(AD13="SI",Q13*$AE$5,0) -> 0 | AF13: =SUMIF('Otras Asesorías y Préstamos'!$B$7:$B$242,B13,'Otras Asesorías y Préstamos'!$F$7:$F$242) -> 100000 | AG13: =SUMIF('Otras Asesorías y Préstamos'!$B$7:$B$242,B13,'Otras Asesorías y Préstamos'!$V$7:$V$242) -> 0 | AH13: =ROUND(SUM(Q13:AG13),-4) -> 2520000
A14: =+A13+1 -> 6 | B14: NOMBRE 6 | C14: =_xlfn.XLOOKUP(B14,Códigos!$B$8:$B$406,Códigos!$A$8:$A$406,"Verificar",0) -> 42 | D14: =_xlfn.XLOOKUP(B14,'Consolidado Cobros'!$B$10:$B$268,'Consolidado Cobros'!$C$10:$C$268,"Verificar",0) -> 21315528 | E14: =IF((MOD((VALUE(MID(TEXT(D14,"000000000000000"),15,1))*3+VALUE(MID(TEXT(D14,"000000000000000"),14,1))*7+VALUE(MID(TEXT(D14,"000000000000000"),13,1))*13+VALUE(MID(TEXT(D14,"000000000000000"),12,1))*17+VALUE(MID(TEXT(D14,"000000000000000"),11,1))*19+VALUE(MID(TEXT(D14,"000000000000000"),10,1))*23+VALUE(MID(TEXT(D14,"000000000000000"),9,1))*29+VALUE(MID(TEXT(D14,"000000000000000"),8,1))*37+VALUE(MID(TEXT(D14,"000000000000000"),7,1))*41+VALUE(MID(TEXT(D14,"000000000000000"),6,1))*43+VALUE(MID(TEXT(D14,"000000000000000"),5,1))*47+VALUE(MID(TEXT(D14,"000000000000000"),4,1))*53+VALUE(MID(TEXT(D14,"000000000000000"),3,1))*59+VALUE(MID(TEXT(D14,"000000000000000"),2,1))*67+VALUE(MID(TEXT(D14,"000000000000000"),1,1))*71),11))=0,0,IF((MOD((VALUE(MID(TEXT(D14,"000000000000000"),15,1))*3+VALUE(MID(TEXT(D14,"000000000000000"),14,1))*7+VALUE(MID(TEXT(D14,"000000000000000"),13,1))*13+VALUE(MID(TEXT(D14,"000000000000000"),12,1))*17+VALUE(MID(TEXT(D14,"000000000000000"),11,1))*19+VALUE(MID(TEXT(D14,"000000000000000"),10,1))*23+VALUE(MID(TEXT(D14,"000000000000000"),9,1))*29+VALUE(MID(TEXT(D14,"000000000000000"),8,1))*37+VALUE(MID(TEXT(D14,"000000000000000"),7,1))*41+VALUE(MID(TEXT(D14,"000000000000000"),6,1))*43+VALUE(MID(TEXT(D14,"000000000000000"),5,1))*47+VALUE(MID(TEXT(D14,"000000000000000"),4,1))*53+VALUE(MID(TEXT(D14,"000000000000000"),3,1))*59+VALUE(MID(TEXT(D14,"000000000000000"),2,1))*67+VALUE(MID(TEXT(D14,"000000000000000"),1,1))*71),11))=1,1,11-(MOD((VALUE(MID(TEXT(D14,"000000000000000"),15,1))*3+VALUE(MID(TEXT(D14,"000000000000000"),14,1))*7+VALUE(MID(TEXT(D14,"000000000000000"),13,1))*13+VALUE(MID(TEXT(D14,"000000000000000"),12,1))*17+VALUE(MID(TEXT(D14,"000000000000000"),11,1))*19+VALUE(MID(TEXT(D14,"000000000000000"),10,1))*23+VALUE(MID(TEXT(D14,"000000000000000"),9,1))*29+VALUE(MID(TEXT(D14,"000000000000000"),8,1))*37+VALUE(MID(TEXT(D14,"000000000000000"),7,1))*41+VALUE(MID(TEXT(D14,"000000000000000"),6,1))*43+VALUE(MID(TEXT(D14,"000000000000000"),5,1))*47+VALUE(MID(TEXT(D14,"000000000000000"),4,1))*53+VALUE(MID(TEXT(D14,"000000000000000"),3,1))*59+VALUE(MID(TEXT(D14,"000000000000000"),2,1))*67+VALUE(MID(TEXT(D14,"000000000000000"),1,1))*71),11)))) -> 6 | F14: =+AH14 -> 2790000 | G14: 25-008 | M14: Se puede elaborar y enviar | P14: SI | Q14: =ROUND(IF(P14="SI",SUMIF('C de C año anterior'!$B$8:$B$229,B14,'C de C año anterior'!$Q$8:$Q$229)*(100%+$Q$5),0),-3)+ROUND(IF(P14="SI",SUMIF('Facturas año anterior'!$B$8:$B$86,B14,'Facturas año anterior'!$V$8:$V$86)*(100%+$AA$5),0),-3) -> 1858000 | R14: SI | S14: =ROUND(IF(R14="SI",Q14*$S$5,0),-3) -> 929000 | U14: =ROUND(IF(T14="SI",Q14*$U$5,0),-3) -> 0 | W14: =ROUND(IF(V14="SI",Q14*$W$5,0),-3) -> 0 | Y14: =ROUND(IF(X14="SI",Q14*$Y$5,0),-3) -> 0 | AA14: =ROUND(IF(Z14="SI",Q14*$AA$5,0),-3) -> 0 | AC14: =ROUND(IF(AB14="SI",Q14*$AC$5,0),-3) -> 0 | AE14: =IF(AD14="SI",Q14*$AE$5,0) -> 0 | AF14: =SUMIF('Otras Asesorías y Préstamos'!$B$7:$B$242,B14,'Otras Asesorías y Préstamos'!$F$7:$F$242) -> 0 | AG14: =SUMIF('Otras Asesorías y Préstamos'!$B$7:$B$242,B14,'Otras Asesorías y Préstamos'!$V$7:$V$242) -> 0 | AH14: =ROUND(SUM(Q14:AG14),-4) -> 2790000
A15: =+A14+1 -> 7 | B15: NOMBRE 7 | C15: =_xlfn.XLOOKUP(B15,Códigos!$B$8:$B$406,Códigos!$A$8:$A$406,"Verificar",0) -> 43 | D15: =_xlfn.XLOOKUP(B15,'Consolidado Cobros'!$B$10:$B$268,'Consolidado Cobros'!$C$10:$C$268,"Verificar",0) -> 32336950 | E15: =IF((MOD((VALUE(MID(TEXT(D15,"000000000000000"),15,1))*3+VALUE(MID(TEXT(D15,"000000000000000"),14,1))*7+VALUE(MID(TEXT(D15,"000000000000000"),13,1))*13+VALUE(MID(TEXT(D15,"000000000000000"),12,1))*17+VALUE(MID(TEXT(D15,"000000000000000"),11,1))*19+VALUE(MID(TEXT(D15,"000000000000000"),10,1))*23+VALUE(MID(TEXT(D15,"000000000000000"),9,1))*29+VALUE(MID(TEXT(D15,"000000000000000"),8,1))*37+VALUE(MID(TEXT(D15,"000000000000000"),7,1))*41+VALUE(MID(TEXT(D15,"000000000000000"),6,1))*43+VALUE(MID(TEXT(D15,"000000000000000"),5,1))*47+VALUE(MID(TEXT(D15,"000000000000000"),4,1))*53+VALUE(MID(TEXT(D15,"000000000000000"),3,1))*59+VALUE(MID(TEXT(D15,"000000000000000"),2,1))*67+VALUE(MID(TEXT(D15,"000000000000000"),1,1))*71),11))=0,0,IF((MOD((VALUE(MID(TEXT(D15,"000000000000000"),15,1))*3+VALUE(MID(TEXT(D15,"000000000000000"),14,1))*7+VALUE(MID(TEXT(D15,"000000000000000"),13,1))*13+VALUE(MID(TEXT(D15,"000000000000000"),12,1))*17+VALUE(MID(TEXT(D15,"000000000000000"),11,1))*19+VALUE(MID(TEXT(D15,"000000000000000"),10,1))*23+VALUE(MID(TEXT(D15,"000000000000000"),9,1))*29+VALUE(MID(TEXT(D15,"000000000000000"),8,1))*37+VALUE(MID(TEXT(D15,"000000000000000"),7,1))*41+VALUE(MID(TEXT(D15,"000000000000000"),6,1))*43+VALUE(MID(TEXT(D15,"000000000000000"),5,1))*47+VALUE(MID(TEXT(D15,"000000000000000"),4,1))*53+VALUE(MID(TEXT(D15,"000000000000000"),3,1))*59+VALUE(MID(TEXT(D15,"000000000000000"),2,1))*67+VALUE(MID(TEXT(D15,"000000000000000"),1,1))*71),11))=1,1,11-(MOD((VALUE(MID(TEXT(D15,"000000000000000"),15,1))*3+VALUE(MID(TEXT(D15,"000000000000000"),14,1))*7+VALUE(MID(TEXT(D15,"000000000000000"),13,1))*13+VALUE(MID(TEXT(D15,"000000000000000"),12,1))*17+VALUE(MID(TEXT(D15,"000000000000000"),11,1))*19+VALUE(MID(TEXT(D15,"000000000000000"),10,1))*23+VALUE(MID(TEXT(D15,"000000000000000"),9,1))*29+VALUE(MID(TEXT(D15,"000000000000000"),8,1))*37+VALUE(MID(TEXT(D15,"000000000000000"),7,1))*41+VALUE(MID(TEXT(D15,"000000000000000"),6,1))*43+VALUE(MID(TEXT(D15,"000000000000000"),5,1))*47+VALUE(MID(TEXT(D15,"000000000000000"),4,1))*53+VALUE(MID(TEXT(D15,"000000000000000"),3,1))*59+VALUE(MID(TEXT(D15,"000000000000000"),2,1))*67+VALUE(MID(TEXT(D15,"000000000000000"),1,1))*71),11)))) -> 1 | F15: =+AH15 -> 2460000 | G15: 25-009 | H15: WhatsApp | I15: 45944 | M15: Se puede elaborar y enviar | P15: SI | Q15: =ROUND(IF(P15="SI",SUMIF('C de C año anterior'!$B$8:$B$229,B15,'C de C año anterior'!$Q$8:$Q$229)*(100%+$Q$5),0),-3)+ROUND(IF(P15="SI",SUMIF('Facturas año anterior'!$B$8:$B$86,B15,'Facturas año anterior'!$V$8:$V$86)*(100%+$AA$5),0),-3) -> 2074000 | S15: =ROUND(IF(R15="SI",Q15*$S$5,0),-3) -> 0 | U15: =ROUND(IF(T15="SI",Q15*$U$5,0),-3) -> 0 | W15: =ROUND(IF(V15="SI",Q15*$W$5,0),-3) -> 0 | Y15: =ROUND(IF(X15="SI",Q15*$Y$5,0),-3) -> 0 | AA15: =ROUND(IF(Z15="SI",Q15*$AA$5,0),-3) -> 0 | AC15: =ROUND(IF(AB15="SI",Q15*$AC$5,0),-3) -> 0 | AE15: =IF(AD15="SI",Q15*$AE$5,0) -> 0 | AF15: =SUMIF('Otras Asesorías y Préstamos'!$B$7:$B$242,B15,'Otras Asesorías y Préstamos'!$F$7:$F$242) -> 384948.68 | AG15: =SUMIF('Otras Asesorías y Préstamos'!$B$7:$B$242,B15,'Otras Asesorías y Préstamos'!$V$7:$V$242) -> 0 | AH15: =ROUND(SUM(Q15:AG15),-4) -> 2460000
A16: =+A15+1 -> 8 | B16: NOMBRE 8 | C16: =_xlfn.XLOOKUP(B16,Códigos!$B$8:$B$406,Códigos!$A$8:$A$406,"Verificar",0) -> 44 | D16: =_xlfn.XLOOKUP(B16,'Consolidado Cobros'!$B$10:$B$268,'Consolidado Cobros'!$C$10:$C$268,"Verificar",0) -> 1152450831 | E16: =IF((MOD((VALUE(MID(TEXT(D16,"000000000000000"),15,1))*3+VALUE(MID(TEXT(D16,"000000000000000"),14,1))*7+VALUE(MID(TEXT(D16,"000000000000000"),13,1))*13+VALUE(MID(TEXT(D16,"000000000000000"),12,1))*17+VALUE(MID(TEXT(D16,"000000000000000"),11,1))*19+VALUE(MID(TEXT(D16,"000000000000000"),10,1))*23+VALUE(MID(TEXT(D16,"000000000000000"),9,1))*29+VALUE(MID(TEXT(D16,"000000000000000"),8,1))*37+VALUE(MID(TEXT(D16,"000000000000000"),7,1))*41+VALUE(MID(TEXT(D16,"000000000000000"),6,1))*43+VALUE(MID(TEXT(D16,"000000000000000"),5,1))*47+VALUE(MID(TEXT(D16,"000000000000000"),4,1))*53+VALUE(MID(TEXT(D16,"000000000000000"),3,1))*59+VALUE(MID(TEXT(D16,"000000000000000"),2,1))*67+VALUE(MID(TEXT(D16,"000000000000000"),1,1))*71),11))=0,0,IF((MOD((VALUE(MID(TEXT(D16,"000000000000000"),15,1))*3+VALUE(MID(TEXT(D16,"000000000000000"),14,1))*7+VALUE(MID(TEXT(D16,"000000000000000"),13,1))*13+VALUE(MID(TEXT(D16,"000000000000000"),12,1))*17+VALUE(MID(TEXT(D16,"000000000000000"),11,1))*19+VALUE(MID(TEXT(D16,"000000000000000"),10,1))*23+VALUE(MID(TEXT(D16,"000000000000000"),9,1))*29+VALUE(MID(TEXT(D16,"000000000000000"),8,1))*37+VALUE(MID(TEXT(D16,"000000000000000"),7,1))*41+VALUE(MID(TEXT(D16,"000000000000000"),6,1))*43+VALUE(MID(TEXT(D16,"000000000000000"),5,1))*47+VALUE(MID(TEXT(D16,"000000000000000"),4,1))*53+VALUE(MID(TEXT(D16,"000000000000000"),3,1))*59+VALUE(MID(TEXT(D16,"000000000000000"),2,1))*67+VALUE(MID(TEXT(D16,"000000000000000"),1,1))*71),11))=1,1,11-(MOD((VALUE(MID(TEXT(D16,"000000000000000"),15,1))*3+VALUE(MID(TEXT(D16,"000000000000000"),14,1))*7+VALUE(MID(TEXT(D16,"000000000000000"),13,1))*13+VALUE(MID(TEXT(D16,"000000000000000"),12,1))*17+VALUE(MID(TEXT(D16,"000000000000000"),11,1))*19+VALUE(MID(TEXT(D16,"000000000000000"),10,1))*23+VALUE(MID(TEXT(D16,"000000000000000"),9,1))*29+VALUE(MID(TEXT(D16,"000000000000000"),8,1))*37+VALUE(MID(TEXT(D16,"000000000000000"),7,1))*41+VALUE(MID(TEXT(D16,"000000000000000"),6,1))*43+VALUE(MID(TEXT(D16,"000000000000000"),5,1))*47+VALUE(MID(TEXT(D16,"000000000000000"),4,1))*53+VALUE(MID(TEXT(D16,"000000000000000"),3,1))*59+VALUE(MID(TEXT(D16,"000000000000000"),2,1))*67+VALUE(MID(TEXT(D16,"000000000000000"),1,1))*71),11)))) -> 7 | F16: =+AH16 -> 230000 | G16: 25-120 | P16: SI | Q16: =ROUND(IF(P16="SI",SUMIF('C de C año anterior'!$B$8:$B$229,B16,'C de C año anterior'!$Q$8:$Q$229)*(100%+$Q$5),0),-3)+ROUND(IF(P16="SI",SUMIF('Facturas año anterior'!$B$8:$B$86,B16,'Facturas año anterior'!$V$8:$V$86)*(100%+$AA$5),0),-3) -> 231000 | S16: =ROUND(IF(R16="SI",Q16*$S$5,0),-3) -> 0 | U16: =ROUND(IF(T16="SI",Q16*$U$5,0),-3) -> 0 | W16: =ROUND(IF(V16="SI",Q16*$W$5,0),-3) -> 0 | Y16: =ROUND(IF(X16="SI",Q16*$Y$5,0),-3) -> 0 | AA16: =ROUND(IF(Z16="SI",Q16*$AA$5,0),-3) -> 0 | AC16: =ROUND(IF(AB16="SI",Q16*$AC$5,0),-3) -> 0 | AE16: =IF(AD16="SI",Q16*$AE$5,0) -> 0 | AF16: =SUMIF('Otras Asesorías y Préstamos'!$B$7:$B$242,B16,'Otras Asesorías y Préstamos'!$F$7:$F$242) -> 0 | AG16: =SUMIF('Otras Asesorías y Préstamos'!$B$7:$B$242,B16,'Otras Asesorías y Préstamos'!$V$7:$V$242) -> 0 | AH16: =ROUND(SUM(Q16:AG16),-4) -> 230000
F178: =+AH178 -> 0 | Q178: =ROUND(IF(P178="SI",SUMIF('C de C año anterior'!$B$8:$B$229,B178,'C de C año anterior'!$Q$8:$Q$229)*(100%+$Q$5),0),-3)+ROUND(IF(P178="SI",SUMIF('Facturas año anterior'!$B$8:$B$86,B178,'Facturas año anterior'!$V$8:$V$86)*(100%+$AA$5),0),-3) -> 0 | S178: =ROUND(IF(R178="SI",Q178*$S$5,0),-3) -> 0 | U178: =ROUND(IF(T178="SI",Q178*$U$5,0),-3) -> 0 | W178: =ROUND(IF(V178="SI",Q178*$W$5,0),-3) -> 0 | Y178: =ROUND(IF(X178="SI",Q178*$Y$5,0),-3) -> 0 | AA178: =ROUND(IF(Z178="SI",Q178*$AA$5,0),-3) -> 0 | AC178: =ROUND(IF(AB178="SI",Q178*$AC$5,0),-3) -> 0 | AE178: =IF(AD178="SI",Q178*$AE$5,0) -> 0 | AF178: =SUMIF('Otras Asesorías y Préstamos'!$B$7:$B$242,B178,'Otras Asesorías y Préstamos'!$F$7:$F$242) -> 0 | AG178: =SUMIF('Otras Asesorías y Préstamos'!$B$7:$B$242,B178,'Otras Asesorías y Préstamos'!$V$7:$V$242) -> 0 | AH178: =ROUND(SUM(Q178:AG178),-4) -> 0
F179: =+AH179 -> 0 | Q179: =ROUND(IF(P179="SI",SUMIF('C de C año anterior'!$B$8:$B$229,B179,'C de C año anterior'!$Q$8:$Q$229)*(100%+$Q$5),0),-3)+ROUND(IF(P179="SI",SUMIF('Facturas año anterior'!$B$8:$B$86,B179,'Facturas año anterior'!$V$8:$V$86)*(100%+$AA$5),0),-3) -> 0 | S179: =ROUND(IF(R179="SI",Q179*$S$5,0),-3) -> 0 | U179: =ROUND(IF(T179="SI",Q179*$U$5,0),-3) -> 0 | W179: =ROUND(IF(V179="SI",Q179*$W$5,0),-3) -> 0 | Y179: =ROUND(IF(X179="SI",Q179*$Y$5,0),-3) -> 0 | AA179: =ROUND(IF(Z179="SI",Q179*$AA$5,0),-3) -> 0 | AC179: =ROUND(IF(AB179="SI",Q179*$AC$5,0),-3) -> 0 | AE179: =IF(AD179="SI",Q179*$AE$5,0) -> 0 | AF179: =SUMIF('Otras Asesorías y Préstamos'!$B$7:$B$242,B179,'Otras Asesorías y Préstamos'!$F$7:$F$242) -> 0 | AG179: =SUMIF('Otras Asesorías y Préstamos'!$B$7:$B$242,B179,'Otras Asesorías y Préstamos'!$V$7:$V$242) -> 0 | AH179: =ROUND(SUM(Q179:AG179),-4) -> 0
F180: =+AH180 -> 0 | Q180: =ROUND(IF(P180="SI",SUMIF('C de C año anterior'!$B$8:$B$229,B180,'C de C año anterior'!$Q$8:$Q$229)*(100%+$Q$5),0),-3)+ROUND(IF(P180="SI",SUMIF('Facturas año anterior'!$B$8:$B$86,B180,'Facturas año anterior'!$V$8:$V$86)*(100%+$AA$5),0),-3) -> 0 | S180: =ROUND(IF(R180="SI",Q180*$S$5,0),-3) -> 0 | U180: =ROUND(IF(T180="SI",Q180*$U$5,0),-3) -> 0 | W180: =ROUND(IF(V180="SI",Q180*$W$5,0),-3) -> 0 | Y180: =ROUND(IF(X180="SI",Q180*$Y$5,0),-3) -> 0 | AA180: =ROUND(IF(Z180="SI",Q180*$AA$5,0),-3) -> 0 | AC180: =ROUND(IF(AB180="SI",Q180*$AC$5,0),-3) -> 0 | AE180: =IF(AD180="SI",Q180*$AE$5,0) -> 0 | AF180: =SUMIF('Otras Asesorías y Préstamos'!$B$7:$B$242,B180,'Otras Asesorías y Préstamos'!$F$7:$F$242) -> 0 | AG180: =SUMIF('Otras Asesorías y Préstamos'!$B$7:$B$242,B180,'Otras Asesorías y Préstamos'!$V$7:$V$242) -> 0 | AH180: =ROUND(SUM(Q180:AG180),-4) -> 0
F181: =+AH181 -> 0 | Q181: =ROUND(IF(P181="SI",SUMIF('C de C año anterior'!$B$8:$B$229,B181,'C de C año anterior'!$Q$8:$Q$229)*(100%+$Q$5),0),-3)+ROUND(IF(P181="SI",SUMIF('Facturas año anterior'!$B$8:$B$86,B181,'Facturas año anterior'!$V$8:$V$86)*(100%+$AA$5),0),-3) -> 0 | S181: =ROUND(IF(R181="SI",Q181*$S$5,0),-3) -> 0 | U181: =ROUND(IF(T181="SI",Q181*$U$5,0),-3) -> 0 | W181: =ROUND(IF(V181="SI",Q181*$W$5,0),-3) -> 0 | Y181: =ROUND(IF(X181="SI",Q181*$Y$5,0),-3) -> 0 | AA181: =ROUND(IF(Z181="SI",Q181*$AA$5,0),-3) -> 0 | AC181: =ROUND(IF(AB181="SI",Q181*$AC$5,0),-3) -> 0 | AE181: =IF(AD181="SI",Q181*$AE$5,0) -> 0 | AF181: =SUMIF('Otras Asesorías y Préstamos'!$B$7:$B$242,B181,'Otras Asesorías y Préstamos'!$F$7:$F$242) -> 0 | AG181: =SUMIF('Otras Asesorías y Préstamos'!$B$7:$B$242,B181,'Otras Asesorías y Préstamos'!$V$7:$V$242) -> 0 | AH181: =ROUND(SUM(Q181:AG181),-4) -> 0
F182: =+AH182 -> 0 | Q182: =ROUND(IF(P182="SI",SUMIF('C de C año anterior'!$B$8:$B$229,B182,'C de C año anterior'!$Q$8:$Q$229)*(100%+$Q$5),0),-3)+ROUND(IF(P182="SI",SUMIF('Facturas año anterior'!$B$8:$B$86,B182,'Facturas año anterior'!$V$8:$V$86)*(100%+$AA$5),0),-3) -> 0 | S182: =ROUND(IF(R182="SI",Q182*$S$5,0),-3) -> 0 | U182: =ROUND(IF(T182="SI",Q182*$U$5,0),-3) -> 0 | W182: =ROUND(IF(V182="SI",Q182*$W$5,0),-3) -> 0 | Y182: =ROUND(IF(X182="SI",Q182*$Y$5,0),-3) -> 0 | AA182: =ROUND(IF(Z182="SI",Q182*$AA$5,0),-3) -> 0 | AC182: =ROUND(IF(AB182="SI",Q182*$AC$5,0),-3) -> 0 | AE182: =IF(AD182="SI",Q182*$AE$5,0) -> 0 | AF182: =SUMIF('Otras Asesorías y Préstamos'!$B$7:$B$242,B182,'Otras Asesorías y Préstamos'!$F$7:$F$242) -> 0 | AG182: =SUMIF('Otras Asesorías y Préstamos'!$B$7:$B$242,B182,'Otras Asesorías y Préstamos'!$V$7:$V$242) -> 0 | AH182: =ROUND(SUM(Q182:AG182),-4) -> 0
F183: =+AH183 -> 0 | Q183: =ROUND(IF(P183="SI",SUMIF('C de C año anterior'!$B$8:$B$229,B183,'C de C año anterior'!$Q$8:$Q$229)*(100%+$Q$5),0),-3)+ROUND(IF(P183="SI",SUMIF('Facturas año anterior'!$B$8:$B$86,B183,'Facturas año anterior'!$V$8:$V$86)*(100%+$AA$5),0),-3) -> 0 | S183: =ROUND(IF(R183="SI",Q183*$S$5,0),-3) -> 0 | U183: =ROUND(IF(T183="SI",Q183*$U$5,0),-3) -> 0 | W183: =ROUND(IF(V183="SI",Q183*$W$5,0),-3) -> 0 | Y183: =ROUND(IF(X183="SI",Q183*$Y$5,0),-3) -> 0 | AA183: =ROUND(IF(Z183="SI",Q183*$AA$5,0),-3) -> 0 | AC183: =ROUND(IF(AB183="SI",Q183*$AC$5,0),-3) -> 0 | AE183: =IF(AD183="SI",Q183*$AE$5,0) -> 0 | AF183: =SUMIF('Otras Asesorías y Préstamos'!$B$7:$B$242,B183,'Otras Asesorías y Préstamos'!$F$7:$F$242) -> 0 | AG183: =SUMIF('Otras Asesorías y Préstamos'!$B$7:$B$242,B183,'Otras Asesorías y Préstamos'!$V$7:$V$242) -> 0 | AH183: =ROUND(SUM(Q183:AG183),-4) -> 0
F184: =+AH184 -> 0 | Q184: =ROUND(IF(P184="SI",SUMIF('C de C año anterior'!$B$8:$B$229,B184,'C de C año anterior'!$Q$8:$Q$229)*(100%+$Q$5),0),-3)+ROUND(IF(P184="SI",SUMIF('Facturas año anterior'!$B$8:$B$86,B184,'Facturas año anterior'!$V$8:$V$86)*(100%+$AA$5),0),-3) -> 0 | S184: =ROUND(IF(R184="SI",Q184*$S$5,0),-3) -> 0 | U184: =ROUND(IF(T184="SI",Q184*$U$5,0),-3) -> 0 | W184: =ROUND(IF(V184="SI",Q184*$W$5,0),-3) -> 0 | Y184: =ROUND(IF(X184="SI",Q184*$Y$5,0),-3) -> 0 | AA184: =ROUND(IF(Z184="SI",Q184*$AA$5,0),-3) -> 0 | AC184: =ROUND(IF(AB184="SI",Q184*$AC$5,0),-3) -> 0 | AE184: =IF(AD184="SI",Q184*$AE$5,0) -> 0 | AF184: =SUMIF('Otras Asesorías y Préstamos'!$B$7:$B$242,B184,'Otras Asesorías y Préstamos'!$F$7:$F$242) -> 0 | AG184: =SUMIF('Otras Asesorías y Préstamos'!$B$7:$B$242,B184,'Otras Asesorías y Préstamos'!$V$7:$V$242) -> 0 | AH184: =ROUND(SUM(Q184:AG184),-4) -> 0
F185: =+AH185 -> 0 | Q185: =ROUND(IF(P185="SI",SUMIF('C de C año anterior'!$B$8:$B$229,B185,'C de C año anterior'!$Q$8:$Q$229)*(100%+$Q$5),0),-3)+ROUND(IF(P185="SI",SUMIF('Facturas año anterior'!$B$8:$B$86,B185,'Facturas año anterior'!$V$8:$V$86)*(100%+$AA$5),0),-3) -> 0 | S185: =ROUND(IF(R185="SI",Q185*$S$5,0),-3) -> 0 | U185: =ROUND(IF(T185="SI",Q185*$U$5,0),-3) -> 0 | W185: =ROUND(IF(V185="SI",Q185*$W$5,0),-3) -> 0 | Y185: =ROUND(IF(X185="SI",Q185*$Y$5,0),-3) -> 0 | AA185: =ROUND(IF(Z185="SI",Q185*$AA$5,0),-3) -> 0 | AC185: =ROUND(IF(AB185="SI",Q185*$AC$5,0),-3) -> 0 | AE185: =IF(AD185="SI",Q185*$AE$5,0) -> 0 | AF185: =SUMIF('Otras Asesorías y Préstamos'!$B$7:$B$242,B185,'Otras Asesorías y Préstamos'!$F$7:$F$242) -> 0 | AG185: =SUMIF('Otras Asesorías y Préstamos'!$B$7:$B$242,B185,'Otras Asesorías y Préstamos'!$V$7:$V$242) -> 0 | AH185: =ROUND(SUM(Q185:AG185),-4) -> 0
F186: =+AH186 -> 0 | Q186: =ROUND(IF(P186="SI",SUMIF('C de C año anterior'!$B$8:$B$229,B186,'C de C año anterior'!$Q$8:$Q$229)*(100%+$Q$5),0),-3)+ROUND(IF(P186="SI",SUMIF('Facturas año anterior'!$B$8:$B$86,B186,'Facturas año anterior'!$V$8:$V$86)*(100%+$AA$5),0),-3) -> 0 | S186: =ROUND(IF(R186="SI",Q186*$S$5,0),-3) -> 0 | U186: =ROUND(IF(T186="SI",Q186*$U$5,0),-3) -> 0 | W186: =ROUND(IF(V186="SI",Q186*$W$5,0),-3) -> 0 | Y186: =ROUND(IF(X186="SI",Q186*$Y$5,0),-3) -> 0 | AA186: =ROUND(IF(Z186="SI",Q186*$AA$5,0),-3) -> 0 | AC186: =ROUND(IF(AB186="SI",Q186*$AC$5,0),-3) -> 0 | AE186: =IF(AD186="SI",Q186*$AE$5,0) -> 0 | AF186: =SUMIF('Otras Asesorías y Préstamos'!$B$7:$B$242,B186,'Otras Asesorías y Préstamos'!$F$7:$F$242) -> 0 | AG186: =SUMIF('Otras Asesorías y Préstamos'!$B$7:$B$242,B186,'Otras Asesorías y Préstamos'!$V$7:$V$242) -> 0 | AH186: =ROUND(SUM(Q186:AG186),-4) -> 0
A189: TOTAL PERSONAS NATURALES | F189: =SUM(F9:F187) -> 12180000 | I189: =+F189 -> 12180000 | Q189: =SUM(Q9:Q187) -> 10763000 | S189: =SUM(S9:S187) -> 929000 | U189: =SUM(U9:U187) -> 0 | AA189: =SUM(AA9:AA187) -> 0 | AC189: =SUM(AC9:AC187) -> 0 | AE189: =SUM(AE9:AE187) -> 0 | AF189: =SUM(AF9:AF187) -> 484948.68 | AG189: =SUM(AG9:AG187) -> 0 | AH189: =SUM(AH9:AH187) -> 12180000
C191: =+A177 -> 0
A193: PERSONAS JURÍDICAS
Q208: =ROUND(IF(P208="SI",SUMIF('C de C año anterior'!$B$8:$B$229,B208,'C de C año anterior'!$F$8:$F$229)*(100%+$Q$5),0),-3)+ROUND(IF(P208="SI",SUMIF('Facturas año anterior'!$B$8:$B$86,B208,'Facturas año anterior'!$F$8:$F$86)*(100%+$AA$5),0),-3) -> 0 | S208: =ROUND(IF(R208="SI",Q208*$S$5,0),-3) -> 0 | U208: =ROUND(IF(T208="SI",Q208*$U$5,0),-3) -> 0 | W208: =ROUND(IF(V208="SI",Q208*$W$5,0),-3) -> 0 | Y208: =ROUND(IF(X208="SI",Q208*$Y$5,0),-3) -> 0 | AA208: =ROUND(IF(Z208="SI",Q208*$AA$5,0),-3) -> 0 | AC208: =ROUND(IF(AB208="SI",Q208*$AC$5,0),-3) -> 0 | AE208: =IF(AD208="SI",Q208*$AE$5,0) -> 0 | AF208: =SUMIF('Otras Asesorías y Préstamos'!$B$7:$B$242,B208,'Otras Asesorías y Préstamos'!$F$7:$F$242) -> 0 | AG208: =SUMIF('Otras Asesorías y Préstamos'!$B$7:$B$242,B208,'Otras Asesorías y Préstamos'!$V$7:$V$242) -> 0 | AH208: =ROUND(SUM(Q208:AG208),-4) -> 0
Q209: =ROUND(IF(P209="SI",SUMIF('C de C año anterior'!$B$8:$B$229,B209,'C de C año anterior'!$F$8:$F$229)*(100%+$Q$5),0),-3)+ROUND(IF(P209="SI",SUMIF('Facturas año anterior'!$B$8:$B$86,B209,'Facturas año anterior'!$F$8:$F$86)*(100%+$AA$5),0),-3) -> 0 | S209: =ROUND(IF(R209="SI",Q209*$S$5,0),-3) -> 0 | U209: =ROUND(IF(T209="SI",Q209*$U$5,0),-3) -> 0 | W209: =ROUND(IF(V209="SI",Q209*$W$5,0),-3) -> 0 | Y209: =ROUND(IF(X209="SI",Q209*$Y$5,0),-3) -> 0 | AA209: =ROUND(IF(Z209="SI",Q209*$AA$5,0),-3) -> 0 | AC209: =ROUND(IF(AB209="SI",Q209*$AC$5,0),-3) -> 0 | AE209: =IF(AD209="SI",Q209*$AE$5,0) -> 0 | AF209: =SUMIF('Otras Asesorías y Préstamos'!$B$7:$B$242,B209,'Otras Asesorías y Préstamos'!$F$7:$F$242) -> 0 | AG209: =SUMIF('Otras Asesorías y Préstamos'!$B$7:$B$242,B209,'Otras Asesorías y Préstamos'!$V$7:$V$242) -> 0 | AH209: =ROUND(SUM(Q209:AG209),-4) -> 0
Q210: =ROUND(IF(P210="SI",SUMIF('C de C año anterior'!$B$8:$B$229,B210,'C de C año anterior'!$F$8:$F$229)*(100%+$Q$5),0),-3)+ROUND(IF(P210="SI",SUMIF('Facturas año anterior'!$B$8:$B$86,B210,'Facturas año anterior'!$F$8:$F$86)*(100%+$AA$5),0),-3) -> 0 | S210: =ROUND(IF(R210="SI",Q210*$S$5,0),-3) -> 0 | U210: =ROUND(IF(T210="SI",Q210*$U$5,0),-3) -> 0 | W210: =ROUND(IF(V210="SI",Q210*$W$5,0),-3) -> 0 | Y210: =ROUND(IF(X210="SI",Q210*$Y$5,0),-3) -> 0 | AA210: =ROUND(IF(Z210="SI",Q210*$AA$5,0),-3) -> 0 | AC210: =ROUND(IF(AB210="SI",Q210*$AC$5,0),-3) -> 0 | AE210: =IF(AD210="SI",Q210*$AE$5,0) -> 0 | AF210: =SUMIF('Otras Asesorías y Préstamos'!$B$7:$B$242,B210,'Otras Asesorías y Préstamos'!$F$7:$F$242) -> 0 | AG210: =SUMIF('Otras Asesorías y Préstamos'!$B$7:$B$242,B210,'Otras Asesorías y Préstamos'!$V$7:$V$242) -> 0 | AH210: =ROUND(SUM(Q210:AG210),-4) -> 0
A213: TOTAL PERSONAS JURÍDICAS | F213: =SUM(F194:F211) -> 0 | P213: =SUM(P194:P211) -> 0 | Q213: =SUM(Q194:Q211) -> 0 | R213: =SUM(R194:R211) -> 0 | S213: =SUM(S194:S211) -> 0 | T213: =SUM(T194:T211) -> 0 | U213: =SUM(U194:U211) -> 0 | V213: 0 | X213: 0 | Z213: =SUM(Z194:Z211) -> 0 | AA213: =SUM(AA194:AA211) -> 0 | AB213: =SUM(AB194:AB211) -> 0 | AC213: =SUM(AC194:AC211) -> 0 | AD213: =SUM(AD194:AD211) -> 0 | AE213: =SUM(AE194:AE211) -> 0 | AF213: =SUM(AF194:AF211) -> 0 | AG213: =SUM(AG194:AG211) -> 0 | AH213: =SUM(AH194:AH211) -> 0
A215: ACUMULADO CLIENTES | C215: =+A199 -> 0 | D215: =+C191+C215 -> 0 | F215: =F189+F213 -> 12180000 | Q215: =Q189+Q213 -> 10763000 | S215: =S189+S213 -> 929000 | U215: =U189+U213 -> 0 | AA215: =AA189+AA213 -> 0 | AC215: =AC189+AC213 -> 0 | AE215: =AE189+AE213 -> 0 | AF215: =AF189+AF213 -> 484948.68 | AG215: =AG189+AG213 -> 0 | AH215: =AH189+AH213 -> 12180000
A217: ACUMULADO C de C | D217: =+A177+A199 -> 0 | F217: =+F189+F213 -> 12180000
A219: ACUMULADO Fras | D219: =+Facturas!D82 -> 29 | F219: =+Facturas!F49+Facturas!F80 -> 12810000
B220: TOTAL Cobrado -Sin IVA ni Ret Fte | D220: =SUM(D217:D219) -> 29 | F220: =SUM(F217:F219) -> 24990000
A221: Pnas Nat | D221: =+#REF! -> #REF!
A222: Pnas Jcas | D222: =+#REF! -> #REF!
D223: =+D221+D222 -> #REF!
A224: NO ELABORADAS o NO COBROS | D224: =-#REF! -> #REF!
D225: =+D223+D224 -> #REF!
C226: Diferencia | D226: =+D220-D225 -> #REF!

Sheet Consolidado Cobros
A1: =+'Grupos Familiares'!$A$3 -> PRESUPUESTO DE COBROS
A2: RELACIÓN COBRO A CLIENTES -CONSOLIDADO-
A3: =+'Grupos Familiares'!$A$4 -> AÑO GRAVABLE 2024
A4: PERSONAS NATURALES Y PERSONAS JURÍDICAS
F5: =+Facturas!F4 -> VALORES A FACTURAR -PRESENTE AÑO- | L5: =+'Cuentas de Cobro'!F4 -> VALORES CUENTAS DE COBRO 2023
G6: 0.19
A7: No. | B7: APELLIDOS Y NOMBRES o RAZÓN SOCIAL | C7: NIT No. | D7: D. V. | E7: CÓDIGO | F7: VALOR BRUTO A ELABORAR LA FACTURA | G7: I V A | H7: RETENCIÓN EN LA FUENTE | I7: VALOR FACTURA antes de RTE FTE | J7: VALOR A PAGAR NETO DE LA FACTURA | K7: FACTURA No. | L7: VALOR A ELABORAR LA CUENTA DE COBRO | M7: CUENTA DE COBRO No. | N7: VALOR TOTAL A PAGAR FACTURAS Y CUENTAS DE COBRO | O7: OBSERVACIONES | P7: FECHA
A9: PERSONAS NATURALES | R9: FACTURAS Y CUENTAS DE COBRO
A10: 1 | B10: NOMBRE 1 | C10: 22126399 | D10: =IF((MOD((VALUE(MID(TEXT(C10,"000000000000000"),15,1))*3+VALUE(MID(TEXT(C10,"000000000000000"),14,1))*7+VALUE(MID(TEXT(C10,"000000000000000"),13,1))*13+VALUE(MID(TEXT(C10,"000000000000000"),12,1))*17+VALUE(MID(TEXT(C10,"000000000000000"),11,1))*19+VALUE(MID(TEXT(C10,"000000000000000"),10,1))*23+VALUE(MID(TEXT(C10,"000000000000000"),9,1))*29+VALUE(MID(TEXT(C10,"000000000000000"),8,1))*37+VALUE(MID(TEXT(C10,"000000000000000"),7,1))*41+VALUE(MID(TEXT(C10,"000000000000000"),6,1))*43+VALUE(MID(TEXT(C10,"000000000000000"),5,1))*47+VALUE(MID(TEXT(C10,"000000000000000"),4,1))*53+VALUE(MID(TEXT(C10,"000000000000000"),3,1))*59+VALUE(MID(TEXT(C10,"000000000000000"),2,1))*67+VALUE(MID(TEXT(C10,"000000000000000"),1,1))*71),11))=0,0,IF((MOD((VALUE(MID(TEXT(C10,"000000000000000"),15,1))*3+VALUE(MID(TEXT(C10,"000000000000000"),14,1))*7+VALUE(MID(TEXT(C10,"000000000000000"),13,1))*13+VALUE(MID(TEXT(C10,"000000000000000"),12,1))*17+VALUE(MID(TEXT(C10,"000000000000000"),11,1))*19+VALUE(MID(TEXT(C10,"000000000000000"),10,1))*23+VALUE(MID(TEXT(C10,"000000000000000"),9,1))*29+VALUE(MID(TEXT(C10,"000000000000000"),8,1))*37+VALUE(MID(TEXT(C10,"000000000000000"),7,1))*41+VALUE(MID(TEXT(C10,"000000000000000"),6,1))*43+VALUE(MID(TEXT(C10,"000000000000000"),5,1))*47+VALUE(MID(TEXT(C10,"000000000000000"),4,1))*53+VALUE(MID(TEXT(C10,"000000000000000"),3,1))*59+VALUE(MID(TEXT(C10,"000000000000000"),2,1))*67+VALUE(MID(TEXT(C10,"000000000000000"),1,1))*71),11))=1,1,11-(MOD((VALUE(MID(TEXT(C10,"000000000000000"),15,1))*3+VALUE(MID(TEXT(C10,"000000000000000"),14,1))*7+VALUE(MID(TEXT(C10,"000000000000000"),13,1))*13+VALUE(MID(TEXT(C10,"000000000000000"),12,1))*17+VALUE(MID(TEXT(C10,"000000000000000"),11,1))*19+VALUE(MID(TEXT(C10,"000000000000000"),10,1))*23+VALUE(MID(TEXT(C10,"000000000000000"),9,1))*29+VALUE(MID(TEXT(C10,"000000000000000"),8,1))*37+VALUE(MID(TEXT(C10,"000000000000000"),7,1))*41+VALUE(MID(TEXT(C10,"000000000000000"),6,1))*43+VALUE(MID(TEXT(C10,"000000000000000"),5,1))*47+VALUE(MID(TEXT(C10,"000000000000000"),4,1))*53+VALUE(MID(TEXT(C10,"000000000000000"),3,1))*59+VALUE(MID(TEXT(C10,"000000000000000"),2,1))*67+VALUE(MID(TEXT(C10,"000000000000000"),1,1))*71),11)))) -> 5 | E10: =_xlfn.XLOOKUP(B10,Códigos!$B$8:$B$406,Códigos!$A$8:$A$406,"Verificar",0) -> 41 | F10: =SUMIF(Facturas!$B$9:$B$79,B10,Facturas!$F$9:$F$79) -> 870000 | G10: =SUMIF(Facturas!$B$9:$B$79,B10,Facturas!$G$9:$G$79) -> 165300 | H10: =SUMIF(Facturas!$B$9:$B$79,B10,Facturas!$I$9:$I$79) -> -95700 | I10: =SUMIF(Facturas!$B$9:$B$79,B10,Facturas!$J$9:$J$79) -> 1035300 | J10: =SUMIF(Facturas!$B$9:$B$79,B10,Facturas!$K$9:$K$79) -> 939600 | L10: =IF(J10>0,0,SUMIF('Cuentas de Cobro'!$B$9:$B$214,B10,'Cuentas de Cobro'!$F$9:$F$214)) -> 0 | N10: =+J10+L10 -> 939600
A11: =+A10+1 -> 2 | B11: NOMBRE 2 | C11: 71581755 | D11: =IF((MOD((VALUE(MID(TEXT(C11,"000000000000000"),15,1))*3+VALUE(MID(TEXT(C11,"000000000000000"),14,1))*7+VALUE(MID(TEXT(C11,"000000000000000"),13,1))*13+VALUE(MID(TEXT(C11,"000000000000000"),12,1))*17+VALUE(MID(TEXT(C11,"000000000000000"),11,1))*19+VALUE(MID(TEXT(C11,"000000000000000"),10,1))*23+VALUE(MID(TEXT(C11,"000000000000000"),9,1))*29+VALUE(MID(TEXT(C11,"000000000000000"),8,1))*37+VALUE(MID(TEXT(C11,"000000000000000"),7,1))*41+VALUE(MID(TEXT(C11,"000000000000000"),6,1))*43+VALUE(MID(TEXT(C11,"000000000000000"),5,1))*47+VALUE(MID(TEXT(C11,"000000000000000"),4,1))*53+VALUE(MID(TEXT(C11,"000000000000000"),3,1))*59+VALUE(MID(TEXT(C11,"000000000000000"),2,1))*67+VALUE(MID(TEXT(C11,"000000000000000"),1,1))*71),11))=0,0,IF((MOD((VALUE(MID(TEXT(C11,"000000000000000"),15,1))*3+VALUE(MID(TEXT(C11,"000000000000000"),14,1))*7+VALUE(MID(TEXT(C11,"000000000000000"),13,1))*13+VALUE(MID(TEXT(C11,"000000000000000"),12,1))*17+VALUE(MID(TEXT(C11,"000000000000000"),11,1))*19+VALUE(MID(TEXT(C11,"000000000000000"),10,1))*23+VALUE(MID(TEXT(C11,"000000000000000"),9,1))*29+VALUE(MID(TEXT(C11,"000000000000000"),8,1))*37+VALUE(MID(TEXT(C11,"000000000000000"),7,1))*41+VALUE(MID(TEXT(C11,"000000000000000"),6,1))*43+VALUE(MID(TEXT(C11,"000000000000000"),5,1))*47+VALUE(MID(TEXT(C11,"000000000000000"),4,1))*53+VALUE(MID(TEXT(C11,"000000000000000"),3,1))*59+VALUE(MID(TEXT(C11,"000000000000000"),2,1))*67+VALUE(MID(TEXT(C11,"000000000000000"),1,1))*71),11))=1,1,11-(MOD((VALUE(MID(TEXT(C11,"000000000000000"),15,1))*3+VALUE(MID(TEXT(C11,"000000000000000"),14,1))*7+VALUE(MID(TEXT(C11,"000000000000000"),13,1))*13+VALUE(MID(TEXT(C11,"000000000000000"),12,1))*17+VALUE(MID(TEXT(C11,"000000000000000"),11,1))*19+VALUE(MID(TEXT(C11,"000000000000000"),10,1))*23+VALUE(MID(TEXT(C11,"000000000000000"),9,1))*29+VALUE(MID(TEXT(C11,"000000000000000"),8,1))*37+VALUE(MID(TEXT(C11,"000000000000000"),7,1))*41+VALUE(MID(TEXT(C11,"000000000000000"),6,1))*43+VALUE(MID(TEXT(C11,"000000000000000"),5,1))*47+VALUE(MID(TEXT(C11,"000000000000000"),4,1))*53+VALUE(MID(TEXT(C11,"000000000000000"),3,1))*59+VALUE(MID(TEXT(C11,"000000000000000"),2,1))*67+VALUE(MID(TEXT(C11,"000000000000000"),1,1))*71),11)))) -> 2 | E11: =_xlfn.XLOOKUP(B11,Códigos!$B$8:$B$406,Códigos!$A$8:$A$406,"Verificar",0) -> 346 | F11: =SUMIF(Facturas!$B$9:$B$79,B11,Facturas!$F$9:$F$79) -> 1000000 | G11: =SUMIF(Facturas!$B$9:$B$79,B11,Facturas!$G$9:$G$79) -> 190000 | H11: =SUMIF(Facturas!$B$9:$B$79,B11,Facturas!$I$9:$I$79) -> 0 | I11: =SUMIF(Facturas!$B$9:$B$79,B11,Facturas!$J$9:$J$79) -> 1190000 | J11: =SUMIF(Facturas!$B$9:$B$79,B11,Facturas!$K$9:$K$79) -> 1190000 | L11: =IF(J11>0,0,SUMIF('Cuentas de Cobro'!$B$9:$B$214,B11,'Cuentas de Cobro'!$F$9:$F$214)) -> 0 | N11: =+J11+L11 -> 1190000
A12: =+A11+1 -> 3 | B12: NOMBRE 3 | C12: 70116694 | D12: =IF((MOD((VALUE(MID(TEXT(C12,"000000000000000"),15,1))*3+VALUE(MID(TEXT(C12,"000000000000000"),14,1))*7+VALUE(MID(TEXT(C12,"000000000000000"),13,1))*13+VALUE(MID(TEXT(C12,"000000000000000"),12,1))*17+VALUE(MID(TEXT(C12,"000000000000000"),11,1))*19+VALUE(MID(TEXT(C12,"000000000000000"),10,1))*23+VALUE(MID(TEXT(C12,"000000000000000"),9,1))*29+VALUE(MID(TEXT(C12,"000000000000000"),8,1))*37+VALUE(MID(TEXT(C12,"000000000000000"),7,1))*41+VALUE(MID(TEXT(C12,"000000000000000"),6,1))*43+VALUE(MID(TEXT(C12,"000000000000000"),5,1))*47+VALUE(MID(TEXT(C12,"000000000000000"),4,1))*53+VALUE(MID(TEXT(C12,"000000000000000"),3,1))*59+VALUE(MID(TEXT(C12,"000000000000000"),2,1))*67+VALUE(MID(TEXT(C12,"000000000000000"),1,1))*71),11))=0,0,IF((MOD((VALUE(MID(TEXT(C12,"000000000000000"),15,1))*3+VALUE(MID(TEXT(C12,"000000000000000"),14,1))*7+VALUE(MID(TEXT(C12,"000000000000000"),13,1))*13+VALUE(MID(TEXT(C12,"000000000000000"),12,1))*17+VALUE(MID(TEXT(C12,"000000000000000"),11,1))*19+VALUE(MID(TEXT(C12,"000000000000000"),10,1))*23+VALUE(MID(TEXT(C12,"000000000000000"),9,1))*29+VALUE(MID(TEXT(C12,"000000000000000"),8,1))*37+VALUE(MID(TEXT(C12,"000000000000000"),7,1))*41+VALUE(MID(TEXT(C12,"000000000000000"),6,1))*43+VALUE(MID(TEXT(C12,"000000000000000"),5,1))*47+VALUE(MID(TEXT(C12,"000000000000000"),4,1))*53+VALUE(MID(TEXT(C12,"000000000000000"),3,1))*59+VALUE(MID(TEXT(C12,"000000000000000"),2,1))*67+VALUE(MID(TEXT(C12,"000000000000000"),1,1))*71),11))=1,1,11-(MOD((VALUE(MID(TEXT(C12,"000000000000000"),15,1))*3+VALUE(MID(TEXT(C12,"000000000000000"),14,1))*7+VALUE(MID(TEXT(C12,"000000000000000"),13,1))*13+VALUE(MID(TEXT(C12,"000000000000000"),12,1))*17+VALUE(MID(TEXT(C12,"000000000000000"),11,1))*19+VALUE(MID(TEXT(C12,"000000000000000"),10,1))*23+VALUE(MID(TEXT(C12,"000000000000000"),9,1))*29+VALUE(MID(TEXT(C12,"000000000000000"),8,1))*37+VALUE(MID(TEXT(C12,"000000000000000"),7,1))*41+VALUE(MID(TEXT(C12,"000000000000000"),6,1))*43+VALUE(MID(TEXT(C12,"000000000000000"),5,1))*47+VALUE(MID(TEXT(C12,"000000000000000"),4,1))*53+VALUE(MID(TEXT(C12,"000000000000000"),3,1))*59+VALUE(MID(TEXT(C12,"000000000000000"),2,1))*67+VALUE(MID(TEXT(C12,"000000000000000"),1,1))*71),11)))) -> 5 | E12: =_xlfn.XLOOKUP(B12,Códigos!$B$8:$B$406,Códigos!$A$8:$A$406,"Verificar",0) -> 300 | F12: =SUMIF(Facturas!$B$9:$B$79,B12,Facturas!$F$9:$F$79) -> 1080000 | G12: =SUMIF(Facturas!$B$9:$B$79,B12,Facturas!$G$9:$G$79) -> 205200 | H12: =SUMIF(Facturas!$B$9:$B$79,B12,Facturas!$I$9:$I$79) -> -118800 | I12: =SUMIF(Facturas!$B$9:$B$79,B12,Facturas!$J$9:$J$79) -> 1285200 | J12: =SUMIF(Facturas!$B$9:$B$79,B12,Facturas!$K$9:$K$79) -> 1166400 | L12: =IF(J12>0,0,SUMIF('Cuentas de Cobro'!$B$9:$B$214,B12,'Cuentas de Cobro'!$F$9:$F$214)) -> 0 | N12: =+J12+L12 -> 1166400
A13: =+A12+1 -> 4 | B13: NOMBRE 4 | C13: 3349249 | D13: =IF((MOD((VALUE(MID(TEXT(C13,"000000000000000"),15,1))*3+VALUE(MID(TEXT(C13,"000000000000000"),14,1))*7+VALUE(MID(TEXT(C13,"000000000000000"),13,1))*13+VALUE(MID(TEXT(C13,"000000000000000"),12,1))*17+VALUE(MID(TEXT(C13,"000000000000000"),11,1))*19+VALUE(MID(TEXT(C13,"000000000000000"),10,1))*23+VALUE(MID(TEXT(C13,"000000000000000"),9,1))*29+VALUE(MID(TEXT(C13,"000000000000000"),8,1))*37+VALUE(MID(TEXT(C13,"000000000000000"),7,1))*41+VALUE(MID(TEXT(C13,"000000000000000"),6,1))*43+VALUE(MID(TEXT(C13,"000000000000000"),5,1))*47+VALUE(MID(TEXT(C13,"000000000000000"),4,1))*53+VALUE(MID(TEXT(C13,"000000000000000"),3,1))*59+VALUE(MID(TEXT(C13,"000000000000000"),2,1))*67+VALUE(MID(TEXT(C13,"000000000000000"),1,1))*71),11))=0,0,IF((MOD((VALUE(MID(TEXT(C13,"000000000000000"),15,1))*3+VALUE(MID(TEXT(C13,"000000000000000"),14,1))*7+VALUE(MID(TEXT(C13,"000000000000000"),13,1))*13+VALUE(MID(TEXT(C13,"000000000000000"),12,1))*17+VALUE(MID(TEXT(C13,"000000000000000"),11,1))*19+VALUE(MID(TEXT(C13,"000000000000000"),10,1))*23+VALUE(MID(TEXT(C13,"000000000000000"),9,1))*29+VALUE(MID(TEXT(C13,"000000000000000"),8,1))*37+VALUE(MID(TEXT(C13,"000000000000000"),7,1))*41+VALUE(MID(TEXT(C13,"000000000000000"),6,1))*43+VALUE(MID(TEXT(C13,"000000000000000"),5,1))*47+VALUE(MID(TEXT(C13,"000000000000000"),4,1))*53+VALUE(MID(TEXT(C13,"000000000000000"),3,1))*59+VALUE(MID(TEXT(C13,"000000000000000"),2,1))*67+VALUE(MID(TEXT(C13,"000000000000000"),1,1))*71),11))=1,1,11-(MOD((VALUE(MID(TEXT(C13,"000000000000000"),15,1))*3+VALUE(MID(TEXT(C13,"000000000000000"),14,1))*7+VALUE(MID(TEXT(C13,"000000000000000"),13,1))*13+VALUE(MID(TEXT(C13,"000000000000000"),12,1))*17+VALUE(MID(TEXT(C13,"000000000000000"),11,1))*19+VALUE(MID(TEXT(C13,"000000000000000"),10,1))*23+VALUE(MID(TEXT(C13,"000000000000000"),9,1))*29+VALUE(MID(TEXT(C13,"000000000000000"),8,1))*37+VALUE(MID(TEXT(C13,"000000000000000"),7,1))*41+VALUE(MID(TEXT(C13,"000000000000000"),6,1))*43+VALUE(MID(TEXT(C13,"000000000000000"),5,1))*47+VALUE(MID(TEXT(C13,"000000000000000"),4,1))*53+VALUE(MID(TEXT(C13,"000000000000000"),3,1))*59+VALUE(MID(TEXT(C13,"000000000000000"),2,1))*67+VALUE(MID(TEXT(C13,"000000000000000"),1,1))*71),11)))) -> 7 | E13: =_xlfn.XLOOKUP(B13,Códigos!$B$8:$B$406,Códigos!$A$8:$A$406,"Verificar",0) -> 312 | F13: =SUMIF(Facturas!$B$9:$B$79,B13,Facturas!$F$9:$F$79) -> 2990000 | G13: =SUMIF(Facturas!$B$9:$B$79,B13,Facturas!$G$9:$G$79) -> 568100 | H13: =SUMIF(Facturas!$B$9:$B$79,B13,Facturas!$I$9:$I$79) -> -328900 | I13: =SUMIF(Facturas!$B$9:$B$79,B13,Facturas!$J$9:$J$79) -> 3558100 | J13: =SUMIF(Facturas!$B$9:$B$79,B13,Facturas!$K$9:$K$79) -> 3229200 | L13: =IF(J13>0,0,SUMIF('Cuentas de Cobro'!$B$9:$B$214,B13,'Cuentas de Cobro'!$F$9:$F$214)) -> 0 | N13: =+J13+L13 -> 3229200
A14: =+A13+1 -> 5 | B14: NOMBRE 5 | C14: 71632774 | D14: =IF((MOD((VALUE(MID(TEXT(C14,"000000000000000"),15,1))*3+VALUE(MID(TEXT(C14,"000000000000000"),14,1))*7+VALUE(MID(TEXT(C14,"000000000000000"),13,1))*13+VALUE(MID(TEXT(C14,"000000000000000"),12,1))*17+VALUE(MID(TEXT(C14,"000000000000000"),11,1))*19+VALUE(MID(TEXT(C14,"000000000000000"),10,1))*23+VALUE(MID(TEXT(C14,"000000000000000"),9,1))*29+VALUE(MID(TEXT(C14,"000000000000000"),8,1))*37+VALUE(MID(TEXT(C14,"000000000000000"),7,1))*41+VALUE(MID(TEXT(C14,"000000000000000"),6,1))*43+VALUE(MID(TEXT(C14,"000000000000000"),5,1))*47+VALUE(MID(TEXT(C14,"000000000000000"),4,1))*53+VALUE(MID(TEXT(C14,"000000000000000"),3,1))*59+VALUE(MID(TEXT(C14,"000000000000000"),2,1))*67+VALUE(MID(TEXT(C14,"000000000000000"),1,1))*71),11))=0,0,IF((MOD((VALUE(MID(TEXT(C14,"000000000000000"),15,1))*3+VALUE(MID(TEXT(C14,"000000000000000"),14,1))*7+VALUE(MID(TEXT(C14,"000000000000000"),13,1))*13+VALUE(MID(TEXT(C14,"000000000000000"),12,1))*17+VALUE(MID(TEXT(C14,"000000000000000"),11,1))*19+VALUE(MID(TEXT(C14,"000000000000000"),10,1))*23+VALUE(MID(TEXT(C14,"000000000000000"),9,1))*29+VALUE(MID(TEXT(C14,"000000000000000"),8,1))*37+VALUE(MID(TEXT(C14,"000000000000000"),7,1))*41+VALUE(MID(TEXT(C14,"000000000000000"),6,1))*43+VALUE(MID(TEXT(C14,"000000000000000"),5,1))*47+VALUE(MID(TEXT(C14,"000000000000000"),4,1))*53+VALUE(MID(TEXT(C14,"000000000000000"),3,1))*59+VALUE(MID(TEXT(C14,"000000000000000"),2,1))*67+VALUE(MID(TEXT(C14,"000000000000000"),1,1))*71),11))=1,1,11-(MOD((VALUE(MID(TEXT(C14,"000000000000000"),15,1))*3+VALUE(MID(TEXT(C14,"000000000000000"),14,1))*7+VALUE(MID(TEXT(C14,"000000000000000"),13,1))*13+VALUE(MID(TEXT(C14,"000000000000000"),12,1))*17+VALUE(MID(TEXT(C14,"000000000000000"),11,1))*19+VALUE(MID(TEXT(C14,"000000000000000"),10,1))*23+VALUE(MID(TEXT(C14,"000000000000000"),9,1))*29+VALUE(MID(TEXT(C14,"000000000000000"),8,1))*37+VALUE(MID(TEXT(C14,"000000000000000"),7,1))*41+VALUE(MID(TEXT(C14,"000000000000000"),6,1))*43+VALUE(MID(TEXT(C14,"000000000000000"),5,1))*47+VALUE(MID(TEXT(C14,"000000000000000"),4,1))*53+VALUE(MID(TEXT(C14,"000000000000000"),3,1))*59+VALUE(MID(TEXT(C14,"000000000000000"),2,1))*67+VALUE(MID(TEXT(C14,"000000000000000"),1,1))*71),11)))) -> 2 | E14: =_xlfn.XLOOKUP(B14,Códigos!$B$8:$B$406,Códigos!$A$8:$A$406,"Verificar",0) -> 217 | F14: =SUMIF(Facturas!$B$9:$B$79,B14,Facturas!$F$9:$F$79) -> 2430000 | G14: =SUMIF(Facturas!$B$9:$B$79,B14,Facturas!$G$9:$G$79) -> 461700 | H14: =SUMIF(Facturas!$B$9:$B$79,B14,Facturas!$I$9:$I$79) -> -267300 | I14: =SUMIF(Facturas!$B$9:$B$79,B14,Facturas!$J$9:$J$79) -> 2891700 | J14: =SUMIF(Facturas!$B$9:$B$79,B14,Facturas!$K$9:$K$79) -> 2624400 | L14: =IF(J14>0,0,SUMIF('Cuentas de Cobro'!$B$9:$B$214,B14,'Cuentas de Cobro'!$F$9:$F$214)) -> 0 | N14: =+J14+L14 -> 2624400
A15: =+A14+1 -> 6 | B15: NOMBRE 6 | C15: 21315528 | D15: =IF((MOD((VALUE(MID(TEXT(C15,"000000000000000"),15,1))*3+VALUE(MID(TEXT(C15,"000000000000000"),14,1))*7+VALUE(MID(TEXT(C15,"000000000000000"),13,1))*13+VALUE(MID(TEXT(C15,"000000000000000"),12,1))*17+VALUE(MID(TEXT(C15,"000000000000000"),11,1))*19+VALUE(MID(TEXT(C15,"000000000000000"),10,1))*23+VALUE(MID(TEXT(C15,"000000000000000"),9,1))*29+VALUE(MID(TEXT(C15,"000000000000000"),8,1))*37+VALUE(MID(TEXT(C15,"000000000000000"),7,1))*41+VALUE(MID(TEXT(C15,"000000000000000"),6,1))*43+VALUE(MID(TEXT(C15,"000000000000000"),5,1))*47+VALUE(MID(TEXT(C15,"000000000000000"),4,1))*53+VALUE(MID(TEXT(C15,"000000000000000"),3,1))*59+VALUE(MID(TEXT(C15,"000000000000000"),2,1))*67+VALUE(MID(TEXT(C15,"000000000000000"),1,1))*71),11))=0,0,IF((MOD((VALUE(MID(TEXT(C15,"000000000000000"),15,1))*3+VALUE(MID(TEXT(C15,"000000000000000"),14,1))*7+VALUE(MID(TEXT(C15,"000000000000000"),13,1))*13+VALUE(MID(TEXT(C15,"000000000000000"),12,1))*17+VALUE(MID(TEXT(C15,"000000000000000"),11,1))*19+VALUE(MID(TEXT(C15,"000000000000000"),10,1))*23+VALUE(MID(TEXT(C15,"000000000000000"),9,1))*29+VALUE(MID(TEXT(C15,"000000000000000"),8,1))*37+VALUE(MID(TEXT(C15,"000000000000000"),7,1))*41+VALUE(MID(TEXT(C15,"000000000000000"),6,1))*43+VALUE(MID(TEXT(C15,"000000000000000"),5,1))*47+VALUE(MID(TEXT(C15,"000000000000000"),4,1))*53+VALUE(MID(TEXT(C15,"000000000000000"),3,1))*59+VALUE(MID(TEXT(C15,"000000000000000"),2,1))*67+VALUE(MID(TEXT(C15,"000000000000000"),1,1))*71),11))=1,1,11-(MOD((VALUE(MID(TEXT(C15,"000000000000000"),15,1))*3+VALUE(MID(TEXT(C15,"000000000000000"),14,1))*7+VALUE(MID(TEXT(C15,"000000000000000"),13,1))*13+VALUE(MID(TEXT(C15,"000000000000000"),12,1))*17+VALUE(MID(TEXT(C15,"000000000000000"),11,1))*19+VALUE(MID(TEXT(C15,"000000000000000"),10,1))*23+VALUE(MID(TEXT(C15,"000000000000000"),9,1))*29+VALUE(MID(TEXT(C15,"000000000000000"),8,1))*37+VALUE(MID(TEXT(C15,"000000000000000"),7,1))*41+VALUE(MID(TEXT(C15,"000000000000000"),6,1))*43+VALUE(MID(TEXT(C15,"000000000000000"),5,1))*47+VALUE(MID(TEXT(C15,"000000000000000"),4,1))*53+VALUE(MID(TEXT(C15,"000000000000000"),3,1))*59+VALUE(MID(TEXT(C15,"000000000000000"),2,1))*67+VALUE(MID(TEXT(C15,"000000000000000"),1,1))*71),11)))) -> 6 | E15: =_xlfn.XLOOKUP(B15,Códigos!$B$8:$B$406,Códigos!$A$8:$A$406,"Verificar",0) -> 42 | F15: =SUMIF(Facturas!$B$9:$B$79,B15,Facturas!$F$9:$F$79) -> 1830000 | G15: =SUMIF(Facturas!$B$9:$B$79,B15,Facturas!$G$9:$G$79) -> 347700 | H15: =SUMIF(Facturas!$B$9:$B$79,B15,Facturas!$I$9:$I$79) -> -201300 | I15: =SUMIF(Facturas!$B$9:$B$79,B15,Facturas!$J$9:$J$79) -> 2177700 | J15: =SUMIF(Facturas!$B$9:$B$79,B15,Facturas!$K$9:$K$79) -> 1976400 | L15: =IF(J15>0,0,SUMIF('Cuentas de Cobro'!$B$9:$B$214,B15,'Cuentas de Cobro'!$F$9:$F$214)) -> 0 | N15: =+J15+L15 -> 1976400
A16: =+A15+1 -> 7 | B16: NOMBRE 7 | C16: 32336950 | D16: =IF((MOD((VALUE(MID(TEXT(C16,"000000000000000"),15,1))*3+VALUE(MID(TEXT(C16,"000000000000000"),14,1))*7+VALUE(MID(TEXT(C16,"000000000000000"),13,1))*13+VALUE(MID(TEXT(C16,"000000000000000"),12,1))*17+VALUE(MID(TEXT(C16,"000000000000000"),11,1))*19+VALUE(MID(TEXT(C16,"000000000000000"),10,1))*23+VALUE(MID(TEXT(C16,"000000000000000"),9,1))*29+VALUE(MID(TEXT(C16,"000000000000000"),8,1))*37+VALUE(MID(TEXT(C16,"000000000000000"),7,1))*41+VALUE(MID(TEXT(C16,"000000000000000"),6,1))*43+VALUE(MID(TEXT(C16,"000000000000000"),5,1))*47+VALUE(MID(TEXT(C16,"000000000000000"),4,1))*53+VALUE(MID(TEXT(C16,"000000000000000"),3,1))*59+VALUE(MID(TEXT(C16,"000000000000000"),2,1))*67+VALUE(MID(TEXT(C16,"000000000000000"),1,1))*71),11))=0,0,IF((MOD((VALUE(MID(TEXT(C16,"000000000000000"),15,1))*3+VALUE(MID(TEXT(C16,"000000000000000"),14,1))*7+VALUE(MID(TEXT(C16,"000000000000000"),13,1))*13+VALUE(MID(TEXT(C16,"000000000000000"),12,1))*17+VALUE(MID(TEXT(C16,"000000000000000"),11,1))*19+VALUE(MID(TEXT(C16,"000000000000000"),10,1))*23+VALUE(MID(TEXT(C16,"000000000000000"),9,1))*29+VALUE(MID(TEXT(C16,"000000000000000"),8,1))*37+VALUE(MID(TEXT(C16,"000000000000000"),7,1))*41+VALUE(MID(TEXT(C16,"000000000000000"),6,1))*43+VALUE(MID(TEXT(C16,"000000000000000"),5,1))*47+VALUE(MID(TEXT(C16,"000000000000000"),4,1))*53+VALUE(MID(TEXT(C16,"000000000000000"),3,1))*59+VALUE(MID(TEXT(C16,"000000000000000"),2,1))*67+VALUE(MID(TEXT(C16,"000000000000000"),1,1))*71),11))=1,1,11-(MOD((VALUE(MID(TEXT(C16,"000000000000000"),15,1))*3+VALUE(MID(TEXT(C16,"000000000000000"),14,1))*7+VALUE(MID(TEXT(C16,"000000000000000"),13,1))*13+VALUE(MID(TEXT(C16,"000000000000000"),12,1))*17+VALUE(MID(TEXT(C16,"000000000000000"),11,1))*19+VALUE(MID(TEXT(C16,"000000000000000"),10,1))*23+VALUE(MID(TEXT(C16,"000000000000000"),9,1))*29+VALUE(MID(TEXT(C16,"000000000000000"),8,1))*37+VALUE(MID(TEXT(C16,"000000000000000"),7,1))*41+VALUE(MID(TEXT(C16,"000000000000000"),6,1))*43+VALUE(MID(TEXT(C16,"000000000000000"),5,1))*47+VALUE(MID(TEXT(C16,"000000000000000"),4,1))*53+VALUE(MID(TEXT(C16,"000000000000000"),3,1))*59+VALUE(MID(TEXT(C16,"000000000000000"),2,1))*67+VALUE(MID(TEXT(C16,"000000000000000"),1,1))*71),11)))) -> 1 | E16: =_xlfn.XLOOKUP(B16,Códigos!$B$8:$B$406,Códigos!$A$8:$A$406,"Verificar",0) -> 43 | F16: =SUMIF(Facturas!$B$9:$B$79,B16,Facturas!$F$9:$F$79) -> 2390000 | G16: =SUMIF(Facturas!$B$9:$B$79,B16,Facturas!$G$9:$G$79) -> 454100 | H16: =SUMIF(Facturas!$B$9:$B$79,B16,Facturas!$I$9:$I$79) -> -262900 | I16: =SUMIF(Facturas!$B$9:$B$79,B16,Facturas!$J$9:$J$79) -> 2844100 | J16: =SUMIF(Facturas!$B$9:$B$79,B16,Facturas!$K$9:$K$79) -> 2581200 | L16: =IF(J16>0,0,SUMIF('Cuentas de Cobro'!$B$9:$B$214,B16,'Cuentas de Cobro'!$F$9:$F$214)) -> 0 | N16: =+J16+L16 -> 2581200
A17: =+A16+1 -> 8 | B17: NOMBRE 8 | C17: 1152450831 | D17: =IF((MOD((VALUE(MID(TEXT(C17,"000000000000000"),15,1))*3+VALUE(MID(TEXT(C17,"000000000000000"),14,1))*7+VALUE(MID(TEXT(C17,"000000000000000"),13,1))*13+VALUE(MID(TEXT(C17,"000000000000000"),12,1))*17+VALUE(MID(TEXT(C17,"000000000000000"),11,1))*19+VALUE(MID(TEXT(C17,"000000000000000"),10,1))*23+VALUE(MID(TEXT(C17,"000000000000000"),9,1))*29+VALUE(MID(TEXT(C17,"000000000000000"),8,1))*37+VALUE(MID(TEXT(C17,"000000000000000"),7,1))*41+VALUE(MID(TEXT(C17,"000000000000000"),6,1))*43+VALUE(MID(TEXT(C17,"000000000000000"),5,1))*47+VALUE(MID(TEXT(C17,"000000000000000"),4,1))*53+VALUE(MID(TEXT(C17,"000000000000000"),3,1))*59+VALUE(MID(TEXT(C17,"000000000000000"),2,1))*67+VALUE(MID(TEXT(C17,"000000000000000"),1,1))*71),11))=0,0,IF((MOD((VALUE(MID(TEXT(C17,"000000000000000"),15,1))*3+VALUE(MID(TEXT(C17,"000000000000000"),14,1))*7+VALUE(MID(TEXT(C17,"000000000000000"),13,1))*13+VALUE(MID(TEXT(C17,"000000000000000"),12,1))*17+VALUE(MID(TEXT(C17,"000000000000000"),11,1))*19+VALUE(MID(TEXT(C17,"000000000000000"),10,1))*23+VALUE(MID(TEXT(C17,"000000000000000"),9,1))*29+VALUE(MID(TEXT(C17,"000000000000000"),8,1))*37+VALUE(MID(TEXT(C17,"000000000000000"),7,1))*41+VALUE(MID(TEXT(C17,"000000000000000"),6,1))*43+VALUE(MID(TEXT(C17,"000000000000000"),5,1))*47+VALUE(MID(TEXT(C17,"000000000000000"),4,1))*53+VALUE(MID(TEXT(C17,"000000000000000"),3,1))*59+VALUE(MID(TEXT(C17,"000000000000000"),2,1))*67+VALUE(MID(TEXT(C17,"000000000000000"),1,1))*71),11))=1,1,11-(MOD((VALUE(MID(TEXT(C17,"000000000000000"),15,1))*3+VALUE(MID(TEXT(C17,"000000000000000"),14,1))*7+VALUE(MID(TEXT(C17,"000000000000000"),13,1))*13+VALUE(MID(TEXT(C17,"000000000000000"),12,1))*17+VALUE(MID(TEXT(C17,"000000000000000"),11,1))*19+VALUE(MID(TEXT(C17,"000000000000000"),10,1))*23+VALUE(MID(TEXT(C17,"000000000000000"),9,1))*29+VALUE(MID(TEXT(C17,"000000000000000"),8,1))*37+VALUE(MID(TEXT(C17,"000000000000000"),7,1))*41+VALUE(MID(TEXT(C17,"000000000000000"),6,1))*43+VALUE(MID(TEXT(C17,"000000000000000"),5,1))*47+VALUE(MID(TEXT(C17,"000000000000000"),4,1))*53+VALUE(MID(TEXT(C17,"000000000000000"),3,1))*59+VALUE(MID(TEXT(C17,"000000000000000"),2,1))*67+VALUE(MID(TEXT(C17,"000000000000000"),1,1))*71),11)))) -> 7 | E17: =_xlfn.XLOOKUP(B17,Códigos!$B$8:$B$406,Códigos!$A$8:$A$406,"Verificar",0) -> 44 | F17: =SUMIF(Facturas!$B$9:$B$79,B17,Facturas!$F$9:$F$79) -> 220000 | G17: =SUMIF(Facturas!$B$9:$B$79,B17,Facturas!$G$9:$G$79) -> 41800 | H17: =SUMIF(Facturas!$B$9:$B$79,B17,Facturas!$I$9:$I$79) -> -24200 | I17: =SUMIF(Facturas!$B$9:$B$79,B17,Facturas!$J$9:$J$79) -> 261800 | J17: =SUMIF(Facturas!$B$9:$B$79,B17,Facturas!$K$9:$K$79) -> 237600 | L17: =IF(J17>0,0,SUMIF('Cuentas de Cobro'!$B$9:$B$214,B17,'Cuentas de Cobro'!$F$9:$F$214)) -> 0 | N17: =+J17+L17 -> 237600

Sheet Otras Asesorías y Préstamos
A2: REGISTRO DE OTRAS ASESORÍAS
A3: =+'Grupos Familiares'!$A$4 -> AÑO GRAVABLE 2024 | H3: ASESORÍAS | V3: PRÉSTAMOS | AD3: COBROS AÑO GRAVABLE ANTERIOR
H4: IPC | J4: =+Facturas!V5 -> 0.052 | L4: =+J4 -> 0.052 | P4: =+J4 -> 0.052 | R4: =+J4 -> 0.052 | U4: =+J4 -> 0.052
A5: No. | B5: APELLIDOS Y NOMBRES | C5: CÓDIGO | D5: NIT No. | E5: D. V. | F5: ACUMULADO ASESORÍAS AÑO | G5: TOTAL ACUMULADO PRÉSTAMOS | H5: TOTAL ASESORÍAS AÑO | I5: CANT | J5: DECLARACIÓN IVA | K5: CANT | L5: DECLARACIÓN RET FTE | M5: SI/NO | N5: DEVOLUCIÓN IMPUESTOS | O5: SI/NO | P5: FACTURACIÓN ELECTRÓNICA | Q5: PROCESO CONTABLE | R5: OTRAS ASESORÍAS | S5: Otras Asesorías: OBSERVACIONES | T5: CANT | U5: ESTADOS FROS | V5: TOTAL PRÉSTAMOS | W5: CANT | X5: PRÉSTAMOS por PAGOS OFICINA | Y5: CANT | Z5: PRÉSTAMOS por CERTIFICADOS | AA5: CANT | AB5: PRÉSTAMOS por PAGOS SEG SOC | AD5: CANT | AE5: DECLARACIÓN IVA | AF5: CANT | AG5: DECLARACIÓN RET FTE | AH5: CANT | AI5: DEVOLUCIÓN IMPUESTOS | AJ5: SI/NO | AK5: FACTURACIÓN ELECTRÓNICA | AL5: PROCESO CONTABLE | AM5: OTRAS ASESORÍAS | AN5: Otras Asesorías: OBSERVACIONES | AO5: CANT | AP5: ESTADOS FROS | AQ5: TOTAL PRÉSTAMOS | AR5: CANT | AS5: PRÉSTAMOS -CERTIFICADOS | AT5: CANT | AU5: PRÉSTAMOS -PAGOS OFICINA | AV5: CANT | AW5: PRÉSTAMOS -SEG SOC
A7: 1 | B7: NOMBRE 1 | C7: =_xlfn.XLOOKUP(B7,Códigos!$B$8:$B$406,Códigos!$A$8:$A$406,"Verificar",0) -> 41 | D7: =_xlfn.XLOOKUP(B7,'Consolidado Cobros'!$B$10:$B$268,'Consolidado Cobros'!$C$10:$C$268,"Verificar",0) -> 22126399 | E7: =IF((MOD((VALUE(MID(TEXT(D7,"000000000000000"),15,1))*3+VALUE(MID(TEXT(D7,"000000000000000"),14,1))*7+VALUE(MID(TEXT(D7,"000000000000000"),13,1))*13+VALUE(MID(TEXT(D7,"000000000000000"),12,1))*17+VALUE(MID(TEXT(D7,"000000000000000"),11,1))*19+VALUE(MID(TEXT(D7,"000000000000000"),10,1))*23+VALUE(MID(TEXT(D7,"000000000000000"),9,1))*29+VALUE(MID(TEXT(D7,"000000000000000"),8,1))*37+VALUE(MID(TEXT(D7,"000000000000000"),7,1))*41+VALUE(MID(TEXT(D7,"000000000000000"),6,1))*43+VALUE(MID(TEXT(D7,"000000000000000"),5,1))*47+VALUE(MID(TEXT(D7,"000000000000000"),4,1))*53+VALUE(MID(TEXT(D7,"000000000000000"),3,1))*59+VALUE(MID(TEXT(D7,"000000000000000"),2,1))*67+VALUE(MID(TEXT(D7,"000000000000000"),1,1))*71),11))=0,0,IF((MOD((VALUE(MID(TEXT(D7,"000000000000000"),15,1))*3+VALUE(MID(TEXT(D7,"000000000000000"),14,1))*7+VALUE(MID(TEXT(D7,"000000000000000"),13,1))*13+VALUE(MID(TEXT(D7,"000000000000000"),12,1))*17+VALUE(MID(TEXT(D7,"000000000000000"),11,1))*19+VALUE(MID(TEXT(D7,"000000000000000"),10,1))*23+VALUE(MID(TEXT(D7,"000000000000000"),9,1))*29+VALUE(MID(TEXT(D7,"000000000000000"),8,1))*37+VALUE(MID(TEXT(D7,"000000000000000"),7,1))*41+VALUE(MID(TEXT(D7,"000000000000000"),6,1))*43+VALUE(MID(TEXT(D7,"000000000000000"),5,1))*47+VALUE(MID(TEXT(D7,"000000000000000"),4,1))*53+VALUE(MID(TEXT(D7,"000000000000000"),3,1))*59+VALUE(MID(TEXT(D7,"000000000000000"),2,1))*67+VALUE(MID(TEXT(D7,"000000000000000"),1,1))*71),11))=1,1,11-(MOD((VALUE(MID(TEXT(D7,"000000000000000"),15,1))*3+VALUE(MID(TEXT(D7,"000000000000000"),14,1))*7+VALUE(MID(TEXT(D7,"000000000000000"),13,1))*13+VALUE(MID(TEXT(D7,"000000000000000"),12,1))*17+VALUE(MID(TEXT(D7,"000000000000000"),11,1))*19+VALUE(MID(TEXT(D7,"000000000000000"),10,1))*23+VALUE(MID(TEXT(D7,"000000000000000"),9,1))*29+VALUE(MID(TEXT(D7,"000000000000000"),8,1))*37+VALUE(MID(TEXT(D7,"000000000000000"),7,1))*41+VALUE(MID(TEXT(D7,"000000000000000"),6,1))*43+VALUE(MID(TEXT(D7,"000000000000000"),5,1))*47+VALUE(MID(TEXT(D7,"000000000000000"),4,1))*53+VALUE(MID(TEXT(D7,"000000000000000"),3,1))*59+VALUE(MID(TEXT(D7,"000000000000000"),2,1))*67+VALUE(MID(TEXT(D7,"000000000000000"),1,1))*71),11)))) -> 5 | F7: =+IF(H7>0,H7,0) -> 0 | G7: =+IF(V7>0,V7,0) -> 0 | H7: =+J7+L7+N7+P7+Q7+R7+U7 -> 0 | J7: =+(AE7/AD7*(100%+$J$4))*I7 -> 0 | L7: =+(AG7/AF7*(100%+$J$4))*K7 -> 0 | N7: 0 | P7: =ROUND(IF(O7="SI",AK7*(100%+$P$4),0),-4) -> 0 | Q7: 0 | R7: 0 | V7: =+X7+Z7+AB7 -> 0 | AD7: =SUMIF('Asesorías AG anterior'!$B$7:$B$236,B7,'Asesorías AG anterior'!$I$7:$I$236) -> 0.001 | AE7: =SUMIF('Asesorías AG anterior'!$B$7:$B$236,B7,'Asesorías AG anterior'!$J$7:$J$236) -> 0 | AF7: =SUMIF('Asesorías AG anterior'!$B$7:$B$236,B7,'Asesorías AG anterior'!$K$7:$K$236) -> 0.001 | AG7: =SUMIF('Asesorías AG anterior'!$B$7:$B$236,B7,'Asesorías AG anterior'!$L$7:$L$236) -> 0 | AH7: =SUMIF('Asesorías AG anterior'!$B$7:$B$236,B7,'Asesorías AG anterior'!$M$7:$M$236) -> 0 | AI7: =SUMIF('Asesorías AG anterior'!$B$7:$B$236,B7,'Asesorías AG anterior'!$N$7:$N$236) -> 0 | AJ7: =SUMIF('Asesorías AG anterior'!$B$7:$B$236,B7,'Asesorías AG anterior'!$O$7:$O$236) -> 0.001 | AK7: =SUMIF('Asesorías AG anterior'!$B$7:$B$236,B7,'Asesorías AG anterior'!$P$7:$P$236) -> 0 | AL7: =SUMIF('Asesorías AG anterior'!$B$7:$B$236,B7,'Asesorías AG anterior'!$Q$7:$Q$236) -> 0 | AM7: =SUMIF('Asesorías AG anterior'!$B$7:$B$236,B7,'Asesorías AG anterior'!$R$7:$R$236) -> 0 | AO7: =SUMIF('Asesorías AG anterior'!$B$7:$B$236,B7,'Asesorías AG anterior'!$T$7:$T$236) -> 0 | AP7: =SUMIF('Asesorías AG anterior'!$B$7:$B$236,B7,'Asesorías AG anterior'!$U$7:$U$236) -> 0 | AQ7: =SUMIF('Asesorías AG anterior'!$B$7:$B$236,B7,'Asesorías AG anterior'!$V$7:$V$236) -> 0 | AR7: =SUMIF('Asesorías AG anterior'!$B$7:$B$236,B7,'Asesorías AG anterior'!$W$7:$W$236) -> 0 | AS7: =SUMIF('Asesorías AG anterior'!$B$7:$B$236,B7,'Asesorías AG anterior'!$X$7:$X$236) -> 0 | AT7: =SUMIF('Asesorías AG anterior'!$B$7:$B$236,B7,'Asesorías AG anterior'!$Y$7:$Y$236) -> 0 | AU7: =SUMIF('Asesorías AG anterior'!$B$7:$B$236,B7,'Asesorías AG anterior'!$Z$7:$Z$236) -> 0 | AV7: =SUMIF('Asesorías AG anterior'!$B$7:$B$236,B7,'Asesorías AG anterior'!$AA$7:$AA$236) -> 0 | AW7: =SUMIF('Asesorías AG anterior'!$B$7:$B$236,B7,'Asesorías AG anterior'!$AB$7:$AB$236) -> 0
A8: =+A7+1 -> 2 | B8: NOMBRE 2 | C8: =_xlfn.XLOOKUP(B8,Códigos!$B$8:$B$406,Códigos!$A$8:$A$406,"Verificar",0) -> 346 | D8: =_xlfn.XLOOKUP(B8,'Consolidado Cobros'!$B$10:$B$268,'Consolidado Cobros'!$C$10:$C$268,"Verificar",0) -> 71581755 | E8: =IF((MOD((VALUE(MID(TEXT(D8,"000000000000000"),15,1))*3+VALUE(MID(TEXT(D8,"000000000000000"),14,1))*7+VALUE(MID(TEXT(D8,"000000000000000"),13,1))*13+VALUE(MID(TEXT(D8,"000000000000000"),12,1))*17+VALUE(MID(TEXT(D8,"000000000000000"),11,1))*19+VALUE(MID(TEXT(D8,"000000000000000"),10,1))*23+VALUE(MID(TEXT(D8,"000000000000000"),9,1))*29+VALUE(MID(TEXT(D8,"000000000000000"),8,1))*37+VALUE(MID(TEXT(D8,"000000000000000"),7,1))*41+VALUE(MID(TEXT(D8,"000000000000000"),6,1))*43+VALUE(MID(TEXT(D8,"000000000000000"),5,1))*47+VALUE(MID(TEXT(D8,"000000000000000"),4,1))*53+VALUE(MID(TEXT(D8,"000000000000000"),3,1))*59+VALUE(MID(TEXT(D8,"000000000000000"),2,1))*67+VALUE(MID(TEXT(D8,"000000000000000"),1,1))*71),11))=0,0,IF((MOD((VALUE(MID(TEXT(D8,"000000000000000"),15,1))*3+VALUE(MID(TEXT(D8,"000000000000000"),14,1))*7+VALUE(MID(TEXT(D8,"000000000000000"),13,1))*13+VALUE(MID(TEXT(D8,"000000000000000"),12,1))*17+VALUE(MID(TEXT(D8,"000000000000000"),11,1))*19+VALUE(MID(TEXT(D8,"000000000000000"),10,1))*23+VALUE(MID(TEXT(D8,"000000000000000"),9,1))*29+VALUE(MID(TEXT(D8,"000000000000000"),8,1))*37+VALUE(MID(TEXT(D8,"000000000000000"),7,1))*41+VALUE(MID(TEXT(D8,"000000000000000"),6,1))*43+VALUE(MID(TEXT(D8,"000000000000000"),5,1))*47+VALUE(MID(TEXT(D8,"000000000000000"),4,1))*53+VALUE(MID(TEXT(D8,"000000000000000"),3,1))*59+VALUE(MID(TEXT(D8,"000000000000000"),2,1))*67+VALUE(MID(TEXT(D8,"000000000000000"),1,1))*71),11))=1,1,11-(MOD((VALUE(MID(TEXT(D8,"000000000000000"),15,1))*3+VALUE(MID(TEXT(D8,"000000000000000"),14,1))*7+VALUE(MID(TEXT(D8,"000000000000000"),13,1))*13+VALUE(MID(TEXT(D8,"000000000000000"),12,1))*17+VALUE(MID(TEXT(D8,"000000000000000"),11,1))*19+VALUE(MID(TEXT(D8,"000000000000000"),10,1))*23+VALUE(MID(TEXT(D8,"000000000000000"),9,1))*29+VALUE(MID(TEXT(D8,"000000000000000"),8,1))*37+VALUE(MID(TEXT(D8,"000000000000000"),7,1))*41+VALUE(MID(TEXT(D8,"000000000000000"),6,1))*43+VALUE(MID(TEXT(D8,"000000000000000"),5,1))*47+VALUE(MID(TEXT(D8,"000000000000000"),4,1))*53+VALUE(MID(TEXT(D8,"000000000000000"),3,1))*59+VALUE(MID(TEXT(D8,"000000000000000"),2,1))*67+VALUE(MID(TEXT(D8,"000000000000000"),1,1))*71),11)))) -> 2 | F8: =+IF(H8>0,H8,0) -> 0 | G8: =+IF(V8>0,V8,0) -> 0 | H8: =+J8+L8+N8+P8+Q8+R8+U8 -> 0 | J8: =+(AE8/AD8*(100%+$J$4))*I8 -> 0 | L8: =+(AG8/AF8*(100%+$J$4))*K8 -> 0 | N8: 0 | P8: =ROUND(IF(O8="SI",AK8*(100%+$P$4),0),-4) -> 0 | Q8: 0 | R8: 0 | V8: =+X8+Z8+AB8 -> 0 | AD8: =SUMIF('Asesorías AG anterior'!$B$7:$B$236,B8,'Asesorías AG anterior'!$I$7:$I$236) -> 0.001 | AE8: =SUMIF('Asesorías AG anterior'!$B$7:$B$236,B8,'Asesorías AG anterior'!$J$7:$J$236) -> 0 | AF8: =SUMIF('Asesorías AG anterior'!$B$7:$B$236,B8,'Asesorías AG anterior'!$K$7:$K$236) -> 0.001 | AG8: =SUMIF('Asesorías AG anterior'!$B$7:$B$236,B8,'Asesorías AG anterior'!$L$7:$L$236) -> 0 | AH8: =SUMIF('Asesorías AG anterior'!$B$7:$B$236,B8,'Asesorías AG anterior'!$M$7:$M$236) -> 0 | AI8: =SUMIF('Asesorías AG anterior'!$B$7:$B$236,B8,'Asesorías AG anterior'!$N$7:$N$236) -> 0 | AJ8: =SUMIF('Asesorías AG anterior'!$B$7:$B$236,B8,'Asesorías AG anterior'!$O$7:$O$236) -> 0.001 | AK8: =SUMIF('Asesorías AG anterior'!$B$7:$B$236,B8,'Asesorías AG anterior'!$P$7:$P$236) -> 0 | AL8: =SUMIF('Asesorías AG anterior'!$B$7:$B$236,B8,'Asesorías AG anterior'!$Q$7:$Q$236) -> 0 | AM8: =SUMIF('Asesorías AG anterior'!$B$7:$B$236,B8,'Asesorías AG anterior'!$R$7:$R$236) -> 0 | AO8: =SUMIF('Asesorías AG anterior'!$B$7:$B$236,B8,'Asesorías AG anterior'!$T$7:$T$236) -> 0 | AP8: =SUMIF('Asesorías AG anterior'!$B$7:$B$236,B8,'Asesorías AG anterior'!$U$7:$U$236) -> 0 | AQ8: =SUMIF('Asesorías AG anterior'!$B$7:$B$236,B8,'Asesorías AG anterior'!$V$7:$V$236) -> 0 | AR8: =SUMIF('Asesorías AG anterior'!$B$7:$B$236,B8,'Asesorías AG anterior'!$W$7:$W$236) -> 0 | AS8: =SUMIF('Asesorías AG anterior'!$B$7:$B$236,B8,'Asesorías AG anterior'!$X$7:$X$236) -> 0 | AT8: =SUMIF('Asesorías AG anterior'!$B$7:$B$236,B8,'Asesorías AG anterior'!$Y$7:$Y$236) -> 0 | AU8: =SUMIF('Asesorías AG anterior'!$B$7:$B$236,B8,'Asesorías AG anterior'!$Z$7:$Z$236) -> 0 | AV8: =SUMIF('Asesorías AG anterior'!$B$7:$B$236,B8,'Asesorías AG anterior'!$AA$7:$AA$236) -> 0 | AW8: =SUMIF('Asesorías AG anterior'!$B$7:$B$236,B8,'Asesorías AG anterior'!$AB$7:$AB$236) -> 0
A9: =+A8+1 -> 3 | B9: NOMBRE 3 | C9: =_xlfn.XLOOKUP(B9,Códigos!$B$8:$B$406,Códigos!$A$8:$A$406,"Verificar",0) -> 300 | D9: =_xlfn.XLOOKUP(B9,'Consolidado Cobros'!$B$10:$B$268,'Consolidado Cobros'!$C$10:$C$268,"Verificar",0) -> 70116694 | E9: =IF((MOD((VALUE(MID(TEXT(D9,"000000000000000"),15,1))*3+VALUE(MID(TEXT(D9,"000000000000000"),14,1))*7+VALUE(MID(TEXT(D9,"000000000000000"),13,1))*13+VALUE(MID(TEXT(D9,"000000000000000"),12,1))*17+VALUE(MID(TEXT(D9,"000000000000000"),11,1))*19+VALUE(MID(TEXT(D9,"000000000000000"),10,1))*23+VALUE(MID(TEXT(D9,"000000000000000"),9,1))*29+VALUE(MID(TEXT(D9,"000000000000000"),8,1))*37+VALUE(MID(TEXT(D9,"000000000000000"),7,1))*41+VALUE(MID(TEXT(D9,"000000000000000"),6,1))*43+VALUE(MID(TEXT(D9,"000000000000000"),5,1))*47+VALUE(MID(TEXT(D9,"000000000000000"),4,1))*53+VALUE(MID(TEXT(D9,"000000000000000"),3,1))*59+VALUE(MID(TEXT(D9,"000000000000000"),2,1))*67+VALUE(MID(TEXT(D9,"000000000000000"),1,1))*71),11))=0,0,IF((MOD((VALUE(MID(TEXT(D9,"000000000000000"),15,1))*3+VALUE(MID(TEXT(D9,"000000000000000"),14,1))*7+VALUE(MID(TEXT(D9,"000000000000000"),13,1))*13+VALUE(MID(TEXT(D9,"000000000000000"),12,1))*17+VALUE(MID(TEXT(D9,"000000000000000"),11,1))*19+VALUE(MID(TEXT(D9,"000000000000000"),10,1))*23+VALUE(MID(TEXT(D9,"000000000000000"),9,1))*29+VALUE(MID(TEXT(D9,"000000000000000"),8,1))*37+VALUE(MID(TEXT(D9,"000000000000000"),7,1))*41+VALUE(MID(TEXT(D9,"000000000000000"),6,1))*43+VALUE(MID(TEXT(D9,"000000000000000"),5,1))*47+VALUE(MID(TEXT(D9,"000000000000000"),4,1))*53+VALUE(MID(TEXT(D9,"000000000000000"),3,1))*59+VALUE(MID(TEXT(D9,"000000000000000"),2,1))*67+VALUE(MID(TEXT(D9,"000000000000000"),1,1))*71),11))=1,1,11-(MOD((VALUE(MID(TEXT(D9,"000000000000000"),15,1))*3+VALUE(MID(TEXT(D9,"000000000000000"),14,1))*7+VALUE(MID(TEXT(D9,"000000000000000"),13,1))*13+VALUE(MID(TEXT(D9,"000000000000000"),12,1))*17+VALUE(MID(TEXT(D9,"000000000000000"),11,1))*19+VALUE(MID(TEXT(D9,"000000000000000"),10,1))*23+VALUE(MID(TEXT(D9,"000000000000000"),9,1))*29+VALUE(MID(TEXT(D9,"000000000000000"),8,1))*37+VALUE(MID(TEXT(D9,"000000000000000"),7,1))*41+VALUE(MID(TEXT(D9,"000000000000000"),6,1))*43+VALUE(MID(TEXT(D9,"000000000000000"),5,1))*47+VALUE(MID(TEXT(D9,"000000000000000"),4,1))*53+VALUE(MID(TEXT(D9,"000000000000000"),3,1))*59+VALUE(MID(TEXT(D9,"000000000000000"),2,1))*67+VALUE(MID(TEXT(D9,"000000000000000"),1,1))*71),11)))) -> 5 | F9: =+IF(H9>0,H9,0) -> 0 | G9: =+IF(V9>0,V9,0) -> 0 | H9: =+J9+L9+N9+P9+Q9+R9+U9 -> 0 | J9: =+(AE9/AD9*(100%+$J$4))*I9 -> 0 | L9: =+(AG9/AF9*(100%+$J$4))*K9 -> 0 | N9: 0 | P9: =ROUND(IF(O9="SI",AK9*(100%+$P$4),0),-4) -> 0 | Q9: 0 | R9: 0 | V9: =+X9+Z9+AB9 -> 0 | AD9: =SUMIF('Asesorías AG anterior'!$B$7:$B$236,B9,'Asesorías AG anterior'!$I$7:$I$236) -> 0.001 | AE9: =SUMIF('Asesorías AG anterior'!$B$7:$B$236,B9,'Asesorías AG anterior'!$J$7:$J$236) -> 0 | AF9: =SUMIF('Asesorías AG anterior'!$B$7:$B$236,B9,'Asesorías AG anterior'!$K$7:$K$236) -> 0.001 | AG9: =SUMIF('Asesorías AG anterior'!$B$7:$B$236,B9,'Asesorías AG anterior'!$L$7:$L$236) -> 0 | AH9: =SUMIF('Asesorías AG anterior'!$B$7:$B$236,B9,'Asesorías AG anterior'!$M$7:$M$236) -> 0 | AI9: =SUMIF('Asesorías AG anterior'!$B$7:$B$236,B9,'Asesorías AG anterior'!$N$7:$N$236) -> 0 | AJ9: =SUMIF('Asesorías AG anterior'!$B$7:$B$236,B9,'Asesorías AG anterior'!$O$7:$O$236) -> 0.001 | AK9: =SUMIF('Asesorías AG anterior'!$B$7:$B$236,B9,'Asesorías AG anterior'!$P$7:$P$236) -> 0 | AL9: =SUMIF('Asesorías AG anterior'!$B$7:$B$236,B9,'Asesorías AG anterior'!$Q$7:$Q$236) -> 0 | AM9: =SUMIF('Asesorías AG anterior'!$B$7:$B$236,B9,'Asesorías AG anterior'!$R$7:$R$236) -> 0 | AO9: =SUMIF('Asesorías AG anterior'!$B$7:$B$236,B9,'Asesorías AG anterior'!$T$7:$T$236) -> 0 | AP9: =SUMIF('Asesorías AG anterior'!$B$7:$B$236,B9,'Asesorías AG anterior'!$U$7:$U$236) -> 0 | AQ9: =SUMIF('Asesorías AG anterior'!$B$7:$B$236,B9,'Asesorías AG anterior'!$V$7:$V$236) -> 0 | AR9: =SUMIF('Asesorías AG anterior'!$B$7:$B$236,B9,'Asesorías AG anterior'!$W$7:$W$236) -> 0 | AS9: =SUMIF('Asesorías AG anterior'!$B$7:$B$236,B9,'Asesorías AG anterior'!$X$7:$X$236) -> 0 | AT9: =SUMIF('Asesorías AG anterior'!$B$7:$B$236,B9,'Asesorías AG anterior'!$Y$7:$Y$236) -> 0 | AU9: =SUMIF('Asesorías AG anterior'!$B$7:$B$236,B9,'Asesorías AG anterior'!$Z$7:$Z$236) -> 0 | AV9: =SUMIF('Asesorías AG anterior'!$B$7:$B$236,B9,'Asesorías AG anterior'!$AA$7:$AA$236) -> 0 | AW9: =SUMIF('Asesorías AG anterior'!$B$7:$B$236,B9,'Asesorías AG anterior'!$AB$7:$AB$236) -> 0
A10: =+A9+1 -> 4 | B10: NOMBRE 4 | C10: =_xlfn.XLOOKUP(B10,Códigos!$B$8:$B$406,Códigos!$A$8:$A$406,"Verificar",0) -> 312 | D10: =_xlfn.XLOOKUP(B10,'Consolidado Cobros'!$B$10:$B$268,'Consolidado Cobros'!$C$10:$C$268,"Verificar",0) -> 3349249 | E10: =IF((MOD((VALUE(MID(TEXT(D10,"000000000000000"),15,1))*3+VALUE(MID(TEXT(D10,"000000000000000"),14,1))*7+VALUE(MID(TEXT(D10,"000000000000000"),13,1))*13+VALUE(MID(TEXT(D10,"000000000000000"),12,1))*17+VALUE(MID(TEXT(D10,"000000000000000"),11,1))*19+VALUE(MID(TEXT(D10,"000000000000000"),10,1))*23+VALUE(MID(TEXT(D10,"000000000000000"),9,1))*29+VALUE(MID(TEXT(D10,"000000000000000"),8,1))*37+VALUE(MID(TEXT(D10,"000000000000000"),7,1))*41+VALUE(MID(TEXT(D10,"000000000000000"),6,1))*43+VALUE(MID(TEXT(D10,"000000000000000"),5,1))*47+VALUE(MID(TEXT(D10,"000000000000000"),4,1))*53+VALUE(MID(TEXT(D10,"000000000000000"),3,1))*59+VALUE(MID(TEXT(D10,"000000000000000"),2,1))*67+VALUE(MID(TEXT(D10,"000000000000000"),1,1))*71),11))=0,0,IF((MOD((VALUE(MID(TEXT(D10,"000000000000000"),15,1))*3+VALUE(MID(TEXT(D10,"000000000000000"),14,1))*7+VALUE(MID(TEXT(D10,"000000000000000"),13,1))*13+VALUE(MID(TEXT(D10,"000000000000000"),12,1))*17+VALUE(MID(TEXT(D10,"000000000000000"),11,1))*19+VALUE(MID(TEXT(D10,"000000000000000"),10,1))*23+VALUE(MID(TEXT(D10,"000000000000000"),9,1))*29+VALUE(MID(TEXT(D10,"000000000000000"),8,1))*37+VALUE(MID(TEXT(D10,"000000000000000"),7,1))*41+VALUE(MID(TEXT(D10,"000000000000000"),6,1))*43+VALUE(MID(TEXT(D10,"000000000000000"),5,1))*47+VALUE(MID(TEXT(D10,"000000000000000"),4,1))*53+VALUE(MID(TEXT(D10,"000000000000000"),3,1))*59+VALUE(MID(TEXT(D10,"000000000000000"),2,1))*67+VALUE(MID(TEXT(D10,"000000000000000"),1,1))*71),11))=1,1,11-(MOD((VALUE(MID(TEXT(D10,"000000000000000"),15,1))*3+VALUE(MID(TEXT(D10,"000000000000000"),14,1))*7+VALUE(MID(TEXT(D10,"000000000000000"),13,1))*13+VALUE(MID(TEXT(D10,"000000000000000"),12,1))*17+VALUE(MID(TEXT(D10,"000000000000000"),11,1))*19+VALUE(MID(TEXT(D10,"000000000000000"),10,1))*23+VALUE(MID(TEXT(D10,"000000000000000"),9,1))*29+VALUE(MID(TEXT(D10,"000000000000000"),8,1))*37+VALUE(MID(TEXT(D10,"000000000000000"),7,1))*41+VALUE(MID(TEXT(D10,"000000000000000"),6,1))*43+VALUE(MID(TEXT(D10,"000000000000000"),5,1))*47+VALUE(MID(TEXT(D10,"000000000000000"),4,1))*53+VALUE(MID(TEXT(D10,"000000000000000"),3,1))*59+VALUE(MID(TEXT(D10,"000000000000000"),2,1))*67+VALUE(MID(TEXT(D10,"000000000000000"),1,1))*71),11)))) -> 7 | F10: =+IF(H10>0,H10,0) -> 0 | G10: =+IF(V10>0,V10,0) -> 0 | H10: =+J10+L10+N10+P10+Q10+R10+U10 -> 0 | J10: =+(AE10/AD10*(100%+$J$4))*I10 -> 0 | L10: =+(AG10/AF10*(100%+$J$4))*K10 -> 0 | N10: 0 | P10: =ROUND(IF(O10="SI",AK10*(100%+$P$4),0),-4) -> 0 | Q10: 0 | R10: =+P10 -> 0 | V10: =+X10+Z10+AB10 -> 0 | AD10: =SUMIF('Asesorías AG anterior'!$B$7:$B$236,B10,'Asesorías AG anterior'!$I$7:$I$236) -> 0.001 | AE10: =SUMIF('Asesorías AG anterior'!$B$7:$B$236,B10,'Asesorías AG anterior'!$J$7:$J$236) -> 0 | AF10: =SUMIF('Asesorías AG anterior'!$B$7:$B$236,B10,'Asesorías AG anterior'!$K$7:$K$236) -> 0.001 | AG10: =SUMIF('Asesorías AG anterior'!$B$7:$B$236,B10,'Asesorías AG anterior'!$L$7:$L$236) -> 0 | AH10: =SUMIF('Asesorías AG anterior'!$B$7:$B$236,B10,'Asesorías AG anterior'!$M$7:$M$236) -> 0 | AI10: =SUMIF('Asesorías AG anterior'!$B$7:$B$236,B10,'Asesorías AG anterior'!$N$7:$N$236) -> 0 | AJ10: =SUMIF('Asesorías AG anterior'!$B$7:$B$236,B10,'Asesorías AG anterior'!$O$7:$O$236) -> 0.001 | AK10: =SUMIF('Asesorías AG anterior'!$B$7:$B$236,B10,'Asesorías AG anterior'!$P$7:$P$236) -> 0 | AL10: =SUMIF('Asesorías AG anterior'!$B$7:$B$236,B10,'Asesorías AG anterior'!$Q$7:$Q$236) -> 0 | AM10: =SUMIF('Asesorías AG anterior'!$B$7:$B$236,B10,'Asesorías AG anterior'!$R$7:$R$236) -> 0 | AO10: =SUMIF('Asesorías AG anterior'!$B$7:$B$236,B10,'Asesorías AG anterior'!$T$7:$T$236) -> 0 | AP10: =SUMIF('Asesorías AG anterior'!$B$7:$B$236,B10,'Asesorías AG anterior'!$U$7:$U$236) -> 0 | AQ10: =SUMIF('Asesorías AG anterior'!$B$7:$B$236,B10,'Asesorías AG anterior'!$V$7:$V$236) -> 0 | AR10: =SUMIF('Asesorías AG anterior'!$B$7:$B$236,B10,'Asesorías AG anterior'!$W$7:$W$236) -> 0 | AS10: =SUMIF('Asesorías AG anterior'!$B$7:$B$236,B10,'Asesorías AG anterior'!$X$7:$X$236) -> 0 | AT10: =SUMIF('Asesorías AG anterior'!$B$7:$B$236,B10,'Asesorías AG anterior'!$Y$7:$Y$236) -> 0 | AU10: =SUMIF('Asesorías AG anterior'!$B$7:$B$236,B10,'Asesorías AG anterior'!$Z$7:$Z$236) -> 0 | AV10: =SUMIF('Asesorías AG anterior'!$B$7:$B$236,B10,'Asesorías AG anterior'!$AA$7:$AA$236) -> 0 | AW10: =SUMIF('Asesorías AG anterior'!$B$7:$B$236,B10,'Asesorías AG anterior'!$AB$7:$AB$236) -> 0
A11: =+A10+1 -> 5 | B11: NOMBRE 5 | C11: =_xlfn.XLOOKUP(B11,Códigos!$B$8:$B$406,Códigos!$A$8:$A$406,"Verificar",0) -> 217 | D11: =_xlfn.XLOOKUP(B11,'Consolidado Cobros'!$B$10:$B$268,'Consolidado Cobros'!$C$10:$C$268,"Verificar",0) -> 71632774 | E11: =IF((MOD((VALUE(MID(TEXT(D11,"000000000000000"),15,1))*3+VALUE(MID(TEXT(D11,"000000000000000"),14,1))*7+VALUE(MID(TEXT(D11,"000000000000000"),13,1))*13+VALUE(MID(TEXT(D11,"000000000000000"),12,1))*17+VALUE(MID(TEXT(D11,"000000000000000"),11,1))*19+VALUE(MID(TEXT(D11,"000000000000000"),10,1))*23+VALUE(MID(TEXT(D11,"000000000000000"),9,1))*29+VALUE(MID(TEXT(D11,"000000000000000"),8,1))*37+VALUE(MID(TEXT(D11,"000000000000000"),7,1))*41+VALUE(MID(TEXT(D11,"000000000000000"),6,1))*43+VALUE(MID(TEXT(D11,"000000000000000"),5,1))*47+VALUE(MID(TEXT(D11,"000000000000000"),4,1))*53+VALUE(MID(TEXT(D11,"000000000000000"),3,1))*59+VALUE(MID(TEXT(D11,"000000000000000"),2,1))*67+VALUE(MID(TEXT(D11,"000000000000000"),1,1))*71),11))=0,0,IF((MOD((VALUE(MID(TEXT(D11,"000000000000000"),15,1))*3+VALUE(MID(TEXT(D11,"000000000000000"),14,1))*7+VALUE(MID(TEXT(D11,"000000000000000"),13,1))*13+VALUE(MID(TEXT(D11,"000000000000000"),12,1))*17+VALUE(MID(TEXT(D11,"000000000000000"),11,1))*19+VALUE(MID(TEXT(D11,"000000000000000"),10,1))*23+VALUE(MID(TEXT(D11,"000000000000000"),9,1))*29+VALUE(MID(TEXT(D11,"000000000000000"),8,1))*37+VALUE(MID(TEXT(D11,"000000000000000"),7,1))*41+VALUE(MID(TEXT(D11,"000000000000000"),6,1))*43+VALUE(MID(TEXT(D11,"000000000000000"),5,1))*47+VALUE(MID(TEXT(D11,"000000000000000"),4,1))*53+VALUE(MID(TEXT(D11,"000000000000000"),3,1))*59+VALUE(MID(TEXT(D11,"000000000000000"),2,1))*67+VALUE(MID(TEXT(D11,"000000000000000"),1,1))*71),11))=1,1,11-(MOD((VALUE(MID(TEXT(D11,"000000000000000"),15,1))*3+VALUE(MID(TEXT(D11,"000000000000000"),14,1))*7+VALUE(MID(TEXT(D11,"000000000000000"),13,1))*13+VALUE(MID(TEXT(D11,"000000000000000"),12,1))*17+VALUE(MID(TEXT(D11,"000000000000000"),11,1))*19+VALUE(MID(TEXT(D11,"000000000000000"),10,1))*23+VALUE(MID(TEXT(D11,"000000000000000"),9,1))*29+VALUE(MID(TEXT(D11,"000000000000000"),8,1))*37+VALUE(MID(TEXT(D11,"000000000000000"),7,1))*41+VALUE(MID(TEXT(D11,"000000000000000"),6,1))*43+VALUE(MID(TEXT(D11,"000000000000000"),5,1))*47+VALUE(MID(TEXT(D11,"000000000000000"),4,1))*53+VALUE(MID(TEXT(D11,"000000000000000"),3,1))*59+VALUE(MID(TEXT(D11,"000000000000000"),2,1))*67+VALUE(MID(TEXT(D11,"000000000000000"),1,1))*71),11)))) -> 2 | F11: =+IF(H11>0,H11,0) -> 100000 | G11: =+IF(V11>0,V11,0) -> 0 | H11: =+J11+L11+N11+P11+Q11+R11+U11 -> 100000 | I11: 3 | J11: =+(AE11/AD11*(100%+$J$4))*I11 -> 0 | L11: =+(AG11/AF11*(100%+$J$4))*K11 -> 0 | N11: 0 | O11: si | P11: =ROUND(IF(O11="SI",AK11*(100%+$P$4),0),-4)-20000 -> 50000 | Q11: 0 | R11: =+P11 -> 50000 | V11: =+X11+Z11+AB11 -> 0 | AD11: =SUMIF('Asesorías AG anterior'!$B$7:$B$236,B11,'Asesorías AG anterior'!$I$7:$I$236) -> 0.001 | AE11: =SUMIF('Asesorías AG anterior'!$B$7:$B$236,B11,'Asesorías AG anterior'!$J$7:$J$236) -> 0 | AF11: =SUMIF('Asesorías AG anterior'!$B$7:$B$236,B11,'Asesorías AG anterior'!$K$7:$K$236) -> 0.001 | AG11: =SUMIF('Asesorías AG anterior'!$B$7:$B$236,B11,'Asesorías AG anterior'!$L$7:$L$236) -> 0 | AH11: =SUMIF('Asesorías AG anterior'!$B$7:$B$236,B11,'Asesorías AG anterior'!$M$7:$M$236) -> 0 | AI11: =SUMIF('Asesorías AG anterior'!$B$7:$B$236,B11,'Asesorías AG anterior'!$N$7:$N$236) -> 0 | AJ11: =SUMIF('Asesorías AG anterior'!$B$7:$B$236,B11,'Asesorías AG anterior'!$O$7:$O$236) -> 0 | AK11: =SUMIF('Asesorías AG anterior'!$B$7:$B$236,B11,'Asesorías AG anterior'!$P$7:$P$236) -> 70000 | AL11: =SUMIF('Asesorías AG anterior'!$B$7:$B$236,B11,'Asesorías AG anterior'!$Q$7:$Q$236) -> 0 | AM11: =SUMIF('Asesorías AG anterior'!$B$7:$B$236,B11,'Asesorías AG anterior'!$R$7:$R$236) -> 0 | AO11: =SUMIF('Asesorías AG anterior'!$B$7:$B$236,B11,'Asesorías AG anterior'!$T$7:$T$236) -> 0 | AP11: =SUMIF('Asesorías AG anterior'!$B$7:$B$236,B11,'Asesorías AG anterior'!$U$7:$U$236) -> 0 | AQ11: =SUMIF('Asesorías AG anterior'!$B$7:$B$236,B11,'Asesorías AG anterior'!$V$7:$V$236) -> 0 | AR11: =SUMIF('Asesorías AG anterior'!$B$7:$B$236,B11,'Asesorías AG anterior'!$W$7:$W$236) -> 0 | AS11: =SUMIF('Asesorías AG anterior'!$B$7:$B$236,B11,'Asesorías AG anterior'!$X$7:$X$236) -> 0 | AT11: =SUMIF('Asesorías AG anterior'!$B$7:$B$236,B11,'Asesorías AG anterior'!$Y$7:$Y$236) -> 0 | AU11: =SUMIF('Asesorías AG anterior'!$B$7:$B$236,B11,'Asesorías AG anterior'!$Z$7:$Z$236) -> 0 | AV11: =SUMIF('Asesorías AG anterior'!$B$7:$B$236,B11,'Asesorías AG anterior'!$AA$7:$AA$236) -> 0 | AW11: =SUMIF('Asesorías AG anterior'!$B$7:$B$236,B11,'Asesorías AG anterior'!$AB$7:$AB$236) -> 0
A12: =+A11+1 -> 6 | B12: NOMBRE 6 | C12: =_xlfn.XLOOKUP(B12,Códigos!$B$8:$B$406,Códigos!$A$8:$A$406,"Verificar",0) -> 42 | D12: =_xlfn.XLOOKUP(B12,'Consolidado Cobros'!$B$10:$B$268,'Consolidado Cobros'!$C$10:$C$268,"Verificar",0) -> 21315528 | E12: =IF((MOD((VALUE(MID(TEXT(D12,"000000000000000"),15,1))*3+VALUE(MID(TEXT(D12,"000000000000000"),14,1))*7+VALUE(MID(TEXT(D12,"000000000000000"),13,1))*13+VALUE(MID(TEXT(D12,"000000000000000"),12,1))*17+VALUE(MID(TEXT(D12,"000000000000000"),11,1))*19+VALUE(MID(TEXT(D12,"000000000000000"),10,1))*23+VALUE(MID(TEXT(D12,"000000000000000"),9,1))*29+VALUE(MID(TEXT(D12,"000000000000000"),8,1))*37+VALUE(MID(TEXT(D12,"000000000000000"),7,1))*41+VALUE(MID(TEXT(D12,"000000000000000"),6,1))*43+VALUE(MID(TEXT(D12,"000000000000000"),5,1))*47+VALUE(MID(TEXT(D12,"000000000000000"),4,1))*53+VALUE(MID(TEXT(D12,"000000000000000"),3,1))*59+VALUE(MID(TEXT(D12,"000000000000000"),2,1))*67+VALUE(MID(TEXT(D12,"000000000000000"),1,1))*71),11))=0,0,IF((MOD((VALUE(MID(TEXT(D12,"000000000000000"),15,1))*3+VALUE(MID(TEXT(D12,"000000000000000"),14,1))*7+VALUE(MID(TEXT(D12,"000000000000000"),13,1))*13+VALUE(MID(TEXT(D12,"000000000000000"),12,1))*17+VALUE(MID(TEXT(D12,"000000000000000"),11,1))*19+VALUE(MID(TEXT(D12,"000000000000000"),10,1))*23+VALUE(MID(TEXT(D12,"000000000000000"),9,1))*29+VALUE(MID(TEXT(D12,"000000000000000"),8,1))*37+VALUE(MID(TEXT(D12,"000000000000000"),7,1))*41+VALUE(MID(TEXT(D12,"000000000000000"),6,1))*43+VALUE(MID(TEXT(D12,"000000000000000"),5,1))*47+VALUE(MID(TEXT(D12,"000000000000000"),4,1))*53+VALUE(MID(TEXT(D12,"000000000000000"),3,1))*59+VALUE(MID(TEXT(D12,"000000000000000"),2,1))*67+VALUE(MID(TEXT(D12,"000000000000000"),1,1))*71),11))=1,1,11-(MOD((VALUE(MID(TEXT(D12,"000000000000000"),15,1))*3+VALUE(MID(TEXT(D12,"000000000000000"),14,1))*7+VALUE(MID(TEXT(D12,"000000000000000"),13,1))*13+VALUE(MID(TEXT(D12,"000000000000000"),12,1))*17+VALUE(MID(TEXT(D12,"000000000000000"),11,1))*19+VALUE(MID(TEXT(D12,"000000000000000"),10,1))*23+VALUE(MID(TEXT(D12,"000000000000000"),9,1))*29+VALUE(MID(TEXT(D12,"000000000000000"),8,1))*37+VALUE(MID(TEXT(D12,"000000000000000"),7,1))*41+VALUE(MID(TEXT(D12,"000000000000000"),6,1))*43+VALUE(MID(TEXT(D12,"000000000000000"),5,1))*47+VALUE(MID(TEXT(D12,"000000000000000"),4,1))*53+VALUE(MID(TEXT(D12,"000000000000000"),3,1))*59+VALUE(MID(TEXT(D12,"000000000000000"),2,1))*67+VALUE(MID(TEXT(D12,"000000000000000"),1,1))*71),11)))) -> 6 | F12: =+IF(H12>0,H12,0) -> 0 | G12: =+IF(V12>0,V12,0) -> 0 | H12: =+J12+L12+N12+P12+Q12+R12+U12 -> 0 | J12: =+(AE12/AD12*(100%+$J$4))*I12 -> 0 | L12: =+(AG12/AF12*(100%+$J$4))*K12 -> 0 | N12: 0 | P12: =ROUND(IF(O12="SI",AK12*(100%+$P$4),0),-4) -> 0 | Q12: 0 | R12: =+P12 -> 0 | V12: =+X12+Z12+AB12 -> 0 | AD12: =SUMIF('Asesorías AG anterior'!$B$7:$B$236,B12,'Asesorías AG anterior'!$I$7:$I$236) -> 0.001 | AE12: =SUMIF('Asesorías AG anterior'!$B$7:$B$236,B12,'Asesorías AG anterior'!$J$7:$J$236) -> 0 | AF12: =SUMIF('Asesorías AG anterior'!$B$7:$B$236,B12,'Asesorías AG anterior'!$K$7:$K$236) -> 0.001 | AG12: =SUMIF('Asesorías AG anterior'!$B$7:$B$236,B12,'Asesorías AG anterior'!$L$7:$L$236) -> 0 | AH12: =SUMIF('Asesorías AG anterior'!$B$7:$B$236,B12,'Asesorías AG anterior'!$M$7:$M$236) -> 0 | AI12: =SUMIF('Asesorías AG anterior'!$B$7:$B$236,B12,'Asesorías AG anterior'!$N$7:$N$236) -> 0 | AJ12: =SUMIF('Asesorías AG anterior'!$B$7:$B$236,B12,'Asesorías AG anterior'!$O$7:$O$236) -> 0.001 | AK12: =SUMIF('Asesorías AG anterior'!$B$7:$B$236,B12,'Asesorías AG anterior'!$P$7:$P$236) -> 0 | AL12: =SUMIF('Asesorías AG anterior'!$B$7:$B$236,B12,'Asesorías AG anterior'!$Q$7:$Q$236) -> 0 | AM12: =SUMIF('Asesorías AG anterior'!$B$7:$B$236,B12,'Asesorías AG anterior'!$R$7:$R$236) -> 0 | AO12: =SUMIF('Asesorías AG anterior'!$B$7:$B$236,B12,'Asesorías AG anterior'!$T$7:$T$236) -> 0 | AP12: =SUMIF('Asesorías AG anterior'!$B$7:$B$236,B12,'Asesorías AG anterior'!$U$7:$U$236) -> 0 | AQ12: =SUMIF('Asesorías AG anterior'!$B$7:$B$236,B12,'Asesorías AG anterior'!$V$7:$V$236) -> 0 | AR12: =SUMIF('Asesorías AG anterior'!$B$7:$B$236,B12,'Asesorías AG anterior'!$W$7:$W$236) -> 0 | AS12: =SUMIF('Asesorías AG anterior'!$B$7:$B$236,B12,'Asesorías AG anterior'!$X$7:$X$236) -> 0 | AT12: =SUMIF('Asesorías AG anterior'!$B$7:$B$236,B12,'Asesorías AG anterior'!$Y$7:$Y$236) -> 0 | AU12: =SUMIF('Asesorías AG anterior'!$B$7:$B$236,B12,'Asesorías AG anterior'!$Z$7:$Z$236) -> 0 | AV12: =SUMIF('Asesorías AG anterior'!$B$7:$B$236,B12,'Asesorías AG anterior'!$AA$7:$AA$236) -> 0 | AW12: =SUMIF('Asesorías AG anterior'!$B$7:$B$236,B12,'Asesorías AG anterior'!$AB$7:$AB$236) -> 0
A13: =+A12+1 -> 7 | B13: NOMBRE 7 | C13: =_xlfn.XLOOKUP(B13,Códigos!$B$8:$B$406,Códigos!$A$8:$A$406,"Verificar",0) -> 43 | D13: =_xlfn.XLOOKUP(B13,'Consolidado Cobros'!$B$10:$B$268,'Consolidado Cobros'!$C$10:$C$268,"Verificar",0) -> 32336950 | E13: =IF((MOD((VALUE(MID(TEXT(D13,"000000000000000"),15,1))*3+VALUE(MID(TEXT(D13,"000000000000000"),14,1))*7+VALUE(MID(TEXT(D13,"000000000000000"),13,1))*13+VALUE(MID(TEXT(D13,"000000000000000"),12,1))*17+VALUE(MID(TEXT(D13,"000000000000000"),11,1))*19+VALUE(MID(TEXT(D13,"000000000000000"),10,1))*23+VALUE(MID(TEXT(D13,"000000000000000"),9,1))*29+VALUE(MID(TEXT(D13,"000000000000000"),8,1))*37+VALUE(MID(TEXT(D13,"000000000000000"),7,1))*41+VALUE(MID(TEXT(D13,"000000000000000"),6,1))*43+VALUE(MID(TEXT(D13,"000000000000000"),5,1))*47+VALUE(MID(TEXT(D13,"000000000000000"),4,1))*53+VALUE(MID(TEXT(D13,"000000000000000"),3,1))*59+VALUE(MID(TEXT(D13,"000000000000000"),2,1))*67+VALUE(MID(TEXT(D13,"000000000000000"),1,1))*71),11))=0,0,IF((MOD((VALUE(MID(TEXT(D13,"000000000000000"),15,1))*3+VALUE(MID(TEXT(D13,"000000000000000"),14,1))*7+VALUE(MID(TEXT(D13,"000000000000000"),13,1))*13+VALUE(MID(TEXT(D13,"000000000000000"),12,1))*17+VALUE(MID(TEXT(D13,"000000000000000"),11,1))*19+VALUE(MID(TEXT(D13,"000000000000000"),10,1))*23+VALUE(MID(TEXT(D13,"000000000000000"),9,1))*29+VALUE(MID(TEXT(D13,"000000000000000"),8,1))*37+VALUE(MID(TEXT(D13,"000000000000000"),7,1))*41+VALUE(MID(TEXT(D13,"000000000000000"),6,1))*43+VALUE(MID(TEXT(D13,"000000000000000"),5,1))*47+VALUE(MID(TEXT(D13,"000000000000000"),4,1))*53+VALUE(MID(TEXT(D13,"000000000000000"),3,1))*59+VALUE(MID(TEXT(D13,"000000000000000"),2,1))*67+VALUE(MID(TEXT(D13,"000000000000000"),1,1))*71),11))=1,1,11-(MOD((VALUE(MID(TEXT(D13,"000000000000000"),15,1))*3+VALUE(MID(TEXT(D13,"000000000000000"),14,1))*7+VALUE(MID(TEXT(D13,"000000000000000"),13,1))*13+VALUE(MID(TEXT(D13,"000000000000000"),12,1))*17+VALUE(MID(TEXT(D13,"000000000000000"),11,1))*19+VALUE(MID(TEXT(D13,"000000000000000"),10,1))*23+VALUE(MID(TEXT(D13,"000000000000000"),9,1))*29+VALUE(MID(TEXT(D13,"000000000000000"),8,1))*37+VALUE(MID(TEXT(D13,"000000000000000"),7,1))*41+VALUE(MID(TEXT(D13,"000000000000000"),6,1))*43+VALUE(MID(TEXT(D13,"000000000000000"),5,1))*47+VALUE(MID(TEXT(D13,"000000000000000"),4,1))*53+VALUE(MID(TEXT(D13,"000000000000000"),3,1))*59+VALUE(MID(TEXT(D13,"000000000000000"),2,1))*67+VALUE(MID(TEXT(D13,"000000000000000"),1,1))*71),11)))) -> 1 | F13: =+IF(H13>0,H13,0) -> 384948.68 | G13: =+IF(V13>0,V13,0) -> 0 | H13: =+J13+L13+N13+P13+Q13+R13+U13 -> 384948.68 | I13: 3 | J13: =+(AE13/AD13*(100%+$J$4))*I13 -> 384948.68 | L13: =+(AG13/AF13*(100%+$J$4))*K13 -> 0 | N13: 0 | P13: =ROUND(IF(O13="SI",AK13*(100%+$P$4),0),-4) -> 0 | Q13: 0 | R13: =+P13 -> 0 | V13: =+X13+Z13+AB13 -> 0 | AD13: =SUMIF('Asesorías AG anterior'!$B$7:$B$236,B13,'Asesorías AG anterior'!$I$7:$I$236) -> 3 | AE13: =SUMIF('Asesorías AG anterior'!$B$7:$B$236,B13,'Asesorías AG anterior'!$J$7:$J$236) -> 365920.8 | AF13: =SUMIF('Asesorías AG anterior'!$B$7:$B$236,B13,'Asesorías AG anterior'!$K$7:$K$236) -> 0.001 | AG13: =SUMIF('Asesorías AG anterior'!$B$7:$B$236,B13,'Asesorías AG anterior'!$L$7:$L$236) -> 0 | AH13: =SUMIF('Asesorías AG anterior'!$B$7:$B$236,B13,'Asesorías AG anterior'!$M$7:$M$236) -> 0 | AI13: =SUMIF('Asesorías AG anterior'!$B$7:$B$236,B13,'Asesorías AG anterior'!$N$7:$N$236) -> 0 | AJ13: =SUMIF('Asesorías AG anterior'!$B$7:$B$236,B13,'Asesorías AG anterior'!$O$7:$O$236) -> 0.001 | AK13: =SUMIF('Asesorías AG anterior'!$B$7:$B$236,B13,'Asesorías AG anterior'!$P$7:$P$236) -> 0 | AL13: =SUMIF('Asesorías AG anterior'!$B$7:$B$236,B13,'Asesorías AG anterior'!$Q$7:$Q$236) -> 0 | AM13: =SUMIF('Asesorías AG anterior'!$B$7:$B$236,B13,'Asesorías AG anterior'!$R$7:$R$236) -> 0 | AO13: =SUMIF('Asesorías AG anterior'!$B$7:$B$236,B13,'Asesorías AG anterior'!$T$7:$T$236) -> 0 | AP13: =SUMIF('Asesorías AG anterior'!$B$7:$B$236,B13,'Asesorías AG anterior'!$U$7:$U$236) -> 0 | AQ13: =SUMIF('Asesorías AG anterior'!$B$7:$B$236,B13,'Asesorías AG anterior'!$V$7:$V$236) -> 0 | AR13: =SUMIF('Asesorías AG anterior'!$B$7:$B$236,B13,'Asesorías AG anterior'!$W$7:$W$236) -> 0 | AS13: =SUMIF('Asesorías AG anterior'!$B$7:$B$236,B13,'Asesorías AG anterior'!$X$7:$X$236) -> 0 | AT13: =SUMIF('Asesorías AG anterior'!$B$7:$B$236,B13,'Asesorías AG anterior'!$Y$7:$Y$236) -> 0 | AU13: =SUMIF('Asesorías AG anterior'!$B$7:$B$236,B13,'Asesorías AG anterior'!$Z$7:$Z$236) -> 0 | AV13: =SUMIF('Asesorías AG anterior'!$B$7:$B$236,B13,'Asesorías AG anterior'!$AA$7:$AA$236) -> 0 | AW13: =SUMIF('Asesorías AG anterior'!$B$7:$B$236,B13,'Asesorías AG anterior'!$AB$7:$AB$236) -> 0
A14: =+A13+1 -> 8 | B14: NOMBRE 8 | C14: =_xlfn.XLOOKUP(B14,Códigos!$B$8:$B$406,Códigos!$A$8:$A$406,"Verificar",0) -> 44 | D14: =_xlfn.XLOOKUP(B14,'Consolidado Cobros'!$B$10:$B$268,'Consolidado Cobros'!$C$10:$C$268,"Verificar",0) -> 1152450831 | E14: =IF((MOD((VALUE(MID(TEXT(D14,"000000000000000"),15,1))*3+VALUE(MID(TEXT(D14,"000000000000000"),14,1))*7+VALUE(MID(TEXT(D14,"000000000000000"),13,1))*13+VALUE(MID(TEXT(D14,"000000000000000"),12,1))*17+VALUE(MID(TEXT(D14,"000000000000000"),11,1))*19+VALUE(MID(TEXT(D14,"000000000000000"),10,1))*23+VALUE(MID(TEXT(D14,"000000000000000"),9,1))*29+VALUE(MID(TEXT(D14,"000000000000000"),8,1))*37+VALUE(MID(TEXT(D14,"000000000000000"),7,1))*41+VALUE(MID(TEXT(D14,"000000000000000"),6,1))*43+VALUE(MID(TEXT(D14,"000000000000000"),5,1))*47+VALUE(MID(TEXT(D14,"000000000000000"),4,1))*53+VALUE(MID(TEXT(D14,"000000000000000"),3,1))*59+VALUE(MID(TEXT(D14,"000000000000000"),2,1))*67+VALUE(MID(TEXT(D14,"000000000000000"),1,1))*71),11))=0,0,IF((MOD((VALUE(MID(TEXT(D14,"000000000000000"),15,1))*3+VALUE(MID(TEXT(D14,"000000000000000"),14,1))*7+VALUE(MID(TEXT(D14,"000000000000000"),13,1))*13+VALUE(MID(TEXT(D14,"000000000000000"),12,1))*17+VALUE(MID(TEXT(D14,"000000000000000"),11,1))*19+VALUE(MID(TEXT(D14,"000000000000000"),10,1))*23+VALUE(MID(TEXT(D14,"000000000000000"),9,1))*29+VALUE(MID(TEXT(D14,"000000000000000"),8,1))*37+VALUE(MID(TEXT(D14,"000000000000000"),7,1))*41+VALUE(MID(TEXT(D14,"000000000000000"),6,1))*43+VALUE(MID(TEXT(D14,"000000000000000"),5,1))*47+VALUE(MID(TEXT(D14,"000000000000000"),4,1))*53+VALUE(MID(TEXT(D14,"000000000000000"),3,1))*59+VALUE(MID(TEXT(D14,"000000000000000"),2,1))*67+VALUE(MID(TEXT(D14,"000000000000000"),1,1))*71),11))=1,1,11-(MOD((VALUE(MID(TEXT(D14,"000000000000000"),15,1))*3+VALUE(MID(TEXT(D14,"000000000000000"),14,1))*7+VALUE(MID(TEXT(D14,"000000000000000"),13,1))*13+VALUE(MID(TEXT(D14,"000000000000000"),12,1))*17+VALUE(MID(TEXT(D14,"000000000000000"),11,1))*19+VALUE(MID(TEXT(D14,"000000000000000"),10,1))*23+VALUE(MID(TEXT(D14,"000000000000000"),9,1))*29+VALUE(MID(TEXT(D14,"000000000000000"),8,1))*37+VALUE(MID(TEXT(D14,"000000000000000"),7,1))*41+VALUE(MID(TEXT(D14,"000000000000000"),6,1))*43+VALUE(MID(TEXT(D14,"000000000000000"),5,1))*47+VALUE(MID(TEXT(D14,"000000000000000"),4,1))*53+VALUE(MID(TEXT(D14,"000000000000000"),3,1))*59+VALUE(MID(TEXT(D14,"000000000000000"),2,1))*67+VALUE(MID(TEXT(D14,"000000000000000"),1,1))*71),11)))) -> 7 | F14: =+IF(H14>0,H14,0) -> 0 | G14: =+IF(V14>0,V14,0) -> 0 | H14: =+J14+L14+N14+P14+Q14+R14+U14 -> 0 | J14: =+(AE14/AD14*(100%+$J$4))*I14 -> 0 | L14: =+(AG14/AF14*(100%+$J$4))*K14 -> 0 | N14: 0 | P14: =ROUND(IF(O14="SI",AK14*(100%+$P$4),0),-4) -> 0 | Q14: 0 | R14: =+P14 -> 0 | V14: =+X14+Z14+AB14 -> 0 | AD14: =SUMIF('Asesorías AG anterior'!$B$7:$B$236,B14,'Asesorías AG anterior'!$I$7:$I$236) -> 0.001 | AE14: =SUMIF('Asesorías AG anterior'!$B$7:$B$236,B14,'Asesorías AG anterior'!$J$7:$J$236) -> 0 | AF14: =SUMIF('Asesorías AG anterior'!$B$7:$B$236,B14,'Asesorías AG anterior'!$K$7:$K$236) -> 0.001 | AG14: =SUMIF('Asesorías AG anterior'!$B$7:$B$236,B14,'Asesorías AG anterior'!$L$7:$L$236) -> 0 | AH14: =SUMIF('Asesorías AG anterior'!$B$7:$B$236,B14,'Asesorías AG anterior'!$M$7:$M$236) -> 0 | AI14: =SUMIF('Asesorías AG anterior'!$B$7:$B$236,B14,'Asesorías AG anterior'!$N$7:$N$236) -> 0 | AJ14: =SUMIF('Asesorías AG anterior'!$B$7:$B$236,B14,'Asesorías AG anterior'!$O$7:$O$236) -> 0.001 | AK14: =SUMIF('Asesorías AG anterior'!$B$7:$B$236,B14,'Asesorías AG anterior'!$P$7:$P$236) -> 0 | AL14: =SUMIF('Asesorías AG anterior'!$B$7:$B$236,B14,'Asesorías AG anterior'!$Q$7:$Q$236) -> 0 | AM14: =SUMIF('Asesorías AG anterior'!$B$7:$B$236,B14,'Asesorías AG anterior'!$R$7:$R$236) -> 0 | AO14: =SUMIF('Asesorías AG anterior'!$B$7:$B$236,B14,'Asesorías AG anterior'!$T$7:$T$236) -> 0 | AP14: =SUMIF('Asesorías AG anterior'!$B$7:$B$236,B14,'Asesorías AG anterior'!$U$7:$U$236) -> 0 | AQ14: =SUMIF('Asesorías AG anterior'!$B$7:$B$236,B14,'Asesorías AG anterior'!$V$7:$V$236) -> 0 | AR14: =SUMIF('Asesorías AG anterior'!$B$7:$B$236,B14,'Asesorías AG anterior'!$W$7:$W$236) -> 0 | AS14: =SUMIF('Asesorías AG anterior'!$B$7:$B$236,B14,'Asesorías AG anterior'!$X$7:$X$236) -> 0 | AT14: =SUMIF('Asesorías AG anterior'!$B$7:$B$236,B14,'Asesorías AG anterior'!$Y$7:$Y$236) -> 0 | AU14: =SUMIF('Asesorías AG anterior'!$B$7:$B$236,B14,'Asesorías AG anterior'!$Z$7:$Z$236) -> 0 | AV14: =SUMIF('Asesorías AG anterior'!$B$7:$B$236,B14,'Asesorías AG anterior'!$AA$7:$AA$236) -> 0 | AW14: =SUMIF('Asesorías AG anterior'!$B$7:$B$236,B14,'Asesorías AG anterior'!$AB$7:$AB$236) -> 0 | AZ14: ALZATE GIRALDO BEATRIZ EUGENIA
R117: =+P117 -> 0 | AD117: =SUMIF('Asesorías AG anterior'!$B$7:$B$236,B117,'Asesorías AG anterior'!$I$7:$I$236) -> 0 | AE117: =SUMIF('Asesorías AG anterior'!$B$7:$B$236,B117,'Asesorías AG anterior'!$J$7:$J$236) -> 0 | AF117: =SUMIF('Asesorías AG anterior'!$B$7:$B$236,B117,'Asesorías AG anterior'!$K$7:$K$236) -> 0 | AG117: =SUMIF('Asesorías AG anterior'!$B$7:$B$236,B117,'Asesorías AG anterior'!$L$7:$L$236) -> 0 | AH117: =SUMIF('Asesorías AG anterior'!$B$7:$B$236,B117,'Asesorías AG anterior'!$M$7:$M$236) -> 0 | AI117: =SUMIF('Asesorías AG anterior'!$B$7:$B$236,B117,'Asesorías AG anterior'!$N$7:$N$236) -> 0 | AJ117: =SUMIF('Asesorías AG anterior'!$B$7:$B$236,B117,'Asesorías AG anterior'!$O$7:$O$236) -> 0 | AK117: =SUMIF('Asesorías AG anterior'!$B$7:$B$236,B117,'Asesorías AG anterior'!$P$7:$P$236) -> 0 | AL117: =SUMIF('Asesorías AG anterior'!$B$7:$B$236,B117,'Asesorías AG anterior'!$Q$7:$Q$236) -> 0 | AM117: =SUMIF('Asesorías AG anterior'!$B$7:$B$236,B117,'Asesorías AG anterior'!$R$7:$R$236) -> 0 | AO117: =SUMIF('Asesorías AG anterior'!$B$7:$B$236,B117,'Asesorías AG anterior'!$T$7:$T$236) -> 0 | AP117: =SUMIF('Asesorías AG anterior'!$B$7:$B$236,B117,'Asesorías AG anterior'!$U$7:$U$236) -> 0 | AQ117: =SUMIF('Asesorías AG anterior'!$B$7:$B$236,B117,'Asesorías AG anterior'!$V$7:$V$236) -> 0 | AR117: =SUMIF('Asesorías AG anterior'!$B$7:$B$236,B117,'Asesorías AG anterior'!$W$7:$W$236) -> 0 | AS117: =SUMIF('Asesorías AG anterior'!$B$7:$B$236,B117,'Asesorías AG anterior'!$X$7:$X$236) -> 0 | AT117: =SUMIF('Asesorías AG anterior'!$B$7:$B$236,B117,'Asesorías AG anterior'!$Y$7:$Y$236) -> 0 | AU117: =SUMIF('Asesorías AG anterior'!$B$7:$B$236,B117,'Asesorías AG anterior'!$Z$7:$Z$236) -> 0 | AV117: =SUMIF('Asesorías AG anterior'!$B$7:$B$236,B117,'Asesorías AG anterior'!$AA$7:$AA$236) -> 0 | AW117: =SUMIF('Asesorías AG anterior'!$B$7:$B$236,B117,'Asesorías AG anterior'!$AB$7:$AB$236) -> 0
J118: REVISORIA FISCAL 2019 | K118: REVISORIA FISCAL 2020 | L118: REVISORIA FISCAL 2021 | M118: REVISORIA FISCAL 2022 | N118: REVISORIA FISCAL 2023 | O118: REVISORIA FISCAL 2024 | R118: =+P118 -> 0 | AD118: =SUMIF('Asesorías AG anterior'!$B$7:$B$236,B118,'Asesorías AG anterior'!$I$7:$I$236) -> 0 | AE118: =SUMIF('Asesorías AG anterior'!$B$7:$B$236,B118,'Asesorías AG anterior'!$J$7:$J$236) -> 0 | AF118: =SUMIF('Asesorías AG anterior'!$B$7:$B$236,B118,'Asesorías AG anterior'!$K$7:$K$236) -> 0 | AG118: =SUMIF('Asesorías AG anterior'!$B$7:$B$236,B118,'Asesorías AG anterior'!$L$7:$L$236) -> 0 | AH118: =SUMIF('Asesorías AG anterior'!$B$7:$B$236,B118,'Asesorías AG anterior'!$M$7:$M$236) -> 0 | AI118: =SUMIF('Asesorías AG anterior'!$B$7:$B$236,B118,'Asesorías AG anterior'!$N$7:$N$236) -> 0 | AJ118: =SUMIF('Asesorías AG anterior'!$B$7:$B$236,B118,'Asesorías AG anterior'!$O$7:$O$236) -> 0 | AK118: =SUMIF('Asesorías AG anterior'!$B$7:$B$236,B118,'Asesorías AG anterior'!$P$7:$P$236) -> 0 | AL118: =SUMIF('Asesorías AG anterior'!$B$7:$B$236,B118,'Asesorías AG anterior'!$Q$7:$Q$236) -> 0 | AM118: =SUMIF('Asesorías AG anterior'!$B$7:$B$236,B118,'Asesorías AG anterior'!$R$7:$R$236) -> 0 | AO118: =SUMIF('Asesorías AG anterior'!$B$7:$B$236,B118,'Asesorías AG anterior'!$T$7:$T$236) -> 0 | AP118: =SUMIF('Asesorías AG anterior'!$B$7:$B$236,B118,'Asesorías AG anterior'!$U$7:$U$236) -> 0 | AQ118: =SUMIF('Asesorías AG anterior'!$B$7:$B$236,B118,'Asesorías AG anterior'!$V$7:$V$236) -> 0 | AR118: =SUMIF('Asesorías AG anterior'!$B$7:$B$236,B118,'Asesorías AG anterior'!$W$7:$W$236) -> 0 | AS118: =SUMIF('Asesorías AG anterior'!$B$7:$B$236,B118,'Asesorías AG anterior'!$X$7:$X$236) -> 0 | AT118: =SUMIF('Asesorías AG anterior'!$B$7:$B$236,B118,'Asesorías AG anterior'!$Y$7:$Y$236) -> 0 | AU118: =SUMIF('Asesorías AG anterior'!$B$7:$B$236,B118,'Asesorías AG anterior'!$Z$7:$Z$236) -> 0 | AV118: =SUMIF('Asesorías AG anterior'!$B$7:$B$236,B118,'Asesorías AG anterior'!$AA$7:$AA$236) -> 0 | AW118: =SUMIF('Asesorías AG anterior'!$B$7:$B$236,B118,'Asesorías AG anterior'!$AB$7:$AB$236) -> 0
N235: 0 | P235: =ROUND(IF(O235="SI",AK235*(100%+$P$4),0),-4) -> 0 | Q235: 0 | R235: 0 | V235: =+X235+Z235+AB235 -> 0 | AD235: =SUMIF('Asesorías AG anterior'!$B$7:$B$236,B235,'Asesorías AG anterior'!$I$7:$I$236) -> 0 | AE235: =SUMIF('Asesorías AG anterior'!$B$7:$B$236,B235,'Asesorías AG anterior'!$J$7:$J$236) -> 0 | AF235: =SUMIF('Asesorías AG anterior'!$B$7:$B$236,B235,'Asesorías AG anterior'!$K$7:$K$236) -> 0 | AG235: =SUMIF('Asesorías AG anterior'!$B$7:$B$236,B235,'Asesorías AG anterior'!$L$7:$L$236) -> 0 | AH235: =SUMIF('Asesorías AG anterior'!$B$7:$B$236,B235,'Asesorías AG anterior'!$M$7:$M$236) -> 0 | AI235: =SUMIF('Asesorías AG anterior'!$B$7:$B$236,B235,'Asesorías AG anterior'!$N$7:$N$236) -> 0 | AJ235: =SUMIF('Asesorías AG anterior'!$B$7:$B$236,B235,'Asesorías AG anterior'!$O$7:$O$236) -> 0 | AK235: =SUMIF('Asesorías AG anterior'!$B$7:$B$236,B235,'Asesorías AG anterior'!$P$7:$P$236) -> 0 | AL235: =SUMIF('Asesorías AG anterior'!$B$7:$B$236,B235,'Asesorías AG anterior'!$Q$7:$Q$236) -> 0 | AM235: =SUMIF('Asesorías AG anterior'!$B$7:$B$236,B235,'Asesorías AG anterior'!$R$7:$R$236) -> 0 | AO235: =SUMIF('Asesorías AG anterior'!$B$7:$B$236,B235,'Asesorías AG anterior'!$T$7:$T$236) -> 0 | AP235: =SUMIF('Asesorías AG anterior'!$B$7:$B$236,B235,'Asesorías AG anterior'!$U$7:$U$236) -> 0 | AQ235: =SUMIF('Asesorías AG anterior'!$B$7:$B$236,B235,'Asesorías AG anterior'!$V$7:$V$236) -> 0 | AR235: =SUMIF('Asesorías AG anterior'!$B$7:$B$236,B235,'Asesorías AG anterior'!$W$7:$W$236) -> 0 | AS235: =SUMIF('Asesorías AG anterior'!$B$7:$B$236,B235,'Asesorías AG anterior'!$X$7:$X$236) -> 0 | AT235: =SUMIF('Asesorías AG anterior'!$B$7:$B$236,B235,'Asesorías AG anterior'!$Y$7:$Y$236) -> 0 | AU235: =SUMIF('Asesorías AG anterior'!$B$7:$B$236,B235,'Asesorías AG anterior'!$Z$7:$Z$236) -> 0 | AV235: =SUMIF('Asesorías AG anterior'!$B$7:$B$236,B235,'Asesorías AG anterior'!$AA$7:$AA$236) -> 0 | AW235: =SUMIF('Asesorías AG anterior'!$B$7:$B$236,B235,'Asesorías AG anterior'!$AB$7:$AB$236) -> 0
N236: 0 | P236: =ROUND(IF(O236="SI",AK236*(100%+$P$4),0),-4) -> 0 | Q236: 0 | R236: 0 | V236: =+X236+Z236+AB236 -> 0 | AD236: =SUMIF('Asesorías AG anterior'!$B$7:$B$236,B236,'Asesorías AG anterior'!$I$7:$I$236) -> 0 | AE236: =SUMIF('Asesorías AG anterior'!$B$7:$B$236,B236,'Asesorías AG anterior'!$J$7:$J$236) -> 0 | AF236: =SUMIF('Asesorías AG anterior'!$B$7:$B$236,B236,'Asesorías AG anterior'!$K$7:$K$236) -> 0 | AG236: =SUMIF('Asesorías AG anterior'!$B$7:$B$236,B236,'Asesorías AG anterior'!$L$7:$L$236) -> 0 | AH236: =SUMIF('Asesorías AG anterior'!$B$7:$B$236,B236,'Asesorías AG anterior'!$M$7:$M$236) -> 0 | AI236: =SUMIF('Asesorías AG anterior'!$B$7:$B$236,B236,'Asesorías AG anterior'!$N$7:$N$236) -> 0 | AJ236: =SUMIF('Asesorías AG anterior'!$B$7:$B$236,B236,'Asesorías AG anterior'!$O$7:$O$236) -> 0 | AK236: =SUMIF('Asesorías AG anterior'!$B$7:$B$236,B236,'Asesorías AG anterior'!$P$7:$P$236) -> 0 | AL236: =SUMIF('Asesorías AG anterior'!$B$7:$B$236,B236,'Asesorías AG anterior'!$Q$7:$Q$236) -> 0 | AM236: =SUMIF('Asesorías AG anterior'!$B$7:$B$236,B236,'Asesorías AG anterior'!$R$7:$R$236) -> 0 | AO236: =SUMIF('Asesorías AG anterior'!$B$7:$B$236,B236,'Asesorías AG anterior'!$T$7:$T$236) -> 0 | AP236: =SUMIF('Asesorías AG anterior'!$B$7:$B$236,B236,'Asesorías AG anterior'!$U$7:$U$236) -> 0 | AQ236: =SUMIF('Asesorías AG anterior'!$B$7:$B$236,B236,'Asesorías AG anterior'!$V$7:$V$236) -> 0 | AR236: =SUMIF('Asesorías AG anterior'!$B$7:$B$236,B236,'Asesorías AG anterior'!$W$7:$W$236) -> 0 | AS236: =SUMIF('Asesorías AG anterior'!$B$7:$B$236,B236,'Asesorías AG anterior'!$X$7:$X$236) -> 0 | AT236: =SUMIF('Asesorías AG anterior'!$B$7:$B$236,B236,'Asesorías AG anterior'!$Y$7:$Y$236) -> 0 | AU236: =SUMIF('Asesorías AG anterior'!$B$7:$B$236,B236,'Asesorías AG anterior'!$Z$7:$Z$236) -> 0 | AV236: =SUMIF('Asesorías AG anterior'!$B$7:$B$236,B236,'Asesorías AG anterior'!$AA$7:$AA$236) -> 0 | AW236: =SUMIF('Asesorías AG anterior'!$B$7:$B$236,B236,'Asesorías AG anterior'!$AB$7:$AB$236) -> 0
N237: 0 | P237: =ROUND(IF(O237="SI",AK237*(100%+$P$4),0),-4) -> 0 | Q237: 0 | R237: 0 | V237: =+X237+Z237+AB237 -> 0 | AD237: =SUMIF('Asesorías AG anterior'!$B$7:$B$236,B237,'Asesorías AG anterior'!$I$7:$I$236) -> 0 | AE237: =SUMIF('Asesorías AG anterior'!$B$7:$B$236,B237,'Asesorías AG anterior'!$J$7:$J$236) -> 0 | AF237: =SUMIF('Asesorías AG anterior'!$B$7:$B$236,B237,'Asesorías AG anterior'!$K$7:$K$236) -> 0 | AG237: =SUMIF('Asesorías AG anterior'!$B$7:$B$236,B237,'Asesorías AG anterior'!$L$7:$L$236) -> 0 | AH237: =SUMIF('Asesorías AG anterior'!$B$7:$B$236,B237,'Asesorías AG anterior'!$M$7:$M$236) -> 0 | AI237: =SUMIF('Asesorías AG anterior'!$B$7:$B$236,B237,'Asesorías AG anterior'!$N$7:$N$236) -> 0 | AJ237: =SUMIF('Asesorías AG anterior'!$B$7:$B$236,B237,'Asesorías AG anterior'!$O$7:$O$236) -> 0 | AK237: =SUMIF('Asesorías AG anterior'!$B$7:$B$236,B237,'Asesorías AG anterior'!$P$7:$P$236) -> 0 | AL237: =SUMIF('Asesorías AG anterior'!$B$7:$B$236,B237,'Asesorías AG anterior'!$Q$7:$Q$236) -> 0 | AM237: =SUMIF('Asesorías AG anterior'!$B$7:$B$236,B237,'Asesorías AG anterior'!$R$7:$R$236) -> 0 | AO237: =SUMIF('Asesorías AG anterior'!$B$7:$B$236,B237,'Asesorías AG anterior'!$T$7:$T$236) -> 0 | AP237: =SUMIF('Asesorías AG anterior'!$B$7:$B$236,B237,'Asesorías AG anterior'!$U$7:$U$236) -> 0 | AQ237: =SUMIF('Asesorías AG anterior'!$B$7:$B$236,B237,'Asesorías AG anterior'!$V$7:$V$236) -> 0 | AR237: =SUMIF('Asesorías AG anterior'!$B$7:$B$236,B237,'Asesorías AG anterior'!$W$7:$W$236) -> 0 | AS237: =SUMIF('Asesorías AG anterior'!$B$7:$B$236,B237,'Asesorías AG anterior'!$X$7:$X$236) -> 0 | AT237: =SUMIF('Asesorías AG anterior'!$B$7:$B$236,B237,'Asesorías AG anterior'!$Y$7:$Y$236) -> 0 | AU237: =SUMIF('Asesorías AG anterior'!$B$7:$B$236,B237,'Asesorías AG anterior'!$Z$7:$Z$236) -> 0 | AV237: =SUMIF('Asesorías AG anterior'!$B$7:$B$236,B237,'Asesorías AG anterior'!$AA$7:$AA$236) -> 0 | AW237: =SUMIF('Asesorías AG anterior'!$B$7:$B$236,B237,'Asesorías AG anterior'!$AB$7:$AB$236) -> 0
N238: 0 | P238: =ROUND(IF(O238="SI",AK238*(100%+$P$4),0),-4) -> 0 | Q238: 0 | R238: 0 | V238: =+X238+Z238+AB238 -> 0 | AD238: =SUMIF('Asesorías AG anterior'!$B$7:$B$236,B238,'Asesorías AG anterior'!$I$7:$I$236) -> 0 | AE238: =SUMIF('Asesorías AG anterior'!$B$7:$B$236,B238,'Asesorías AG anterior'!$J$7:$J$236) -> 0 | AF238: =SUMIF('Asesorías AG anterior'!$B$7:$B$236,B238,'Asesorías AG anterior'!$K$7:$K$236) -> 0 | AG238: =SUMIF('Asesorías AG anterior'!$B$7:$B$236,B238,'Asesorías AG anterior'!$L$7:$L$236) -> 0 | AH238: =SUMIF('Asesorías AG anterior'!$B$7:$B$236,B238,'Asesorías AG anterior'!$M$7:$M$236) -> 0 | AI238: =SUMIF('Asesorías AG anterior'!$B$7:$B$236,B238,'Asesorías AG anterior'!$N$7:$N$236) -> 0 | AJ238: =SUMIF('Asesorías AG anterior'!$B$7:$B$236,B238,'Asesorías AG anterior'!$O$7:$O$236) -> 0 | AK238: =SUMIF('Asesorías AG anterior'!$B$7:$B$236,B238,'Asesorías AG anterior'!$P$7:$P$236) -> 0 | AL238: =SUMIF('Asesorías AG anterior'!$B$7:$B$236,B238,'Asesorías AG anterior'!$Q$7:$Q$236) -> 0 | AM238: =SUMIF('Asesorías AG anterior'!$B$7:$B$236,B238,'Asesorías AG anterior'!$R$7:$R$236) -> 0 | AO238: =SUMIF('Asesorías AG anterior'!$B$7:$B$236,B238,'Asesorías AG anterior'!$T$7:$T$236) -> 0 | AP238: =SUMIF('Asesorías AG anterior'!$B$7:$B$236,B238,'Asesorías AG anterior'!$U$7:$U$236) -> 0 | AQ238: =SUMIF('Asesorías AG anterior'!$B$7:$B$236,B238,'Asesorías AG anterior'!$V$7:$V$236) -> 0 | AR238: =SUMIF('Asesorías AG anterior'!$B$7:$B$236,B238,'Asesorías AG anterior'!$W$7:$W$236) -> 0 | AS238: =SUMIF('Asesorías AG anterior'!$B$7:$B$236,B238,'Asesorías AG anterior'!$X$7:$X$236) -> 0 | AT238: =SUMIF('Asesorías AG anterior'!$B$7:$B$236,B238,'Asesorías AG anterior'!$Y$7:$Y$236) -> 0 | AU238: =SUMIF('Asesorías AG anterior'!$B$7:$B$236,B238,'Asesorías AG anterior'!$Z$7:$Z$236) -> 0 | AV238: =SUMIF('Asesorías AG anterior'!$B$7:$B$236,B238,'Asesorías AG anterior'!$AA$7:$AA$236) -> 0 | AW238: =SUMIF('Asesorías AG anterior'!$B$7:$B$236,B238,'Asesorías AG anterior'!$AB$7:$AB$236) -> 0
B240: TOTALES | F240: =SUM(F6:F239) -> 484948.68 | J240: =SUM(J6:J239) -> 384948.68 | L240: =SUM(L6:L239) -> 0 | N240: =SUM(N6:N239) -> 0 | P240: =SUM(P6:P239) -> 50000 | Q240: =SUM(Q6:Q239) -> 0 | R240: =SUM(R6:R239) -> 50000 | U240: =SUM(U7:U239) -> 0 | V240: =SUM(V7:V239) -> 0 | X240: =SUM(X7:X239) -> 0 | Z240: =SUM(Z7:Z239) -> 0 | AB240: =SUM(AB7:AB239) -> 0 | AE240: =SUM(AE7:AE239) -> 365920.8 | AG240: =SUM(AG7:AG239) -> 0 | AI240: =SUM(AI7:AI239) -> 0 | AK240: =SUM(AK7:AK239) -> 70000 | AL240: =SUM(AL7:AL239) -> 0 | AM240: =SUM(AM7:AM239) -> 0 | AN240: =SUM(AN7:AN239) -> 0 | AP240: =SUM(AP7:AP239) -> 0 | AQ240: =SUM(AQ7:AQ239) -> 0 | AR240: =SUM(AR7:AR239) -> 0 | AS240: =SUM(AS7:AS239) -> 0 | AT240: =SUM(AT7:AT239) -> 0 | AU240: =SUM(AU7:AU239) -> 0 | AV240: =SUM(AV7:AV239) -> 0 | AW240: =SUM(AW7:AW239) -> 0
A243: =+Facturas!D82+'Cuentas de Cobro'!D215 -> 29
A244: =+A234-A243 -> -29
A248: RETIRADOS EN 2025

Sheet Facturas año anterior
A2: PRESUPUESTO DE COBROS -FACTURAS- | Q2: Mínima Mvto | S2: Mínima 1° Vez | U2: PARA CALCULAR EL VALOR A COBRAR POR EL PRESENTE AÑO | AO2: IPC 2023 | AP2: Mínima Mvto -año anterior- | AQ2: Mínima 1° Vez -Año anterior-
A3: AÑO GRAVABLE 2023 | Q3: 220000 | S3: 350000 | AO3: 0.0928 | AP3: 200000 | AQ3: 320000
A4: PERSONAS NATURALES Y PERSONAS JURÍDICAS | F4: VALORES A FACTURAR -PRESENTE AÑO- | U4: PRESUPUESTOS DE COBRO -AÑO GRAVABLE 2022- | AO4: Vr Incrementado | AP4: 218560 | AQ4: 349696
G5: 0.19 | I5: 0.11 | U5: IPC | V5: 0.0928 | X5: 0.5 | Z5: 0.75 | AB5: 0.15 | AD5: 0.2 | AF5: 0.1 | AH5: 0.2 | AJ5: 0.3
A6: No. | B6: APELLIDOS Y NOMBRES o RAZÓN SOCIAL | C6: CÓDIGO | D6: NIT No. | E6: D. V. | F6: VALOR BRUTO A ELABORAR LA FACTURA | G6: I V A | H6: AGENTE RETENEDOR | I6: RETENCIÓN EN LA FUENTE | J6: VALOR FACTURA antes de RTE FTE | K6: VALOR A PAGAR NETO DE LA FACTURA | L6: VoBo ELABORAR Fra. | M6: FACTURA No. | N6: MEDIO | O6: FECHA | P6: ESTADO | Q6: VALOR CUENTA DE COBRO -POR PRÉSTAMOS- | R6: CUENTA DE COBRO No. | S6: OBSERVACIONES | U6: SI o NO | V6: VALOR DECLARACIÓN RENTA | W6: SI o NO | X6: VALOR DECLARACIÓN I AL P 2023 | Y6: SI o NO | Z6: VALOR MEDIOS MAGNÉTICOS | AA6: SI o NO | AB6: EXÓGENA MPIO MEDELLÍN | AC6: SI o NO | AD6: REG ÚNICO de BENEFICIARIOS | AE6: SI o NO | AF6: VALOR FORMATO 2516 CONSERVAR | AG6: SI o NO | AH6: VALOR FORMATO 2516 TRANSMITIR | AI6: SI o NO | AJ6: VALOR DECLARACIÓN ACTIVOS EN EL EXTERIOR | AK6: VALOR OTRAS ASESORÍAS | AL6: PRÉSTAMOS | AM6: TOTAL PRESUPUESTADO | AO6: FACTURAS y C de C
A8: PERSONAS NATURALES
A9: 1 | B9: NOMBRE 1 | C9: 52 | D9: 43431768 | E9: 3 | F9: 490000 | G9: 93100 | H9: S | I9: -53900 | J9: 583100 | K9: 529200 | M9: GTFF141 | N9: Correo | O9: 45614 | P9: OK/ | Q9: 0 | S9: Fra con -Ruiz González Álvaro H. | U9: SI | V9: 488000 | X9: 0 | Z9: 0 | AB9: 0 | AD9: 0 | AF9: 0 | AH9: 0 | AJ9: 0 | AK9: 0 | AL9: 0 | AM9: 490000
A10: 2 | B10: NOMBRE 2 | C10: 56 | D10: 87082052990 | E10: 2 | F10: 1830000 | G10: 347700 | H10: NO | I10: NO RETENCIÓN | J10: 2177700 | K10: 2177700 | Q10: 0 | S10: BETANCUR RESTREPO SARA LUISA | U10: SI | V10: 582000 | X10: 0 | Y10: SI | Z10: 437000 | AB10: 0 | AD10: 0 | AF10: 0 | AH10: 0 | AI10: SI | AJ10: 174600 | AK10: 631552 | AL10: 0 | AM10: 1830000
A11: 3 | B11: NOMBRE 3 | C11: 59 | D11: 43255512 | E11: 0 | F11: 580000 | G11: 110200 | H11: S | I11: -63800 | J11: 690200 | K11: 626400 | M11: GTFF143 | N11: Correo | O11: 45615 | Q11: 0 | S11: Fra con -San Antonio de la Almería | U11: SI | V11: 582000 | X11: 0 | Z11: 0 | AB11: 0 | AD11: 0 | AF11: 0 | AH11: 0 | AJ11: 0 | AK11: 0 | AL11: 0 | AM11: 580000
A12: 4 | B12: NOMBRE 4 | C12: 75 | D12: 21829209 | E12: 8 | F12: 1420000 | G12: 269800 | H12: S | I12: -156200 | J12: 1689800 | K12: 1533600 | M12: GFTT150 | N12: Correo | O12: 45621 | Q12: 0 | S12: Fra con -Javier Ríos e Hijos | U12: SI | V12: 946000 | W12: SI | X12: 473000 | Z12: 0 | AB12: 0 | AD12: 0 | AF12: 0 | AH12: 0 | AJ12: 0 | AK12: 0 | AL12: 0 | AM12: 1420000
A13: 5 | B13: NOMBRE 5 | C13: 81 | D13: 21378780 | E13: 6 | F13: 1810000 | G13: 343900 | H13: S | I13: -199100 | J13: 2153900 | K13: 1954800 | L13: SI | M13: ojo truly | Q13: 0 | S13: Fra con -Truly Nolen | U13: SI | V13: 1812000 | X13: 0 | Z13: 0 | AB13: 0 | AD13: 0 | AF13: 0 | AH13: 0 | AJ13: 0 | AK13: 0 | AL13: 0 | AM13: 1810000
A14: 6 | B14: NOMBRE 6 | C14: 54 | D14: 43422834 | E14: 3 | F14: 580000 | G14: 110200 | H14: S | I14: -63800 | J14: 690200 | K14: 626400 | M14: GTFF143 | N14: Correo | O14: 45615 | Q14: 0 | S14: Fra con -San Antonio de la Almería | U14: SI | V14: 582000 | X14: 0 | Z14: 0 | AB14: 0 | AD14: 0 | AF14: 0 | AH14: 0 | AJ14: 0 | AK14: 0 | AL14: 0 | AM14: 580000
A15: 7 | B15: NOMBRE 7 | C15: 99 | D15: 43422711 | E15: 6 | F15: 1340000 | G15: 254600 | H15: S | I15: -147400 | J15: 1594600 | K15: 1447200 | M15: GTFF143 | N15: Correo | O15: 45615 | Q15: 0 | S15: Fra con -San Antonio de la Almería | U15: SI | V15: 1342000 | X15: 0 | Z15: 0 | AB15: 0 | AD15: 0 | AF15: 0 | AH15: 0 | AJ15: 0 | AK15: 0 | AL15: 0 | AM15: 1340000
A16: 8 | B16: NOMBRE 8 | C16: 80 | D16: 1037630601 | E16: 5 | F16: 210000 | G16: 39900 | H16: S | I16: -23100 | J16: 249900 | K16: 226800 | M16: GTFF141 | N16: Correo | O16: 45614 | P16: PENDIENTE | Q16: 0 | S16: Fra con -Ruiz González Álvaro H. | U16: SI | V16: 210000 | X16: 0 | Z16: 0 | AB16: 0 | AD16: 0 | AF16: 0 | AH16: 0 | AJ16: 0 | AK16: 0 | AL16: 0 | AM16: 210000

Sheet C de C año anterior
H1: OJO PAGO POR 356MIL REVISAR QUIÉN?
A2: PRESUPUESTO DE COBROS -FACTURAS- | M2: Mínima Mvto | N2: Mínima 1° Vez | P2: PARA CALCULAR EL VALOR A COBRAR POR EL PRESENTE AÑO
A3: AÑO GRAVABLE 2024 | M3: 220000 | N3: 350000
A4: PERSONAS NATURALES Y PERSONAS JURÍDICAS | F4: VALORES CUENTAS DE COBRO 2023 | P4: PRESUPUESTOS DE COBRO -AÑO GRAVABLE 2022-
Q5: 0.0928 | S5: 0.5 | U5: 0.75 | W5: 0.15 | Y5: 0.2 | AA5: 0.1 | AC5: 0.2 | AE5: 0.3
A6: No. | B6: APELLIDOS Y NOMBRES o RAZÓN SOCIAL | C6: CÓDIGO | D6: NIT No. | E6: D. V. | F6: VALOR A ELABORAR LA CUENTA DE COBRO | G6: CUENTA DE COBRO No. | H6: ENVIADA | I6: FECHA ENVIO | J6: ESTADO DEL COBRO | K6: MEDIO DE PAGO | L6: FECHA DE PAGO | M6: OBSERVACIONES-1 | N6: OBSERVACIONES-2 | P6: SI o NO | Q6: VALOR DECLARACIÓN RENTA | R6: SI o NO | S6: VALOR DECLARACIÓN I AL P | T6: SI o NO | U6: VALOR MEDIOS MAGNÉTICOS | V6: SI o NO | W6: EXÓGENA MPIO MEDELLÍN | X6: SI o NO | Y6: REG ÚNICO de BENEFICIARIOS | Z6: SI o NO | AA6: VALOR FORMATO 2516 CONSERVAR | AB6: SI o NO | AC6: VALOR FORMATO 2516 TRANSMITIR | AD6: SI o NO | AE6: VALOR DECLARACIÓN ACTIVOS EN EL EXTERIOR | AF6: VALOR ASESORÍAS | AG6: VALOR PRÉSTAMOS | AH6: TOTAL PRESUPUESTADO
A8: PERSONAS NATURALES
A9: 1 | B9: NOMBRE 1 | C9: 41 | D9: 22126399 | E9: 5 | F9: 340000 | G9: 24-135 | M9: Anexos y toca llamar | P9: SI | Q9: 340000 | S9: 0 | U9: 0 | W9: 0 | Y9: 0 | AA9: 0 | AC9: 0 | AE9: 0 | AF9: 0 | AG9: 0 | AH9: 340000
A10: 2 | B10: NOMBRE 2 | C10: 346 | D10: 71581755 | E10: 2 | F10: 150000 | G10: 24-042 | H10: WhatsApp | I10: 45554 | J10: OK/ | K10: Consignación | L10: 45554 | P10: SI | Q10: 153000 | S10: 0 | U10: 0 | W10: 0 | Y10: 0 | AA10: 0 | AC10: 0 | AE10: 0 | AF10: 0 | AG10: 0 | AH10: 150000
A11: 3 | B11: NOMBRE 3 | C11: 300 | D11: 70116694 | E11: 5 | F11: 450000 | G11: 24-127 | H11: WhatsApp | I11: 45594 | J11: OK/ | K11: Transferencia | L11: Revisar | P11: SI | Q11: 448000 | S11: 0 | U11: 0 | W11: 0 | Y11: 0 | AA11: 0 | AC11: 0 | AE11: 0 | AF11: 0 | AG11: 0 | AH11: 450000
A12: 4 | B12: NOMBRE 4 | C12: 217 | D12: 3349249 | E12: 7 | F12: 290000 | G12: 24-035 | H12: Físico | J12: OK/ | K12: Efectivo | L12: 45570 | P12: SI | Q12: 317000 | S12: 0 | U12: 0 | W12: 0 | Y12: 0 | AA12: 0 | AC12: 0 | AE12: 0 | AF12: 0 | AG12: 0 | AH12: 320000
A13: 5 | B13: NOMBRE 5 | C13: 43 | D13: 71632774 | E13: 2 | F13: 480000 | G13: 24-100 | H13: WhatsApp | I13: 45593 | P13: SI | Q13: 405000 | S13: 0 | U13: 0 | W13: 0 | Y13: 0 | AA13: 0 | AC13: 0 | AE13: 0 | AF13: 70000 | AG13: 0 | AH13: 480000
A14: 6 | B14: NOMBRE 6 | C14: 44 | D14: 21315528 | E14: 6 | F14: 1740000 | G14: 24-075 | H14: Correo | I14: 45618 | M14: Tener en cuenta a finales de NOV | P14: SI | Q14: 1158000 | R14: SI | S14: 579000 | U14: 0 | W14: 0 | Y14: 0 | AA14: 0 | AC14: 0 | AE14: 0 | AF14: 0 | AG14: 0 | AH14: 1740000
A15: 7 | B15: NOMBRE 7 | C15: 45 | D15: 32336950 | E15: 1 | F15: 930000 | G15: 24-041 | H15: WhatsApp | I15: 45553 | J15: OK/ | K15: Transferencia | L15: 45554 | P15: SI | Q15: 568000 | S15: 0 | U15: 0 | W15: 0 | Y15: 0 | AA15: 0 | AC15: 0 | AE15: 0 | AF15: 365920.8 | AG15: 0 | AH15: 930000

Sheet Asesorías AG anterior
A1: GERMÁN TULIO FERNÁNDEZ FERNÁNDEZ
A2: REGISTRO DE ASESORÍAS
A3: AÑO GRAVABLE 2023 | H3: ASESORÍAS | V3: PRÉSTAMOS | AD3: COBROS AÑO GRAVABLE ANTERIOR
H4: IPC | J4: 0.0928 | L4: 0.0928 | P4: 0.0928 | R4: 0.0928 | U4: 0.0928
A5: No. | B5: APELLIDOS Y NOMBRES | C5: CÓDIGO | D5: NIT No. | E5: D. V. | F5: ACUMULADO ASESORÍAS AÑO | G5: TOTAL ACUMULADO PRÉSTAMOS | H5: TOTAL ASESORÍAS AÑO | I5: CANT | J5: DECLARACIÓN IVA | K5: CANT | L5: DECLARACIÓN RET FTE | M5: SI/NO | N5: DEVOLUCIÓN IMPUESTOS | O5: SI/NO | P5: FACTURACIÓN ELECTRÓNICA | Q5: PROCESO CONTABLE | R5: OTRAS ASESORÍAS | S5: Otras Asesorías: OBSERVACIONES | T5: CANT | U5: ESTADOS FROS | V5: TOTAL PRÉSTAMOS | W5: CANT | X5: PRÉSTAMOS por PAGOS OFICINA | Y5: CANT | Z5: PRÉSTAMOS por CERTIFICADOS | AA5: CANT | AB5: PRÉSTAMOS por PAGOS SEG SOC | AD5: CANT | AE5: DECLARACIÓN IVA | AF5: CANT | AG5: DECLARACIÓN RET FTE | AH5: CANT | AI5: DEVOLUCIÓN IMPUESTOS | AJ5: SI/NO | AK5: FACTURACIÓN ELECTRÓNICA | AL5: PROCESO CONTABLE | AM5: OTRAS ASESORÍAS | AN5: Otras Asesorías: OBSERVACIONES | AO5: CANT | AP5: ESTADOS FROS | AQ5: TOTAL PRÉSTAMOS | AR5: CANT | AS5: PRÉSTAMOS -CERTIFICADOS | AT5: CANT | AU5: PRÉSTAMOS -PAGOS OFICINA | AV5: CANT | AW5: PRÉSTAMOS -SEG SOC
A7: 1 | B7: NOMBRE 1 | C7: 41 | D7: 22126399 | E7: 5 | F7: 0 | G7: 0 | H7: 0 | I7: 0.001 | J7: 0 | K7: 0.001 | L7: 0 | N7: 0 | O7: 0.001 | P7: 0 | Q7: 0 | R7: 0 | V7: 0 | AD7: 0.001 | AE7: 0.001 | AF7: 0.001 | AG7: 0.001 | AH7: 0.001 | AI7: 0.001 | AJ7: 0.001 | AK7: 0.001 | AL7: 0.001 | AM7: 0.001 | AN7: 0.001 | AO7: 0.001 | AP7: 0.001 | AQ7: 0.001 | AR7: 0.001 | AS7: 0.001 | AT7: 0.001 | AU7: 0.001 | AV7: 0.001 | AW7: 0.001
A8: 2 | B8: NOMBRE 2 | C8: 346 | D8: 71581755 | E8: 2 | F8: 0 | G8: 0 | H8: 0 | I8: 0.001 | J8: 0 | K8: 0.001 | L8: 0 | N8: 0 | O8: 0.001 | P8: 0 | Q8: 0 | R8: 0 | V8: 0 | AD8: 0.001 | AE8: 0.001 | AF8: 0.001 | AG8: 0.001 | AH8: 0.001 | AI8: 0.001 | AJ8: 0.001 | AK8: 0.001 | AL8: 0.001 | AM8: 0.001 | AN8: 0.001 | AO8: 0.001 | AP8: 0.001 | AQ8: 0.001 | AR8: 0.001 | AS8: 0.001 | AT8: 0.001 | AU8: 0.001 | AV8: 0.001 | AW8: 0.001
A9: 3 | B9: NOMBRE 3 | C9: 300 | D9: 70116694 | E9: 5 | F9: 0 | G9: 0 | H9: 0 | I9: 0.001 | J9: 0 | K9: 0.001 | L9: 0 | N9: 0 | O9: 0.001 | P9: 0 | Q9: 0 | R9: 0 | V9: 0 | AD9: 0.001 | AE9: 0.001 | AF9: 0.001 | AG9: 0.001 | AH9: 0.001 | AI9: 0.001 | AJ9: 0.001 | AK9: 0.001 | AL9: 0.001 | AM9: 0.001 | AN9: 0.001 | AO9: 0.001 | AP9: 0.001 | AQ9: 0.001 | AR9: 0.001 | AS9: 0.001 | AT9: 0.001 | AU9: 0.001 | AV9: 0.001 | AW9: 0.001
A10: 4 | B10: NOMBRE 4 | C10: 217 | D10: 3349249 | E10: 7 | F10: 0 | G10: 0 | H10: 0 | I10: 0.001 | J10: 0 | K10: 0.001 | L10: 0 | N10: 0 | O10: 0.001 | P10: 0 | Q10: 0 | R10: 0 | V10: 0 | AD10: 0.001 | AE10: 0.001 | AF10: 0.001 | AG10: 0.001 | AH10: 0.001 | AI10: 0.001 | AJ10: 0.001 | AK10: 0.001 | AL10: 0.001 | AM10: 0.001 | AN10: 0.001 | AO10: 0.001 | AP10: 0.001 | AQ10: 0.001 | AR10: 0.001 | AS10: 0.001 | AT10: 0.001 | AU10: 0.001 | AV10: 0.001 | AW10: 0.001
A11: 5 | B11: NOMBRE 5 | C11: 43 | D11: 71632774 | E11: 2 | F11: 70000 | G11: 0 | H11: 70000 | I11: 0.001 | J11: 0 | K11: 0.001 | L11: 0 | N11: 0 | O11: SI | P11: 70000 | Q11: 0 | R11: 0 | V11: 0 | AD11: 0.001 | AE11: 0.001 | AF11: 0.001 | AG11: 0.001 | AH11: 0.001 | AI11: 0.001 | AJ11: SI | AK11: 60000 | AL11: 0.001 | AM11: 0.001 | AN11: 0.001 | AO11: 0.001 | AP11: 0.001 | AQ11: 0.001 | AR11: 0.001 | AS11: 0.001 | AT11: 0.001 | AU11: 0.001 | AV11: 0.001 | AW11: 0.001
A12: 6 | B12: NOMBRE 6 | C12: 44 | D12: 21315528 | E12: 6 | F12: 0 | G12: 0 | H12: 0 | I12: 0.001 | J12: 0 | K12: 0.001 | L12: 0 | N12: 0 | O12: 0.001 | P12: 0 | Q12: 0 | R12: 0 | V12: 0 | AD12: 0.001 | AE12: 0.001 | AF12: 0.001 | AG12: 0.001 | AH12: 0.001 | AI12: 0.001 | AJ12: 0.001 | AK12: 0.001 | AL12: 0.001 | AM12: 0.001 | AN12: 0.001 | AO12: 0.001 | AP12: 0.001 | AQ12: 0.001 | AR12: 0.001 | AS12: 0.001 | AT12: 0.001 | AU12: 0.001 | AV12: 0.001 | AW12: 0.001
A13: 7 | B13: NOMBRE 7 | C13: 45 | D13: 32336950 | E13: 1 | F13: 365920.8 | G13: 0 | H13: 365920.8 | I13: 3 | J13: 365920.8 | K13: 0.001 | L13: 0 | N13: 0 | O13: 0.001 | P13: 0 | Q13: 0 | R13: 0 | V13: 0 | AD13: 3 | AE13: 334847 | AF13: 0.001 | AG13: 0.001 | AH13: 0.001 | AI13: 0.001 | AJ13: 0.001 | AK13: 0.001 | AL13: 0.001 | AM13: 0.001 | AN13: 0.001 | AO13: 0.001 | AP13: 0.001 | AQ13: 0.001 | AR13: 0.001 | AS13: 0.001 | AT13: 0.001 | AU13: 0.001 | AV13: 0.001 | AW13: 0.001
A14: 8 | B14: NOMBRE 8 | C14: 156 | D14: 43079999 | E14: 9 | F14: 0 | G14: 0 | H14: 0 | I14: 0.001 | J14: 0 | K14: 0.001 | L14: 0 | N14: 0 | O14: 0.001 | P14: 0 | Q14: 0 | R14: 0 | V14: 0 | AD14: 0.001 | AE14: 0.001 | AF14: 0.001 | AG14: 0.001 | AH14: 0.001 | AI14: 0.001 | AJ14: 0.001 | AK14: 0.001 | AL14: 0.001 | AM14: 0.001 | AN14: 0.001 | AO14: 0.001 | AP14: 0.001 | AQ14: 0.001 | AR14: 0.001 | AS14: 0.001 | AT14: 0.001 | AU14: 0.001 | AV14: 0.001 | AW14: 0.001
AZ116: 81622954 | BA116: 13603826 | BB116: 1133652.1

Sheet Códigos
A1: GERMÁN TULIO FERNÁNDEZ FERNÁNDEZ
A2: BASE DE DATOS Y CÓDIGOS
A3: =+'Grupos Familiares'!A4 -> AÑO GRAVABLE 2024
A5: CÓDIGO | B5: APELLIDOS Y NOMBRES o RAZÓN SOCIAL o CONCEPTO DEL CÓDIGO | D5: OBSERVACIONES
A8: 41 | B8: NOMBRE 1
A9: 346 | B9: NOMBRE 2
A10: 300 | B10: NOMBRE 3
A11: 312 | B11: NOMBRE 4
A12: 217 | B12: NOMBRE 5
A13: 42 | B13: NOMBRE 6
A14: 43 | B14: NOMBRE 7
A15: 44 | B15: NOMBRE 8
A16: 45 | B16: NOMBRE 9
A17: 172 | B17: NOMBRE 10
A18: 156 | B18: NOMBRE 11
A19: 47 | B19: NOMBRE 12
... A21: 48 | B21: NOMBRE 14
A22: 36
A23: 38
A24: 49
A25: 50
A26: 51
A27: 52
A28: 1
A29: 53
A30: 2
A31: 3
A32: 5
A33: 341
... A378: 370
A379: =+A378+1 -> 371
A380: =+A379+1 -> 372
A381: =+A380+1 -> 373
A382: =+A381+1 -> 374
A383: =+A382+1 -> 375
A384: =+A383+1 -> 376
A385: =+A384+1 -> 377
A386: =+A385+1 -> 378
A387: =+A386+1 -> 379
A388: =+A387+1 -> 380

Sheet TABLA RetFte
H1: U V T
H2: UVT 2023 | I2: 42412
H3: UVT 2022 | I3: 38004
A7: LIQUIDACIÓN DE RETENCIONES EN LA FUENTE
A9: Ingreso Base Retención en la Fuente | B9: =+'Grupos Familiares'!M33 -> 0
A10: UVT año gravable | B10: =+I2 -> 42412
A11: Ingreso Base Retención en la Fuente en UVT | B11: =B9/B10 -> 0
A13: RETENCIONES EN LA FUENTE | B13: =+E17 -> 0
A15: ARTÍCULO 383. Tarifa. La retención en la fuente aplicable a los pagos gravables efectuados por las personas naturales o jurídicas, las sociedades de hecho, las comunidades organizadas y las sucesiones ilíquidas, originados en la relación laboral, o legal y reglamentaria, y los pagos recibidos por concepto de pensiones de jubilación, invalidez, vejez, de sobrevivientes y sobre riesgos laborales, será la que resulte de aplicar a dichos pagos la siguiente tabla de retención en la fuente:
A16: Artículo 1.2.4.1.17. Retención en la fuente para las cédulas de rentas de trabajo y de pensiones. Conforme lo establece el artículo 383 del Estatuto Tributario, la retención en la fuente aplicable por las personas naturales o jurídicas, las sociedades de hecho, las comunidades organizadas y las sucesiones ilíquidas, a las personas naturales cuyos ingresos provengan de la cédula de rentas de trabajo y la cédula
A17: RETENCIONES EN LA FUENTE | E17: =SUM(E22:E28) -> 0
A19: RANGOS EN UVT | C19: TARIFA MARGINAL | D19: UVT a | E19: IMPUESTO | F19: IMPUESTO
A20: DESDE | B20: HASTA | C20: IMPUESTO | D20: ADICIONAR | E20: RENTA
A22: 0 | B22: 95 | C22: 0 | D22: 0 | E22: =ROUND(IF(+B$11>A22,IF(B$11<B22,IF(((B$11-0)*B$10*C22+D22*B$10)>0,((B$11-0)*B$10*C22+D22*B$10),0),0),0),-3) -> 0 | F22: 0 | H22: =ROUND(IF(+B$11>A22,IF(B$11<B22,IF(((B$11-0)*B$10*C22+D22*B$10)>0,((B$11-0)*B$10*C22+D22*B$10),0),0),0),-3)+ROUND(IF(+B$11>A23,IF(B$11<B23,IF(((B$11-B22)*B$10*C23+D23*B$10)>0,((B$11-B22)*B$10*C23+D23*B$10),0),0),0),-3)+ROUND(IF(+B$11>A24,IF(B$11<B24,IF(((B$11-B23)*B$10*C24+D24*B$10)>0,((B$11-B23)*B$10*C24+D24*B$10),0),0),0),-3)+ROUND(IF(+B$11>A25,IF(B$11<B25,IF(((B$11-B24)*B$10*C25+D25*B$10)>0,((B$11-B24)*B$10*C25+D25*B$10),0),0),0),-3)+ROUND(IF(+B$11>A26,IF(B$11<B26,IF(((B$11-B25)*B$10*C26+D26*B$10)>0,((B$11-B25)*B$10*C26+D26*B$10),0),0),0),-3)+ROUND(IF(+B$11>A27,IF(B$11<B27,IF(((B$11-B26)*B$10*C27+D27*B$10)>0,((B$11-B26)*B$10*C27+D27*B$10),0),0),0),-3)+ROUND(IF(+B$11>A28,IF(B$11<B28,IF(((B$11-B27)*B$10*C28+D28*B$10)>0,((B$11-B27)*B$10*C28+D28*B$10),0),0),0),-3) -> 0
A23: =+B22 -> 95 | B23: 150 | C23: 0.19 | D23: 0 | E23: =ROUND(IF(+B$11>A23,IF(B$11<B23,IF(((B$11-B22)*B$10*C23+D23*B$10)>0,((B$11-B22)*B$10*C23+D23*B$10),0),0),0),-3) -> 0 | F23: (Base gravable en UVT menos 95 UVT) x 19%
A24: =+B23 -> 150 | B24: 360 | C24: 0.28 | D24: 10 | E24: =ROUND(IF(+B$11>A24,IF(B$11<B24,IF(((B$11-B23)*B$10*C24+D24*B$10)>0,((B$11-B23)*B$10*C24+D24*B$10),0),0),0),-3) -> 0 | F24: (Base gravable en UVT menos 150 UVT) x 28% + 10 UVT
A25: =+B24 -> 360 | B25: 640 | C25: 0.33 | D25: 69 | E25: =ROUND(IF(+B$11>A25,IF(B$11<B25,IF(((B$11-B24)*B$10*C25+D25*B$10)>0,((B$11-B24)*B$10*C25+D25*B$10),0),0),0),-3) -> 0 | F25: (Base gravable en UVT menos 360 UVT*) x 33% + 69 UVT*
A26: =+B25 -> 640 | B26: 945 | C26: 0.35 | D26: 162 | E26: =ROUND(IF(+B$11>A26,IF(B$11<B26,IF(((B$11-B25)*B$10*C26+D26*B$10)>0,((B$11-B25)*B$10*C26+D26*B$10),0),0),0),-3) -> 0 | F26: (Base gravable en UVT menos 640 UVT*) x 35% + 162 UVT*
A27: =+B26 -> 945 | B27: 2300 | C27: 0.37 | D27: 268 | E27: =ROUND(IF(+B$11>A27,IF(B$11<B27,IF(((B$11-B26)*B$10*C27+D27*B$10)>0,((B$11-B26)*B$10*C27+D27*B$10),0),0),0),-3) -> 0 | F27: (Base gravable en UVT menos 945 UVT*) x 37% + 268 UVT*
A28: =+B27 -> 2300 | B28: 999999999999 | C28: 0.39 | D28: 770 | E28: =ROUND(IF(+B$11>A28,IF(B$11<B28,IF(((B$11-B27)*B$10*C28+D28*B$10)>0,((B$11-B27)*B$10*C28+D28*B$10),0),0),0),-3) -> 0 | F28: (Base gravable en UVT menos 2.300 UVT*) x 39% + 770 UVT*
